Workbook

Sheet imagens
A1: pasta | B1: volume | C1: imagem | D1: url_pagina | E1: imagens_texto | F1: Categoria-1 | G1: Categoria-2 | H1: Categoria-3 | I1: ncb | J1: purl | K1: capa | L1: tipo de material | M1: língua | N1: língua da obra original | O1: título | P1: subtítulo | Q1: título original | R1: edição | S1: publicação | T1: data da publicação | U1: data da publicação2 | V1: dimensões | W1: autor | X1: autor - organização | Y1: co-autores | Z1: autores secundários | AA1: co-autores - organizações | AB1: autores secundários - organizações | AC1: cota | AD1: coleção | AE1: id persistente | AF1: acesso
A2: 367428 | B2: 1 | C2: 1 | D2: https://permalinkbnd.bnportugal.gov.pt/viewer/272369/?offset=#page=1&viewer=picture&o=info&n=0&q= | E2: 1 | I2: 367428 | J2: https://purl.pt/43428 | K2: https://bndigital.bnportugal.gov.pt//i/?IIIF=/a3/eb/b0/67/a3ebb067-89f3-40ff-a518-1fc158846d4b/iiif/cam-479-p_0003.tif/full/!300,500/0/default.jpg | L2: Livro impresso | M2: Italiano | O2: I Lusiadi | P2: poema | R2: 1.ª ed. | S2: Milano : Edoardo Sonzogno,editore | T2: 1882 | U2: 1882 | V2: 196 p. | W2: Camões, Luís de, 1524-1580 | Z2: Nervi, Antonio, 1760-1836, Tradutor | AC2: CAM. 479 P. | AD2: CAM500 | AE2: http://id.bnportugal.gov.pt/bib/catbnp/367428 | AF2: Livre
A3: 381074 | B3: 1 | C3: 499 | D3: https://permalinkbnd.bnportugal.gov.pt/viewer/274089/?offset=#page=499&viewer=picture&o=info&n=0&q= | E3: 10 [site], 11, 103 [site pelicano direita], 107, 142, 107, 142, 145, 185, 235, 270 [site assassinato de Inês], 273, 306, 309 [site ninfas], 342, 345, 374, 377, 410, 413, 447, 499, 526 [site apontamento] [pintura de Camões por Columbano, portada, fac-símile do frontispício da 1.ª Ed. de Os Lusíadas, ilustrações da obra] | F3: Cantos - Canto I|1791 | G3: Episódios - Concílio "Conselho dos Deuses"|1809 | H3: Retratos - |1801 | I3: 381074 | J3: https://purl.pt/43747 | K3: https://bndigital.bnportugal.gov.pt//i/?IIIF=/7d/bb/9c/38/7dbb9c38-ff88-4f0e-8125-42d713ee62f7/iiif/cam-21-a_0007.tif/full/!300,500/0/default.jpg | L3: Livro impresso | M3: Português | O3: Os Lusíadas | P3: edição consagrada a comemorar o terceiro centenário do poeta... | R3: 1.ª ed. | S3: Lisboa : Of. de Castro Irmão | T3: 1880 | U3: 1880 | V3: XCIII, 422 p., 1 il. | W3: Camões, Luís de, 1524-1580 | Z3: Coelho, Adolfo, 1847-1919, Revisor ; Ortigão, Ramalho, 1836-1915, Autor da introdução, etc. ; Montoro, Reinaldo Carlos, 1831-?, Autor da introdução, etc. | AB3: Gabinete Português de Leitura, Editor literário | AC3: L. 94571 V. | AD3: CAM500 | AE3: http://id.bnportugal.gov.pt/bib/catbnp/381074 | AF3: Livre
A4: 381465 | B4: 1 | C4: 644 | D4: https://permalinkbnd.bnportugal.gov.pt/viewer/271573/?offset=#page=644&viewer=picture&o=info&n=0&q= | E4: 5 [site], 10 [site], 11 [site], 43, 46 [Vasco da Gama], 47, 100, 101, 160, 161, 163, 235, 237, 289, 291 [site Adamastor], 293, 343 [site apontamento livros e pena], 345, 347, 397, 443, 445, 495 [site Mercúrio, caduceu e navegador], 545 [site máquina do mundo], 547, 625, 627, 644 [monge com livro] [portadas, retrato de Camões, fotogravuras em cada Canto] | F4: Cantos - Canto II|1792 | G4: Episódios - Vénus aplaca os Ventos e a tormenta|1813 | H4: Retratos - Vasco da Gama|1803 | I4: 381465 | J4: https://purl.pt/43233 | K4: https://bndigital.bnportugal.gov.pt//i/?IIIF=/1b/9b/a2/7b/1b9ba27b-8449-49d7-b8fa-ec3081a88a08/iiif/cam-30-a_0000_000005.tif/full/!300,500/0/default.jpg | L4: Livro impresso | M4: Português | O4: Os Lusíadas | P4: profusamente illustrada com desenhos allegoricos... | R4: 1.ª ed. | S4: Lisboa : Silvestre Castanheiro | T4: 1898 | U4: 1898 | V4: XXXIII, 599 p. | W4: Camões, Luís de, 1524-1580 | Z4: Belo, António Mendes, 1842-1929, Comentador (em meio audiovisual) ; Chagas, Pinheiro, 1842-1895, Comentador (em meio audiovisual) ; Costa, José Fernandes, 1848-1920, Comentador (em meio audiovisual) | AC4: L. 5864 A. | AD4: CAM500 | AE4: http://id.bnportugal.gov.pt/bib/catbnp/381465 | AF4: Livre
A5: 381468 | B5: 1 | C5: 8 | D5: https://permalinkbnd.bnportugal.gov.pt/viewer/274087/?offset=#page=8&viewer=picture&o=info&n=0&q= | E5: 8 [site retrato de Camões] | F5: Cantos - Canto III|1793 | G5: Episódios - Sonho d'El-Rei D. Manuel, no qual lhe aparecem os rios Indo e Ganges|1810 | H5: Retratos - António José Gomes Monteiro|1805 | I5: 381468 | J5: https://purl.pt/43745 | K5: https://bndigital.bnportugal.gov.pt//i/?IIIF=/e0/20/89/c0/e02089c0-dfb3-4507-bf34-b897aa5b2b44/iiif/cam-33-a_0009.tif/full/!300,500/0/default.jpg | L5: Livro impresso | M5: Espanhol | N5: Português | O5: Os Lusiadas (Los Portugueses) | R5: Edicion acompañada del legitimo texto portugues y de copiosas notas y noticias biograficas sobre el insigne poeta ibero | S5: Badajoz : Establecimiento Tipográfico de José Santamaría | T5: 1873 | U5: 1873 | V5: 263, 1 p. | W5: Camões, Luís de, 1524-1580 | Z5: Soler y Arqués, Carlos, 1836-1896, Tradutor | AC5: CAM. 33 A. | AD5: CAM500 | AE5: http://id.bnportugal.gov.pt/bib/catbnp/381468 | AF5: Livre
A6: 381701 | B6: 1 | C6: 11 | D6: https://permalinkbnd.bnportugal.gov.pt/viewer/281141/?offset=#page=11&viewer=picture&o=info&n=0&q= | E6: 11 | F6: Cantos - Canto VI|1796 | G6: Retratos - Vasco da Gama|1803 | H6: Episódios - Concílio "Conselho dos Deuses"|1809 | I6: 381701 | J6: https://purl.pt/43724 | K6: https://bndigital.bnportugal.gov.pt//i/?IIIF=/58/a8/a6/57/58a8a657-7fb2-4700-9b55-408036c37806/iiif/cam-40-a_0001.tif/full/!300,500/0/default.jpg | L6: Livro impresso | M6: Poliglota | N6: Português | O6: Inês de Castro | P6: episódio extraído do canto terceiro do poema épico Os Lusíadas | R6: 1.ª ed. | S6: Lisboa : Imprensa Nacional | T6: 1873 | U6: 1873 | V6: 76 p. | W6: Camões, Luís de, 1524-1580 | AC6: CAM. 40 A. | AD6: CAM500 | AE6: http://id.bnportugal.gov.pt/bib/catbnp/381701 | AF6: Livre
A7: 381889 | B7: 1 | C7: 1 | D7: https://permalinkbnd.bnportugal.gov.pt/viewer/273118/?offset=#page=1&viewer=picture&o=info&n=0&q= | E7: 1 [Inês de Castro, Vasco da Gama, Catarina de Ataíde e retrato de Camões] | F7: Cantos - Canto VI|1796 | I7: 381889 | J7: https://purl.pt/43659 | K7: https://bndigital.bnportugal.gov.pt//i/?IIIF=/5b/91/40/8a/5b91408a-4af1-4a94-bccc-2d03ee894a1c/iiif/cam-44-2-a_0000_000001.tif/full/!300,500/0/default.jpg | L7: Periódico | M7: Português | O7: Pérolas de Camões | P7: publicação dedicada ao povo | R7: 1.ª ed. | S7: Lisboa : Lallement Fréres | T7: 1880 | U7: 1880 | AB7: Lallement Frères, Editor comercial | AC7: CAM. 44//2 A. | AD7: CAM500 | AE7: http://id.bnportugal.gov.pt/bib/catbnp/381889 | AF7: Livre
A8: 381903 | B8: 1 | C8: 5 | D8: https://permalinkbnd.bnportugal.gov.pt/viewer/270037/?offset=#page=5&viewer=picture&o=info&n=0&q= | E8: 5 [1.º] | F8: Cantos - Canto V|1795 | G8: Retratos - Camões|1802 | I8: 381903 | J8: https://purl.pt/42920 | K8: https://bndigital.bnportugal.gov.pt//i/?IIIF=/84/00/0c/50/84000c50-b90e-4a7c-aa5e-5cb3dfef4dab/iiif/cam-45-2-a_0000_000001.tif/full/!300,500/0/default.jpg | L8: Periódico | M8: Polaco | O8: Illustrowane Tygedniowe | R8: 1.ª ed. | T8: 1880 | U8: 1880 | AC8: CAM. 45//2 A. | AD8: CAM500 | AE8: http://id.bnportugal.gov.pt/bib/catbnp/381903 | AF8: Livre
A9: 382749 | B9: 1 | C9: 7 | D9: https://permalinkbnd.bnportugal.gov.pt/viewer/270109/?offset=#page=7&viewer=picture&o=info&n=0&q= | E9: 7 [site], 19, 23 [frisos site, esta obra contém mais apontamentos e frisos belíssimos] | F9: Episódios - Vénus aplaca os Ventos e a tormenta|1813 | I9: 382749 | J9: https://purl.pt/42835 | K9: https://bndigital.bnportugal.gov.pt//i/?IIIF=/60/58/22/4f/6058224f-9454-448f-8489-96a3a71253f5/iiif/cam-47-a_0000_000007.tif/full/!300,500/0/default.jpg | L9: Livro impresso | M9: Português | O9: Pretidão de amor | P9: endechas a Bárbara escrava seguidas da respectiva tradução em várias línguas... | R9: 1.ª ed. | S9: Lisboa : Imprensa Nacional | T9: 1893 | U9: 1893 | V9: 2 v. | W9: Camões, Luís de, 1524-1580 | Z9: Cunha, Xavier da, 1840-1920, Autor da introdução, etc. | AC9: CAM. 270 V. | AD9: CAM500 | AE9: http://id.bnportugal.gov.pt/bib/catbnp/382749 | AF9: Livre
A10: 382749 | B10: 1 | C10: 19 | D10: https://permalinkbnd.bnportugal.gov.pt/viewer/270109/?offset=#page=19&viewer=picture&o=info&n=0&q= | F10: Retratos - Vasco da Gama|1803 | I10: 382749 | J10: https://purl.pt/42835 | K10: https://bndigital.bnportugal.gov.pt//i/?IIIF=/60/58/22/4f/6058224f-9454-448f-8489-96a3a71253f5/iiif/cam-47-a_0000_000007.tif/full/!300,500/0/default.jpg | L10: Livro impresso | M10: Português | O10: Pretidão de amor | P10: endechas a Bárbara escrava seguidas da respectiva tradução em várias línguas... | R10: 1.ª ed. | S10: Lisboa : Imprensa Nacional | T10: 1893 | U10: 1893 | V10: 2 v. | W10: Camões, Luís de, 1524-1580 | Z10: Cunha, Xavier da, 1840-1920, Autor da introdução, etc. | AC10: CAM. 270 V. | AD10: CAM500 | AE10: http://id.bnportugal.gov.pt/bib/catbnp/382749 | AF10: Livre
A11: 382749 | B11: 1 | C11: 23 | D11: https://permalinkbnd.bnportugal.gov.pt/viewer/270109/?offset=#page=23&viewer=picture&o=info&n=0&q= | I11: 382749 | J11: https://purl.pt/42835 | K11: https://bndigital.bnportugal.gov.pt//i/?IIIF=/60/58/22/4f/6058224f-9454-448f-8489-96a3a71253f5/iiif/cam-47-a_0000_000007.tif/full/!300,500/0/default.jpg | L11: Livro impresso | M11: Português | O11: Pretidão de amor | P11: endechas a Bárbara escrava seguidas da respectiva tradução em várias línguas... | R11: 1.ª ed. | S11: Lisboa : Imprensa Nacional | T11: 1893 | U11: 1893 | V11: 2 v. | W11: Camões, Luís de, 1524-1580 | Z11: Cunha, Xavier da, 1840-1920, Autor da introdução, etc. | AC11: CAM. 270 V. | AD11: CAM500 | AE11: http://id.bnportugal.gov.pt/bib/catbnp/382749 | AF11: Livre
A12: 382834 | B12: 1 | C12: 11 | D12: https://permalinkbnd.bnportugal.gov.pt/viewer/273316/?offset=#page=11&viewer=picture&o=info&n=0&q= | E12: 11 [caravela com Vasco da Gama] | I12: 382834 | J12: https://purl.pt/43815 | K12: https://bndigital.bnportugal.gov.pt//i/?IIIF=/b6/d0/71/c6/b6d071c6-e05d-4c17-96b2-07a62e35fb7f/iiif/cam-82-1-v_0000_000005.tif/full/!300,500/0/default.jpg | L12: Livro impresso | M12: Português | O12: Comemoração gloriosa da morte de Luiz de Camões 10 de Junho de 1889 | R12: 1.ª ed. | S12: Evora : Minerva Eborense de J. José Baptista, Rua d'Aviz | T12: 1889 | U12: 1889 | V12: 12, 4 p. | W12: Barata, António Francisco, 1836-1910 | Z12: Camões, Luís de, 1524-1580, Antecedente bibliográfico | AC12: CAM. 309//13 V. | AD12: CAM500 | AE12: http://id.bnportugal.gov.pt/bib/catbnp/382834 | AF12: Livre
A13: 382844 | B13: 1 | C13: 3 | D13: https://permalinkbnd.bnportugal.gov.pt/viewer/271559/?offset=#page=3&viewer=picture&o=info&n=0&q= | E13: 3 | I13: 382844 | J13: https://purl.pt/43227 | K13: https://bndigital.bnportugal.gov.pt//i/?IIIF=/be/12/df/5e/be12df5e-248d-4e0b-823f-bb93ea5db616/iiif/cam-2058-v_0001.tif/full/!300,500/0/default.jpg | L13: Livro impresso | M13: Português | O13: A Luiz de Camões | P13: com notas curiosas e tres ineditos do poeta | R13: 1.ª ed. | S13: Evora : Tip. Minerva, de A.F. Barata | T13: 1880 | U13: 1880 | V13: 24 p. | W13: Barata, António Francisco, 1836-1910 | Z13: Camões, Luís de, 1524-1580, Antecedente bibliográfico | AC13: L. 599//32 A. | AD13: CAM500 | AE13: http://id.bnportugal.gov.pt/bib/catbnp/382844 | AF13: Livre
A14: 382955 | B14: 1 | C14: 6 | D14: https://permalinkbnd.bnportugal.gov.pt/viewer/274171/?offset=#page=6&viewer=picture&o=info&n=0&q= | E14: 6 [site, retrato do Poeta laureado] | I14: 382955 | J14: https://purl.pt/43816 | K14: https://bndigital.bnportugal.gov.pt//i/?IIIF=/df/8e/1b/e5/df8e1be5-0f74-4fdb-9b58-5bfa696ca99d/iiif/cam-53-5-a_0001.tif/full/!300,500/0/default.jpg | L14: Livro impresso | M14: Português | O14: Auto da cunhagem da medalha comemorativa das festas da Grande Comissão Portuense... | R14: 1.ª ed. | S14: Porto : s. n. | T14: 1880 | U14: 1880 | X14: Grande Comissão Portuense | Z14: Camões, Luís de, 1524-1580, Antecedente bibliográfico | AC14: CAM. 53//5 A. | AD14: CAM500 | AE14: http://id.bnportugal.gov.pt/bib/catbnp/382955 | AF14: Livre
A15: 382972 | B15: 1 | C15: 14 | D15: https://permalinkbnd.bnportugal.gov.pt/viewer/274229/?offset=#page=14&viewer=picture&o=info&n=0&q= | E15: 14 [site, imagem da medalha/gravura comemorativa do monumento erigido à memória do Poeta] | I15: 382972 | J15: https://purl.pt/43819 | K15: https://bndigital.bnportugal.gov.pt//i/?IIIF=/80/3b/b9/df/803bb9df-b4de-496a-adbc-25a9d95b3638/iiif/cam-55-a_0007.tif/full/!300,500/0/default.jpg | L15: Livro impresso | M15: Português | O15: Surrexit | P15: homenagem a Luís de Camões | R15: 1.ª ed. | S15: Lisboa : Imprensa Nacional | T15: 1880 | U15: 1880 | W15: Ribeiro, Tomás, 1831-1901 | AC15: CAM. 55 A. | AD15: CAM500 | AE15: http://id.bnportugal.gov.pt/bib/catbnp/382972 | AF15: Livre
A16: 382978 | B16: 1 | C16: 7 | D16: https://permalinkbnd.bnportugal.gov.pt/viewer/274235/?offset=#page=7&viewer=picture&o=info&n=0&q= | E16: 7 [site], 13 [site, itinerário do cortejo triunfal], 15 [site préstito cívico e triunfal] | I16: 382978 | J16: https://purl.pt/43823 | K16: https://bndigital.bnportugal.gov.pt//i/?IIIF=/8a/04/06/d1/8a0406d1-dcdf-40af-9ba2-5fa354405f51/iiif/cam-56-a_0001.tif/full/!300,500/0/default.jpg | L16: Livro impresso | M16: Português | O16: Programa da celebração em Lisboa do terceiro centenário de Luís de Camões | P16: comemoração promovida pela imprensa jornalística auxiliada pela Câmara Municipal | R16: 1.ª ed. | S16: Lisboa : Tip. Universal | T16: 1880 | U16: 1880 | V16: 8 p. | Z16: Camões, Luís de, 1524-1580, Antecedente bibliográfico | AC16: CAM. 134 A. | AD16: CAM500 | AE16: http://id.bnportugal.gov.pt/bib/catbnp/382978 | AF16: Livre
A17: 382978 | B17: 1 | C17: 13 | D17: https://permalinkbnd.bnportugal.gov.pt/viewer/274235/?offset=#page=13&viewer=picture&o=info&n=0&q= | E17: 7 [site], 13 [site, itinerário do cortejo triunfal], 15 [site préstito cívico e triunfal] | I17: 382978 | J17: https://purl.pt/43823 | K17: https://bndigital.bnportugal.gov.pt//i/?IIIF=/8a/04/06/d1/8a0406d1-dcdf-40af-9ba2-5fa354405f51/iiif/cam-56-a_0001.tif/full/!300,500/0/default.jpg | L17: Livro impresso | M17: Português | O17: Programa da celebração em Lisboa do terceiro centenário de Luís de Camões | P17: comemoração promovida pela imprensa jornalística auxiliada pela Câmara Municipal | R17: 1.ª ed. | S17: Lisboa : Tip. Universal | T17: 1880 | U17: 1880 | V17: 8 p. | Z17: Camões, Luís de, 1524-1580, Antecedente bibliográfico | AC17: CAM. 134 A. | AD17: CAM500 | AE17: http://id.bnportugal.gov.pt/bib/catbnp/382978 | AF17: Livre
A18: 382978 | B18: 1 | C18: 15 | D18: https://permalinkbnd.bnportugal.gov.pt/viewer/274235/?offset=#page=15&viewer=picture&o=info&n=0&q= | E18: 7 [site], 13 [site, itinerário do cortejo triunfal], 15 [site préstito cívico e triunfal] | I18: 382978 | J18: https://purl.pt/43823 | K18: https://bndigital.bnportugal.gov.pt//i/?IIIF=/8a/04/06/d1/8a0406d1-dcdf-40af-9ba2-5fa354405f51/iiif/cam-56-a_0001.tif/full/!300,500/0/default.jpg | L18: Livro impresso | M18: Português | O18: Programa da celebração em Lisboa do terceiro centenário de Luís de Camões | P18: comemoração promovida pela imprensa jornalística auxiliada pela Câmara Municipal | R18: 1.ª ed. | S18: Lisboa : Tip. Universal | T18: 1880 | U18: 1880 | V18: 8 p. | Z18: Camões, Luís de, 1524-1580, Antecedente bibliográfico | AC18: CAM. 134 A. | AD18: CAM500 | AE18: http://id.bnportugal.gov.pt/bib/catbnp/382978 | AF18: Livre
A19: 382981 | B19: 1 | C19: 9 | D19: https://permalinkbnd.bnportugal.gov.pt/viewer/1880/?offset=#page=9&viewer=picture&o=info&n=0&q= | E19: 9 | I19: 382981 | J19: https://purl.pt/43818 | K19: https://bndigital.bnportugal.gov.pt//i/?IIIF=/2b/2d/51/1b/2b2d511b-4290-4cc3-b338-dffc6cbedad2/iiif/cam-57-a_0001.tif/full/!300,500/0/default.jpg | L19: Livro impresso | M19: Português | O19: Relatório da Directoria do Gabinete de Leitura do Rio de Janeiro em 1880 | R19: 1.ª ed. | S19: Rio de Janeiro : Tip e lit. Moreira Maximino | T19: 1881 | U19: 1881 | AB19: Real Gabinete Português de Leitura do Rio de Janeiro | AC19: CAM. 57 A. | AD19: CAM500 | AE19: http://id.bnportugal.gov.pt/bib/catbnp/382981 | AF19: Livre
A20: 385945 | B20: 1 | C20: 15 | D20: https://permalinkbnd.bnportugal.gov.pt/viewer/273149/?offset=#page=15&viewer=picture&o=info&n=0&q= | E20: 10 [fotografia do autor], 11 [portada], 15 | I20: 385945 | J20: https://purl.pt/43873 | K20: https://bndigital.bnportugal.gov.pt//i/?IIIF=/ca/5d/8c/c5/ca5d8cc5-b85c-4f76-893f-7de2d31a6d43/iiif/cam-63-a_0000_000007.tif/full/!300,500/0/default.jpg | L20: Livro impresso | M20: Poliglota | N20: Português | O20: Álbum literário comemorativo do terceiro centenário de Luís de Camões | R20: 1.ª ed. | S20: Porto : Tip. Ocidental | T20: 1880 | U20: 1880 | V20: 28 p. | Z20: Esteves, Francisco Xavier, 1864-1944, Editor literário | AC20: CAM. 133 A. | AD20: CAM500 | AE20: http://id.bnportugal.gov.pt/bib/catbnp/385945 | AF20: Livre
A21: 385949 | B21: 1 | C21: 1 | D21: https://permalinkbnd.bnportugal.gov.pt/viewer/274256/?offset=#page=1&viewer=picture&o=info&n=0&q= | E21: 1 | I21: 385949 | J21: https://purl.pt/43866 | K21: https://bndigital.bnportugal.gov.pt//i/?IIIF=/06/33/d8/97/0633d897-92cc-4a30-beb0-aa004a6f6470/iiif/cam-64-1-a_0001.tif/full/!300,500/0/default.jpg | L21: Livro impresso | M21: Português | O21: Homenagem a Camões | P21: Luís de Camões e a nacionalidade portuguesa | R21: 1.ª ed. | S21: São Miguel : s. n. | T21: 1880 | U21: 1880 | X21: Centro Republicano Federal de Ponta Delgada | AC21: CAM. 64//1 A. | AD21: CAM500 | AE21: http://id.bnportugal.gov.pt/bib/catbnp/385949 | AF21: Livre
A22: 386935 | B22: 1 | C22: 1 | D22: https://permalinkbnd.bnportugal.gov.pt/viewer/273122/?offset=#page=1&viewer=picture&o=info&n=0&q= | E22: 1 | I22: 386935 | J22: https://purl.pt/43871 | K22: https://bndigital.bnportugal.gov.pt//i/?IIIF=/c8/18/91/78/c8189178-5871-4300-9edd-154703c6e75a/iiif/cam-64-3-a_0000_000001.tif/full/!300,500/0/default.jpg | L22: Livro impresso | M22: Português | O22: Vianna a Camões | P22: comemoração do tricentenário do imortal cantor dos Lusíadas | R22: 1.ª ed. | S22: Viana do Castelo : André Jorge Pereira & Filho | T22: 1880 | U22: 1880 | AC22: CAM. 64//3 A. | AD22: CAM500 | AE22: http://id.bnportugal.gov.pt/bib/catbnp/386935 | AF22: Livre
A23: 386992 | B23: 1 | C23: 1 | D23: https://permalinkbnd.bnportugal.gov.pt/viewer/273124/?offset=#page=1&viewer=picture&o=info&n=0&q= | E23: 1 | I23: 386992 | J23: https://purl.pt/43661 | K23: https://bndigital.bnportugal.gov.pt//i/?IIIF=/0c/53/05/58/0c530558-6907-414a-974d-e379f3070104/iiif/cam-64-4-a_0000_000001.tif/full/!300,500/0/default.jpg | L23: Livro impresso | M23: Português | O23: Homenagem da Sociedade Amizade, Recreio e Ínstrução | R23: 1.ª ed. | S23: S. Miguel : Lit. dos Açores | T23: 1880 | U23: 1880 | Z23: Camões, Luís de, 1524-1580, Antecedente bibliográfico | AB23: Sociedade Amizade Recreio e Ínstrução | AC23: CAM. 64//4 A. | AD23: CAM500 | AE23: http://id.bnportugal.gov.pt/bib/catbnp/386992 | AF23: Livre
A24: 396405 | B24: 1 | C24: 1 | D24: https://permalinkbnd.bnportugal.gov.pt/viewer/36059/?offset=#page=1&viewer=picture&o=info&n=0&q= | E24: 1 | I24: 396405 | J24: https://purl.pt/6115 | K24: https://bndigital.bnportugal.gov.pt//i/?IIIF=/11/21/33/35/11213335-0c6f-4347-8501-397d47049e54/iiif/e-2172-v_0000_1-2_p24-C-R0150_000001.tif/full/!300,500/0/default.jpg | L24: Iconografia | M24: Português | O24: Luís de Camões | R24: 1.ª ed. | S24: Macau : Com. Org. Comem. Dia de Portugal de Camões e das Comunid. Portuguesas | T24: 1992 | U24: 1992 | V24: 1 imagem | W24: Fialho, Fernando Jorge, 1965- | AC24: PURL 6115/0 | AE24: http://id.bnportugal.gov.pt/bib/catbnp/396405 | AF24: Interno
A25: 397670 | B25: 1 | C25: 11 | D25: https://permalinkbnd.bnportugal.gov.pt/viewer/273150/?offset=#page=11&viewer=picture&o=info&n=0&q= | E25: 11, 13 [apontamento sobre o Centenário de Camões, site?] | I25: 397670 | J25: https://purl.pt/43874 | K25: https://bndigital.bnportugal.gov.pt//i/?IIIF=/f4/b1/c2/b3/f4b1c2b3-f0bb-4cb4-b767-93d0dae46bc3/iiif/cam-70-v_0000_000007.tif/full/!300,500/0/default.jpg | L25: Livro impresso | M25: Português ; Francês | O25: Episodio da Ilha de Venus extrahido dos Lusiadas de Camões | R25: 1.ª ed. | S25: Braga : Typ. Lealdade : Sociedade Democrática Recreativa | T25: 1880 | U25: 1880 | V25: 23 p. | W25: Camões, Luís de, 1524-1580 | Z25: Caldas, José Joaquim da Silva Pereira, 1818-1903, Autor da introdução, etc. ; Cournand, Antoine de, Autor da introdução, etc. | AC25: L. 5895//9 A | AD25: CAM500 | AE25: http://id.bnportugal.gov.pt/bib/catbnp/397670 | AF25: Livre
A26: 397818 | B26: 1 | C26: 6 | D26: https://permalinkbnd.bnportugal.gov.pt/viewer/272368/?offset=#page=6&viewer=picture&o=info&n=0&q= | E26: 6, 106 [retrato de Camões, padrão levantado por Vasco da Gama] | I26: 397818 | J26: https://purl.pt/43426 | K26: https://bndigital.bnportugal.gov.pt//i/?IIIF=/58/13/66/39/58136639-f7f1-4612-94b8-d6a78a970d34/iiif/cam-707-p_0007.tif/full/!300,500/0/default.jpg | L26: Livro impresso | M26: Português | O26: Os Lusíadas | P26: poema épico | R26: Nova ed., cuidadosamente revista | S26: Lisboa : Livraria de António Maria Pereira | T26: 1891 | U26: 1891 | V26: XVIII, 457 p., 2 est. | W26: Camões, Luís de, 1524-1580 | Z26: Silva, Inocêncio Francisco da, 1810-1876, Autor da introdução, etc. | AC26: CAM. 707 P. | AD26: CAM500 | AE26: http://id.bnportugal.gov.pt/bib/catbnp/397818 | AF26: Livre
A27: 397822 | B27: 1 | C27: 7 | D27: https://permalinkbnd.bnportugal.gov.pt/viewer/274090/?offset=#page=7&viewer=picture&o=info&n=0&q= | E27: 7, 388 [apontamento site] | I27: 397822 | J27: https://purl.pt/43741 | K27: https://bndigital.bnportugal.gov.pt//i/?IIIF=/53/07/f6/e6/5307f6e6-7747-45f0-8d9c-435d2871d068/iiif/cam-35-v_0007.tif/full/!300,500/0/default.jpg | L27: Livro impresso | M27: Português | O27: Os Lusíadas | R27: Ed. comemorativa do IV Centenário do Descobrimento Marítimo da India | S27: Lisboa : Typographia do Commercio | T27: 1898 | U27: 1898 | V27: 186 fls. | W27: Camões, Luís de, 1524-1580 | AC27: CAM. 35 V. | AD27: CAM500 | AE27: http://id.bnportugal.gov.pt/bib/catbnp/397822 | AF27: Livre
A28: 397852 | B28: 1 | C28: 14 | D28: https://permalinkbnd.bnportugal.gov.pt/viewer/274172/?offset=#page=14&viewer=picture&o=info&n=0&q= | E28: 14 [vinheta site] | I28: 397852 | J28: https://purl.pt/43811 | K28: https://bndigital.bnportugal.gov.pt//i/?IIIF=/97/d2/74/d0/97d274d0-35d0-4540-bdbb-0b1af3d4ba91/iiif/cam-45-v_0005.tif/full/!300,500/0/default.jpg | L28: Livro impresso | M28: Francês ; Português | O28: Les Lusiades | P28: chant primier | R28: Edition commemorative du septieme anniversaire du tricentenaire de Camöes | S28: Lisboa : Imprensa Nacional | T28: 1887 | U28: 1887 | V28: 79 p. | W28: Camões, Luís de, 1524-1580 | Z28: Courtois, Henri de, Tradutor | AC28: L. 5907//7 A. | AD28: CAM500 | AE28: http://id.bnportugal.gov.pt/bib/catbnp/397852 | AF28: Livre
A29: 397863 | B29: 1 | C29: 11 | D29: https://permalinkbnd.bnportugal.gov.pt/viewer/273148/?offset=#page=11&viewer=picture&o=info&n=0&q= | E29: 11 [portada] | I29: 397863 | J29: https://purl.pt/43931 | K29: https://bndigital.bnportugal.gov.pt//i/?IIIF=/c3/91/eb/4c/c391eb4c-8bd2-4992-a05f-625f8ef77ebc/iiif/cam-69-v_0000_000001.tif/full/!300,500/0/default.jpg | L29: Livro impresso | M29: Português | O29: A Ode de Luiz de Camões ao Conde do Redondo, restituida á sua primitiva licção | R29: Edição commemorativa do 4º anniversario do Tricentenario Camoniano | S29: Lisboa : Typographia Elzeviriana | T29: 1884 | U29: 1884 | V29: 22, 2 p. | W29: Camões, Luís de, 1524-1580 | Z29: Cunha, Xavier da, 1840-1920, Editor literário ; Carvalho, Alfredo de, fl. 1884, Tipógrafo | AC29: CAM. 69 V. | AD29: CAM500 | AE29: http://id.bnportugal.gov.pt/bib/catbnp/397863 | AF29: Livre
A30: 397876 | B30: 1 | C30: 9 | D30: https://permalinkbnd.bnportugal.gov.pt/viewer/274230/?offset=#page=9&viewer=picture&o=info&n=0&q= | E30: 9 | I30: 397876 | J30: https://purl.pt/43825 | K30: https://bndigital.bnportugal.gov.pt//i/?IIIF=/de/b5/45/9c/deb5459c-316c-4583-bb29-fa7038aaebdc/iiif/cam-59-v_0009.tif/full/!300,500/0/default.jpg | L30: Livro impresso | M30: Francês | N30: Português | O30: Sonnets choisis | R30: 1.ª ed. | S30: Paris : Plon | T30: 1879 | U30: 1879 | V30: VII, 40 p. | W30: Camões, Luís de, 1524-1580 | Z30: Cazaubon, Léonce, Tradutor | AC30: CAM. 59 V. | AD30: CAM500 | AE30: http://id.bnportugal.gov.pt/bib/catbnp/397876 | AF30: Livre
A31: 397877 | B31: 1 | C31: 9 | D31: https://permalinkbnd.bnportugal.gov.pt/viewer/1576/?offset=#page=9&viewer=picture&o=info&n=0&q= | E31: 9 [retrato de Camões] | I31: 397877 | J31: https://purl.pt/43875 | K31: https://bndigital.bnportugal.gov.pt//i/?IIIF=/3a/34/50/28/3a345028-610d-4c37-af11-98e95904bfe5/iiif/cam-75-1-v_0000_000001.tif/full/!300,500/0/default.jpg | L31: Livro impresso | M31: Português | O31: Tercetos impressos pela primeira vez, em 1576, na História da Província de Santa Cruz, de Pedro de Magalhães Gandavo | R31: 1.ª ed. | S31: Lisboa : Joaquim Eusébio dos Santos | T31: 1894 | U31: 1894 | V31: 12 p., 1 est. | W31: Camões, Luís de, 1524-1580 | Z31: Braga, Teófilo, 1843-1924, Comentador (em meio audiovisual) | AC31: CAM. 75//1 V. | AD31: CAM500 | AE31: http://id.bnportugal.gov.pt/bib/catbnp/397877 | AF31: Livre
A32: 401648 | B32: 1 | C32: 3 | D32: https://permalinkbnd.bnportugal.gov.pt/viewer/273125/?offset=#page=3&viewer=picture&o=info&n=0&q= | E32: 1, 3 [site] [portada, retrato Camões] | I32: 401648 | J32: https://purl.pt/43662 | K32: https://bndigital.bnportugal.gov.pt//i/?IIIF=/c5/6f/77/dc/c56f77dc-6fe1-4b19-8eac-61a13ea62b02/iiif/cam-64-7-a_0000_000001.tif/full/!300,500/0/default.jpg | L32: Periódico | M32: Português | O32: Plutarcho portuguez | P32: colecção de retratos e biographias dos principaes vultos historicos da civilisação portugueza | R32: 1.ª ed. | S32: Porto : Julio Costa, Emilio Biel | T32: 1881 | U32: 1881 | AC32: J. 1690//7 V. | AD32: CAM500 | AE32: http://id.bnportugal.gov.pt/bib/catbnp/401648 | AF32: Livre
A33: 401658 | B33: 1 | C33: 1 | D33: https://permalinkbnd.bnportugal.gov.pt/viewer/3/?offset=#page=1&viewer=picture&o=info&n=0&q= | E33: 1 | I33: 401658 | J33: https://purl.pt/43862 | K33: https://bndigital.bnportugal.gov.pt//i/?IIIF=/9e/f3/33/17/9ef33317-4c7f-4371-8da7-082d54e2724e/iiif/cam-66-2-a_0001.tif/full/!300,500/0/default.jpg | L33: Livro impresso | M33: Português | O33: Victor Hugo a Camões no 3º centenário | R33: 1.ª ed. | S33: Lisboa : J. Camilo Videira | T33: 1880 | U33: 1880 | AC33: CAM. 66//2 A. | AD33: CAM500 | AE33: http://id.bnportugal.gov.pt/bib/catbnp/401658 | AF33: Livre
A34: 401739 | B34: 1 | C34: 1 | D34: https://permalinkbnd.bnportugal.gov.pt/viewer/274260/?offset=#page=1&viewer=picture&o=info&n=0&q= | E34: 1 | I34: 401739 | J34: https://purl.pt/43865 | K34: https://bndigital.bnportugal.gov.pt//i/?IIIF=/2d/fe/15/07/2dfe1507-1025-44a9-b149-33c026517803/iiif/cam-66-5-a_0001.tif/full/!300,500/0/default.jpg | L34: Livro impresso | M34: Português | O34: Homenagem ao príncipe dos poetas peninsulares ao reconstrutor da língua portuguesa, a Luís de Camões | R34: 1.ª ed. | S34: Lisboa : Emp. Dic. Univ. Português | T34: 1880 | U34: 1880 | V34: 4 p. | AC34: CAM. 66//5 A. | AD34: CAM500 | AE34: http://id.bnportugal.gov.pt/bib/catbnp/401739 | AF34: Livre
A35: 402086 | B35: 1 | C35: 16 | D35: https://permalinkbnd.bnportugal.gov.pt/viewer/274280/?offset=#page=16&viewer=picture&o=info&n=0&q= | E35: 16 [site], 22 | I35: 402086 | J35: https://purl.pt/43891 | K35: https://bndigital.bnportugal.gov.pt//i/?IIIF=/dc/d1/27/77/dcd12777-3117-4eb1-94d0-a5bb23f4e7b6/iiif/cam-69-a_0005.tif/full/!300,500/0/default.jpg | L35: Livro impresso | M35: Português | O35: Collecção Camoneana de José do Canto | P35: tentativa de um catalogo methodico e remissivo | R35: 1.ª ed. | S35: Lisboa : Imprensa Nacional | T35: 1895 | U35: 1895 | V35: XI, 357, 5 p. | W35: Canto, José do, 1820-1898 | Z35: Reis, Jaime Batalha, 1847-1935, Antigo possuidor | AC35: CAM. 69 A. | AD35: CAM500 | AE35: http://id.bnportugal.gov.pt/bib/catbnp/402086 | AF35: Livre
A36: 402086 | B36: 1 | C36: 22 | D36: https://permalinkbnd.bnportugal.gov.pt/viewer/274280/?offset=#page=22&viewer=picture&o=info&n=0&q= | E36: 16 [site], 22 | I36: 402086 | J36: https://purl.pt/43891 | K36: https://bndigital.bnportugal.gov.pt//i/?IIIF=/dc/d1/27/77/dcd12777-3117-4eb1-94d0-a5bb23f4e7b6/iiif/cam-69-a_0005.tif/full/!300,500/0/default.jpg | L36: Livro impresso | M36: Português | O36: Collecção Camoneana de José do Canto | P36: tentativa de um catalogo methodico e remissivo | R36: 1.ª ed. | S36: Lisboa : Imprensa Nacional | T36: 1895 | U36: 1895 | V36: XI, 357, 5 p. | W36: Canto, José do, 1820-1898 | Z36: Reis, Jaime Batalha, 1847-1935, Antigo possuidor | AC36: CAM. 69 A. | AD36: CAM500 | AE36: http://id.bnportugal.gov.pt/bib/catbnp/402086 | AF36: Livre
A37: 402917 | B37: 1 | C37: 9 | D37: https://permalinkbnd.bnportugal.gov.pt/viewer/273560/?offset=#page=9&viewer=picture&o=info&n=0&q= | E37: 9 | I37: 402917 | J37: https://purl.pt/43923 | K37: https://bndigital.bnportugal.gov.pt//i/?IIIF=/68/36/f7/0d/6836f70d-c35f-47cf-856b-993a65ff926c/iiif/cam-130-a_0000_000001.tif/full/!300,500/0/default.jpg | L37: Livro impresso | M37: Português | N37: Alemão | O37: Camoëns in Cintra | P37: (poemeto extrahido do livro Tag und Nachstucke) | R37: 1.ª ed. | S37: Lisboa : M. Gomes, Livreiro-Editor | T37: 1891 | U37: 1891 | V37: 39, 1 p. | W37: Schack, Adolf Friederich Graf von, 1815-1894 | Z37: Camões, Luís de, 1524-1580, Antecedente bibliográfico | AC37: CAM. 71//1 A. | AD37: CAM500 | AE37: http://id.bnportugal.gov.pt/bib/catbnp/402917 | AF37: Livre
A38: 404543 | B38: 1 | C38: 7 | D38: https://permalinkbnd.bnportugal.gov.pt/viewer/273347/?offset=#page=7&viewer=picture&o=info&n=0&q= | E38: 7 | I38: 404543 | J38: https://purl.pt/43827 | K38: https://bndigital.bnportugal.gov.pt//i/?IIIF=/9f/79/bf/47/9f79bf47-41ea-438e-b7e9-2c631c46bb91/iiif/cam-81-a_0000_000001.tif/full/!300,500/0/default.jpg | L38: Livro impresso | M38: Português | O38: Excerptos dos Lusíadas | P38: canto II | R38: 1.ª ed. | S38: Lisboa : Imprensa Nacional | T38: 1889 | U38: 1889 | W38: Camões, Luís de, 1524-1580 | AC38: CAM. 81 A. | AD38: CAM500 | AE38: http://id.bnportugal.gov.pt/bib/catbnp/404543 | AF38: Livre
A39: 404800 | B39: 1 | C39: 21 | D39: https://permalinkbnd.bnportugal.gov.pt/viewer/274348/?offset=#page=21&viewer=picture&o=info&n=0&q= | E39: 3, 21, 69 | I39: 404800 | J39: https://purl.pt/43914 | K39: https://bndigital.bnportugal.gov.pt//i/?IIIF=/1f/06/28/af/1f0628af-b385-4108-b72c-0016b004b60d/iiif/cam-85-a_0003.tif/full/!300,500/0/default.jpg | L39: Livro impresso | M39: Português | O39: Os festejos do centenario da India | P39: grande album commemorativo | R39: 1.ª ed. | S39: Lisboa : publicado pela empreza do Pimpão | T39: 1898 | U39: 1898 | V39: 31 f. | AC39: CAM. 85 A. | AD39: CAM500 | AE39: http://id.bnportugal.gov.pt/bib/catbnp/404800 | AF39: Livre
A40: 404800 | B40: 1 | C40: 69 | D40: https://permalinkbnd.bnportugal.gov.pt/viewer/274348/?offset=#page=69&viewer=picture&o=info&n=0&q= | E40: 3, 21, 69 | I40: 404800 | J40: https://purl.pt/43914 | K40: https://bndigital.bnportugal.gov.pt//i/?IIIF=/1f/06/28/af/1f0628af-b385-4108-b72c-0016b004b60d/iiif/cam-85-a_0003.tif/full/!300,500/0/default.jpg | L40: Livro impresso | M40: Português | O40: Os festejos do centenario da India | P40: grande album commemorativo | R40: 1.ª ed. | S40: Lisboa : publicado pela empreza do Pimpão | T40: 1898 | U40: 1898 | V40: 31 f. | AC40: CAM. 85 A. | AD40: CAM500 | AE40: http://id.bnportugal.gov.pt/bib/catbnp/404800 | AF40: Livre
A41: 410449 | B41: 1 | C41: 6 | D41: https://permalinkbnd.bnportugal.gov.pt/viewer/274346/?offset=#page=6&viewer=picture&o=info&n=0&q= | E41: 6 [site] | I41: 410449 | J41: https://purl.pt/43911 | K41: https://bndigital.bnportugal.gov.pt//i/?IIIF=/37/17/31/09/37173109-2f71-495e-bea5-e4ca2470680c/iiif/cam-96-a_0007.tif/full/!300,500/0/default.jpg | L41: Livro impresso | M41: Espanhol | N41: Português | O41: Os Lusiadas (Los Portugueses) | R41: Edicion acompañada del legitimo texto portugues y de copiosas notas y noticias biograficas sobre el insigne poeta ibero | S41: Badajoz : Establecimiento Tipográfico de José Santamaría | T41: 1873 | U41: 1873 | V41: 263, 1 p. | W41: Camões, Luís de, 1524-1580 | Z41: Soler y Arqués, Carlos, 1836-1896, Tradutor | AC41: CAM. 96 A. | AD41: CAM500 | AE41: http://id.bnportugal.gov.pt/bib/catbnp/410449 | AF41: Livre
A42: 411542 | B42: 1 | C42: 1 | D42: https://permalinkbnd.bnportugal.gov.pt/viewer/273798/?offset=#page=1&viewer=picture&o=info&n=0&q= | E42: 1 | I42: 411542 | J42: https://purl.pt/43786 | K42: https://bndigital.bnportugal.gov.pt//i/?IIIF=/b5/4f/7e/1e/b54f7e1e-307d-47a6-9282-e41a7c32124d/iiif/cam-221-3-v_0000_000001.tif/full/!300,500/0/default.jpg | L42: Livro impresso | M42: Português | O42: O centenario no estrangeiro | P42: conferencia realisada na Sociedade de Geographia de Lisboa no dia 11 de Novembro de 1897 | R42: 1.ª ed. | S42: Lisboa : A Liberal | T42: 1897 | U42: 1897 | V42: 30, 1 p. | W42: Lima, Magalhães, 1850-1928 | Z42: Vilhena, Ernesto Jardim de, 1876-1967, Antigo possuidor | AC42: H.G. 5865//1 A. | AD42: CAM500 | AE42: http://id.bnportugal.gov.pt/bib/catbnp/411542 | AF42: Livre
A43: 426512 | B43: 1 | C43: 1 | D43: https://permalinkbnd.bnportugal.gov.pt/viewer/272882/?offset=#page=1&viewer=picture&o=info&n=0&q= | E43: 1 | I43: 426512 | J43: https://purl.pt/43588 | K43: https://bndigital.bnportugal.gov.pt//i/?IIIF=/ed/9c/ac/ac/ed9cacac-104b-435c-b7cc-8aa38ac8bca3/iiif/426512_0001.tif/full/!300,500/0/default.jpg | L43: Livro impresso | M43: Português | O43: Homenagem a Camões | P43: melodia para piano | R43: 1.ª ed. | S43: Lisboa : s.n. | T43: 1870 | U43: 1870 | V43: 1 partitura (2 p.) | W43: Pacheco, Maria Cornélia de Melo de Castro | AC43: C.I.C. 142 A. | AD43: PRR2022 | AE43: http://id.bnportugal.gov.pt/bib/catbnp/426512 | AF43: Livre
A44: 446302 | B44: 1 | C44: 11 | D44: https://permalinkbnd.bnportugal.gov.pt/viewer/1880/?offset=#page=11&viewer=picture&o=info&n=0&q= | E44: 11 | I44: 446302 | J44: https://purl.pt/43429 | K44: https://bndigital.bnportugal.gov.pt//i/?IIIF=/c1/c1/f9/e2/c1c1f9e2-a3e8-476d-a59f-c07a10de4bed/iiif/cam-516-v_0011.tif/full/!300,500/0/default.jpg | L44: Livro impresso | M44: Português | O44: Primeiros documentos para a historia do Jubileu Nacional de 1880 | R44: 1.ª ed. | S44: Lisboa : Impr. Nacional | T44: 1887 | U44: 1887 | V44: 29 p. | AB44: Sociedade de Geografia de Lisboa, Editor literário | AC44: H.G. 18363//4 V. | AD44: CAM500 | AE44: http://id.bnportugal.gov.pt/bib/catbnp/446302 | AF44: Livre
A45: 452363 | B45: 1 | C45: 1 | D45: https://permalinkbnd.bnportugal.gov.pt/viewer/35644/?offset=#page=1&viewer=picture&o=info&n=0&q= | E45: 1 site | I45: 452363 | J45: https://purl.pt/11841 | K45: https://bndigital.bnportugal.gov.pt//i/?IIIF=/b5/32/68/9d/b532689d-3818-4d28-ab3a-df022c3eb88e/iiif/e-1029-a_0000_000001.tif/full/!300,500/0/default.jpg | L45: Iconografia | M45: Português | O45: Camões | R45: 1.ª ed. | S45: S.l. : s.n. | T45: 1887 | U45: 1887 | V45: 1 gravura | W45: David, Lubin, fl. ca 1887 | Z45: Champollion, Eugène-André, 1848-1901, Gravador em metal ; Salmon, Louis Adolphe, 1806-1895, Impressor de ilustrações em chapa gravada | AC45: PURL 11841/0 | AE45: http://id.bnportugal.gov.pt/bib/catbnp/452363 | AF45: Livre
A46: 453897 | B46: 1 | C46: 9 | D46: https://permalinkbnd.bnportugal.gov.pt/viewer/1880/?offset=#page=9&viewer=picture&o=info&n=0&q= | E46: 9 | I46: 453897 | J46: https://purl.pt/43792 | K46: https://bndigital.bnportugal.gov.pt//i/?IIIF=/7e/2c/17/63/7e2c1763-4416-4162-88ba-4e958901ed3d/iiif/cam-384-9-v_0000_000001.tif/full/!300,500/0/default.jpg | L46: Livro impresso | M46: Português | O46: Á memoria de Luiz de Camões no seu tricentenario em 10 de Junho de 1880... | R46: 1.ª ed. | S46: Braga : Typ. de Gonçalves Gouvea | T46: 1880 | U46: 1880 | V46: 16 p. | AC46: CAM. 384//9 V. | AD46: CAM500 | AE46: http://id.bnportugal.gov.pt/bib/catbnp/453897 | AF46: Livre
A47: 454218 | B47: 1 | C47: 3 | D47: https://permalinkbnd.bnportugal.gov.pt/viewer/273923/?offset=#page=3&viewer=picture&o=info&n=0&q= | E47: 3 | I47: 454218 | J47: https://purl.pt/43793 | K47: https://bndigital.bnportugal.gov.pt//i/?IIIF=/a4/54/ba/df/a454badf-dc23-49b9-8ac1-fff9a72f6856/iiif/cam-386-6-v_0000_000001.tif/full/!300,500/0/default.jpg | L47: Livro impresso | M47: Português | O47: Vida de Luiz de Camões e seu retrato | R47: 1.ª ed. | S47: Coimbra : Impr. Academica | T47: 1881 | U47: 1881 | V47: 15 p. | AC47: CAM. 386//6 V. | AD47: CAM500 | AE47: http://id.bnportugal.gov.pt/bib/catbnp/454218 | AF47: Livre
A48: 455268 | B48: 1 | C48: 8 | D48: https://permalinkbnd.bnportugal.gov.pt/viewer/270331/?offset=#page=8&viewer=picture&o=info&n=0&q= | E48: 8, 62 [1.º: retrato de Camões e visita do Rei de Melinde a V. da Gama] 8 [2.º: Vasco da Gama em Calecute] | I48: 455268 | J48: https://purl.pt/42934 | K48: https://bndigital.bnportugal.gov.pt//i/?IIIF=/e0/e2/36/8e/e0e2368e-06b5-4efd-bb33-762145de2b06/iiif/cam-408-v_0000_000011.tif/full/!300,500/0/default.jpg | L48: Livro impresso | M48: Italiano | N48: Português | O48: I Lusiadi | R48: Seconde edizione illustrata con note di D. B. | S48: Milano : Societá Tipog. dei Classici Italiani | T48: 1821 | U48: 1821 | V48: XXXX, 517, 1 p. (2 v.) | W48: Camões, Luís de, 1524-1580 | Z48: Nervi, Antonio, 1760-1836, Tradutor | AC48: CAM. 408 V. | AD48: CAM500 | AE48: http://id.bnportugal.gov.pt/bib/catbnp/455268 | AF48: Livre
A49: 455268 | B49: 1 | C49: 62 | D49: https://permalinkbnd.bnportugal.gov.pt/viewer/270331/?offset=#page=62&viewer=picture&o=info&n=0&q= | E49: 8, 62 [1.º: retrato de Camões e visita do Rei de Melinde a V. da Gama] 8 [2.º: Vasco da Gama em Calecute] | F49: Episódios - Visita do Rei de Melinde a Gama|1808 | I49: 455268 | J49: https://purl.pt/42934 | K49: https://bndigital.bnportugal.gov.pt//i/?IIIF=/e0/e2/36/8e/e0e2368e-06b5-4efd-bb33-762145de2b06/iiif/cam-408-v_0000_000011.tif/full/!300,500/0/default.jpg | L49: Livro impresso | M49: Italiano | N49: Português | O49: I Lusiadi | R49: Seconde edizione illustrata con note di D. B. | S49: Milano : Societá Tipog. dei Classici Italiani | T49: 1821 | U49: 1821 | V49: XXXX, 517, 1 p. (2 v.) | W49: Camões, Luís de, 1524-1580 | Z49: Nervi, Antonio, 1760-1836, Tradutor | AC49: CAM. 408 V. | AD49: CAM500 | AE49: http://id.bnportugal.gov.pt/bib/catbnp/455268 | AF49: Livre
A50: 455268 | B50: 2 | C50: 8 | D50: https://permalinkbnd.bnportugal.gov.pt/viewer/270331/?offset=#page=8&viewer=picture&o=info&n=0&q= | E50: 8, 62 [1.º: retrato de Camões e visita do Rei de Melinde a V. da Gama] 8 [2.º: Vasco da Gama em Calecute] | F50: Episódios - Desembarque de Gama em Calecut|1814 | I50: 455268 | J50: https://purl.pt/42934 | K50: https://bndigital.bnportugal.gov.pt//i/?IIIF=/e0/e2/36/8e/e0e2368e-06b5-4efd-bb33-762145de2b06/iiif/cam-408-v_0000_000011.tif/full/!300,500/0/default.jpg | L50: Livro impresso | M50: Italiano | N50: Português | O50: I Lusiadi | R50: Seconde edizione illustrata con note di D. B. | S50: Milano : Societá Tipog. dei Classici Italiani | T50: 1821 | U50: 1821 | V50: XXXX, 517, 1 p. (2 v.) | W50: Camões, Luís de, 1524-1580 | Z50: Nervi, Antonio, 1760-1836, Tradutor | AC50: CAM. 408 V. | AD50: CAM500 | AE50: http://id.bnportugal.gov.pt/bib/catbnp/455268 | AF50: Livre
A51: 455275 | B51: 1 | C51: 10 | D51: https://permalinkbnd.bnportugal.gov.pt/viewer/270345/?offset=#page=10&viewer=picture&o=info&n=0&q= | E51: 10, 13 [1.º: retrato de Camões, portada, 426 apontamento caravela; 3.º: 154, apontamento site] | I51: 455275 | J51: https://purl.pt/42943 | K51: https://bndigital.bnportugal.gov.pt//i/?IIIF=/5d/28/c9/4e/5d28c94e-b940-4e81-8f76-f7b1ef6f5a4b/iiif/cam-410-v_0000_000013.tif/full/!300,500/0/default.jpg | L51: Livro impresso | M51: Português | O51: Obras completas de Luis de Camões | R51: 1.ª ed. | S51: Lisboa : s.n. | T51: 1843 | U51: 1843 | V51: 3 t. | W51: Camões, Luís de, 1524-1580 | Z51: Feio, José Vitorino Barreto, 1782-1850, Compilador ; Monteiro, José Gomes, 1807-1879, Compilador | AC51: CAM. 410 V. | AD51: CAM500 | AE51: http://id.bnportugal.gov.pt/bib/catbnp/455275 | AF51: Livre
A52: 458290 | B52: 1 | C52: 10 | D52: https://permalinkbnd.bnportugal.gov.pt/viewer/273525/?offset=#page=10&viewer=picture&o=info&n=0&q= | E52: 10, 11 [7, 15 e 37 apontamentos site] | I52: 458290 | J52: https://purl.pt/43921 | K52: https://bndigital.bnportugal.gov.pt//i/?IIIF=/3d/ef/d5/dc/3defd5dc-8364-472f-9969-dc10b3471470/iiif/cam-129-a_0000_000011.tif/full/!300,500/0/default.jpg | L52: Livro impresso | M52: Português ; Francês | N52: Português | O52: A ilha de Venus | P52: episodio extrahido do nono canto dos Lusiadas | R52: 1.ª ed. | S52: Porto : Livraria Camões de Fernandes Possas | T52: 1890 | U52: 1890 | V52: VII, 1 br., 38, 2 p. | W52: Camões, Luís de, 1524-1580 | Z52: Baour-Lormian, P. L. M., 1770-1854, Tradutor ; Grandmaison, M. Parsival, Tradutor ; Aranha, Brito, 1833-1914, Antigo possuidor | AC52: CAM. 129 A. | AD52: CAM500 | AE52: http://id.bnportugal.gov.pt/bib/catbnp/458290 | AF52: Livre
A53: 458655 | B53: 1 | C53: 11 | D53: https://permalinkbnd.bnportugal.gov.pt/viewer/270116/?offset=#page=11&viewer=picture&o=info&n=0&q= | E53: 5, 11 [1.º: imagem, portada], 5 [2.º retrato de Camões], 12 [3.º: partida de V. da Gama para a Índia], 12 [4.º: O espírito do Cabo surge à frota de V. da Gama], 11 [7.º: portada], 12 [8.º: Ilha dos Amores] | I53: 458655 | J53: https://purl.pt/42928 | K53: https://bndigital.bnportugal.gov.pt//i/?IIIF=/c4/0f/74/3f/c40f743f-cbf4-4bf9-8481-bce3fdf02c38/iiif/cam-152-a_0000_000011.tif/full/!300,500/0/default.jpg | L53: Livro impresso | M53: Português | O53: Florilegio camoneano | R53: 1.ª ed. | S53: Porto : Livr. Camões | T53: 1887 | U53: 1887 | V53: 8 T. | AC53: CAM. 152 A. | AD53: CAM500 | AE53: http://id.bnportugal.gov.pt/bib/catbnp/458655 | AF53: Livre
A54: 458655 | B54: 2 | C54: 5 | D54: https://permalinkbnd.bnportugal.gov.pt/viewer/270116/?offset=#page=5&viewer=picture&o=info&n=0&q= | E54: 5, 11 [1.º: imagem, portada], 5 [2.º retrato de Camões], 12 [3.º: partida de V. da Gama para a Índia], 12 [4.º: O espírito do Cabo surge à frota de V. da Gama], 11 [7.º: portada], 12 [8.º: Ilha dos Amores] | I54: 458655 | J54: https://purl.pt/42928 | K54: https://bndigital.bnportugal.gov.pt//i/?IIIF=/c4/0f/74/3f/c40f743f-cbf4-4bf9-8481-bce3fdf02c38/iiif/cam-152-a_0000_000011.tif/full/!300,500/0/default.jpg | L54: Livro impresso | M54: Português | O54: Florilegio camoneano | R54: 1.ª ed. | S54: Porto : Livr. Camões | T54: 1887 | U54: 1887 | V54: 8 T. | AC54: CAM. 152 A. | AD54: CAM500 | AE54: http://id.bnportugal.gov.pt/bib/catbnp/458655 | AF54: Livre
A55: 458655 | B55: 2 | C55: 12 | D55: https://permalinkbnd.bnportugal.gov.pt/viewer/270116/?offset=#page=12&viewer=picture&o=info&n=0&q= | E55: 5, 11 [1.º: imagem, portada], 5 [2.º retrato de Camões], 12 [3.º: partida de V. da Gama para a Índia], 12 [4.º: O espírito do Cabo surge à frota de V. da Gama], 11 [7.º: portada], 12 [8.º: Ilha dos Amores] | I55: 458655 | J55: https://purl.pt/42928 | K55: https://bndigital.bnportugal.gov.pt//i/?IIIF=/c4/0f/74/3f/c40f743f-cbf4-4bf9-8481-bce3fdf02c38/iiif/cam-152-a_0000_000011.tif/full/!300,500/0/default.jpg | L55: Livro impresso | M55: Português | O55: Florilegio camoneano | R55: 1.ª ed. | S55: Porto : Livr. Camões | T55: 1887 | U55: 1887 | V55: 8 T. | AC55: CAM. 152 A. | AD55: CAM500 | AE55: http://id.bnportugal.gov.pt/bib/catbnp/458655 | AF55: Livre
A56: 458655 | B56: 2 | C56: 12 | D56: https://permalinkbnd.bnportugal.gov.pt/viewer/270116/?offset=#page=12&viewer=picture&o=info&n=0&q= | E56: 5, 11 [1.º: imagem, portada], 5 [2.º retrato de Camões], 12 [3.º: partida de V. da Gama para a Índia], 12 [4.º: O espírito do Cabo surge à frota de V. da Gama], 11 [7.º: portada], 12 [8.º: Ilha dos Amores] | I56: 458655 | J56: https://purl.pt/42928 | K56: https://bndigital.bnportugal.gov.pt//i/?IIIF=/c4/0f/74/3f/c40f743f-cbf4-4bf9-8481-bce3fdf02c38/iiif/cam-152-a_0000_000011.tif/full/!300,500/0/default.jpg | L56: Livro impresso | M56: Português | O56: Florilegio camoneano | R56: 1.ª ed. | S56: Porto : Livr. Camões | T56: 1887 | U56: 1887 | V56: 8 T. | AC56: CAM. 152 A. | AD56: CAM500 | AE56: http://id.bnportugal.gov.pt/bib/catbnp/458655 | AF56: Livre
A57: 458655 | B57: 3 | C57: 11 | D57: https://permalinkbnd.bnportugal.gov.pt/viewer/270116/?offset=#page=11&viewer=picture&o=info&n=0&q= | E57: 5, 11 [1.º: imagem, portada], 5 [2.º retrato de Camões], 12 [3.º: partida de V. da Gama para a Índia], 12 [4.º: O espírito do Cabo surge à frota de V. da Gama], 11 [7.º: portada], 12 [8.º: Ilha dos Amores] | I57: 458655 | J57: https://purl.pt/42928 | K57: https://bndigital.bnportugal.gov.pt//i/?IIIF=/c4/0f/74/3f/c40f743f-cbf4-4bf9-8481-bce3fdf02c38/iiif/cam-152-a_0000_000011.tif/full/!300,500/0/default.jpg | L57: Livro impresso | M57: Português | O57: Florilegio camoneano | R57: 1.ª ed. | S57: Porto : Livr. Camões | T57: 1887 | U57: 1887 | V57: 8 T. | AC57: CAM. 152 A. | AD57: CAM500 | AE57: http://id.bnportugal.gov.pt/bib/catbnp/458655 | AF57: Livre
A58: 458655 | B58: 3 | C58: 12 | D58: https://permalinkbnd.bnportugal.gov.pt/viewer/270116/?offset=#page=12&viewer=picture&o=info&n=0&q= | E58: 5, 11 [1.º: imagem, portada], 5 [2.º retrato de Camões], 12 [3.º: partida de V. da Gama para a Índia], 12 [4.º: O espírito do Cabo surge à frota de V. da Gama], 11 [7.º: portada], 12 [8.º: Ilha dos Amores] | I58: 458655 | J58: https://purl.pt/42928 | K58: https://bndigital.bnportugal.gov.pt//i/?IIIF=/c4/0f/74/3f/c40f743f-cbf4-4bf9-8481-bce3fdf02c38/iiif/cam-152-a_0000_000011.tif/full/!300,500/0/default.jpg | L58: Livro impresso | M58: Português | O58: Florilegio camoneano | R58: 1.ª ed. | S58: Porto : Livr. Camões | T58: 1887 | U58: 1887 | V58: 8 T. | AC58: CAM. 152 A. | AD58: CAM500 | AE58: http://id.bnportugal.gov.pt/bib/catbnp/458655 | AF58: Livre
A59: 465606 | B59: 1 | C59: 3 | D59: https://permalinkbnd.bnportugal.gov.pt/viewer/274117/?offset=#page=3&viewer=picture&o=info&n=0&q= | E59: 3 | I59: 465606 | J59: https://purl.pt/43836 | K59: https://bndigital.bnportugal.gov.pt//i/?IIIF=/42/cd/d2/e6/42cdd2e6-50ac-44e8-a7c5-107037a0f860/iiif/cam-674-v_0000_000003.tif/full/!300,500/0/default.jpg | L59: Livro impresso | M59: Inglês | O59: Sonnets | R59: 1.ª ed. | S59: Newcastle upon Tinet : Impr. by M. A. Richardson | T59: 1845 | U59: 1845 | V59: 16 p. | W59: Adamson, John, 1787-1851 | Z59: Sucena, 1850-?, Antigo possuidor | AC59: CAM. 674 V. | AD59: CAM500 | AE59: http://id.bnportugal.gov.pt/bib/catbnp/465606 | AF59: Livre
A60: 471392 | B60: 1 | C60: 5 | D60: https://permalinkbnd.bnportugal.gov.pt/viewer/274153/?offset=#page=5&viewer=picture&o=info&n=0&q= | E60: 5 | I60: 471392 | J60: https://purl.pt/43854 | K60: https://bndigital.bnportugal.gov.pt//i/?IIIF=/f2/8b/c2/cc/f28bc2cc-79a2-4081-ab33-b9fabce3fa4a/iiif/cam-1451-v_0000_000005.tif/full/!300,500/0/default.jpg | L60: Livro impresso | M60: Italiano | O60: Camões | P60: musica | R60: 1.ª ed. | S60: Lisboa : s.n. | T60: 1857 | U60: 1857 | V60: 36 p. | W60: Farina, Luigi | AC60: CAM. 1451 V. | AD60: CAM500 | AE60: http://id.bnportugal.gov.pt/bib/catbnp/471392 | AF60: Livre
A61: 475171 | B61: 1 | C61: 13 | D61: https://permalinkbnd.bnportugal.gov.pt/viewer/272371/?offset=#page=13&viewer=picture&o=info&n=0&q= | E61: 13 | I61: 475171 | J61: https://purl.pt/43413 | K61: https://bndigital.bnportugal.gov.pt//i/?IIIF=/5d/bd/60/12/5dbd6012-a3b6-4853-b7f9-a7245fc80226/iiif/cam-782-p_0013.tif/full/!300,500/0/default.jpg | L61: Livro manuscrito | M61: Latim | N61: Português | O61: Ludouici Camoenij Lusitani libri X ex materno rhythmico in latinum & virgilianu carmen à D. Andrea Baiano Lusiada Orientali traducti & ab eodem manuscripti. Anno jubilei CI)I)CXXV 1625 | R61: 1.ª ed. | T61: 1625 | U61: 1625 | V61: 24, 383 p. | W61: Camões, Luís de, 1524-1580 | Z61: Baião, André, 1566-1639, Tradutor | AC61: F. 9 | AD61: CAM500 | AE61: http://id.bnportugal.gov.pt/bib/catbnp/475171 | AF61: Livre
A62: 475214 | B62: 1 | C62: 7 | D62: https://permalinkbnd.bnportugal.gov.pt/viewer/273182/?offset=#page=7&viewer=picture&o=info&n=0&q= | E62: 7 | I62: 475214 | J62: https://purl.pt/43856 | K62: https://bndigital.bnportugal.gov.pt//i/?IIIF=/70/3f/cc/e5/703fcce5-cee9-4fd0-b063-c58c42d156ac/iiif/cam-74-7-v_0000_000001.tif/full/!300,500/0/default.jpg | L62: Livro impresso | M62: Hebraico antigo ; Francês | O62: Inês de Castro | P62: episode des Lusiades ... | R62: 1.ª ed. | S62: Lisbonne : Imp. Nationale | T62: 1892 | U62: 1892 | V62: XI, 24 p. | W62: Camões, Luís de, 1524-1580 | Z62: Vilhena, Ernesto Jardim de, 1876-1967, Antigo possuidor ; Benoliel, Joseph, 1873-1932, Tradutor ; Wogue, Lazare Eliezer, 1817-1897, Comentador (em meio audiovisual) | AB62: Congresso Internacional dos Orientalistas, Organizador de conferência | AC62: H.G. 7378//5 V. | AD62: CAM500 | AE62: http://id.bnportugal.gov.pt/bib/catbnp/475214 | AF62: Livre
A63: 475453 | B63: 1 | C63: 1 | D63: https://permalinkbnd.bnportugal.gov.pt/viewer/273318/?offset=#page=1&viewer=picture&o=info&n=0&q= | E63: 1 | I63: 475453 | J63: https://purl.pt/43768 | K63: https://bndigital.bnportugal.gov.pt//i/?IIIF=/57/26/e4/65/5726e465-1ee7-4c62-b7c4-06c930646aa0/iiif/cam-83-1-a_0000_000001.tif/full/!300,500/0/default.jpg | L63: Periódico | M63: Português | O63: Recreio musical | P63: album de musicas para piano | R63: 1.ª ed. | S63: Lisboa : s.n. | T63: 1880 | U63: 1880 | AC63: CAM. 83//1 A. | AD63: CAM500 | AE63: http://id.bnportugal.gov.pt/bib/catbnp/475453 | AF63: Livre
A64: 475458 | B64: 1 | C64: 1 | D64: https://permalinkbnd.bnportugal.gov.pt/viewer/273319/?offset=#page=1&viewer=picture&o=info&n=0&q= | E64: 1 | I64: 475458 | J64: https://purl.pt/43675 | K64: https://bndigital.bnportugal.gov.pt//i/?IIIF=/36/69/d9/d4/3669d9d4-f77b-4fe3-a244-701d17f3e42a/iiif/cam-83-2-a_0000_000001.tif/full/!300,500/0/default.jpg | L64: Livro impresso | M64: Português | O64: Os Lusíadas | P64: musica para piano e canto | R64: 1.ª ed. | S64: Lisboa : Verol Senior | T64: 1880 | U64: 1880 | V64: 1 partitura (5 p.) | W64: Carvalho, Augusto José de, 1848-1910 | Y64: Camões, Luís de, 1524-1580 | AC64: C.I.C. 140 A. | AD64: PRR2022 | AE64: http://id.bnportugal.gov.pt/bib/catbnp/475458 | AF64: Livre
A65: 476957 | B65: 1 | C65: 5 | D65: https://permalinkbnd.bnportugal.gov.pt/viewer/273102/?offset=#page=5&viewer=picture&o=info&n=0&q= | E65: 1, 7 [site] | I65: 476957 | J65: https://purl.pt/43755 | K65: https://bndigital.bnportugal.gov.pt//i/?IIIF=/86/6c/46/07/866c4607-1618-436f-b006-ed4e4b3aa2eb/iiif/cam-25-a_0000_000005.tif/full/!300,500/0/default.jpg | L65: Livro impresso | M65: Português | O65: Os Lusiadas | R65: Ed. popular gratuita | S65: Lisboa : Emp. do Diario de Noticias | T65: 1880 | U65: 1880 | V65: 17, 1 p. | W65: Camões, Luís de, 1524-1580 | AC65: CAM. 25 A. | AD65: CAM500 | AE65: http://id.bnportugal.gov.pt/bib/catbnp/476957 | AF65: Livre
A66: 479076 | B66: 1 | C66: 1 | D66: https://permalinkbnd.bnportugal.gov.pt/viewer/270341/?offset=#page=1&viewer=picture&o=info&n=0&q= | E66: 1 [2.º Vol.] | I66: 479076 | J66: https://purl.pt/42929 | K66: https://bndigital.bnportugal.gov.pt//i/?IIIF=/61/6e/1e/85/616e1e85-5eec-40f5-81a2-56ec93537919/iiif/cam-80-63-a_0000_000001.tif/full/!300,500/0/default.jpg | L66: Periódico | M66: Polaco | O66: Tygodnik Illustrowany | R66: 1.ª ed. | S66: Warszawa : drukiem J. Ungra | T66: 1880 | U66: 1880 | Z66: Lenike, J., Editor literário | AC66: CAM. 80//63 A. | AD66: CAM500 | AE66: http://id.bnportugal.gov.pt/bib/catbnp/479076 | AF66: Livre
A67: 479079 | B67: 1 | C67: 1 | D67: https://permalinkbnd.bnportugal.gov.pt/viewer/270336/?offset=#page=1&viewer=picture&o=info&n=0&q= | E67: 1 [2.º Vol.] | I67: 479079 | J67: https://purl.pt/42930 | K67: https://bndigital.bnportugal.gov.pt//i/?IIIF=/c5/1b/85/f9/c51b85f9-2522-413e-b7ef-aebc584037d9/iiif/cam-80-65-a_0000_000001.tif/full/!300,500/0/default.jpg | L67: Periódico | M67: Polaco | O67: Tygodnik Powszechny | R67: 1.ª ed. | S67: Warszawa : drukarni S. Orgelbrando Synow | T67: 1880 | U67: 1880 | Z67: Orgelbrand, Maurycy, Editor literário | AC67: CAM. 80//65 A. | AD67: CAM500 | AE67: http://id.bnportugal.gov.pt/bib/catbnp/479079 | AF67: Livre
A68: 480058 | B68: 1 | C68: 1 | D68: https://permalinkbnd.bnportugal.gov.pt/viewer/273314/?offset=#page=1&viewer=picture&o=info&n=0&q= | E68: 1 | I68: 480058 | J68: https://purl.pt/43673 | K68: https://bndigital.bnportugal.gov.pt//i/?IIIF=/ac/03/49/21/ac034921-8f14-43b9-a5d4-7c9ee7950d1c/iiif/cam-80-71-a_0000_000001.tif/full/!300,500/0/default.jpg | L68: Periódico | M68: Português | O68: Jornal do Commercio | R68: 1.ª ed. | S68: Rio de Janeiro : s.n. | T68: 1880 | U68: 1880 | Z68: Villeneuve, Júlio Constâncio de, Director | AC68: CAM. 80//71 A. | AD68: CAM500 | AE68: http://id.bnportugal.gov.pt/bib/catbnp/480058 | AF68: Livre
A69: 357297 | B69: 1 | C69: 10 | D69: https://permalinkbnd.bnportugal.gov.pt/viewer/281908/?offset=#page=10&viewer=picture&o=info&n=0&q= | E69: 1 [retrato do Poeta, antes da folha de rosto] | I69: 357297 | J69: https://purl.pt/43384 | K69: https://bndigital.bnportugal.gov.pt//i/?IIIF=/b2/56/5a/a6/b2565aa6-70f7-48fe-a06c-6e301f3b710c/iiif/cam-6-v_0011.tif/full/!300,500/0/default.jpg | L69: Livro impresso | M69: Português | O69: Os Lusíadas | R69: Nova edição correcta, e dada á luz, conforme á de 1817, in-4º | S69: Paris : na officina typographica de Firmino Didot... | T69: 1817 | U69: 1817 | V69: CX, 420 p. | W69: Camões, Luís de, 1524-1580 | Z69: Mateus, Morgado de, 1758-1825, Editor literário ; Didot, Firmin, fl. 1789-1829, Impressor ; Norton, Tomás, 1804-1860, Antigo possuidor | AC69: CAM. 6 V. | AD69: CAM500 | AE69: http://id.bnportugal.gov.pt/bib/catbnp/357297 | AF69: Livre
A70: 601741 | B70: 1 | C70: 1 | D70: https://permalinkbnd.bnportugal.gov.pt/viewer/36540/?offset=#page=1&viewer=picture&o=info&n=0&q= | E70: 1 site | I70: 601741 | J70: https://purl.pt/1066 | K70: https://bndigital.bnportugal.gov.pt//i/?IIIF=/50/1e/d4/2a/501ed42a-3de0-4cf9-821c-15ebd89b7023/iiif/e-3415-p_0000_000001.tif/full/!300,500/0/default.jpg | L70: Iconografia | M70: Francês | O70: Camoens | R70: 1.ª ed. | S70: La Haye : van Lier fréres | T70: 1860 | U70: 1860 | V70: 1 gravura | AC70: PURL 1066/0 | AE70: http://id.bnportugal.gov.pt/bib/catbnp/601741 | AF70: Livre
A71: 604127 | B71: 1 | C71: 1 | D71: https://permalinkbnd.bnportugal.gov.pt/viewer/14040/?offset=#page=1&viewer=picture&o=info&n=0&q= | E71: 1 site carta da geografia de Os Lusíadas | I71: 604127 | J71: https://purl.pt/27537 | K71: https://bndigital.bnportugal.gov.pt//i/?IIIF=/84/ce/f5/25/84cef525-7874-41a2-b678-e38e5372d53b/iiif/cc-1054-r_0000_000001.tif/full/!300,500/0/default.jpg | L71: Cartografia | M71: Português | O71: Carta da geographia dos Lusiadas | P71: dedicada a S.M. El-rei D. Luis I | R71: 1.ª ed. | S71: Lisboa : Litografia da Imprensa Nacional | T71: 1883 | U71: 1883 | V71: 1 mapa | W71: Figueiredo, António Cardoso Borges de, 1851?-1890 | Z71: Camões, Luís de, 1524-1580, Antecedente bibliográfico | AC71: C.C. 1054 R. | AE71: http://id.bnportugal.gov.pt/bib/catbnp/604127 | AF71: Livre
A72: 613457 | B72: 1 | C72: 1 | D72: https://permalinkbnd.bnportugal.gov.pt/viewer/272734/?offset=#page=1&viewer=picture&o=info&n=0&q= | E72: 1 | I72: 613457 | J72: https://purl.pt/43563 | K72: https://bndigital.bnportugal.gov.pt//i/?IIIF=/d6/fc/1e/ec/d6fc1eec-5431-4985-ae4f-544438336cce/iiif/e-3525-p_0000_000001.tif/full/!300,500/0/default.jpg | L72: Iconografia | M72: Português | O72: Camões | R72: 1.ª ed. | S72: S.l. : s.n. | T72: 1968 | U72: 1968 | V72: 1 imagem | AC72: E. 3525 P. | AD72: CAM500 | AE72: http://id.bnportugal.gov.pt/bib/catbnp/613457 | AF72: Livre
A73: 614521 | B73: 1 | C73: 1 | D73: https://permalinkbnd.bnportugal.gov.pt/viewer/36741/?offset=#page=1&viewer=picture&o=info&n=0&q= | E73: 1 | I73: 614521 | J73: https://purl.pt/1127 | K73: https://bndigital.bnportugal.gov.pt//i/?IIIF=/97/cc/bc/96/97ccbc96-a88e-42be-92ff-c6a0010e4a17/iiif/e-3548-p_0000_000001.tif/full/!300,500/0/default.jpg | L73: Iconografia | M73: Português | O73: Luiz de Camões | R73: 1.ª ed. | S73: Lisboa : Imprensa Nacional | T73: 1873 | U73: 1873 | V73: 1 gravura | W73: Sousa, Joaquim Pedro de, 1822-1878 | AC73: PURL 1127/0 | AE73: http://id.bnportugal.gov.pt/bib/catbnp/614521 | AF73: Livre
A74: 626460 | B74: 1 | C74: 1 | D74: https://permalinkbnd.bnportugal.gov.pt/viewer/37180/?offset=#page=1&viewer=picture&o=info&n=0&q= | E74: 1 site | I74: 626460 | J74: https://purl.pt/12554 | L74: Iconografia | M74: Francês | O74: Camoens | R74: 1.ª ed. | S74: Paris : s.n. | T74: 1846 | U74: 1846 | V74: 1 gravura | W74: Lemaitre, Augustin François, 1797-1870 | AC74: PURL 12554/0 | AE74: http://id.bnportugal.gov.pt/bib/catbnp/626460 | AF74: Livre
A75: 626703 | B75: 1 | C75: 1 | D75: https://permalinkbnd.bnportugal.gov.pt/viewer/37208/?offset=#page=1&viewer=picture&o=info&n=0&q= | E75: 1 site | I75: 626703 | J75: https://purl.pt/12562 | L75: Iconografia | M75: Alemão | O75: Camoëns im Gefangnisse zu Goa | R75: 1.ª ed. | S75: S.l. : s.n. | T75: 1840 | U75: 1840 | V75: 1 gravura | W75: Duncan, Andrew, 1795-? | Z75: Moreaux, Charles Florent Léon, 1815-?, Antecedente bibliográfico | AC75: PURL 12562/0 | AE75: http://id.bnportugal.gov.pt/bib/catbnp/626703 | AF75: Livre
A76: 636335 | B76: 1 | C76: 1 | D76: https://permalinkbnd.bnportugal.gov.pt/viewer/35147/?offset=#page=1&viewer=picture&o=info&n=0&q= | E76: 1 | I76: 636335 | J76: https://purl.pt/5762 | L76: Iconografia | M76: Português | O76: Á memoria do immortal cantor das glorias portuguezas | R76: 1.ª ed. | S76: Lisboa : s.n. | T76: 1880 | U76: 1880 | V76: 1 gravura | AC76: PURL 5762/0 | AE76: http://id.bnportugal.gov.pt/bib/catbnp/636335 | AF76: Livre
A77: 636337 | B77: 1 | C77: 1 | D77: https://permalinkbnd.bnportugal.gov.pt/viewer/1880/?offset=#page=1&viewer=picture&o=info&n=0&q= | E77: 1 | I77: 636337 | J77: https://purl.pt/5763 | K77: https://bndigital.bnportugal.gov.pt//i/?IIIF=/a1/c7/1e/30/a1c71e30-149f-4d01-a4cd-17eb6386f4ec/iiif/e-1773-v_0000_000001.tif/full/!300,500/0/default.jpg | L77: Iconografia | M77: Português | O77: 10 de Junho de 1880 | R77: 1.ª ed. | S77: Lisboa : s.n. | T77: 1880 | U77: 1880 | V77: 1 gravura | AC77: PURL 5763/0 | AE77: http://id.bnportugal.gov.pt/bib/catbnp/636337 | AF77: Livre
A78: 636371 | B78: 1 | C78: 1 | D78: https://permalinkbnd.bnportugal.gov.pt/viewer/35133/?offset=#page=1&viewer=picture&o=info&n=0&q= | E78: 1 site | I78: 636371 | J78: https://purl.pt/5756 | K78: https://bndigital.bnportugal.gov.pt//i/?IIIF=/4d/33/d1/a8/4d33d1a8-9b14-4816-b086-3bfda8beb020/iiif/e-1775-v_0000_000001.tif/full/!300,500/0/default.jpg | L78: Iconografia | M78: Português | O78: Camões na gruta de Macau | P78: homenagem do Diario de Portugal a Luiz de Camões | R78: 1.ª ed. | S78: S.l. : s.n. | T78: 1880 | U78: 1880 | V78: 1 gravura | W78: Cardon, ca 1880 | Z78: Metrass, Francisco Augusto, 1825-1861, Antecedente bibliográfico | AC78: PURL 5756/0 | AD78: OChina | AE78: http://id.bnportugal.gov.pt/bib/catbnp/636371 | AF78: Livre
A79: 636385 | B79: 1 | C79: 1 | D79: https://permalinkbnd.bnportugal.gov.pt/viewer/35127/?offset=#page=1&viewer=picture&o=info&n=0&q= | E79: 1 | I79: 636385 | J79: https://purl.pt/5757 | K79: https://bndigital.bnportugal.gov.pt//i/?IIIF=/77/c8/5e/5a/77c85e5a-2edc-447a-be9f-e3b9247fe8a1/iiif/e-1774-v_0000_000001.tif/full/!300,500/0/default.jpg | L79: Iconografia | M79: Português | O79: Monumento a Camões | R79: 1.ª ed. | S79: S.l. : s.n. | T79: 1868 | U79: 1868 | V79: 1 gravura | W79: Sousa, Joaquim Pedro de, 1822-1878 | Z79: Barros, Silêncio Cristão de, 1798-1867, Impressor de ilustrações em chapa gravada | AC79: PURL 5757/0 | AD79: CAM500 | AE79: http://id.bnportugal.gov.pt/bib/catbnp/636385 | AF79: Livre
A80: 636389 | B80: 1 | C80: 1 | D80: https://permalinkbnd.bnportugal.gov.pt/viewer/35137/?offset=#page=1&viewer=picture&o=info&n=0&q= | E80: 1 site | I80: 636389 | J80: https://purl.pt/5761 | K80: https://bndigital.bnportugal.gov.pt//i/?IIIF=/7e/61/9f/18/7e619f18-7c28-4232-b632-4cb06e6e808f/iiif/e-1776-v_0000_000001.tif/full/!300,500/0/default.jpg | L80: Iconografia | M80: Português | O80: O tempo levando os Lusíadas à posteridade | R80: 1.ª ed. | S80: S.l. : s.n. | T80: 1880 | U80: 1880 | V80: 1 gravura | W80: Medeiros, J., ca. 18- - | AC80: PURL 5761/0 | AE80: http://id.bnportugal.gov.pt/bib/catbnp/636389 | AF80: Livre
A81: 637133 | B81: 1 | C81: 1 | D81: https://permalinkbnd.bnportugal.gov.pt/viewer/37203/?offset=#page=1&viewer=picture&o=info&n=0&q= | E81: 1 site | I81: 637133 | J81: https://purl.pt/4762 | K81: https://bndigital.bnportugal.gov.pt//i/?IIIF=/2b/63/53/2f/2b63532f-998a-4f7b-8b8c-b4e456bc6390/iiif/e-403-v_0000_000001.tif/full/!300,500/0/default.jpg | L81: Iconografia | M81: Português | O81: Epitome da vida de Luiz de Camoens | R81: 1.ª ed. | S81: Lisboa : s.n. | T81: 1808 | U81: 1808 | V81: 1 gravura | W81: Cardini, João, fl. 1804-1825? | AC81: PURL 4762/0 | AE81: http://id.bnportugal.gov.pt/bib/catbnp/637133 | AF81: Livre
A82: 637139 | B82: 1 | C82: 1 | D82: https://permalinkbnd.bnportugal.gov.pt/viewer/37132/?offset=#page=1&viewer=picture&o=info&n=0&q= | E82: 1 site | I82: 637139 | J82: https://purl.pt/4760 | K82: https://bndigital.bnportugal.gov.pt//i/?IIIF=/91/93/ef/9e/9193ef9e-3647-4d04-a920-6fce8a1629b8/iiif/e-404-v_0000_000001.tif/full/!300,500/0/default.jpg | L82: Iconografia | M82: Português | O82: Ao tricentenário de Luiz de Camões | P82: aos 10 de Junho de 1880, Rio de Janeiro | R82: 1.ª ed. | S82: Rio de Janeiro : s.n. | T82: 1880 | U82: 1880 | V82: 1 gravura | AB82: Litografia António Lobo & Companhia | AC82: PURL 4760/0 | AE82: http://id.bnportugal.gov.pt/bib/catbnp/637139 | AF82: Livre
A83: 665442 | B83: 1 | C83: 1 | D83: https://permalinkbnd.bnportugal.gov.pt/viewer/34623/?offset=#page=1&viewer=picture&o=info&n=0&q= | E83: 1 | I83: 665442 | J83: https://purl.pt/5904 | L83: Iconografia | O83: Tricentenário de Camões | R83: 1.ª ed. | S83: S.l. : s.n. | T83: 1880 | U83: 1880 | V83: 1 gravura | AC83: PURL 5904/0 | AE83: http://id.bnportugal.gov.pt/bib/catbnp/665442 | AF83: Livre
A84: 700486 | B84: 1 | C84: 1 | D84: https://permalinkbnd.bnportugal.gov.pt/viewer/37092/?offset=#page=1&viewer=picture&o=info&n=0&q= | E84: 1 | I84: 700486 | J84: https://purl.pt/6773 | K84: https://bndigital.bnportugal.gov.pt//i/?IIIF=/68/60/bf/0c/6860bf0c-8b2d-42e5-8809-1edc675de42b/iiif/e-40-a_0000_000001.tif/full/!300,500/0/default.jpg | L84: Iconografia | M84: Português | O84: Camões lendo os Lusíadas a D. Sebastião | R84: 1.ª ed. | S84: Lisboa : s.n. | T84: 1893 | U84: 1893 | V84: 1 gravura | W84: Ramalho, António, 1858-1916 | AB84: Litografia de Portugal, Impressor | AC84: PURL 6773/0 | AE84: http://id.bnportugal.gov.pt/bib/catbnp/700486 | AF84: Livre
A85: 700487 | B85: 1 | C85: 1 | D85: https://permalinkbnd.bnportugal.gov.pt/viewer/37325/?offset=#page=1&viewer=picture&o=info&n=0&q= | E85: 1 | I85: 700487 | J85: https://purl.pt/6771 | K85: https://bndigital.bnportugal.gov.pt//i/?IIIF=/f1/a9/3d/d6/f1a93dd6-7849-41fe-998c-148d7cb7b2dd/iiif/e-41-a_0000_000001.tif/full/!300,500/0/default.jpg | L85: Iconografia | M85: Português | O85: Camões no leito de morte | R85: 1.ª ed. | S85: Lisboa : s.n. | T85: 1861 | U85: 1861 | V85: 1 gravura | W85: Cupertino, fl. 1860 | AC85: PURL 6771/0 | AE85: http://id.bnportugal.gov.pt/bib/catbnp/700487 | AF85: Livre
A86: 704429 | B86: 1 | C86: 1 | D86: https://permalinkbnd.bnportugal.gov.pt/viewer/33427/?offset=#page=1&viewer=picture&o=info&n=0&q= | E86: 1 | I86: 704429 | J86: https://purl.pt/1227 | K86: https://bndigital.bnportugal.gov.pt//i/?IIIF=/ed/6c/2b/55/ed6c2b55-9065-4ce7-97e4-d3437ec4bfa1/iiif/d-392-v_0000_000001.tif/full/!300,500/0/default.jpg | L86: Iconografia | M86: Português | O86: Os Lusíadas | P86: ilustração | R86: 1.ª ed. | T86: 1900 | U86: 1900 | V86: 1 desenho | W86: Gameiro, Alfredo Roque, 1864-1935 | AC86: PURL 1227/0 | AE86: http://id.bnportugal.gov.pt/bib/catbnp/704429 | AF86: Livre
A87: 709106 | B87: 1 | C87: 1 | D87: https://permalinkbnd.bnportugal.gov.pt/viewer/36374/?offset=#page=1&viewer=picture&o=info&n=0&q= | E87: 1 | I87: 709106 | J87: https://purl.pt/6901 | K87: https://bndigital.bnportugal.gov.pt//i/?IIIF=/c6/65/ed/04/c665ed04-906d-47be-afa9-f49402d8909b/iiif/e-271-a_0000_000001.tif/full/!300,500/0/default.jpg | L87: Iconografia | M87: Português | O87: Luiz de Camões | R87: 1.ª ed. | S87: S.l. : s.n. | T87: 1878 | U87: 1878 | V87: 1 gravura | W87: Grossi, ca 1880 | AC87: PURL 6901/0 | AE87: http://id.bnportugal.gov.pt/bib/catbnp/709106 | AF87: Livre
A88: 709129 | B88: 1 | C88: 1 | D88: https://permalinkbnd.bnportugal.gov.pt/viewer/36554/?offset=#page=1&viewer=picture&o=info&n=0&q= | E88: 1 | I88: 709129 | J88: https://purl.pt/6844 | K88: https://bndigital.bnportugal.gov.pt//i/?IIIF=/d5/4a/55/8b/d54a558b-4168-4ce9-95b6-7b9ac715137f/iiif/e-274-a_0000_000001.tif/full/!300,500/0/default.jpg | L88: Iconografia | M88: Português | O88: Vasco da Gama apresenta a D. Manuel as primicias da India | P88: Entraram pela foz do Tejo ameno... Lusiadas, canto X, est. 144 | R88: 1.ª ed. | S88: Lisboa ; : João Romano Torres | T88: 1890 | U88: 1890 | V88: 1 imagem | Z88: Camões, Luís de, 1524-1580, Autor em citações ou excertos de textos ; Marinho, José Pires, 1857-1929?, Técnico gráfico ; Torres, João Romano, 1855-1935, Editor comercial | AC88: PURL 6844/0 | AE88: http://id.bnportugal.gov.pt/bib/catbnp/709129 | AF88: Livre
A89: 729122 | B89: 1 | C89: 1 | D89: https://permalinkbnd.bnportugal.gov.pt/viewer/37663/?offset=#page=1&viewer=picture&o=info&n=0&q= | E89: 1 | I89: 729122 | J89: https://purl.pt/12937 | K89: https://bndigital.bnportugal.gov.pt//i/?IIIF=/15/56/29/ac/155629ac-1d4f-4db2-92f1-9e806d18975b/iiif/e-4482-p_0000_000001.tif/full/!300,500/0/default.jpg | L89: Iconografia | M89: Latim | O89: Ludovicus Camonius, Lusitanus epicorum poetar, in Hispania Princeps, vixit an. LV. obiit an M.DLXXIX | R89: 1.ª ed. | S89: Lisboa : na Officina Luisiana | T89: 1779 | U89: 1779 | V89: 1 gravura | W89: Rodrigues, António Fernandes, 1727-1807 | AB89: Oficina Luisiana, Impressor | AC89: PURL 12937/0 | AE89: http://id.bnportugal.gov.pt/bib/catbnp/729122 | AF89: Livre
A90: 730341 | B90: 1 | C90: 1 | D90: https://permalinkbnd.bnportugal.gov.pt/viewer/37195/?offset=#page=1&viewer=picture&o=info&n=0&q= | E90: 1 site | I90: 730341 | J90: https://purl.pt/12929 | L90: Iconografia | M90: Francês | O90: Camoens | R90: 1.ª ed. | S90: Paris : Furne | T90: 1841 | U90: 1841 | V90: 1 gravura | W90: Audibran, François Adolphe Bruneau, 1810-? | AC90: PURL 12929/0 | AE90: http://id.bnportugal.gov.pt/bib/catbnp/730341 | AF90: Livre
A91: 733501 | B91: 1 | C91: 1 | D91: https://permalinkbnd.bnportugal.gov.pt/viewer/37674/?offset=#page=1&viewer=picture&o=info&n=0&q= | E91: 1 | I91: 733501 | J91: https://purl.pt/12938 | L91: Iconografia | M91: Inglês | O91: Luis de Camoens | R91: 1.ª ed. | S91: London : Longman | T91: 1820 | U91: 1820 | V91: 1 gravura | W91: Skelton, William, 1763-1848 | AC91: PURL 12938/0 | AD91: PCulture | AE91: http://id.bnportugal.gov.pt/bib/catbnp/733501 | AF91: Livre
A92: 742171 | B92: 1 | C92: 10 | D92: https://permalinkbnd.bnportugal.gov.pt/viewer/274166/?offset=#page=10&viewer=picture&o=info&n=0&q= | E92: 10, 18 [retratos de Camões e de Vasco da Gama] | I92: 742171 | J92: https://purl.pt/43810 | K92: https://bndigital.bnportugal.gov.pt//i/?IIIF=/20/0e/92/c5/200e92c5-aec5-4489-a61a-b6480cdafb72/iiif/cam-41-v_0005.tif/full/!300,500/0/default.jpg | L92: Livro impresso | M92: Francês | O92: Les Lusiades | R92: 1.ª ed. | S92: Lisboa : Tip da Comp. Nacional Editora | T92: 1889 | U92: 1889 | V92: 338 p. | W92: Camões, Luís de, 1524-1580 | Z92: Garin, Hyacinthe, Editor literário | AC92: L. 5855 A. | AD92: CAM500 | AE92: http://id.bnportugal.gov.pt/bib/catbnp/742171 | AF92: Livre
A93: 742171 | B93: 1 | C93: 18 | D93: https://permalinkbnd.bnportugal.gov.pt/viewer/274166/?offset=#page=18&viewer=picture&o=info&n=0&q= | E93: 10, 18 [retratos de Camões e de Vasco da Gama] | I93: 742171 | J93: https://purl.pt/43810 | K93: https://bndigital.bnportugal.gov.pt//i/?IIIF=/20/0e/92/c5/200e92c5-aec5-4489-a61a-b6480cdafb72/iiif/cam-41-v_0005.tif/full/!300,500/0/default.jpg | L93: Livro impresso | M93: Francês | O93: Les Lusiades | R93: 1.ª ed. | S93: Lisboa : Tip da Comp. Nacional Editora | T93: 1889 | U93: 1889 | V93: 338 p. | W93: Camões, Luís de, 1524-1580 | Z93: Garin, Hyacinthe, Editor literário | AC93: L. 5855 A. | AD93: CAM500 | AE93: http://id.bnportugal.gov.pt/bib/catbnp/742171 | AF93: Livre
A94: 764770 | B94: 1 | C94: 7 | D94: https://permalinkbnd.bnportugal.gov.pt/viewer/270042/?offset=#page=7&viewer=picture&o=info&n=0&q= | E94: 7 [portada e 46 apontamento final Canto I] | I94: 764770 | J94: https://purl.pt/42608 | K94: https://bndigital.bnportugal.gov.pt//i/?IIIF=/9e/91/6e/ad/9e916ead-0a6f-45ca-96ba-ec9f9d845df0/iiif/cam-17-p_0000_000007.tif/full/!300,500/0/default.jpg | L94: Livro impresso | M94: Português | O94: Os Lusiadas | R94: 1.ª ed. | S94: Em Lisboa : por Pedro Crasbeeck : com privilegio, à custa de Domingos Fernandez livreyro | T94: 1609 | U94: 1609 | V94: 2, 186 f. | W94: Camões, Luís de, 1524-1580 | Z94: Cunha, Rodrigo da, 1577-1643, Personalidade a quem é dedicada a obra ; Sousa, Luís de, 1555-1632, Autor ; Mendonça, Pedro da Silva e, Autor ; Tasso, Torquato, 1544-1595, Autor ; Leitão, Diogo Taborda, 15--, Autor ; Tamayo de Vargas, Tomás, 1588-1641, Autor ; Bernardes, Diogo, ca 1530-1596, Autor ; Craesbeeck, Pedro, fl. 1597-1632, Impressor ; Norton, Tomás, 1804-1860, Antigo possuidor ; Fernandes, Domingos, 15---16--, Editor comercial ; Barreto, Domingos da Costa, Antigo possuidor ; Caminha, António Lourenço, ?-1831, Antigo possuidor | AC94: F. 2553 | AD94: CAM500 | AE94: http://id.bnportugal.gov.pt/bib/catbnp/764770 | AF94: Livre
A95: 767226 | B95: 1 | C95: 4 | D95: https://permalinkbnd.bnportugal.gov.pt/viewer/273943/?offset=#page=4&viewer=picture&o=info&n=0&q= | E95: 4 | I95: 767226 | J95: https://purl.pt/43749 | L95: Livro impresso | M95: Português | O95: Os Lusiadas | P95: poema épico... | R95: Nova ed. cuidadosamente revista e conforme às de 1572, precedida da biografia do poeta e seguida de um dicionário dos nomes próprios | S95: Lisboa : Livr. António Maria Pereira | T95: 1875 | U95: 1875 | V95: XVIII, 457, 6 p. | W95: Camões, Luís de, 1524-1580 | AC95: CAM. 566 P. | AD95: CAM500 | AE95: http://id.bnportugal.gov.pt/bib/catbnp/767226 | AF95: Livre
A96: 767525 | B96: 1 | C96: 3 | D96: https://permalinkbnd.bnportugal.gov.pt/viewer/273427/?offset=#page=3&viewer=picture&o=info&n=0&q= | E96: 3 | I96: 767525 | J96: https://purl.pt/43772 | K96: https://bndigital.bnportugal.gov.pt//i/?IIIF=/7c/53/55/55/7c535555-bf57-4fa5-b6f4-b9bad743d540/iiif/cam-106-2-v_0000_000001.tif/full/!300,500/0/default.jpg | L96: Livro impresso | M96: Português | O96: Á memoria de Luiz de Camões | P96: 301.º anniversario do fallecimento do grande épico | R96: 1.ª ed. | S96: Loanda : Tip. do Mercantil | T96: 1881 | U96: 1881 | V96: 26, 2 p. | X96: Sociedade Propagadora de Conhecimentos Geográfico-Africanos | Z96: Vilhena, Ernesto Jardim de, 1876-1967, Antigo possuidor | AC96: H.G. 12224//6 V. | AD96: CAM500 | AE96: http://id.bnportugal.gov.pt/bib/catbnp/767525 | AF96: Livre
A97: 782745 | B97: 1 | C97: 6 | D97: https://permalinkbnd.bnportugal.gov.pt/viewer/272372/?offset=#page=6&viewer=picture&o=info&n=0&q= | E97: 6, 286, 322 | I97: 782745 | J97: https://purl.pt/43415 | K97: https://bndigital.bnportugal.gov.pt//i/?IIIF=/a1/d0/ad/31/a1d0ad31-73b5-460a-ba20-5f53415efc39/iiif/cam-709-p_0007.tif/full/!300,500/0/default.jpg | L97: Livro impresso | M97: Português | O97: Os Lusiadas | P97: poema épico | R97: Nova ed | S97: Porto : Livr. Ed. Cruz Coutinho | T97: 1889 | U97: 1889 | V97: XII, 480 p. | W97: Camões, Luís de, 1524-1580 | AC97: CAM. 709 P. | AD97: CAM500 | AE97: http://id.bnportugal.gov.pt/bib/catbnp/782745 | AF97: Livre
A98: 784907 | B98: 1 | C98: 21 | D98: https://permalinkbnd.bnportugal.gov.pt/viewer/272381/?offset=#page=21&viewer=picture&o=info&n=0&q= | E98: 21, 24, 25, 28, 29 [site], 32, 33, 36, 37, 40, 41 | I98: 784907 | J98: https://purl.pt/43424 | K98: https://bndigital.bnportugal.gov.pt//i/?IIIF=/b1/0e/f2/ad/b10ef2ad-b90f-419d-ac6d-791303f80865/iiif/cam-738-p_0018.tif/full/!300,500/0/default.jpg | L98: Livro impresso | M98: Português | O98: Lusiadas de Luis de Camões a que se ajuntam a vida do Poeta, hum argumento historico dos Lusiadas... com 10 estampas | R98: 1.ª ed. | S98: Lisboa : Tip. de Eugénio Augusti | T98: 1836 | U98: 1836 | W98: Camões, Luís de, 1524-1580 | AC98: CAM. 738 P. | AD98: CAM500 | AE98: http://id.bnportugal.gov.pt/bib/catbnp/784907 | AF98: Livre
A99: 784907 | B99: 1 | C99: 24 | D99: https://permalinkbnd.bnportugal.gov.pt/viewer/272381/?offset=#page=24&viewer=picture&o=info&n=0&q= | E99: 21, 24, 25, 28, 29 [site], 32, 33, 36, 37, 40, 41 | I99: 784907 | J99: https://purl.pt/43424 | K99: https://bndigital.bnportugal.gov.pt//i/?IIIF=/b1/0e/f2/ad/b10ef2ad-b90f-419d-ac6d-791303f80865/iiif/cam-738-p_0018.tif/full/!300,500/0/default.jpg | L99: Livro impresso | M99: Português | O99: Lusiadas de Luis de Camões a que se ajuntam a vida do Poeta, hum argumento historico dos Lusiadas... com 10 estampas | R99: 1.ª ed. | S99: Lisboa : Tip. de Eugénio Augusti | T99: 1836 | U99: 1836 | W99: Camões, Luís de, 1524-1580 | AC99: CAM. 738 P. | AD99: CAM500 | AE99: http://id.bnportugal.gov.pt/bib/catbnp/784907 | AF99: Livre
A100: 784907 | B100: 1 | C100: 25 | D100: https://permalinkbnd.bnportugal.gov.pt/viewer/272381/?offset=#page=25&viewer=picture&o=info&n=0&q= | E100: 21, 24, 25, 28, 29 [site], 32, 33, 36, 37, 40, 41 | I100: 784907 | J100: https://purl.pt/43424 | K100: https://bndigital.bnportugal.gov.pt//i/?IIIF=/b1/0e/f2/ad/b10ef2ad-b90f-419d-ac6d-791303f80865/iiif/cam-738-p_0018.tif/full/!300,500/0/default.jpg | L100: Livro impresso | M100: Português | O100: Lusiadas de Luis de Camões a que se ajuntam a vida do Poeta, hum argumento historico dos Lusiadas... com 10 estampas | R100: 1.ª ed. | S100: Lisboa : Tip. de Eugénio Augusti | T100: 1836 | U100: 1836 | W100: Camões, Luís de, 1524-1580 | AC100: CAM. 738 P. | AD100: CAM500 | AE100: http://id.bnportugal.gov.pt/bib/catbnp/784907 | AF100: Livre
...

Sheet imagens-partilhar
A1: id | B1: pasta | C1: volume | D1: imagem | E1: purl | F1: imagens_texto | G1: imagens | H1: notas Regina | I1: url_página | J1: Categoria-1 | K1: Categoria-2 | L1: Categoria-3 | M1: url_purl | N1: number | O1: link_pagina | P1: ncb | Q1: purl | R1: capa | S1: tipo de material | T1: língua | U1: língua da obra original | V1: título | W1: subtítulo | X1: título original | Y1: edição | Z1: publicação | AA1: data da publicação | AB1: data da publicação2 | AC1: dimensões | AD1: autor | AE1: autor - organização | AF1: co-autores | AG1: autores secundários | AH1: co-autores - organizações | AI1: autores secundários - organizações | AJ1: cota | AK1: coleção | AL1: id persistente | AM1: acesso | AN1: notas gerais | AO1: notas título | AP1: notas conteúdo | AQ1: sumário | AR1: título uniforme | AS1: título colectivo uniforme | AT1: Column1
A2: 9951 | B2: 367428 | C2: 1 | D2: 1 | E2: https://purl.pt/43428 | F2: 1 | G2: 1 | I2: =HYPERLINK(O2) -> https://permalinkbnd.bnportugal.gov.pt/viewer/272369/?offset=#page=1&viewer=picture&o=info&n=0&q= | M2: https://purl.pt/43428 | N2: 272369 | O2: =CONCATENATE("https://permalinkbnd.bnportugal.gov.pt/viewer/",N2,"/?offset=#page=",D2,"&viewer=picture&o=info&n=0&q=") -> https://permalinkbnd.bnportugal.gov.pt/viewer/272369/?offset=#page=1&viewer=picture&o=info&n=0&q= | P2: 367428 | Q2: https://purl.pt/43428 | R2: https://bndigital.bnportugal.gov.pt//i/?IIIF=/a3/eb/b0/67/a3ebb067-89f3-40ff-a518-1fc158846d4b/iiif/cam-479-p_0003.tif/full/!300,500/0/default.jpg | S2: Livro impresso | T2: Italiano | V2: I Lusiadi | W2: poema | Y2: 1.ª ed. | Z2: Milano : Edoardo Sonzogno,editore | AA2: 1882 | AB2: 1882 | AC2: 196 p. | AD2: Camões, Luís de, 1524-1580 | AG2: Nervi, Antonio, 1760-1836, Tradutor | AJ2: CAM. 479 P. | AK2: CAM500 | AL2: http://id.bnportugal.gov.pt/bib/catbnp/367428 | AM2: Livre
A3: 9968 | B3: 381074 | C3: 1 | D3: 499 | E3: https://purl.pt/43747 | F3: 10 [site], 11, 103 [site pelicano direita], 107, 142, 107, 142, 145, 185, 235, 270 [site assassinato de Inês], 273, 306, 309 [site ninfas], 342, 345, 374, 377, 410, 413, 447, 499, 526 [site apontamento] [pintura de Camões por Columbano, portada, fac-símile do frontispício da 1.ª Ed. de Os Lusíadas, ilustrações da obra] | G3: 10, 11, 103, 145, 235, 270, 273, 306, 309, 342, 345, 374, 377, 410, 413, 447, 499 | I3: =HYPERLINK(O3) -> https://permalinkbnd.bnportugal.gov.pt/viewer/274089/?offset=#page=499&viewer=picture&o=info&n=0&q= | M3: https://purl.pt/43747 | N3: 274089 | O3: =CONCATENATE("https://permalinkbnd.bnportugal.gov.pt/viewer/",N3,"/?offset=#page=",D3,"&viewer=picture&o=info&n=0&q=") -> https://permalinkbnd.bnportugal.gov.pt/viewer/274089/?offset=#page=499&viewer=picture&o=info&n=0&q= | P3: 381074 | Q3: https://purl.pt/43747 | R3: https://bndigital.bnportugal.gov.pt//i/?IIIF=/7d/bb/9c/38/7dbb9c38-ff88-4f0e-8125-42d713ee62f7/iiif/cam-21-a_0007.tif/full/!300,500/0/default.jpg | S3: Livro impresso | T3: Português | V3: Os Lusíadas | W3: edição consagrada a comemorar o terceiro centenário do poeta... | Y3: 1.ª ed. | Z3: Lisboa : Of. de Castro Irmão | AA3: 1880 | AB3: 1880 | AC3: XCIII, 422 p., 1 il. | AD3: Camões, Luís de, 1524-1580 | AG3: Coelho, Adolfo, 1847-1919, Revisor ; Ortigão, Ramalho, 1836-1915, Autor da introdução, etc. ; Montoro, Reinaldo Carlos, 1831-?, Autor da introdução, etc. | AI3: Gabinete Português de Leitura, Editor literário | AJ3: L. 94571 V. | AK3: CAM500 | AL3: http://id.bnportugal.gov.pt/bib/catbnp/381074 | AM3: Livre
A4: 9993 | B4: 381465 | C4: 1 | D4: 644 | E4: https://purl.pt/43233 | F4: 5 [site], 10 [site], 11 [site], 43, 46 [Vasco da Gama], 47, 100, 101, 160, 161, 163, 235, 237, 289, 291 [site Adamastor], 293, 343 [site apontamento livros e pena], 345, 347, 397, 443, 445, 495 [site Mercúrio, caduceu e navegador], 545 [site máquina do mundo], 547, 625, 627, 644 [monge com livro] [portadas, retrato de Camões, fotogravuras em cada Canto] | G4: 5, 10, 11, 43, 46 , 47, 101, 160, 161, 163, 235, 237, 291, 293, 343, 345, 347, 397, 443, 445, 495 , 545, 547, 627, 644 | I4: =HYPERLINK(O4) -> https://permalinkbnd.bnportugal.gov.pt/viewer/271573/?offset=#page=644&viewer=picture&o=info&n=0&q= | M4: https://purl.pt/43233 | N4: 271573 | O4: =CONCATENATE("https://permalinkbnd.bnportugal.gov.pt/viewer/",N4,"/?offset=#page=",D4,"&viewer=picture&o=info&n=0&q=") -> https://permalinkbnd.bnportugal.gov.pt/viewer/271573/?offset=#page=644&viewer=picture&o=info&n=0&q= | P4: 381465 | Q4: https://purl.pt/43233 | R4: https://bndigital.bnportugal.gov.pt//i/?IIIF=/1b/9b/a2/7b/1b9ba27b-8449-49d7-b8fa-ec3081a88a08/iiif/cam-30-a_0000_000005.tif/full/!300,500/0/default.jpg | S4: Livro impresso | T4: Português | V4: Os Lusíadas | W4: profusamente illustrada com desenhos allegoricos... | Y4: 1.ª ed. | Z4: Lisboa : Silvestre Castanheiro | AA4: 1898 | AB4: 1898 | AC4: XXXIII, 599 p. | AD4: Camões, Luís de, 1524-1580 | AG4: Belo, António Mendes, 1842-1929, Comentador (em meio audiovisual) ; Chagas, Pinheiro, 1842-1895, Comentador (em meio audiovisual) ; Costa, José Fernandes, 1848-1920, Comentador (em meio audiovisual) | AJ4: L. 5864 A. | AK4: CAM500 | AL4: http://id.bnportugal.gov.pt/bib/catbnp/381465 | AM4: Livre
A5: 9994 | B5: 381468 | C5: 1 | D5: 8 | E5: https://purl.pt/43745 | F5: 8 [site retrato de Camões] | G5: 8 | I5: =HYPERLINK(O5) -> https://permalinkbnd.bnportugal.gov.pt/viewer/274087/?offset=#page=8&viewer=picture&o=info&n=0&q= | M5: https://purl.pt/43745 | N5: 274087 | O5: =CONCATENATE("https://permalinkbnd.bnportugal.gov.pt/viewer/",N5,"/?offset=#page=",D5,"&viewer=picture&o=info&n=0&q=") -> https://permalinkbnd.bnportugal.gov.pt/viewer/274087/?offset=#page=8&viewer=picture&o=info&n=0&q= | P5: 381468 | Q5: https://purl.pt/43745 | R5: https://bndigital.bnportugal.gov.pt//i/?IIIF=/e0/20/89/c0/e02089c0-dfb3-4507-bf34-b897aa5b2b44/iiif/cam-33-a_0009.tif/full/!300,500/0/default.jpg | S5: Livro impresso | T5: Espanhol | U5: Português | V5: Os Lusiadas (Los Portugueses) | Y5: Edicion acompañada del legitimo texto portugues y de copiosas notas y noticias biograficas sobre el insigne poeta ibero | Z5: Badajoz : Establecimiento Tipográfico de José Santamaría | AA5: 1873 | AB5: 1873 | AC5: 263, 1 p. | AD5: Camões, Luís de, 1524-1580 | AG5: Soler y Arqués, Carlos, 1836-1896, Tradutor | AJ5: CAM. 33 A. | AK5: CAM500 | AL5: http://id.bnportugal.gov.pt/bib/catbnp/381468 | AM5: Livre
A6: 9995 | B6: 381701 | C6: 1 | D6: 11 | E6: https://purl.pt/43724 | F6: 11 | G6: 11 | I6: =HYPERLINK(O6) -> https://permalinkbnd.bnportugal.gov.pt/viewer/281141/?offset=#page=11&viewer=picture&o=info&n=0&q= | M6: https://purl.pt/43724 | N6: 281141 | O6: =CONCATENATE("https://permalinkbnd.bnportugal.gov.pt/viewer/",N6,"/?offset=#page=",D6,"&viewer=picture&o=info&n=0&q=") -> https://permalinkbnd.bnportugal.gov.pt/viewer/281141/?offset=#page=11&viewer=picture&o=info&n=0&q= | P6: 381701 | Q6: https://purl.pt/43724 | R6: https://bndigital.bnportugal.gov.pt//i/?IIIF=/58/a8/a6/57/58a8a657-7fb2-4700-9b55-408036c37806/iiif/cam-40-a_0001.tif/full/!300,500/0/default.jpg | S6: Livro impresso | T6: Poliglota | U6: Português | V6: Inês de Castro | W6: episódio extraído do canto terceiro do poema épico Os Lusíadas | Y6: 1.ª ed. | Z6: Lisboa : Imprensa Nacional | AA6: 1873 | AB6: 1873 | AC6: 76 p. | AD6: Camões, Luís de, 1524-1580 | AJ6: CAM. 40 A. | AK6: CAM500 | AL6: http://id.bnportugal.gov.pt/bib/catbnp/381701 | AM6: Livre
A7: 9998 | B7: 381889 | C7: 1 | D7: 1 | E7: https://purl.pt/43659 | F7: 1 [Inês de Castro, Vasco da Gama, Catarina de Ataíde e retrato de Camões] | G7: 1 | I7: =HYPERLINK(O7) -> https://permalinkbnd.bnportugal.gov.pt/viewer/273118/?offset=#page=1&viewer=picture&o=info&n=0&q= | M7: https://purl.pt/43659 | N7: 273118 | O7: =CONCATENATE("https://permalinkbnd.bnportugal.gov.pt/viewer/",N7,"/?offset=#page=",D7,"&viewer=picture&o=info&n=0&q=") -> https://permalinkbnd.bnportugal.gov.pt/viewer/273118/?offset=#page=1&viewer=picture&o=info&n=0&q= | P7: 381889 | Q7: https://purl.pt/43659 | R7: https://bndigital.bnportugal.gov.pt//i/?IIIF=/5b/91/40/8a/5b91408a-4af1-4a94-bccc-2d03ee894a1c/iiif/cam-44-2-a_0000_000001.tif/full/!300,500/0/default.jpg | S7: Periódico | T7: Português | V7: Pérolas de Camões | W7: publicação dedicada ao povo | Y7: 1.ª ed. | Z7: Lisboa : Lallement Fréres | AA7: 1880 | AB7: 1880 | AI7: Lallement Frères, Editor comercial | AJ7: CAM. 44//2 A. | AK7: CAM500 | AL7: http://id.bnportugal.gov.pt/bib/catbnp/381889 | AM7: Livre
A8: 9999 | B8: 381903 | C8: 1 | D8: 5 | E8: https://purl.pt/42920 | F8: 5 [1.º] | G8: 5 | I8: =HYPERLINK(O8) -> https://permalinkbnd.bnportugal.gov.pt/viewer/270037/?offset=#page=5&viewer=picture&o=info&n=0&q= | M8: https://purl.pt/42920 | N8: 270037 | O8: =CONCATENATE("https://permalinkbnd.bnportugal.gov.pt/viewer/",N8,"/?offset=#page=",D8,"&viewer=picture&o=info&n=0&q=") -> https://permalinkbnd.bnportugal.gov.pt/viewer/270037/?offset=#page=5&viewer=picture&o=info&n=0&q= | P8: 381903 | Q8: https://purl.pt/42920 | R8: https://bndigital.bnportugal.gov.pt//i/?IIIF=/84/00/0c/50/84000c50-b90e-4a7c-aa5e-5cb3dfef4dab/iiif/cam-45-2-a_0000_000001.tif/full/!300,500/0/default.jpg | S8: Periódico | T8: Polaco | V8: Illustrowane Tygedniowe | Y8: 1.ª ed. | AA8: 1880 | AB8: 1880 | AJ8: CAM. 45//2 A. | AK8: CAM500 | AL8: http://id.bnportugal.gov.pt/bib/catbnp/381903 | AM8: Livre
A9: 10000 | B9: 382749 | C9: 1 | D9: 7 | E9: https://purl.pt/42835 | F9: 7 [site], 19, 23 [frisos site, esta obra contém mais apontamentos e frisos belíssimos] | I9: =HYPERLINK(O9) -> https://permalinkbnd.bnportugal.gov.pt/viewer/270109/?offset=#page=7&viewer=picture&o=info&n=0&q= | M9: https://purl.pt/42835 | N9: 270109 | O9: =CONCATENATE("https://permalinkbnd.bnportugal.gov.pt/viewer/",N9,"/?offset=#page=",D9,"&viewer=picture&o=info&n=0&q=") -> https://permalinkbnd.bnportugal.gov.pt/viewer/270109/?offset=#page=7&viewer=picture&o=info&n=0&q= | P9: 382749 | Q9: https://purl.pt/42835 | R9: https://bndigital.bnportugal.gov.pt//i/?IIIF=/60/58/22/4f/6058224f-9454-448f-8489-96a3a71253f5/iiif/cam-47-a_0000_000007.tif/full/!300,500/0/default.jpg | S9: Livro impresso | T9: Português | V9: Pretidão de amor | W9: endechas a Bárbara escrava seguidas da respectiva tradução em várias línguas... | Y9: 1.ª ed. | Z9: Lisboa : Imprensa Nacional | AA9: 1893 | AB9: 1893 | AC9: 2 v. | AD9: Camões, Luís de, 1524-1580 | AG9: Cunha, Xavier da, 1840-1920, Autor da introdução, etc. | AJ9: CAM. 270 V. | AK9: CAM500 | AL9: http://id.bnportugal.gov.pt/bib/catbnp/382749 | AM9: Livre
A10: 10003 | B10: 382749 | C10: 1 | D10: 19 | E10: https://purl.pt/42835 | I10: =HYPERLINK(O10) -> https://permalinkbnd.bnportugal.gov.pt/viewer/270109/?offset=#page=19&viewer=picture&o=info&n=0&q= | M10: https://purl.pt/42835 | N10: 270109 | O10: =CONCATENATE("https://permalinkbnd.bnportugal.gov.pt/viewer/",N10,"/?offset=#page=",D10,"&viewer=picture&o=info&n=0&q=") -> https://permalinkbnd.bnportugal.gov.pt/viewer/270109/?offset=#page=19&viewer=picture&o=info&n=0&q= | P10: 382749 | Q10: https://purl.pt/42835 | R10: https://bndigital.bnportugal.gov.pt//i/?IIIF=/60/58/22/4f/6058224f-9454-448f-8489-96a3a71253f5/iiif/cam-47-a_0000_000007.tif/full/!300,500/0/default.jpg | S10: Livro impresso | T10: Português | V10: Pretidão de amor | W10: endechas a Bárbara escrava seguidas da respectiva tradução em várias línguas... | Y10: 1.ª ed. | Z10: Lisboa : Imprensa Nacional | AA10: 1893 | AB10: 1893 | AC10: 2 v. | AD10: Camões, Luís de, 1524-1580 | AG10: Cunha, Xavier da, 1840-1920, Autor da introdução, etc. | AJ10: CAM. 270 V. | AK10: CAM500 | AL10: http://id.bnportugal.gov.pt/bib/catbnp/382749 | AM10: Livre
B11: 382749 | C11: 1 | D11: 23 | E11: https://purl.pt/42835 | I11: =HYPERLINK(O11) -> https://permalinkbnd.bnportugal.gov.pt/viewer/270109/?offset=#page=23&viewer=picture&o=info&n=0&q= | M11: https://purl.pt/42835 | N11: 270109 | O11: =CONCATENATE("https://permalinkbnd.bnportugal.gov.pt/viewer/",N11,"/?offset=#page=",D11,"&viewer=picture&o=info&n=0&q=") -> https://permalinkbnd.bnportugal.gov.pt/viewer/270109/?offset=#page=23&viewer=picture&o=info&n=0&q= | P11: 382749 | Q11: https://purl.pt/42835 | R11: https://bndigital.bnportugal.gov.pt//i/?IIIF=/60/58/22/4f/6058224f-9454-448f-8489-96a3a71253f5/iiif/cam-47-a_0000_000007.tif/full/!300,500/0/default.jpg | S11: Livro impresso | T11: Português | V11: Pretidão de amor | W11: endechas a Bárbara escrava seguidas da respectiva tradução em várias línguas... | Y11: 1.ª ed. | Z11: Lisboa : Imprensa Nacional | AA11: 1893 | AB11: 1893 | AC11: 2 v. | AD11: Camões, Luís de, 1524-1580 | AG11: Cunha, Xavier da, 1840-1920, Autor da introdução, etc. | AJ11: CAM. 270 V. | AK11: CAM500 | AL11: http://id.bnportugal.gov.pt/bib/catbnp/382749 | AM11: Livre
B12: 382834 | C12: 1 | D12: 11 | E12: https://purl.pt/43815 | F12: 11 [caravela com Vasco da Gama] | G12: 11 | I12: =HYPERLINK(O12) -> https://permalinkbnd.bnportugal.gov.pt/viewer/273316/?offset=#page=11&viewer=picture&o=info&n=0&q= | M12: https://purl.pt/43815 | N12: 273316 | O12: =CONCATENATE("https://permalinkbnd.bnportugal.gov.pt/viewer/",N12,"/?offset=#page=",D12,"&viewer=picture&o=info&n=0&q=") -> https://permalinkbnd.bnportugal.gov.pt/viewer/273316/?offset=#page=11&viewer=picture&o=info&n=0&q= | P12: 382834 | Q12: https://purl.pt/43815 | R12: https://bndigital.bnportugal.gov.pt//i/?IIIF=/b6/d0/71/c6/b6d071c6-e05d-4c17-96b2-07a62e35fb7f/iiif/cam-82-1-v_0000_000005.tif/full/!300,500/0/default.jpg | S12: Livro impresso | T12: Português | V12: Comemoração gloriosa da morte de Luiz de Camões 10 de Junho de 1889 | Y12: 1.ª ed. | Z12: Evora : Minerva Eborense de J. José Baptista, Rua d'Aviz | AA12: 1889 | AB12: 1889 | AC12: 12, 4 p. | AD12: Barata, António Francisco, 1836-1910 | AG12: Camões, Luís de, 1524-1580, Antecedente bibliográfico | AJ12: CAM. 309//13 V. | AK12: CAM500 | AL12: http://id.bnportugal.gov.pt/bib/catbnp/382834 | AM12: Livre
A13: 10004 | B13: 382844 | C13: 1 | D13: 3 | E13: https://purl.pt/43227 | F13: 3 | I13: =HYPERLINK(O13) -> https://permalinkbnd.bnportugal.gov.pt/viewer/271559/?offset=#page=3&viewer=picture&o=info&n=0&q= | M13: https://purl.pt/43227 | N13: 271559 | O13: =CONCATENATE("https://permalinkbnd.bnportugal.gov.pt/viewer/",N13,"/?offset=#page=",D13,"&viewer=picture&o=info&n=0&q=") -> https://permalinkbnd.bnportugal.gov.pt/viewer/271559/?offset=#page=3&viewer=picture&o=info&n=0&q= | P13: 382844 | Q13: https://purl.pt/43227 | R13: https://bndigital.bnportugal.gov.pt//i/?IIIF=/be/12/df/5e/be12df5e-248d-4e0b-823f-bb93ea5db616/iiif/cam-2058-v_0001.tif/full/!300,500/0/default.jpg | S13: Livro impresso | T13: Português | V13: A Luiz de Camões | W13: com notas curiosas e tres ineditos do poeta | Y13: 1.ª ed. | Z13: Evora : Tip. Minerva, de A.F. Barata | AA13: 1880 | AB13: 1880 | AC13: 24 p. | AD13: Barata, António Francisco, 1836-1910 | AG13: Camões, Luís de, 1524-1580, Antecedente bibliográfico | AJ13: L. 599//32 A. | AK13: CAM500 | AL13: http://id.bnportugal.gov.pt/bib/catbnp/382844 | AM13: Livre
A14: 10005 | B14: 382955 | C14: 1 | D14: 6 | E14: https://purl.pt/43816 | F14: 6 [site, retrato do Poeta laureado] | G14: 6 | I14: =HYPERLINK(O14) -> https://permalinkbnd.bnportugal.gov.pt/viewer/274171/?offset=#page=6&viewer=picture&o=info&n=0&q= | M14: https://purl.pt/43816 | N14: 274171 | O14: =CONCATENATE("https://permalinkbnd.bnportugal.gov.pt/viewer/",N14,"/?offset=#page=",D14,"&viewer=picture&o=info&n=0&q=") -> https://permalinkbnd.bnportugal.gov.pt/viewer/274171/?offset=#page=6&viewer=picture&o=info&n=0&q= | P14: 382955 | Q14: https://purl.pt/43816 | R14: https://bndigital.bnportugal.gov.pt//i/?IIIF=/df/8e/1b/e5/df8e1be5-0f74-4fdb-9b58-5bfa696ca99d/iiif/cam-53-5-a_0001.tif/full/!300,500/0/default.jpg | S14: Livro impresso | T14: Português | V14: Auto da cunhagem da medalha comemorativa das festas da Grande Comissão Portuense... | Y14: 1.ª ed. | Z14: Porto : s. n. | AA14: 1880 | AB14: 1880 | AE14: Grande Comissão Portuense | AG14: Camões, Luís de, 1524-1580, Antecedente bibliográfico | AJ14: CAM. 53//5 A. | AK14: CAM500 | AL14: http://id.bnportugal.gov.pt/bib/catbnp/382955 | AM14: Livre
A15: 10007 | B15: 382972 | C15: 1 | D15: 14 | E15: https://purl.pt/43819 | F15: 14 [site, imagem da medalha/gravura comemorativa do monumento erigido à memória do Poeta] | G15: 14 | I15: =HYPERLINK(O15) -> https://permalinkbnd.bnportugal.gov.pt/viewer/274229/?offset=#page=14&viewer=picture&o=info&n=0&q= | M15: https://purl.pt/43819 | N15: 274229 | O15: =CONCATENATE("https://permalinkbnd.bnportugal.gov.pt/viewer/",N15,"/?offset=#page=",D15,"&viewer=picture&o=info&n=0&q=") -> https://permalinkbnd.bnportugal.gov.pt/viewer/274229/?offset=#page=14&viewer=picture&o=info&n=0&q= | P15: 382972 | Q15: https://purl.pt/43819 | R15: https://bndigital.bnportugal.gov.pt//i/?IIIF=/80/3b/b9/df/803bb9df-b4de-496a-adbc-25a9d95b3638/iiif/cam-55-a_0007.tif/full/!300,500/0/default.jpg | S15: Livro impresso | T15: Português | V15: Surrexit | W15: homenagem a Luís de Camões | Y15: 1.ª ed. | Z15: Lisboa : Imprensa Nacional | AA15: 1880 | AB15: 1880 | AD15: Ribeiro, Tomás, 1831-1901 | AJ15: CAM. 55 A. | AK15: CAM500 | AL15: http://id.bnportugal.gov.pt/bib/catbnp/382972 | AM15: Livre
A16: 10008 | B16: 382978 | C16: 1 | D16: 7 | E16: https://purl.pt/43823 | F16: 7 [site], 13 [site, itinerário do cortejo triunfal], 15 [site préstito cívico e triunfal] | G16: 7, 13, 15 | I16: =HYPERLINK(O16) -> https://permalinkbnd.bnportugal.gov.pt/viewer/274235/?offset=#page=7&viewer=picture&o=info&n=0&q= | M16: https://purl.pt/43823 | N16: 274235 | O16: =CONCATENATE("https://permalinkbnd.bnportugal.gov.pt/viewer/",N16,"/?offset=#page=",D16,"&viewer=picture&o=info&n=0&q=") -> https://permalinkbnd.bnportugal.gov.pt/viewer/274235/?offset=#page=7&viewer=picture&o=info&n=0&q= | P16: 382978 | Q16: https://purl.pt/43823 | R16: https://bndigital.bnportugal.gov.pt//i/?IIIF=/8a/04/06/d1/8a0406d1-dcdf-40af-9ba2-5fa354405f51/iiif/cam-56-a_0001.tif/full/!300,500/0/default.jpg | S16: Livro impresso | T16: Português | V16: Programa da celebração em Lisboa do terceiro centenário de Luís de Camões | W16: comemoração promovida pela imprensa jornalística auxiliada pela Câmara Municipal | Y16: 1.ª ed. | Z16: Lisboa : Tip. Universal | AA16: 1880 | AB16: 1880 | AC16: 8 p. | AG16: Camões, Luís de, 1524-1580, Antecedente bibliográfico | AJ16: CAM. 134 A. | AK16: CAM500 | AL16: http://id.bnportugal.gov.pt/bib/catbnp/382978 | AM16: Livre
A17: 10009 | B17: 382978 | C17: 1 | D17: 13 | E17: https://purl.pt/43823 | F17: 7 [site], 13 [site, itinerário do cortejo triunfal], 15 [site préstito cívico e triunfal] | G17: 7, 13, 15 | I17: =HYPERLINK(O17) -> https://permalinkbnd.bnportugal.gov.pt/viewer/274235/?offset=#page=13&viewer=picture&o=info&n=0&q= | M17: https://purl.pt/43823 | N17: 274235 | O17: =CONCATENATE("https://permalinkbnd.bnportugal.gov.pt/viewer/",N17,"/?offset=#page=",D17,"&viewer=picture&o=info&n=0&q=") -> https://permalinkbnd.bnportugal.gov.pt/viewer/274235/?offset=#page=13&viewer=picture&o=info&n=0&q= | P17: 382978 | Q17: https://purl.pt/43823 | R17: https://bndigital.bnportugal.gov.pt//i/?IIIF=/8a/04/06/d1/8a0406d1-dcdf-40af-9ba2-5fa354405f51/iiif/cam-56-a_0001.tif/full/!300,500/0/default.jpg | S17: Livro impresso | T17: Português | V17: Programa da celebração em Lisboa do terceiro centenário de Luís de Camões | W17: comemoração promovida pela imprensa jornalística auxiliada pela Câmara Municipal | Y17: 1.ª ed. | Z17: Lisboa : Tip. Universal | AA17: 1880 | AB17: 1880 | AC17: 8 p. | AG17: Camões, Luís de, 1524-1580, Antecedente bibliográfico | AJ17: CAM. 134 A. | AK17: CAM500 | AL17: http://id.bnportugal.gov.pt/bib/catbnp/382978 | AM17: Livre
A18: 10010 | B18: 382978 | C18: 1 | D18: 15 | E18: https://purl.pt/43823 | F18: 7 [site], 13 [site, itinerário do cortejo triunfal], 15 [site préstito cívico e triunfal] | G18: 7, 13, 15 | I18: =HYPERLINK(O18) -> https://permalinkbnd.bnportugal.gov.pt/viewer/274235/?offset=#page=15&viewer=picture&o=info&n=0&q= | M18: https://purl.pt/43823 | N18: 274235 | O18: =CONCATENATE("https://permalinkbnd.bnportugal.gov.pt/viewer/",N18,"/?offset=#page=",D18,"&viewer=picture&o=info&n=0&q=") -> https://permalinkbnd.bnportugal.gov.pt/viewer/274235/?offset=#page=15&viewer=picture&o=info&n=0&q= | P18: 382978 | Q18: https://purl.pt/43823 | R18: https://bndigital.bnportugal.gov.pt//i/?IIIF=/8a/04/06/d1/8a0406d1-dcdf-40af-9ba2-5fa354405f51/iiif/cam-56-a_0001.tif/full/!300,500/0/default.jpg | S18: Livro impresso | T18: Português | V18: Programa da celebração em Lisboa do terceiro centenário de Luís de Camões | W18: comemoração promovida pela imprensa jornalística auxiliada pela Câmara Municipal | Y18: 1.ª ed. | Z18: Lisboa : Tip. Universal | AA18: 1880 | AB18: 1880 | AC18: 8 p. | AG18: Camões, Luís de, 1524-1580, Antecedente bibliográfico | AJ18: CAM. 134 A. | AK18: CAM500 | AL18: http://id.bnportugal.gov.pt/bib/catbnp/382978 | AM18: Livre
A19: 10011 | B19: 382981 | C19: 1 | D19: 9 | E19: https://purl.pt/43818 | F19: 9 | I19: =HYPERLINK(O19) -> https://permalinkbnd.bnportugal.gov.pt/viewer/1880/?offset=#page=9&viewer=picture&o=info&n=0&q= | M19: https://purl.pt/43818 | N19: 1880 | O19: =CONCATENATE("https://permalinkbnd.bnportugal.gov.pt/viewer/",N19,"/?offset=#page=",D19,"&viewer=picture&o=info&n=0&q=") -> https://permalinkbnd.bnportugal.gov.pt/viewer/1880/?offset=#page=9&viewer=picture&o=info&n=0&q= | P19: 382981 | Q19: https://purl.pt/43818 | R19: https://bndigital.bnportugal.gov.pt//i/?IIIF=/2b/2d/51/1b/2b2d511b-4290-4cc3-b338-dffc6cbedad2/iiif/cam-57-a_0001.tif/full/!300,500/0/default.jpg | S19: Livro impresso | T19: Português | V19: Relatório da Directoria do Gabinete de Leitura do Rio de Janeiro em 1880 | Y19: 1.ª ed. | Z19: Rio de Janeiro : Tip e lit. Moreira Maximino | AA19: 1881 | AB19: 1881 | AI19: Real Gabinete Português de Leitura do Rio de Janeiro | AJ19: CAM. 57 A. | AK19: CAM500 | AL19: http://id.bnportugal.gov.pt/bib/catbnp/382981 | AM19: Livre
A20: 10013 | B20: 385945 | C20: 1 | D20: 15 | E20: https://purl.pt/43873 | F20: 10 [fotografia do autor], 11 [portada], 15 | G20: 15 | I20: =HYPERLINK(O20) -> https://permalinkbnd.bnportugal.gov.pt/viewer/273149/?offset=#page=15&viewer=picture&o=info&n=0&q= | M20: https://purl.pt/43873 | N20: 273149 | O20: =CONCATENATE("https://permalinkbnd.bnportugal.gov.pt/viewer/",N20,"/?offset=#page=",D20,"&viewer=picture&o=info&n=0&q=") -> https://permalinkbnd.bnportugal.gov.pt/viewer/273149/?offset=#page=15&viewer=picture&o=info&n=0&q= | P20: 385945 | Q20: https://purl.pt/43873 | R20: https://bndigital.bnportugal.gov.pt//i/?IIIF=/ca/5d/8c/c5/ca5d8cc5-b85c-4f76-893f-7de2d31a6d43/iiif/cam-63-a_0000_000007.tif/full/!300,500/0/default.jpg | S20: Livro impresso | T20: Poliglota | U20: Português | V20: Álbum literário comemorativo do terceiro centenário de Luís de Camões | Y20: 1.ª ed. | Z20: Porto : Tip. Ocidental | AA20: 1880 | AB20: 1880 | AC20: 28 p. | AG20: Esteves, Francisco Xavier, 1864-1944, Editor literário | AJ20: CAM. 133 A. | AK20: CAM500 | AL20: http://id.bnportugal.gov.pt/bib/catbnp/385945 | AM20: Livre
A21: 10014 | B21: 385949 | C21: 1 | D21: 1 | E21: https://purl.pt/43866 | F21: 1 | G21: 1 | I21: =HYPERLINK(O21) -> https://permalinkbnd.bnportugal.gov.pt/viewer/274256/?offset=#page=1&viewer=picture&o=info&n=0&q= | M21: https://purl.pt/43866 | N21: 274256 | O21: =CONCATENATE("https://permalinkbnd.bnportugal.gov.pt/viewer/",N21,"/?offset=#page=",D21,"&viewer=picture&o=info&n=0&q=") -> https://permalinkbnd.bnportugal.gov.pt/viewer/274256/?offset=#page=1&viewer=picture&o=info&n=0&q= | P21: 385949 | Q21: https://purl.pt/43866 | R21: https://bndigital.bnportugal.gov.pt//i/?IIIF=/06/33/d8/97/0633d897-92cc-4a30-beb0-aa004a6f6470/iiif/cam-64-1-a_0001.tif/full/!300,500/0/default.jpg | S21: Livro impresso | T21: Português | V21: Homenagem a Camões | W21: Luís de Camões e a nacionalidade portuguesa | Y21: 1.ª ed. | Z21: São Miguel : s. n. | AA21: 1880 | AB21: 1880 | AE21: Centro Republicano Federal de Ponta Delgada | AJ21: CAM. 64//1 A. | AK21: CAM500 | AL21: http://id.bnportugal.gov.pt/bib/catbnp/385949 | AM21: Livre
A22: 10015 | B22: 386935 | C22: 1 | D22: 1 | E22: https://purl.pt/43871 | F22: 1 | I22: =HYPERLINK(O22) -> https://permalinkbnd.bnportugal.gov.pt/viewer/273122/?offset=#page=1&viewer=picture&o=info&n=0&q= | M22: https://purl.pt/43871 | N22: 273122 | O22: =CONCATENATE("https://permalinkbnd.bnportugal.gov.pt/viewer/",N22,"/?offset=#page=",D22,"&viewer=picture&o=info&n=0&q=") -> https://permalinkbnd.bnportugal.gov.pt/viewer/273122/?offset=#page=1&viewer=picture&o=info&n=0&q= | P22: 386935 | Q22: https://purl.pt/43871 | R22: https://bndigital.bnportugal.gov.pt//i/?IIIF=/c8/18/91/78/c8189178-5871-4300-9edd-154703c6e75a/iiif/cam-64-3-a_0000_000001.tif/full/!300,500/0/default.jpg | S22: Livro impresso | T22: Português | V22: Vianna a Camões | W22: comemoração do tricentenário do imortal cantor dos Lusíadas | Y22: 1.ª ed. | Z22: Viana do Castelo : André Jorge Pereira & Filho | AA22: 1880 | AB22: 1880 | AJ22: CAM. 64//3 A. | AK22: CAM500 | AL22: http://id.bnportugal.gov.pt/bib/catbnp/386935 | AM22: Livre
A23: 10016 | B23: 386992 | C23: 1 | D23: 1 | E23: https://purl.pt/43661 | F23: 1 | G23: 1 | I23: =HYPERLINK(O23) -> https://permalinkbnd.bnportugal.gov.pt/viewer/273124/?offset=#page=1&viewer=picture&o=info&n=0&q= | M23: https://purl.pt/43661 | N23: 273124 | O23: =CONCATENATE("https://permalinkbnd.bnportugal.gov.pt/viewer/",N23,"/?offset=#page=",D23,"&viewer=picture&o=info&n=0&q=") -> https://permalinkbnd.bnportugal.gov.pt/viewer/273124/?offset=#page=1&viewer=picture&o=info&n=0&q= | P23: 386992 | Q23: https://purl.pt/43661 | R23: https://bndigital.bnportugal.gov.pt//i/?IIIF=/0c/53/05/58/0c530558-6907-414a-974d-e379f3070104/iiif/cam-64-4-a_0000_000001.tif/full/!300,500/0/default.jpg | S23: Livro impresso | T23: Português | V23: Homenagem da Sociedade Amizade, Recreio e Ínstrução | Y23: 1.ª ed. | Z23: S. Miguel : Lit. dos Açores | AA23: 1880 | AB23: 1880 | AG23: Camões, Luís de, 1524-1580, Antecedente bibliográfico | AI23: Sociedade Amizade Recreio e Ínstrução | AJ23: CAM. 64//4 A. | AK23: CAM500 | AL23: http://id.bnportugal.gov.pt/bib/catbnp/386992 | AM23: Livre
A24: 10019 | B24: 396405 | C24: 1 | D24: 1 | E24: https://purl.pt/6115 | F24: 1 | G24: 1 | I24: =HYPERLINK(O24) -> https://permalinkbnd.bnportugal.gov.pt/viewer/36059/?offset=#page=1&viewer=picture&o=info&n=0&q= | M24: https://purl.pt/6115 | N24: 36059 | O24: =CONCATENATE("https://permalinkbnd.bnportugal.gov.pt/viewer/",N24,"/?offset=#page=",D24,"&viewer=picture&o=info&n=0&q=") -> https://permalinkbnd.bnportugal.gov.pt/viewer/36059/?offset=#page=1&viewer=picture&o=info&n=0&q= | P24: 396405 | Q24: https://purl.pt/6115 | R24: https://bndigital.bnportugal.gov.pt//i/?IIIF=/11/21/33/35/11213335-0c6f-4347-8501-397d47049e54/iiif/e-2172-v_0000_1-2_p24-C-R0150_000001.tif/full/!300,500/0/default.jpg | S24: Iconografia | T24: Português | V24: Luís de Camões | Y24: 1.ª ed. | Z24: Macau : Com. Org. Comem. Dia de Portugal de Camões e das Comunid. Portuguesas | AA24: 1992 | AB24: 1992 | AC24: 1 imagem | AD24: Fialho, Fernando Jorge, 1965- | AJ24: PURL 6115/0 | AL24: http://id.bnportugal.gov.pt/bib/catbnp/396405 | AM24: Interno
A25: 10021 | B25: 397670 | C25: 1 | D25: 11 | E25: https://purl.pt/43874 | F25: 11, 13 [apontamento sobre o Centenário de Camões, site?] | H25: pag. assumida 11 | I25: =HYPERLINK(O25) -> https://permalinkbnd.bnportugal.gov.pt/viewer/273150/?offset=#page=11&viewer=picture&o=info&n=0&q= | M25: https://purl.pt/43874 | N25: 273150 | O25: =CONCATENATE("https://permalinkbnd.bnportugal.gov.pt/viewer/",N25,"/?offset=#page=",D25,"&viewer=picture&o=info&n=0&q=") -> https://permalinkbnd.bnportugal.gov.pt/viewer/273150/?offset=#page=11&viewer=picture&o=info&n=0&q= | P25: 397670 | Q25: https://purl.pt/43874 | R25: https://bndigital.bnportugal.gov.pt//i/?IIIF=/f4/b1/c2/b3/f4b1c2b3-f0bb-4cb4-b767-93d0dae46bc3/iiif/cam-70-v_0000_000007.tif/full/!300,500/0/default.jpg | S25: Livro impresso | T25: Português ; Francês | V25: Episodio da Ilha de Venus extrahido dos Lusiadas de Camões | Y25: 1.ª ed. | Z25: Braga : Typ. Lealdade : Sociedade Democrática Recreativa | AA25: 1880 | AB25: 1880 | AC25: 23 p. | AD25: Camões, Luís de, 1524-1580 | AG25: Caldas, José Joaquim da Silva Pereira, 1818-1903, Autor da introdução, etc. ; Cournand, Antoine de, Autor da introdução, etc. | AJ25: L. 5895//9 A | AK25: CAM500 | AL25: http://id.bnportugal.gov.pt/bib/catbnp/397670 | AM25: Livre | AN25: Tricentenário de Camões, 10 de Junho de 1880
A26: 10024 | B26: 397818 | C26: 1 | D26: 6 | E26: https://purl.pt/43426 | F26: 6, 106 [retrato de Camões, padrão levantado por Vasco da Gama] | G26: 6 | I26: =HYPERLINK(O26) -> https://permalinkbnd.bnportugal.gov.pt/viewer/272368/?offset=#page=6&viewer=picture&o=info&n=0&q= | M26: https://purl.pt/43426 | N26: 272368 | O26: =CONCATENATE("https://permalinkbnd.bnportugal.gov.pt/viewer/",N26,"/?offset=#page=",D26,"&viewer=picture&o=info&n=0&q=") -> https://permalinkbnd.bnportugal.gov.pt/viewer/272368/?offset=#page=6&viewer=picture&o=info&n=0&q= | P26: 397818 | Q26: https://purl.pt/43426 | R26: https://bndigital.bnportugal.gov.pt//i/?IIIF=/58/13/66/39/58136639-f7f1-4612-94b8-d6a78a970d34/iiif/cam-707-p_0007.tif/full/!300,500/0/default.jpg | S26: Livro impresso | T26: Português | V26: Os Lusíadas | W26: poema épico | Y26: Nova ed., cuidadosamente revista | Z26: Lisboa : Livraria de António Maria Pereira | AA26: 1891 | AB26: 1891 | AC26: XVIII, 457 p., 2 est. | AD26: Camões, Luís de, 1524-1580 | AG26: Silva, Inocêncio Francisco da, 1810-1876, Autor da introdução, etc. | AJ26: CAM. 707 P. | AK26: CAM500 | AL26: http://id.bnportugal.gov.pt/bib/catbnp/397818 | AM26: Livre
A27: 10026 | B27: 397822 | C27: 1 | D27: 7 | E27: https://purl.pt/43741 | F27: 7, 388 [apontamento site] | H27: pag. assumida 7 | I27: =HYPERLINK(O27) -> https://permalinkbnd.bnportugal.gov.pt/viewer/274090/?offset=#page=7&viewer=picture&o=info&n=0&q= | M27: https://purl.pt/43741 | N27: 274090 | O27: =CONCATENATE("https://permalinkbnd.bnportugal.gov.pt/viewer/",N27,"/?offset=#page=",D27,"&viewer=picture&o=info&n=0&q=") -> https://permalinkbnd.bnportugal.gov.pt/viewer/274090/?offset=#page=7&viewer=picture&o=info&n=0&q= | P27: 397822 | Q27: https://purl.pt/43741 | R27: https://bndigital.bnportugal.gov.pt//i/?IIIF=/53/07/f6/e6/5307f6e6-7747-45f0-8d9c-435d2871d068/iiif/cam-35-v_0007.tif/full/!300,500/0/default.jpg | S27: Livro impresso | T27: Português | V27: Os Lusíadas | Y27: Ed. comemorativa do IV Centenário do Descobrimento Marítimo da India | Z27: Lisboa : Typographia do Commercio | AA27: 1898 | AB27: 1898 | AC27: 186 fls. | AD27: Camões, Luís de, 1524-1580 | AJ27: CAM. 35 V. | AK27: CAM500 | AL27: http://id.bnportugal.gov.pt/bib/catbnp/397822 | AM27: Livre
A28: 10030 | B28: 397852 | C28: 1 | D28: 14 | E28: https://purl.pt/43811 | F28: 14 [vinheta site] | H28: pag. assumida 14 | I28: =HYPERLINK(O28) -> https://permalinkbnd.bnportugal.gov.pt/viewer/274172/?offset=#page=14&viewer=picture&o=info&n=0&q= | M28: https://purl.pt/43811 | N28: 274172 | O28: =CONCATENATE("https://permalinkbnd.bnportugal.gov.pt/viewer/",N28,"/?offset=#page=",D28,"&viewer=picture&o=info&n=0&q=") -> https://permalinkbnd.bnportugal.gov.pt/viewer/274172/?offset=#page=14&viewer=picture&o=info&n=0&q= | P28: 397852 | Q28: https://purl.pt/43811 | R28: https://bndigital.bnportugal.gov.pt//i/?IIIF=/97/d2/74/d0/97d274d0-35d0-4540-bdbb-0b1af3d4ba91/iiif/cam-45-v_0005.tif/full/!300,500/0/default.jpg | S28: Livro impresso | T28: Francês ; Português | V28: Les Lusiades | W28: chant primier | Y28: Edition commemorative du septieme anniversaire du tricentenaire de Camöes | Z28: Lisboa : Imprensa Nacional | AA28: 1887 | AB28: 1887 | AC28: 79 p. | AD28: Camões, Luís de, 1524-1580 | AG28: Courtois, Henri de, Tradutor | AJ28: L. 5907//7 A. | AK28: CAM500 | AL28: http://id.bnportugal.gov.pt/bib/catbnp/397852 | AM28: Livre | AN28: Texto em português e francês
A29: 10031 | B29: 397863 | C29: 1 | D29: 11 | E29: https://purl.pt/43931 | F29: 11 [portada] | H29: pag. assumida 11 | I29: =HYPERLINK(O29) -> https://permalinkbnd.bnportugal.gov.pt/viewer/273148/?offset=#page=11&viewer=picture&o=info&n=0&q= | M29: https://purl.pt/43931 | N29: 273148 | O29: =CONCATENATE("https://permalinkbnd.bnportugal.gov.pt/viewer/",N29,"/?offset=#page=",D29,"&viewer=picture&o=info&n=0&q=") -> https://permalinkbnd.bnportugal.gov.pt/viewer/273148/?offset=#page=11&viewer=picture&o=info&n=0&q= | P29: 397863 | Q29: https://purl.pt/43931 | R29: https://bndigital.bnportugal.gov.pt//i/?IIIF=/c3/91/eb/4c/c391eb4c-8bd2-4992-a05f-625f8ef77ebc/iiif/cam-69-v_0000_000001.tif/full/!300,500/0/default.jpg | S29: Livro impresso | T29: Português | V29: A Ode de Luiz de Camões ao Conde do Redondo, restituida á sua primitiva licção | Y29: Edição commemorativa do 4º anniversario do Tricentenario Camoniano | Z29: Lisboa : Typographia Elzeviriana | AA29: 1884 | AB29: 1884 | AC29: 22, 2 p. | AD29: Camões, Luís de, 1524-1580 | AG29: Cunha, Xavier da, 1840-1920, Editor literário ; Carvalho, Alfredo de, fl. 1884, Tipógrafo | AJ29: CAM. 69 V. | AK29: CAM500 | AL29: http://id.bnportugal.gov.pt/bib/catbnp/397863 | AM29: Livre
A30: 10033 | B30: 397876 | C30: 1 | D30: 9 | E30: https://purl.pt/43825 | F30: 9 | H30: pag. assumida 9 | I30: =HYPERLINK(O30) -> https://permalinkbnd.bnportugal.gov.pt/viewer/274230/?offset=#page=9&viewer=picture&o=info&n=0&q= | M30: https://purl.pt/43825 | N30: 274230 | O30: =CONCATENATE("https://permalinkbnd.bnportugal.gov.pt/viewer/",N30,"/?offset=#page=",D30,"&viewer=picture&o=info&n=0&q=") -> https://permalinkbnd.bnportugal.gov.pt/viewer/274230/?offset=#page=9&viewer=picture&o=info&n=0&q= | P30: 397876 | Q30: https://purl.pt/43825 | R30: https://bndigital.bnportugal.gov.pt//i/?IIIF=/de/b5/45/9c/deb5459c-316c-4583-bb29-fa7038aaebdc/iiif/cam-59-v_0009.tif/full/!300,500/0/default.jpg | S30: Livro impresso | T30: Francês | U30: Português | V30: Sonnets choisis | Y30: 1.ª ed. | Z30: Paris : Plon | AA30: 1879 | AB30: 1879 | AC30: VII, 40 p. | AD30: Camões, Luís de, 1524-1580 | AG30: Cazaubon, Léonce, Tradutor | AJ30: CAM. 59 V. | AK30: CAM500 | AL30: http://id.bnportugal.gov.pt/bib/catbnp/397876 | AM30: Livre
A31: 10034 | B31: 397877 | C31: 1 | D31: 9 | E31: https://purl.pt/43875 | F31: 9 [retrato de Camões] | G31: 9 | I31: =HYPERLINK(O31) -> https://permalinkbnd.bnportugal.gov.pt/viewer/1576/?offset=#page=9&viewer=picture&o=info&n=0&q= | M31: https://purl.pt/43875 | N31: 1576 | O31: =CONCATENATE("https://permalinkbnd.bnportugal.gov.pt/viewer/",N31,"/?offset=#page=",D31,"&viewer=picture&o=info&n=0&q=") -> https://permalinkbnd.bnportugal.gov.pt/viewer/1576/?offset=#page=9&viewer=picture&o=info&n=0&q= | P31: 397877 | Q31: https://purl.pt/43875 | R31: https://bndigital.bnportugal.gov.pt//i/?IIIF=/3a/34/50/28/3a345028-610d-4c37-af11-98e95904bfe5/iiif/cam-75-1-v_0000_000001.tif/full/!300,500/0/default.jpg | S31: Livro impresso | T31: Português | V31: Tercetos impressos pela primeira vez, em 1576, na História da Província de Santa Cruz, de Pedro de Magalhães Gandavo | Y31: 1.ª ed. | Z31: Lisboa : Joaquim Eusébio dos Santos | AA31: 1894 | AB31: 1894 | AC31: 12 p., 1 est. | AD31: Camões, Luís de, 1524-1580 | AG31: Braga, Teófilo, 1843-1924, Comentador (em meio audiovisual) | AJ31: CAM. 75//1 V. | AK31: CAM500 | AL31: http://id.bnportugal.gov.pt/bib/catbnp/397877 | AM31: Livre
A32: 10035 | B32: 401648 | C32: 1 | D32: 3 | E32: https://purl.pt/43662 | F32: 1, 3 [site] [portada, retrato Camões] | G32: 3 | I32: =HYPERLINK(O32) -> https://permalinkbnd.bnportugal.gov.pt/viewer/273125/?offset=#page=3&viewer=picture&o=info&n=0&q= | M32: https://purl.pt/43662 | N32: 273125 | O32: =CONCATENATE("https://permalinkbnd.bnportugal.gov.pt/viewer/",N32,"/?offset=#page=",D32,"&viewer=picture&o=info&n=0&q=") -> https://permalinkbnd.bnportugal.gov.pt/viewer/273125/?offset=#page=3&viewer=picture&o=info&n=0&q= | P32: 401648 | Q32: https://purl.pt/43662 | R32: https://bndigital.bnportugal.gov.pt//i/?IIIF=/c5/6f/77/dc/c56f77dc-6fe1-4b19-8eac-61a13ea62b02/iiif/cam-64-7-a_0000_000001.tif/full/!300,500/0/default.jpg | S32: Periódico | T32: Português | V32: Plutarcho portuguez | W32: colecção de retratos e biographias dos principaes vultos historicos da civilisação portugueza | Y32: 1.ª ed. | Z32: Porto : Julio Costa, Emilio Biel | AA32: 1881 | AB32: 1881 | AJ32: J. 1690//7 V. | AK32: CAM500 | AL32: http://id.bnportugal.gov.pt/bib/catbnp/401648 | AM32: Livre | AR32: Plutarco português
A33: 10038 | B33: 401658 | C33: 1 | D33: 1 | E33: https://purl.pt/43862 | F33: 1 | G33: 1 | I33: =HYPERLINK(O33) -> https://permalinkbnd.bnportugal.gov.pt/viewer/3/?offset=#page=1&viewer=picture&o=info&n=0&q= | M33: https://purl.pt/43862 | N33: 3 | O33: =CONCATENATE("https://permalinkbnd.bnportugal.gov.pt/viewer/",N33,"/?offset=#page=",D33,"&viewer=picture&o=info&n=0&q=") -> https://permalinkbnd.bnportugal.gov.pt/viewer/3/?offset=#page=1&viewer=picture&o=info&n=0&q= | P33: 401658 | Q33: https://purl.pt/43862 | R33: https://bndigital.bnportugal.gov.pt//i/?IIIF=/9e/f3/33/17/9ef33317-4c7f-4371-8da7-082d54e2724e/iiif/cam-66-2-a_0001.tif/full/!300,500/0/default.jpg | S33: Livro impresso | T33: Português | V33: Victor Hugo a Camões no 3º centenário | Y33: 1.ª ed. | Z33: Lisboa : J. Camilo Videira | AA33: 1880 | AB33: 1880 | AJ33: CAM. 66//2 A. | AK33: CAM500 | AL33: http://id.bnportugal.gov.pt/bib/catbnp/401658 | AM33: Livre
A34: 10040 | B34: 401739 | C34: 1 | D34: 1 | E34: https://purl.pt/43865 | F34: 1 | G34: 1 | I34: =HYPERLINK(O34) -> https://permalinkbnd.bnportugal.gov.pt/viewer/274260/?offset=#page=1&viewer=picture&o=info&n=0&q= | M34: https://purl.pt/43865 | N34: 274260 | O34: =CONCATENATE("https://permalinkbnd.bnportugal.gov.pt/viewer/",N34,"/?offset=#page=",D34,"&viewer=picture&o=info&n=0&q=") -> https://permalinkbnd.bnportugal.gov.pt/viewer/274260/?offset=#page=1&viewer=picture&o=info&n=0&q= | P34: 401739 | Q34: https://purl.pt/43865 | R34: https://bndigital.bnportugal.gov.pt//i/?IIIF=/2d/fe/15/07/2dfe1507-1025-44a9-b149-33c026517803/iiif/cam-66-5-a_0001.tif/full/!300,500/0/default.jpg | S34: Livro impresso | T34: Português | V34: Homenagem ao príncipe dos poetas peninsulares ao reconstrutor da língua portuguesa, a Luís de Camões | Y34: 1.ª ed. | Z34: Lisboa : Emp. Dic. Univ. Português | AA34: 1880 | AB34: 1880 | AC34: 4 p. | AJ34: CAM. 66//5 A. | AK34: CAM500 | AL34: http://id.bnportugal.gov.pt/bib/catbnp/401739 | AM34: Livre
A35: 10048 | B35: 402086 | C35: 1 | D35: 16 | E35: https://purl.pt/43891 | F35: 16 [site], 22 | G35: 16, 22 | I35: =HYPERLINK(O35) -> https://permalinkbnd.bnportugal.gov.pt/viewer/274280/?offset=#page=16&viewer=picture&o=info&n=0&q= | M35: https://purl.pt/43891 | N35: 274280 | O35: =CONCATENATE("https://permalinkbnd.bnportugal.gov.pt/viewer/",N35,"/?offset=#page=",D35,"&viewer=picture&o=info&n=0&q=") -> https://permalinkbnd.bnportugal.gov.pt/viewer/274280/?offset=#page=16&viewer=picture&o=info&n=0&q= | P35: 402086 | Q35: https://purl.pt/43891 | R35: https://bndigital.bnportugal.gov.pt//i/?IIIF=/dc/d1/27/77/dcd12777-3117-4eb1-94d0-a5bb23f4e7b6/iiif/cam-69-a_0005.tif/full/!300,500/0/default.jpg | S35: Livro impresso | T35: Português | V35: Collecção Camoneana de José do Canto | W35: tentativa de um catalogo methodico e remissivo | Y35: 1.ª ed. | Z35: Lisboa : Imprensa Nacional | AA35: 1895 | AB35: 1895 | AC35: XI, 357, 5 p. | AD35: Canto, José do, 1820-1898 | AG35: Reis, Jaime Batalha, 1847-1935, Antigo possuidor | AJ35: CAM. 69 A. | AK35: CAM500 | AL35: http://id.bnportugal.gov.pt/bib/catbnp/402086 | AM35: Livre
A36: 10049 | B36: 402086 | C36: 1 | D36: 22 | E36: https://purl.pt/43891 | F36: 16 [site], 22 | G36: 16, 22 | I36: =HYPERLINK(O36) -> https://permalinkbnd.bnportugal.gov.pt/viewer/274280/?offset=#page=22&viewer=picture&o=info&n=0&q= | M36: https://purl.pt/43891 | N36: 274280 | O36: =CONCATENATE("https://permalinkbnd.bnportugal.gov.pt/viewer/",N36,"/?offset=#page=",D36,"&viewer=picture&o=info&n=0&q=") -> https://permalinkbnd.bnportugal.gov.pt/viewer/274280/?offset=#page=22&viewer=picture&o=info&n=0&q= | P36: 402086 | Q36: https://purl.pt/43891 | R36: https://bndigital.bnportugal.gov.pt//i/?IIIF=/dc/d1/27/77/dcd12777-3117-4eb1-94d0-a5bb23f4e7b6/iiif/cam-69-a_0005.tif/full/!300,500/0/default.jpg | S36: Livro impresso | T36: Português | V36: Collecção Camoneana de José do Canto | W36: tentativa de um catalogo methodico e remissivo | Y36: 1.ª ed. | Z36: Lisboa : Imprensa Nacional | AA36: 1895 | AB36: 1895 | AC36: XI, 357, 5 p. | AD36: Canto, José do, 1820-1898 | AG36: Reis, Jaime Batalha, 1847-1935, Antigo possuidor | AJ36: CAM. 69 A. | AK36: CAM500 | AL36: http://id.bnportugal.gov.pt/bib/catbnp/402086 | AM36: Livre
A37: 10050 | B37: 402917 | C37: 1 | D37: 9 | E37: https://purl.pt/43923 | F37: 9 | H37: pag. assumida 9 | I37: =HYPERLINK(O37) -> https://permalinkbnd.bnportugal.gov.pt/viewer/273560/?offset=#page=9&viewer=picture&o=info&n=0&q= | M37: https://purl.pt/43923 | N37: 273560 | O37: =CONCATENATE("https://permalinkbnd.bnportugal.gov.pt/viewer/",N37,"/?offset=#page=",D37,"&viewer=picture&o=info&n=0&q=") -> https://permalinkbnd.bnportugal.gov.pt/viewer/273560/?offset=#page=9&viewer=picture&o=info&n=0&q= | P37: 402917 | Q37: https://purl.pt/43923 | R37: https://bndigital.bnportugal.gov.pt//i/?IIIF=/68/36/f7/0d/6836f70d-c35f-47cf-856b-993a65ff926c/iiif/cam-130-a_0000_000001.tif/full/!300,500/0/default.jpg | S37: Livro impresso | T37: Português | U37: Alemão | V37: Camoëns in Cintra | W37: (poemeto extrahido do livro Tag und Nachstucke) | Y37: 1.ª ed. | Z37: Lisboa : M. Gomes, Livreiro-Editor | AA37: 1891 | AB37: 1891 | AC37: 39, 1 p. | AD37: Schack, Adolf Friederich Graf von, 1815-1894 | AG37: Camões, Luís de, 1524-1580, Antecedente bibliográfico | AJ37: CAM. 71//1 A. | AK37: CAM500 | AL37: http://id.bnportugal.gov.pt/bib/catbnp/402917 | AM37: Livre
A38: 10054 | B38: 404543 | C38: 1 | D38: 7 | E38: https://purl.pt/43827 | F38: 7 | H38: pag. assumida 7 | I38: =HYPERLINK(O38) -> https://permalinkbnd.bnportugal.gov.pt/viewer/273347/?offset=#page=7&viewer=picture&o=info&n=0&q= | M38: https://purl.pt/43827 | N38: 273347 | O38: =CONCATENATE("https://permalinkbnd.bnportugal.gov.pt/viewer/",N38,"/?offset=#page=",D38,"&viewer=picture&o=info&n=0&q=") -> https://permalinkbnd.bnportugal.gov.pt/viewer/273347/?offset=#page=7&viewer=picture&o=info&n=0&q= | P38: 404543 | Q38: https://purl.pt/43827 | R38: https://bndigital.bnportugal.gov.pt//i/?IIIF=/9f/79/bf/47/9f79bf47-41ea-438e-b7e9-2c631c46bb91/iiif/cam-81-a_0000_000001.tif/full/!300,500/0/default.jpg | S38: Livro impresso | T38: Português | V38: Excerptos dos Lusíadas | W38: canto II | Y38: 1.ª ed. | Z38: Lisboa : Imprensa Nacional | AA38: 1889 | AB38: 1889 | AD38: Camões, Luís de, 1524-1580 | AJ38: CAM. 81 A. | AK38: CAM500 | AL38: http://id.bnportugal.gov.pt/bib/catbnp/404543 | AM38: Livre
A39: 10055 | B39: 404800 | C39: 1 | D39: 21 | E39: https://purl.pt/43914 | F39: 3, 21, 69 | G39: 21, 69 | I39: =HYPERLINK(O39) -> https://permalinkbnd.bnportugal.gov.pt/viewer/274348/?offset=#page=21&viewer=picture&o=info&n=0&q= | M39: https://purl.pt/43914 | N39: 274348 | O39: =CONCATENATE("https://permalinkbnd.bnportugal.gov.pt/viewer/",N39,"/?offset=#page=",D39,"&viewer=picture&o=info&n=0&q=") -> https://permalinkbnd.bnportugal.gov.pt/viewer/274348/?offset=#page=21&viewer=picture&o=info&n=0&q= | P39: 404800 | Q39: https://purl.pt/43914 | R39: https://bndigital.bnportugal.gov.pt//i/?IIIF=/1f/06/28/af/1f0628af-b385-4108-b72c-0016b004b60d/iiif/cam-85-a_0003.tif/full/!300,500/0/default.jpg | S39: Livro impresso | T39: Português | V39: Os festejos do centenario da India | W39: grande album commemorativo | Y39: 1.ª ed. | Z39: Lisboa : publicado pela empreza do Pimpão | AA39: 1898 | AB39: 1898 | AC39: 31 f. | AJ39: CAM. 85 A. | AK39: CAM500 | AL39: http://id.bnportugal.gov.pt/bib/catbnp/404800 | AM39: Livre
A40: 10056 | B40: 404800 | C40: 1 | D40: 69 | E40: https://purl.pt/43914 | F40: 3, 21, 69 | G40: 21, 69 | I40: =HYPERLINK(O40) -> https://permalinkbnd.bnportugal.gov.pt/viewer/274348/?offset=#page=69&viewer=picture&o=info&n=0&q= | M40: https://purl.pt/43914 | N40: 274348 | O40: =CONCATENATE("https://permalinkbnd.bnportugal.gov.pt/viewer/",N40,"/?offset=#page=",D40,"&viewer=picture&o=info&n=0&q=") -> https://permalinkbnd.bnportugal.gov.pt/viewer/274348/?offset=#page=69&viewer=picture&o=info&n=0&q= | P40: 404800 | Q40: https://purl.pt/43914 | R40: https://bndigital.bnportugal.gov.pt//i/?IIIF=/1f/06/28/af/1f0628af-b385-4108-b72c-0016b004b60d/iiif/cam-85-a_0003.tif/full/!300,500/0/default.jpg | S40: Livro impresso | T40: Português | V40: Os festejos do centenario da India | W40: grande album commemorativo | Y40: 1.ª ed. | Z40: Lisboa : publicado pela empreza do Pimpão | AA40: 1898 | AB40: 1898 | AC40: 31 f. | AJ40: CAM. 85 A. | AK40: CAM500 | AL40: http://id.bnportugal.gov.pt/bib/catbnp/404800 | AM40: Livre
A41: 10057 | B41: 410449 | C41: 1 | D41: 6 | E41: https://purl.pt/43911 | F41: 6 [site] | G41: 6 | I41: =HYPERLINK(O41) -> https://permalinkbnd.bnportugal.gov.pt/viewer/274346/?offset=#page=6&viewer=picture&o=info&n=0&q= | M41: https://purl.pt/43911 | N41: 274346 | O41: =CONCATENATE("https://permalinkbnd.bnportugal.gov.pt/viewer/",N41,"/?offset=#page=",D41,"&viewer=picture&o=info&n=0&q=") -> https://permalinkbnd.bnportugal.gov.pt/viewer/274346/?offset=#page=6&viewer=picture&o=info&n=0&q= | P41: 410449 | Q41: https://purl.pt/43911 | R41: https://bndigital.bnportugal.gov.pt//i/?IIIF=/37/17/31/09/37173109-2f71-495e-bea5-e4ca2470680c/iiif/cam-96-a_0007.tif/full/!300,500/0/default.jpg | S41: Livro impresso | T41: Espanhol | U41: Português | V41: Os Lusiadas (Los Portugueses) | Y41: Edicion acompañada del legitimo texto portugues y de copiosas notas y noticias biograficas sobre el insigne poeta ibero | Z41: Badajoz : Establecimiento Tipográfico de José Santamaría | AA41: 1873 | AB41: 1873 | AC41: 263, 1 p. | AD41: Camões, Luís de, 1524-1580 | AG41: Soler y Arqués, Carlos, 1836-1896, Tradutor | AJ41: CAM. 96 A. | AK41: CAM500 | AL41: http://id.bnportugal.gov.pt/bib/catbnp/410449 | AM41: Livre
A42: 10058 | B42: 411542 | C42: 1 | D42: 1 | E42: https://purl.pt/43786 | F42: 1 | H42: pag. assumida 1 | I42: =HYPERLINK(O42) -> https://permalinkbnd.bnportugal.gov.pt/viewer/273798/?offset=#page=1&viewer=picture&o=info&n=0&q= | M42: https://purl.pt/43786 | N42: 273798 | O42: =CONCATENATE("https://permalinkbnd.bnportugal.gov.pt/viewer/",N42,"/?offset=#page=",D42,"&viewer=picture&o=info&n=0&q=") -> https://permalinkbnd.bnportugal.gov.pt/viewer/273798/?offset=#page=1&viewer=picture&o=info&n=0&q= | P42: 411542 | Q42: https://purl.pt/43786 | R42: https://bndigital.bnportugal.gov.pt//i/?IIIF=/b5/4f/7e/1e/b54f7e1e-307d-47a6-9282-e41a7c32124d/iiif/cam-221-3-v_0000_000001.tif/full/!300,500/0/default.jpg | S42: Livro impresso | T42: Português | V42: O centenario no estrangeiro | W42: conferencia realisada na Sociedade de Geographia de Lisboa no dia 11 de Novembro de 1897 | Y42: 1.ª ed. | Z42: Lisboa : A Liberal | AA42: 1897 | AB42: 1897 | AC42: 30, 1 p. | AD42: Lima, Magalhães, 1850-1928 | AG42: Vilhena, Ernesto Jardim de, 1876-1967, Antigo possuidor | AJ42: H.G. 5865//1 A. | AK42: CAM500 | AL42: http://id.bnportugal.gov.pt/bib/catbnp/411542 | AM42: Livre
A43: 10062 | B43: 426512 | C43: 1 | D43: 1 | E43: https://purl.pt/43588 | F43: 1 | G43: 1 | I43: =HYPERLINK(O43) -> https://permalinkbnd.bnportugal.gov.pt/viewer/272882/?offset=#page=1&viewer=picture&o=info&n=0&q= | M43: https://purl.pt/43588 | N43: 272882 | O43: =CONCATENATE("https://permalinkbnd.bnportugal.gov.pt/viewer/",N43,"/?offset=#page=",D43,"&viewer=picture&o=info&n=0&q=") -> https://permalinkbnd.bnportugal.gov.pt/viewer/272882/?offset=#page=1&viewer=picture&o=info&n=0&q= | P43: 426512 | Q43: https://purl.pt/43588 | R43: https://bndigital.bnportugal.gov.pt//i/?IIIF=/ed/9c/ac/ac/ed9cacac-104b-435c-b7cc-8aa38ac8bca3/iiif/426512_0001.tif/full/!300,500/0/default.jpg | S43: Livro impresso | T43: Português | V43: Homenagem a Camões | W43: melodia para piano | Y43: 1.ª ed. | Z43: Lisboa : s.n. | AA43: 1870 | AB43: 1870 | AC43: 1 partitura (2 p.) | AD43: Pacheco, Maria Cornélia de Melo de Castro | AJ43: C.I.C. 142 A. | AK43: PRR2022 | AL43: http://id.bnportugal.gov.pt/bib/catbnp/426512 | AM43: Livre | AS43: Canções,
A44: 10063 | B44: 446302 | C44: 1 | D44: 11 | E44: https://purl.pt/43429 | F44: 11 | I44: =HYPERLINK(O44) -> https://permalinkbnd.bnportugal.gov.pt/viewer/1880/?offset=#page=11&viewer=picture&o=info&n=0&q= | M44: https://purl.pt/43429 | N44: 1880 | O44: =CONCATENATE("https://permalinkbnd.bnportugal.gov.pt/viewer/",N44,"/?offset=#page=",D44,"&viewer=picture&o=info&n=0&q=") -> https://permalinkbnd.bnportugal.gov.pt/viewer/1880/?offset=#page=11&viewer=picture&o=info&n=0&q= | P44: 446302 | Q44: https://purl.pt/43429 | R44: https://bndigital.bnportugal.gov.pt//i/?IIIF=/c1/c1/f9/e2/c1c1f9e2-a3e8-476d-a59f-c07a10de4bed/iiif/cam-516-v_0011.tif/full/!300,500/0/default.jpg | S44: Livro impresso | T44: Português | V44: Primeiros documentos para a historia do Jubileu Nacional de 1880 | Y44: 1.ª ed. | Z44: Lisboa : Impr. Nacional | AA44: 1887 | AB44: 1887 | AC44: 29 p. | AI44: Sociedade de Geografia de Lisboa, Editor literário | AJ44: H.G. 18363//4 V. | AK44: CAM500 | AL44: http://id.bnportugal.gov.pt/bib/catbnp/446302 | AM44: Livre | AN44: Ed. comemorativa do sétimo anniversário
A45: 10064 | B45: 452363 | C45: 1 | D45: 1 | E45: https://purl.pt/11841 | F45: 1 site | G45: 1 | I45: =HYPERLINK(O45) -> https://permalinkbnd.bnportugal.gov.pt/viewer/35644/?offset=#page=1&viewer=picture&o=info&n=0&q= | M45: https://purl.pt/11841 | N45: 35644 | O45: =CONCATENATE("https://permalinkbnd.bnportugal.gov.pt/viewer/",N45,"/?offset=#page=",D45,"&viewer=picture&o=info&n=0&q=") -> https://permalinkbnd.bnportugal.gov.pt/viewer/35644/?offset=#page=1&viewer=picture&o=info&n=0&q= | P45: 452363 | Q45: https://purl.pt/11841 | R45: https://bndigital.bnportugal.gov.pt//i/?IIIF=/b5/32/68/9d/b532689d-3818-4d28-ab3a-df022c3eb88e/iiif/e-1029-a_0000_000001.tif/full/!300,500/0/default.jpg | S45: Iconografia | T45: Português | V45: Camões | Y45: 1.ª ed. | Z45: S.l. : s.n. | AA45: 1887 | AB45: 1887 | AC45: 1 gravura | AD45: David, Lubin, fl. ca 1887 | AG45: Champollion, Eugène-André, 1848-1901, Gravador em metal ; Salmon, Louis Adolphe, 1806-1895, Impressor de ilustrações em chapa gravada | AJ45: PURL 11841/0 | AL45: http://id.bnportugal.gov.pt/bib/catbnp/452363 | AM45: Livre | AO45: Identidade provável do impressor, fundamentada no teor do registo de autoridade
A46: 10073 | B46: 453897 | C46: 1 | D46: 9 | E46: https://purl.pt/43792 | F46: 9 | G46: 9 | I46: =HYPERLINK(O46) -> https://permalinkbnd.bnportugal.gov.pt/viewer/1880/?offset=#page=9&viewer=picture&o=info&n=0&q= | M46: https://purl.pt/43792 | N46: 1880 | O46: =CONCATENATE("https://permalinkbnd.bnportugal.gov.pt/viewer/",N46,"/?offset=#page=",D46,"&viewer=picture&o=info&n=0&q=") -> https://permalinkbnd.bnportugal.gov.pt/viewer/1880/?offset=#page=9&viewer=picture&o=info&n=0&q= | P46: 453897 | Q46: https://purl.pt/43792 | R46: https://bndigital.bnportugal.gov.pt//i/?IIIF=/7e/2c/17/63/7e2c1763-4416-4162-88ba-4e958901ed3d/iiif/cam-384-9-v_0000_000001.tif/full/!300,500/0/default.jpg | S46: Livro impresso | T46: Português | V46: Á memoria de Luiz de Camões no seu tricentenario em 10 de Junho de 1880... | Y46: 1.ª ed. | Z46: Braga : Typ. de Gonçalves Gouvea | AA46: 1880 | AB46: 1880 | AC46: 16 p. | AJ46: CAM. 384//9 V. | AK46: CAM500 | AL46: http://id.bnportugal.gov.pt/bib/catbnp/453897 | AM46: Livre | AR46: Á memória de Luís de Camões
A47: 10075 | B47: 454218 | C47: 1 | D47: 3 | E47: https://purl.pt/43793 | F47: 3 | G47: 3 | I47: =HYPERLINK(O47) -> https://permalinkbnd.bnportugal.gov.pt/viewer/273923/?offset=#page=3&viewer=picture&o=info&n=0&q= | M47: https://purl.pt/43793 | N47: 273923 | O47: =CONCATENATE("https://permalinkbnd.bnportugal.gov.pt/viewer/",N47,"/?offset=#page=",D47,"&viewer=picture&o=info&n=0&q=") -> https://permalinkbnd.bnportugal.gov.pt/viewer/273923/?offset=#page=3&viewer=picture&o=info&n=0&q= | P47: 454218 | Q47: https://purl.pt/43793 | R47: https://bndigital.bnportugal.gov.pt//i/?IIIF=/a4/54/ba/df/a454badf-dc23-49b9-8ac1-fff9a72f6856/iiif/cam-386-6-v_0000_000001.tif/full/!300,500/0/default.jpg | S47: Livro impresso | T47: Português | V47: Vida de Luiz de Camões e seu retrato | Y47: 1.ª ed. | Z47: Coimbra : Impr. Academica | AA47: 1881 | AB47: 1881 | AC47: 15 p. | AJ47: CAM. 386//6 V. | AK47: CAM500 | AL47: http://id.bnportugal.gov.pt/bib/catbnp/454218 | AM47: Livre | AR47: Vida de Luís de Camões e seu retrato
A48: 10088 | B48: 455268 | C48: 1 | D48: 8 | E48: https://purl.pt/42934 | F48: 8, 62 [1.º: retrato de Camões e visita do Rei de Melinde a V. da Gama] 8 [2.º: Vasco da Gama em Calecute] | G48: 8, 62, 8 | I48: =HYPERLINK(O48) -> https://permalinkbnd.bnportugal.gov.pt/viewer/270331/?offset=#page=8&viewer=picture&o=info&n=0&q= | M48: https://purl.pt/42934 | N48: 270331 | O48: =CONCATENATE("https://permalinkbnd.bnportugal.gov.pt/viewer/",N48,"/?offset=#page=",D48,"&viewer=picture&o=info&n=0&q=") -> https://permalinkbnd.bnportugal.gov.pt/viewer/270331/?offset=#page=8&viewer=picture&o=info&n=0&q= | P48: 455268 | Q48: https://purl.pt/42934 | R48: https://bndigital.bnportugal.gov.pt//i/?IIIF=/e0/e2/36/8e/e0e2368e-06b5-4efd-bb33-762145de2b06/iiif/cam-408-v_0000_000011.tif/full/!300,500/0/default.jpg | S48: Livro impresso | T48: Italiano | U48: Português | V48: I Lusiadi | Y48: Seconde edizione illustrata con note di D. B. | Z48: Milano : Societá Tipog. dei Classici Italiani | AA48: 1821 | AB48: 1821 | AC48: XXXX, 517, 1 p. (2 v.) | AD48: Camões, Luís de, 1524-1580 | AG48: Nervi, Antonio, 1760-1836, Tradutor | AJ48: CAM. 408 V. | AK48: CAM500 | AL48: http://id.bnportugal.gov.pt/bib/catbnp/455268 | AM48: Livre
A49: 10089 | B49: 455268 | C49: 1 | D49: 62 | E49: https://purl.pt/42934 | F49: 8, 62 [1.º: retrato de Camões e visita do Rei de Melinde a V. da Gama] 8 [2.º: Vasco da Gama em Calecute] | G49: 8, 62, 8 | I49: =HYPERLINK(O49) -> https://permalinkbnd.bnportugal.gov.pt/viewer/270331/?offset=#page=62&viewer=picture&o=info&n=0&q= | M49: https://purl.pt/42934 | N49: 270331 | O49: =CONCATENATE("https://permalinkbnd.bnportugal.gov.pt/viewer/",N49,"/?offset=#page=",D49,"&viewer=picture&o=info&n=0&q=") -> https://permalinkbnd.bnportugal.gov.pt/viewer/270331/?offset=#page=62&viewer=picture&o=info&n=0&q= | P49: 455268 | Q49: https://purl.pt/42934 | R49: https://bndigital.bnportugal.gov.pt//i/?IIIF=/e0/e2/36/8e/e0e2368e-06b5-4efd-bb33-762145de2b06/iiif/cam-408-v_0000_000011.tif/full/!300,500/0/default.jpg | S49: Livro impresso | T49: Italiano | U49: Português | V49: I Lusiadi | Y49: Seconde edizione illustrata con note di D. B. | Z49: Milano : Societá Tipog. dei Classici Italiani | AA49: 1821 | AB49: 1821 | AC49: XXXX, 517, 1 p. (2 v.) | AD49: Camões, Luís de, 1524-1580 | AG49: Nervi, Antonio, 1760-1836, Tradutor | AJ49: CAM. 408 V. | AK49: CAM500 | AL49: http://id.bnportugal.gov.pt/bib/catbnp/455268 | AM49: Livre
A50: 10090 | B50: 455268 | C50: 2 | D50: 8 | E50: https://purl.pt/42934 | F50: 8, 62 [1.º: retrato de Camões e visita do Rei de Melinde a V. da Gama] 8 [2.º: Vasco da Gama em Calecute] | G50: 8, 62, 8 | I50: =HYPERLINK(O50) -> https://permalinkbnd.bnportugal.gov.pt/viewer/270331/?offset=#page=8&viewer=picture&o=info&n=0&q= | M50: https://purl.pt/42934 | N50: 270331 | O50: =CONCATENATE("https://permalinkbnd.bnportugal.gov.pt/viewer/",N50,"/?offset=#page=",D50,"&viewer=picture&o=info&n=0&q=") -> https://permalinkbnd.bnportugal.gov.pt/viewer/270331/?offset=#page=8&viewer=picture&o=info&n=0&q= | P50: 455268 | Q50: https://purl.pt/42934 | R50: https://bndigital.bnportugal.gov.pt//i/?IIIF=/e0/e2/36/8e/e0e2368e-06b5-4efd-bb33-762145de2b06/iiif/cam-408-v_0000_000011.tif/full/!300,500/0/default.jpg | S50: Livro impresso | T50: Italiano | U50: Português | V50: I Lusiadi | Y50: Seconde edizione illustrata con note di D. B. | Z50: Milano : Societá Tipog. dei Classici Italiani | AA50: 1821 | AB50: 1821 | AC50: XXXX, 517, 1 p. (2 v.) | AD50: Camões, Luís de, 1524-1580 | AG50: Nervi, Antonio, 1760-1836, Tradutor | AJ50: CAM. 408 V. | AK50: CAM500 | AL50: http://id.bnportugal.gov.pt/bib/catbnp/455268 | AM50: Livre
A51: 10091 | B51: 455275 | C51: 1 | D51: 10 | E51: https://purl.pt/42943 | F51: 10, 13 [1.º: retrato de Camões, portada, 426 apontamento caravela; 3.º: 154, apontamento site] | G51: 10 | I51: =HYPERLINK(O51) -> https://permalinkbnd.bnportugal.gov.pt/viewer/270345/?offset=#page=10&viewer=picture&o=info&n=0&q= | M51: https://purl.pt/42943 | N51: 270345 | O51: =CONCATENATE("https://permalinkbnd.bnportugal.gov.pt/viewer/",N51,"/?offset=#page=",D51,"&viewer=picture&o=info&n=0&q=") -> https://permalinkbnd.bnportugal.gov.pt/viewer/270345/?offset=#page=10&viewer=picture&o=info&n=0&q= | P51: 455275 | Q51: https://purl.pt/42943 | R51: https://bndigital.bnportugal.gov.pt//i/?IIIF=/5d/28/c9/4e/5d28c94e-b940-4e81-8f76-f7b1ef6f5a4b/iiif/cam-410-v_0000_000013.tif/full/!300,500/0/default.jpg | S51: Livro impresso | T51: Português | V51: Obras completas de Luis de Camões | Y51: 1.ª ed. | Z51: Lisboa : s.n. | AA51: 1843 | AB51: 1843 | AC51: 3 t. | AD51: Camões, Luís de, 1524-1580 | AG51: Feio, José Vitorino Barreto, 1782-1850, Compilador ; Monteiro, José Gomes, 1807-1879, Compilador | AJ51: CAM. 410 V. | AK51: CAM500 | AL51: http://id.bnportugal.gov.pt/bib/catbnp/455275 | AM51: Livre | AP51: T. 1: Os Lusíadas. - XLII, 2, 396, 2 p. : 1 retr. ; T. 2: Vida de Luís de Camões; Rimas: sonetos, éclogas, canções e odes. - LXIX, 3, 420 p. ; T. 3: Rimas: redondilhas, sextinas, elegias, epistolas, oitavas; comédias; cartas. - 516 p.
A52: 10097 | B52: 458290 | C52: 1 | D52: 10 | E52: https://purl.pt/43921 | F52: 10, 11 [7, 15 e 37 apontamentos site] | G52: 10 | H52: imagem pouco vísivel | I52: =HYPERLINK(O52) -> https://permalinkbnd.bnportugal.gov.pt/viewer/273525/?offset=#page=10&viewer=picture&o=info&n=0&q= | M52: https://purl.pt/43921 | N52: 273525 | O52: =CONCATENATE("https://permalinkbnd.bnportugal.gov.pt/viewer/",N52,"/?offset=#page=",D52,"&viewer=picture&o=info&n=0&q=") -> https://permalinkbnd.bnportugal.gov.pt/viewer/273525/?offset=#page=10&viewer=picture&o=info&n=0&q= | P52: 458290 | Q52: https://purl.pt/43921 | R52: https://bndigital.bnportugal.gov.pt//i/?IIIF=/3d/ef/d5/dc/3defd5dc-8364-472f-9969-dc10b3471470/iiif/cam-129-a_0000_000011.tif/full/!300,500/0/default.jpg | S52: Livro impresso | T52: Português ; Francês | U52: Português | V52: A ilha de Venus | W52: episodio extrahido do nono canto dos Lusiadas | Y52: 1.ª ed. | Z52: Porto : Livraria Camões de Fernandes Possas | AA52: 1890 | AB52: 1890 | AC52: VII, 1 br., 38, 2 p. | AD52: Camões, Luís de, 1524-1580 | AG52: Baour-Lormian, P. L. M., 1770-1854, Tradutor ; Grandmaison, M. Parsival, Tradutor ; Aranha, Brito, 1833-1914, Antigo possuidor | AJ52: CAM. 129 A. | AK52: CAM500 | AL52: http://id.bnportugal.gov.pt/bib/catbnp/458290 | AM52: Livre
A53: 10100 | B53: 458655 | C53: 1 | D53: 11 | E53: https://purl.pt/42928 | F53: 5, 11 [1.º: imagem, portada], 5 [2.º retrato de Camões], 12 [3.º: partida de V. da Gama para a Índia], 12 [4.º: O espírito do Cabo surge à frota de V. da Gama], 11 [7.º: portada], 12 [8.º: Ilha dos Amores] | G53: 11, 5, 12, 12, 11, 12 | I53: =HYPERLINK(O53) -> https://permalinkbnd.bnportugal.gov.pt/viewer/270116/?offset=#page=11&viewer=picture&o=info&n=0&q= | M53: https://purl.pt/42928 | N53: 270116 | O53: =CONCATENATE("https://permalinkbnd.bnportugal.gov.pt/viewer/",N53,"/?offset=#page=",D53,"&viewer=picture&o=info&n=0&q=") -> https://permalinkbnd.bnportugal.gov.pt/viewer/270116/?offset=#page=11&viewer=picture&o=info&n=0&q= | P53: 458655 | Q53: https://purl.pt/42928 | R53: https://bndigital.bnportugal.gov.pt//i/?IIIF=/c4/0f/74/3f/c40f743f-cbf4-4bf9-8481-bce3fdf02c38/iiif/cam-152-a_0000_000011.tif/full/!300,500/0/default.jpg | S53: Livro impresso | T53: Português | V53: Florilegio camoneano | Y53: 1.ª ed. | Z53: Porto : Livr. Camões | AA53: 1887 | AB53: 1887 | AC53: 8 T. | AJ53: CAM. 152 A. | AK53: CAM500 | AL53: http://id.bnportugal.gov.pt/bib/catbnp/458655 | AM53: Livre
A54: 10101 | B54: 458655 | C54: 2 | D54: 5 | E54: https://purl.pt/42928 | F54: 5, 11 [1.º: imagem, portada], 5 [2.º retrato de Camões], 12 [3.º: partida de V. da Gama para a Índia], 12 [4.º: O espírito do Cabo surge à frota de V. da Gama], 11 [7.º: portada], 12 [8.º: Ilha dos Amores] | G54: 11, 5, 12, 12, 11, 12 | I54: =HYPERLINK(O54) -> https://permalinkbnd.bnportugal.gov.pt/viewer/270116/?offset=#page=5&viewer=picture&o=info&n=0&q= | M54: https://purl.pt/42928 | N54: 270116 | O54: =CONCATENATE("https://permalinkbnd.bnportugal.gov.pt/viewer/",N54,"/?offset=#page=",D54,"&viewer=picture&o=info&n=0&q=") -> https://permalinkbnd.bnportugal.gov.pt/viewer/270116/?offset=#page=5&viewer=picture&o=info&n=0&q= | P54: 458655 | Q54: https://purl.pt/42928 | R54: https://bndigital.bnportugal.gov.pt//i/?IIIF=/c4/0f/74/3f/c40f743f-cbf4-4bf9-8481-bce3fdf02c38/iiif/cam-152-a_0000_000011.tif/full/!300,500/0/default.jpg | S54: Livro impresso | T54: Português | V54: Florilegio camoneano | Y54: 1.ª ed. | Z54: Porto : Livr. Camões | AA54: 1887 | AB54: 1887 | AC54: 8 T. | AJ54: CAM. 152 A. | AK54: CAM500 | AL54: http://id.bnportugal.gov.pt/bib/catbnp/458655 | AM54: Livre
A55: 10102 | B55: 458655 | C55: 2 | D55: 12 | E55: https://purl.pt/42928 | F55: 5, 11 [1.º: imagem, portada], 5 [2.º retrato de Camões], 12 [3.º: partida de V. da Gama para a Índia], 12 [4.º: O espírito do Cabo surge à frota de V. da Gama], 11 [7.º: portada], 12 [8.º: Ilha dos Amores] | G55: 11, 5, 12, 12, 11, 12 | H55: sem imagem | I55: =HYPERLINK(O55) -> https://permalinkbnd.bnportugal.gov.pt/viewer/270116/?offset=#page=12&viewer=picture&o=info&n=0&q= | M55: https://purl.pt/42928 | N55: 270116 | O55: =CONCATENATE("https://permalinkbnd.bnportugal.gov.pt/viewer/",N55,"/?offset=#page=",D55,"&viewer=picture&o=info&n=0&q=") -> https://permalinkbnd.bnportugal.gov.pt/viewer/270116/?offset=#page=12&viewer=picture&o=info&n=0&q= | P55: 458655 | Q55: https://purl.pt/42928 | R55: https://bndigital.bnportugal.gov.pt//i/?IIIF=/c4/0f/74/3f/c40f743f-cbf4-4bf9-8481-bce3fdf02c38/iiif/cam-152-a_0000_000011.tif/full/!300,500/0/default.jpg | S55: Livro impresso | T55: Português | V55: Florilegio camoneano | Y55: 1.ª ed. | Z55: Porto : Livr. Camões | AA55: 1887 | AB55: 1887 | AC55: 8 T. | AJ55: CAM. 152 A. | AK55: CAM500 | AL55: http://id.bnportugal.gov.pt/bib/catbnp/458655 | AM55: Livre
A56: 10103 | B56: 458655 | C56: 2 | D56: 12 | E56: https://purl.pt/42928 | F56: 5, 11 [1.º: imagem, portada], 5 [2.º retrato de Camões], 12 [3.º: partida de V. da Gama para a Índia], 12 [4.º: O espírito do Cabo surge à frota de V. da Gama], 11 [7.º: portada], 12 [8.º: Ilha dos Amores] | G56: 11, 5, 12, 12, 11, 12 | H56: sem imagem | I56: =HYPERLINK(O56) -> https://permalinkbnd.bnportugal.gov.pt/viewer/270116/?offset=#page=12&viewer=picture&o=info&n=0&q= | M56: https://purl.pt/42928 | N56: 270116 | O56: =CONCATENATE("https://permalinkbnd.bnportugal.gov.pt/viewer/",N56,"/?offset=#page=",D56,"&viewer=picture&o=info&n=0&q=") -> https://permalinkbnd.bnportugal.gov.pt/viewer/270116/?offset=#page=12&viewer=picture&o=info&n=0&q= | P56: 458655 | Q56: https://purl.pt/42928 | R56: https://bndigital.bnportugal.gov.pt//i/?IIIF=/c4/0f/74/3f/c40f743f-cbf4-4bf9-8481-bce3fdf02c38/iiif/cam-152-a_0000_000011.tif/full/!300,500/0/default.jpg | S56: Livro impresso | T56: Português | V56: Florilegio camoneano | Y56: 1.ª ed. | Z56: Porto : Livr. Camões | AA56: 1887 | AB56: 1887 | AC56: 8 T. | AJ56: CAM. 152 A. | AK56: CAM500 | AL56: http://id.bnportugal.gov.pt/bib/catbnp/458655 | AM56: Livre
A57: 10104 | B57: 458655 | C57: 3 | D57: 11 | E57: https://purl.pt/42928 | F57: 5, 11 [1.º: imagem, portada], 5 [2.º retrato de Camões], 12 [3.º: partida de V. da Gama para a Índia], 12 [4.º: O espírito do Cabo surge à frota de V. da Gama], 11 [7.º: portada], 12 [8.º: Ilha dos Amores] | G57: 11, 5, 12, 12, 11, 12 | H57: sem imagem | I57: =HYPERLINK(O57) -> https://permalinkbnd.bnportugal.gov.pt/viewer/270116/?offset=#page=11&viewer=picture&o=info&n=0&q= | M57: https://purl.pt/42928 | N57: 270116 | O57: =CONCATENATE("https://permalinkbnd.bnportugal.gov.pt/viewer/",N57,"/?offset=#page=",D57,"&viewer=picture&o=info&n=0&q=") -> https://permalinkbnd.bnportugal.gov.pt/viewer/270116/?offset=#page=11&viewer=picture&o=info&n=0&q= | P57: 458655 | Q57: https://purl.pt/42928 | R57: https://bndigital.bnportugal.gov.pt//i/?IIIF=/c4/0f/74/3f/c40f743f-cbf4-4bf9-8481-bce3fdf02c38/iiif/cam-152-a_0000_000011.tif/full/!300,500/0/default.jpg | S57: Livro impresso | T57: Português | V57: Florilegio camoneano | Y57: 1.ª ed. | Z57: Porto : Livr. Camões | AA57: 1887 | AB57: 1887 | AC57: 8 T. | AJ57: CAM. 152 A. | AK57: CAM500 | AL57: http://id.bnportugal.gov.pt/bib/catbnp/458655 | AM57: Livre
A58: 10105 | B58: 458655 | C58: 3 | D58: 12 | E58: https://purl.pt/42928 | F58: 5, 11 [1.º: imagem, portada], 5 [2.º retrato de Camões], 12 [3.º: partida de V. da Gama para a Índia], 12 [4.º: O espírito do Cabo surge à frota de V. da Gama], 11 [7.º: portada], 12 [8.º: Ilha dos Amores] | G58: 11, 5, 12, 12, 11, 12 | H58: sem imagem | I58: =HYPERLINK(O58) -> https://permalinkbnd.bnportugal.gov.pt/viewer/270116/?offset=#page=12&viewer=picture&o=info&n=0&q= | M58: https://purl.pt/42928 | N58: 270116 | O58: =CONCATENATE("https://permalinkbnd.bnportugal.gov.pt/viewer/",N58,"/?offset=#page=",D58,"&viewer=picture&o=info&n=0&q=") -> https://permalinkbnd.bnportugal.gov.pt/viewer/270116/?offset=#page=12&viewer=picture&o=info&n=0&q= | P58: 458655 | Q58: https://purl.pt/42928 | R58: https://bndigital.bnportugal.gov.pt//i/?IIIF=/c4/0f/74/3f/c40f743f-cbf4-4bf9-8481-bce3fdf02c38/iiif/cam-152-a_0000_000011.tif/full/!300,500/0/default.jpg | S58: Livro impresso | T58: Português | V58: Florilegio camoneano | Y58: 1.ª ed. | Z58: Porto : Livr. Camões | AA58: 1887 | AB58: 1887 | AC58: 8 T. | AJ58: CAM. 152 A. | AK58: CAM500 | AL58: http://id.bnportugal.gov.pt/bib/catbnp/458655 | AM58: Livre
A59: 10107 | B59: 465606 | C59: 1 | D59: 3 | E59: https://purl.pt/43836 | F59: 3 | H59: pag. assumida 3 | I59: =HYPERLINK(O59) -> https://permalinkbnd.bnportugal.gov.pt/viewer/274117/?offset=#page=3&viewer=picture&o=info&n=0&q= | M59: https://purl.pt/43836 | N59: 274117 | O59: =CONCATENATE("https://permalinkbnd.bnportugal.gov.pt/viewer/",N59,"/?offset=#page=",D59,"&viewer=picture&o=info&n=0&q=") -> https://permalinkbnd.bnportugal.gov.pt/viewer/274117/?offset=#page=3&viewer=picture&o=info&n=0&q= | P59: 465606 | Q59: https://purl.pt/43836 | R59: https://bndigital.bnportugal.gov.pt//i/?IIIF=/42/cd/d2/e6/42cdd2e6-50ac-44e8-a7c5-107037a0f860/iiif/cam-674-v_0000_000003.tif/full/!300,500/0/default.jpg | S59: Livro impresso | T59: Inglês | V59: Sonnets | Y59: 1.ª ed. | Z59: Newcastle upon Tinet : Impr. by M. A. Richardson | AA59: 1845 | AB59: 1845 | AC59: 16 p. | AD59: Adamson, John, 1787-1851 | AG59: Sucena, 1850-?, Antigo possuidor | AJ59: CAM. 674 V. | AK59: CAM500 | AL59: http://id.bnportugal.gov.pt/bib/catbnp/465606 | AM59: Livre
A60: 10112 | B60: 471392 | C60: 1 | D60: 5 | E60: https://purl.pt/43854 | F60: 5 | H60: pag. assumida 5 | I60: =HYPERLINK(O60) -> https://permalinkbnd.bnportugal.gov.pt/viewer/274153/?offset=#page=5&viewer=picture&o=info&n=0&q= | M60: https://purl.pt/43854 | N60: 274153 | O60: =CONCATENATE("https://permalinkbnd.bnportugal.gov.pt/viewer/",N60,"/?offset=#page=",D60,"&viewer=picture&o=info&n=0&q=") -> https://permalinkbnd.bnportugal.gov.pt/viewer/274153/?offset=#page=5&viewer=picture&o=info&n=0&q= | P60: 471392 | Q60: https://purl.pt/43854 | R60: https://bndigital.bnportugal.gov.pt//i/?IIIF=/f2/8b/c2/cc/f28bc2cc-79a2-4081-ab33-b9fabce3fa4a/iiif/cam-1451-v_0000_000005.tif/full/!300,500/0/default.jpg | S60: Livro impresso | T60: Italiano | V60: Camões | W60: musica | Y60: 1.ª ed. | Z60: Lisboa : s.n. | AA60: 1857 | AB60: 1857 | AC60: 36 p. | AD60: Farina, Luigi | AJ60: CAM. 1451 V. | AK60: CAM500 | AL60: http://id.bnportugal.gov.pt/bib/catbnp/471392 | AM60: Livre | AP60: Contém só o texto
A61: 10113 | B61: 475171 | C61: 1 | D61: 13 | E61: https://purl.pt/43413 | F61: 13 | G61: 13 | I61: =HYPERLINK(O61) -> https://permalinkbnd.bnportugal.gov.pt/viewer/272371/?offset=#page=13&viewer=picture&o=info&n=0&q= | M61: https://purl.pt/43413 | N61: 272371 | O61: =CONCATENATE("https://permalinkbnd.bnportugal.gov.pt/viewer/",N61,"/?offset=#page=",D61,"&viewer=picture&o=info&n=0&q=") -> https://permalinkbnd.bnportugal.gov.pt/viewer/272371/?offset=#page=13&viewer=picture&o=info&n=0&q= | P61: 475171 | Q61: https://purl.pt/43413 | R61: https://bndigital.bnportugal.gov.pt//i/?IIIF=/5d/bd/60/12/5dbd6012-a3b6-4853-b7f9-a7245fc80226/iiif/cam-782-p_0013.tif/full/!300,500/0/default.jpg | S61: Livro manuscrito | T61: Latim | U61: Português | V61: Ludouici Camoenij Lusitani libri X ex materno rhythmico in latinum & virgilianu carmen à D. Andrea Baiano Lusiada Orientali traducti & ab eodem manuscripti. Anno jubilei CI)I)CXXV 1625 | Y61: 1.ª ed. | AA61: 1625 | AB61: 1625 | AC61: 24, 383 p. | AD61: Camões, Luís de, 1524-1580 | AG61: Baião, André, 1566-1639, Tradutor | AJ61: F. 9 | AK61: CAM500 | AL61: http://id.bnportugal.gov.pt/bib/catbnp/475171 | AM61: Livre | AN61: Original | AO61: Rosto com cercadura florida desenhada à pena | AR61: Lusiada Orientali
A62: 10116 | B62: 475214 | C62: 1 | D62: 7 | E62: https://purl.pt/43856 | F62: 7 | H62: pag. assumida 7 | I62: =HYPERLINK(O62) -> https://permalinkbnd.bnportugal.gov.pt/viewer/273182/?offset=#page=7&viewer=picture&o=info&n=0&q= | M62: https://purl.pt/43856 | N62: 273182 | O62: =CONCATENATE("https://permalinkbnd.bnportugal.gov.pt/viewer/",N62,"/?offset=#page=",D62,"&viewer=picture&o=info&n=0&q=") -> https://permalinkbnd.bnportugal.gov.pt/viewer/273182/?offset=#page=7&viewer=picture&o=info&n=0&q= | P62: 475214 | Q62: https://purl.pt/43856 | R62: https://bndigital.bnportugal.gov.pt//i/?IIIF=/70/3f/cc/e5/703fcce5-cee9-4fd0-b063-c58c42d156ac/iiif/cam-74-7-v_0000_000001.tif/full/!300,500/0/default.jpg | S62: Livro impresso | T62: Hebraico antigo ; Francês | V62: Inês de Castro | W62: episode des Lusiades ... | Y62: 1.ª ed. | Z62: Lisbonne : Imp. Nationale | AA62: 1892 | AB62: 1892 | AC62: XI, 24 p. | AD62: Camões, Luís de, 1524-1580 | AG62: Vilhena, Ernesto Jardim de, 1876-1967, Antigo possuidor ; Benoliel, Joseph, 1873-1932, Tradutor ; Wogue, Lazare Eliezer, 1817-1897, Comentador (em meio audiovisual) | AI62: Congresso Internacional dos Orientalistas, Organizador de conferência | AJ62: H.G. 7378//5 V. | AK62: CAM500 | AL62: http://id.bnportugal.gov.pt/bib/catbnp/475214 | AM62: Livre | AN62: Memória apresentada na 10ª Sessão do Congresso Internacional dos Orientalistas
A63: 10119 | B63: 475453 | C63: 1 | D63: 1 | E63: https://purl.pt/43768 | F63: 1 | G63: 1 | I63: =HYPERLINK(O63) -> https://permalinkbnd.bnportugal.gov.pt/viewer/273318/?offset=#page=1&viewer=picture&o=info&n=0&q= | M63: https://purl.pt/43768 | N63: 273318 | O63: =CONCATENATE("https://permalinkbnd.bnportugal.gov.pt/viewer/",N63,"/?offset=#page=",D63,"&viewer=picture&o=info&n=0&q=") -> https://permalinkbnd.bnportugal.gov.pt/viewer/273318/?offset=#page=1&viewer=picture&o=info&n=0&q= | P63: 475453 | Q63: https://purl.pt/43768 | R63: https://bndigital.bnportugal.gov.pt//i/?IIIF=/57/26/e4/65/5726e465-1ee7-4c62-b7c4-06c930646aa0/iiif/cam-83-1-a_0000_000001.tif/full/!300,500/0/default.jpg | S63: Periódico | T63: Português | V63: Recreio musical | W63: album de musicas para piano | Y63: 1.ª ed. | Z63: Lisboa : s.n. | AA63: 1880 | AB63: 1880 | AJ63: CAM. 83//1 A. | AK63: CAM500 | AL63: http://id.bnportugal.gov.pt/bib/catbnp/475453 | AM63: Livre
A64: 10120 | B64: 475458 | C64: 1 | D64: 1 | E64: https://purl.pt/43675 | F64: 1 | G64: 1 | I64: =HYPERLINK(O64) -> https://permalinkbnd.bnportugal.gov.pt/viewer/273319/?offset=#page=1&viewer=picture&o=info&n=0&q= | M64: https://purl.pt/43675 | N64: 273319 | O64: =CONCATENATE("https://permalinkbnd.bnportugal.gov.pt/viewer/",N64,"/?offset=#page=",D64,"&viewer=picture&o=info&n=0&q=") -> https://permalinkbnd.bnportugal.gov.pt/viewer/273319/?offset=#page=1&viewer=picture&o=info&n=0&q= | P64: 475458 | Q64: https://purl.pt/43675 | R64: https://bndigital.bnportugal.gov.pt//i/?IIIF=/36/69/d9/d4/3669d9d4-f77b-4fe3-a244-701d17f3e42a/iiif/cam-83-2-a_0000_000001.tif/full/!300,500/0/default.jpg | S64: Livro impresso | T64: Português | V64: Os Lusíadas | W64: musica para piano e canto | Y64: 1.ª ed. | Z64: Lisboa : Verol Senior | AA64: 1880 | AB64: 1880 | AC64: 1 partitura (5 p.) | AD64: Carvalho, Augusto José de, 1848-1910 | AF64: Camões, Luís de, 1524-1580 | AJ64: C.I.C. 140 A. | AK64: PRR2022 | AL64: http://id.bnportugal.gov.pt/bib/catbnp/475458 | AM64: Livre | AN64: Dedicada à digna Comissão dos Festejos de Camões | AS64: Canções,
A65: 10121 | B65: 476957 | C65: 1 | D65: 5 | E65: https://purl.pt/43755 | F65: 1, 7 [site] | H65: pag. assumida 5 | I65: =HYPERLINK(O65) -> https://permalinkbnd.bnportugal.gov.pt/viewer/273102/?offset=#page=5&viewer=picture&o=info&n=0&q= | M65: https://purl.pt/43755 | N65: 273102 | O65: =CONCATENATE("https://permalinkbnd.bnportugal.gov.pt/viewer/",N65,"/?offset=#page=",D65,"&viewer=picture&o=info&n=0&q=") -> https://permalinkbnd.bnportugal.gov.pt/viewer/273102/?offset=#page=5&viewer=picture&o=info&n=0&q= | P65: 476957 | Q65: https://purl.pt/43755 | R65: https://bndigital.bnportugal.gov.pt//i/?IIIF=/86/6c/46/07/866c4607-1618-436f-b006-ed4e4b3aa2eb/iiif/cam-25-a_0000_000005.tif/full/!300,500/0/default.jpg | S65: Livro impresso | T65: Português | V65: Os Lusiadas | Y65: Ed. popular gratuita | Z65: Lisboa : Emp. do Diario de Noticias | AA65: 1880 | AB65: 1880 | AC65: 17, 1 p. | AD65: Camões, Luís de, 1524-1580 | AJ65: CAM. 25 A. | AK65: CAM500 | AL65: http://id.bnportugal.gov.pt/bib/catbnp/476957 | AM65: Livre | AR65: Os Lusíadas
A66: 10138 | B66: 479076 | C66: 1 | D66: 1 | E66: https://purl.pt/42929 | F66: 1 [2.º Vol.] | G66: 1 | I66: =HYPERLINK(O66) -> https://permalinkbnd.bnportugal.gov.pt/viewer/270341/?offset=#page=1&viewer=picture&o=info&n=0&q= | M66: https://purl.pt/42929 | N66: 270341 | O66: =CONCATENATE("https://permalinkbnd.bnportugal.gov.pt/viewer/",N66,"/?offset=#page=",D66,"&viewer=picture&o=info&n=0&q=") -> https://permalinkbnd.bnportugal.gov.pt/viewer/270341/?offset=#page=1&viewer=picture&o=info&n=0&q= | P66: 479076 | Q66: https://purl.pt/42929 | R66: https://bndigital.bnportugal.gov.pt//i/?IIIF=/61/6e/1e/85/616e1e85-5eec-40f5-81a2-56ec93537919/iiif/cam-80-63-a_0000_000001.tif/full/!300,500/0/default.jpg | S66: Periódico | T66: Polaco | V66: Tygodnik Illustrowany | Y66: 1.ª ed. | Z66: Warszawa : drukiem J. Ungra | AA66: 1880 | AB66: 1880 | AG66: Lenike, J., Editor literário | AJ66: CAM. 80//63 A. | AK66: CAM500 | AL66: http://id.bnportugal.gov.pt/bib/catbnp/479076 | AM66: Livre
A67: 10139 | B67: 479079 | C67: 1 | D67: 1 | E67: https://purl.pt/42930 | F67: 1 [2.º Vol.] | G67: 1 | I67: =HYPERLINK(O67) -> https://permalinkbnd.bnportugal.gov.pt/viewer/270336/?offset=#page=1&viewer=picture&o=info&n=0&q= | M67: https://purl.pt/42930 | N67: 270336 | O67: =CONCATENATE("https://permalinkbnd.bnportugal.gov.pt/viewer/",N67,"/?offset=#page=",D67,"&viewer=picture&o=info&n=0&q=") -> https://permalinkbnd.bnportugal.gov.pt/viewer/270336/?offset=#page=1&viewer=picture&o=info&n=0&q= | P67: 479079 | Q67: https://purl.pt/42930 | R67: https://bndigital.bnportugal.gov.pt//i/?IIIF=/c5/1b/85/f9/c51b85f9-2522-413e-b7ef-aebc584037d9/iiif/cam-80-65-a_0000_000001.tif/full/!300,500/0/default.jpg | S67: Periódico | T67: Polaco | V67: Tygodnik Powszechny | Y67: 1.ª ed. | Z67: Warszawa : drukarni S. Orgelbrando Synow | AA67: 1880 | AB67: 1880 | AG67: Orgelbrand, Maurycy, Editor literário | AJ67: CAM. 80//65 A. | AK67: CAM500 | AL67: http://id.bnportugal.gov.pt/bib/catbnp/479079 | AM67: Livre
A68: 10141 | B68: 480058 | C68: 1 | D68: 1 | E68: https://purl.pt/43673 | F68: 1 | G68: 1 | I68: =HYPERLINK(O68) -> https://permalinkbnd.bnportugal.gov.pt/viewer/273314/?offset=#page=1&viewer=picture&o=info&n=0&q= | M68: https://purl.pt/43673 | N68: 273314 | O68: =CONCATENATE("https://permalinkbnd.bnportugal.gov.pt/viewer/",N68,"/?offset=#page=",D68,"&viewer=picture&o=info&n=0&q=") -> https://permalinkbnd.bnportugal.gov.pt/viewer/273314/?offset=#page=1&viewer=picture&o=info&n=0&q= | P68: 480058 | Q68: https://purl.pt/43673 | R68: https://bndigital.bnportugal.gov.pt//i/?IIIF=/ac/03/49/21/ac034921-8f14-43b9-a5d4-7c9ee7950d1c/iiif/cam-80-71-a_0000_000001.tif/full/!300,500/0/default.jpg | S68: Periódico | T68: Português | V68: Jornal do Commercio | Y68: 1.ª ed. | Z68: Rio de Janeiro : s.n. | AA68: 1880 | AB68: 1880 | AG68: Villeneuve, Júlio Constâncio de, Director | AJ68: CAM. 80//71 A. | AK68: CAM500 | AL68: http://id.bnportugal.gov.pt/bib/catbnp/480058 | AM68: Livre | AR68: Jornal de Comércio
A69: 10147 | B69: 357297 | C69: 1 | D69: 10 | E69: https://purl.pt/43384 | F69: 1 [retrato do Poeta, antes da folha de rosto] | G69: 1 | H69: pag. assumida 10 | I69: =HYPERLINK(O69) -> https://permalinkbnd.bnportugal.gov.pt/viewer/281908/?offset=#page=10&viewer=picture&o=info&n=0&q= | M69: https://purl.pt/43384 | N69: 281908 | O69: =CONCATENATE("https://permalinkbnd.bnportugal.gov.pt/viewer/",N69,"/?offset=#page=",D69,"&viewer=picture&o=info&n=0&q=") -> https://permalinkbnd.bnportugal.gov.pt/viewer/281908/?offset=#page=10&viewer=picture&o=info&n=0&q= | P69: 357297 | Q69: https://purl.pt/43384 | R69: https://bndigital.bnportugal.gov.pt//i/?IIIF=/b2/56/5a/a6/b2565aa6-70f7-48fe-a06c-6e301f3b710c/iiif/cam-6-v_0011.tif/full/!300,500/0/default.jpg | S69: Livro impresso | T69: Português | V69: Os Lusíadas | Y69: Nova edição correcta, e dada á luz, conforme á de 1817, in-4º | Z69: Paris : na officina typographica de Firmino Didot... | AA69: 1817 | AB69: 1817 | AC69: CX, 420 p. | AD69: Camões, Luís de, 1524-1580 | AG69: Mateus, Morgado de, 1758-1825, Editor literário ; Didot, Firmin, fl. 1789-1829, Impressor ; Norton, Tomás, 1804-1860, Antigo possuidor | AJ69: CAM. 6 V. | AK69: CAM500 | AL69: http://id.bnportugal.gov.pt/bib/catbnp/357297 | AM69: Livre
A70: 10148 | B70: 601741 | C70: 1 | D70: 1 | E70: https://purl.pt/1066 | F70: 1 site | G70: 1 | I70: =HYPERLINK(O70) -> https://permalinkbnd.bnportugal.gov.pt/viewer/36540/?offset=#page=1&viewer=picture&o=info&n=0&q= | M70: https://purl.pt/1066 | N70: 36540 | O70: =CONCATENATE("https://permalinkbnd.bnportugal.gov.pt/viewer/",N70,"/?offset=#page=",D70,"&viewer=picture&o=info&n=0&q=") -> https://permalinkbnd.bnportugal.gov.pt/viewer/36540/?offset=#page=1&viewer=picture&o=info&n=0&q= | P70: 601741 | Q70: https://purl.pt/1066 | R70: https://bndigital.bnportugal.gov.pt//i/?IIIF=/50/1e/d4/2a/501ed42a-3de0-4cf9-821c-15ebd89b7023/iiif/e-3415-p_0000_000001.tif/full/!300,500/0/default.jpg | S70: Iconografia | T70: Francês | V70: Camoens | Y70: 1.ª ed. | Z70: La Haye : van Lier fréres | AA70: 1860 | AB70: 1860 | AC70: 1 gravura | AJ70: PURL 1066/0 | AL70: http://id.bnportugal.gov.pt/bib/catbnp/601741 | AM70: Livre
A71: 10149 | B71: 604127 | C71: 1 | D71: 1 | E71: https://purl.pt/27537 | F71: 1 site carta da geografia de Os Lusíadas | G71: 1 | I71: =HYPERLINK(O71) -> https://permalinkbnd.bnportugal.gov.pt/viewer/14040/?offset=#page=1&viewer=picture&o=info&n=0&q= | M71: https://purl.pt/27537 | N71: 14040 | O71: =CONCATENATE("https://permalinkbnd.bnportugal.gov.pt/viewer/",N71,"/?offset=#page=",D71,"&viewer=picture&o=info&n=0&q=") -> https://permalinkbnd.bnportugal.gov.pt/viewer/14040/?offset=#page=1&viewer=picture&o=info&n=0&q= | P71: 604127 | Q71: https://purl.pt/27537 | R71: https://bndigital.bnportugal.gov.pt//i/?IIIF=/84/ce/f5/25/84cef525-7874-41a2-b678-e38e5372d53b/iiif/cc-1054-r_0000_000001.tif/full/!300,500/0/default.jpg | S71: Cartografia | T71: Português | V71: Carta da geographia dos Lusiadas | W71: dedicada a S.M. El-rei D. Luis I | Y71: 1.ª ed. | Z71: Lisboa : Litografia da Imprensa Nacional | AA71: 1883 | AB71: 1883 | AC71: 1 mapa | AD71: Figueiredo, António Cardoso Borges de, 1851?-1890 | AG71: Camões, Luís de, 1524-1580, Antecedente bibliográfico | AJ71: C.C. 1054 R. | AL71: http://id.bnportugal.gov.pt/bib/catbnp/604127 | AM71: Livre | AP71: India - Escala ca 1:26000000, determinada com o valor calculado 0,43 cm para o grau de latitude | AR71: Carta da geografia dos Lusíadas
A72: 10150 | B72: 613457 | C72: 1 | D72: 1 | E72: https://purl.pt/43563 | F72: 1 | G72: 1 | I72: =HYPERLINK(O72) -> https://permalinkbnd.bnportugal.gov.pt/viewer/272734/?offset=#page=1&viewer=picture&o=info&n=0&q= | M72: https://purl.pt/43563 | N72: 272734 | O72: =CONCATENATE("https://permalinkbnd.bnportugal.gov.pt/viewer/",N72,"/?offset=#page=",D72,"&viewer=picture&o=info&n=0&q=") -> https://permalinkbnd.bnportugal.gov.pt/viewer/272734/?offset=#page=1&viewer=picture&o=info&n=0&q= | P72: 613457 | Q72: https://purl.pt/43563 | R72: https://bndigital.bnportugal.gov.pt//i/?IIIF=/d6/fc/1e/ec/d6fc1eec-5431-4985-ae4f-544438336cce/iiif/e-3525-p_0000_000001.tif/full/!300,500/0/default.jpg | S72: Iconografia | T72: Português | V72: Camões | Y72: 1.ª ed. | Z72: S.l. : s.n. | AA72: 1968 | AB72: 1968 | AC72: 1 imagem | AJ72: E. 3525 P. | AK72: CAM500 | AL72: http://id.bnportugal.gov.pt/bib/catbnp/613457 | AM72: Livre
A73: 10151 | B73: 614521 | C73: 1 | D73: 1 | E73: https://purl.pt/1127 | F73: 1 | G73: 1 | I73: =HYPERLINK(O73) -> https://permalinkbnd.bnportugal.gov.pt/viewer/36741/?offset=#page=1&viewer=picture&o=info&n=0&q= | M73: https://purl.pt/1127 | N73: 36741 | O73: =CONCATENATE("https://permalinkbnd.bnportugal.gov.pt/viewer/",N73,"/?offset=#page=",D73,"&viewer=picture&o=info&n=0&q=") -> https://permalinkbnd.bnportugal.gov.pt/viewer/36741/?offset=#page=1&viewer=picture&o=info&n=0&q= | P73: 614521 | Q73: https://purl.pt/1127 | R73: https://bndigital.bnportugal.gov.pt//i/?IIIF=/97/cc/bc/96/97ccbc96-a88e-42be-92ff-c6a0010e4a17/iiif/e-3548-p_0000_000001.tif/full/!300,500/0/default.jpg | S73: Iconografia | T73: Português | V73: Luiz de Camões | Y73: 1.ª ed. | Z73: Lisboa : Imprensa Nacional | AA73: 1873 | AB73: 1873 | AC73: 1 gravura | AD73: Sousa, Joaquim Pedro de, 1822-1878 | AJ73: PURL 1127/0 | AL73: http://id.bnportugal.gov.pt/bib/catbnp/614521 | AM73: Livre | AR73: Luís de Camões
A74: 10152 | B74: 626460 | C74: 1 | D74: 1 | E74: https://purl.pt/12554 | F74: 1 site | G74: 1 | I74: =HYPERLINK(O74) -> https://permalinkbnd.bnportugal.gov.pt/viewer/37180/?offset=#page=1&viewer=picture&o=info&n=0&q= | M74: https://purl.pt/12554 | N74: 37180 | O74: =CONCATENATE("https://permalinkbnd.bnportugal.gov.pt/viewer/",N74,"/?offset=#page=",D74,"&viewer=picture&o=info&n=0&q=") -> https://permalinkbnd.bnportugal.gov.pt/viewer/37180/?offset=#page=1&viewer=picture&o=info&n=0&q= | P74: 626460 | Q74: https://purl.pt/12554 | S74: Iconografia | T74: Francês | V74: Camoens | Y74: 1.ª ed. | Z74: Paris : s.n. | AA74: 1846 | AB74: 1846 | AC74: 1 gravura | AD74: Lemaitre, Augustin François, 1797-1870 | AJ74: PURL 12554/0 | AL74: http://id.bnportugal.gov.pt/bib/catbnp/626460 | AM74: Livre
A75: 10153 | B75: 626703 | C75: 1 | D75: 1 | E75: https://purl.pt/12562 | F75: 1 site | G75: 1 | I75: =HYPERLINK(O75) -> https://permalinkbnd.bnportugal.gov.pt/viewer/37208/?offset=#page=1&viewer=picture&o=info&n=0&q= | M75: https://purl.pt/12562 | N75: 37208 | O75: =CONCATENATE("https://permalinkbnd.bnportugal.gov.pt/viewer/",N75,"/?offset=#page=",D75,"&viewer=picture&o=info&n=0&q=") -> https://permalinkbnd.bnportugal.gov.pt/viewer/37208/?offset=#page=1&viewer=picture&o=info&n=0&q= | P75: 626703 | Q75: https://purl.pt/12562 | S75: Iconografia | T75: Alemão | V75: Camoëns im Gefangnisse zu Goa | Y75: 1.ª ed. | Z75: S.l. : s.n. | AA75: 1840 | AB75: 1840 | AC75: 1 gravura | AD75: Duncan, Andrew, 1795-? | AG75: Moreaux, Charles Florent Léon, 1815-?, Antecedente bibliográfico | AJ75: PURL 12562/0 | AL75: http://id.bnportugal.gov.pt/bib/catbnp/626703 | AM75: Livre
A76: 10154 | B76: 636335 | C76: 1 | D76: 1 | E76: https://purl.pt/5762 | F76: 1 | G76: 1 | I76: =HYPERLINK(O76) -> https://permalinkbnd.bnportugal.gov.pt/viewer/35147/?offset=#page=1&viewer=picture&o=info&n=0&q= | M76: https://purl.pt/5762 | N76: 35147 | O76: =CONCATENATE("https://permalinkbnd.bnportugal.gov.pt/viewer/",N76,"/?offset=#page=",D76,"&viewer=picture&o=info&n=0&q=") -> https://permalinkbnd.bnportugal.gov.pt/viewer/35147/?offset=#page=1&viewer=picture&o=info&n=0&q= | P76: 636335 | Q76: https://purl.pt/5762 | S76: Iconografia | T76: Português | V76: Á memoria do immortal cantor das glorias portuguezas | Y76: 1.ª ed. | Z76: Lisboa : s.n. | AA76: 1880 | AB76: 1880 | AC76: 1 gravura | AJ76: PURL 5762/0 | AL76: http://id.bnportugal.gov.pt/bib/catbnp/636335 | AM76: Livre | AR76: Á memória do imortal cantor das glórias portuguesas
A77: 10155 | B77: 636337 | C77: 1 | D77: 1 | E77: https://purl.pt/5763 | F77: 1 | G77: 1 | I77: =HYPERLINK(O77) -> https://permalinkbnd.bnportugal.gov.pt/viewer/1880/?offset=#page=1&viewer=picture&o=info&n=0&q= | M77: https://purl.pt/5763 | N77: 1880 | O77: =CONCATENATE("https://permalinkbnd.bnportugal.gov.pt/viewer/",N77,"/?offset=#page=",D77,"&viewer=picture&o=info&n=0&q=") -> https://permalinkbnd.bnportugal.gov.pt/viewer/1880/?offset=#page=1&viewer=picture&o=info&n=0&q= | P77: 636337 | Q77: https://purl.pt/5763 | R77: https://bndigital.bnportugal.gov.pt//i/?IIIF=/a1/c7/1e/30/a1c71e30-149f-4d01-a4cd-17eb6386f4ec/iiif/e-1773-v_0000_000001.tif/full/!300,500/0/default.jpg | S77: Iconografia | T77: Português | V77: 10 de Junho de 1880 | Y77: 1.ª ed. | Z77: Lisboa : s.n. | AA77: 1880 | AB77: 1880 | AC77: 1 gravura | AJ77: PURL 5763/0 | AL77: http://id.bnportugal.gov.pt/bib/catbnp/636337 | AM77: Livre
A78: 10156 | B78: 636371 | C78: 1 | D78: 1 | E78: https://purl.pt/5756 | F78: 1 site | G78: 1 | I78: =HYPERLINK(O78) -> https://permalinkbnd.bnportugal.gov.pt/viewer/35133/?offset=#page=1&viewer=picture&o=info&n=0&q= | M78: https://purl.pt/5756 | N78: 35133 | O78: =CONCATENATE("https://permalinkbnd.bnportugal.gov.pt/viewer/",N78,"/?offset=#page=",D78,"&viewer=picture&o=info&n=0&q=") -> https://permalinkbnd.bnportugal.gov.pt/viewer/35133/?offset=#page=1&viewer=picture&o=info&n=0&q= | P78: 636371 | Q78: https://purl.pt/5756 | R78: https://bndigital.bnportugal.gov.pt//i/?IIIF=/4d/33/d1/a8/4d33d1a8-9b14-4816-b086-3bfda8beb020/iiif/e-1775-v_0000_000001.tif/full/!300,500/0/default.jpg | S78: Iconografia | T78: Português | V78: Camões na gruta de Macau | W78: homenagem do Diario de Portugal a Luiz de Camões | Y78: 1.ª ed. | Z78: S.l. : s.n. | AA78: 1880 | AB78: 1880 | AC78: 1 gravura | AD78: Cardon, ca 1880 | AG78: Metrass, Francisco Augusto, 1825-1861, Antecedente bibliográfico | AJ78: PURL 5756/0 | AK78: OChina | AL78: http://id.bnportugal.gov.pt/bib/catbnp/636371 | AM78: Livre
A79: 10157 | B79: 636385 | C79: 1 | D79: 1 | E79: https://purl.pt/5757 | F79: 1 | G79: 1 | I79: =HYPERLINK(O79) -> https://permalinkbnd.bnportugal.gov.pt/viewer/35127/?offset=#page=1&viewer=picture&o=info&n=0&q= | M79: https://purl.pt/5757 | N79: 35127 | O79: =CONCATENATE("https://permalinkbnd.bnportugal.gov.pt/viewer/",N79,"/?offset=#page=",D79,"&viewer=picture&o=info&n=0&q=") -> https://permalinkbnd.bnportugal.gov.pt/viewer/35127/?offset=#page=1&viewer=picture&o=info&n=0&q= | P79: 636385 | Q79: https://purl.pt/5757 | R79: https://bndigital.bnportugal.gov.pt//i/?IIIF=/77/c8/5e/5a/77c85e5a-2edc-447a-be9f-e3b9247fe8a1/iiif/e-1774-v_0000_000001.tif/full/!300,500/0/default.jpg | S79: Iconografia | T79: Português | V79: Monumento a Camões | Y79: 1.ª ed. | Z79: S.l. : s.n. | AA79: 1868 | AB79: 1868 | AC79: 1 gravura | AD79: Sousa, Joaquim Pedro de, 1822-1878 | AG79: Barros, Silêncio Cristão de, 1798-1867, Impressor de ilustrações em chapa gravada | AJ79: PURL 5757/0 | AK79: CAM500 | AL79: http://id.bnportugal.gov.pt/bib/catbnp/636385 | AM79: Livre
A80: 10158 | B80: 636389 | C80: 1 | D80: 1 | E80: https://purl.pt/5761 | F80: 1 site | G80: 1 | I80: =HYPERLINK(O80) -> https://permalinkbnd.bnportugal.gov.pt/viewer/35137/?offset=#page=1&viewer=picture&o=info&n=0&q= | M80: https://purl.pt/5761 | N80: 35137 | O80: =CONCATENATE("https://permalinkbnd.bnportugal.gov.pt/viewer/",N80,"/?offset=#page=",D80,"&viewer=picture&o=info&n=0&q=") -> https://permalinkbnd.bnportugal.gov.pt/viewer/35137/?offset=#page=1&viewer=picture&o=info&n=0&q= | P80: 636389 | Q80: https://purl.pt/5761 | R80: https://bndigital.bnportugal.gov.pt//i/?IIIF=/7e/61/9f/18/7e619f18-7c28-4232-b632-4cb06e6e808f/iiif/e-1776-v_0000_000001.tif/full/!300,500/0/default.jpg | S80: Iconografia | T80: Português | V80: O tempo levando os Lusíadas à posteridade | Y80: 1.ª ed. | Z80: S.l. : s.n. | AA80: 1880 | AB80: 1880 | AC80: 1 gravura | AD80: Medeiros, J., ca. 18- - | AJ80: PURL 5761/0 | AL80: http://id.bnportugal.gov.pt/bib/catbnp/636389 | AM80: Livre
A81: 10159 | B81: 637133 | C81: 1 | D81: 1 | E81: https://purl.pt/4762 | F81: 1 site | G81: 1 | I81: =HYPERLINK(O81) -> https://permalinkbnd.bnportugal.gov.pt/viewer/37203/?offset=#page=1&viewer=picture&o=info&n=0&q= | M81: https://purl.pt/4762 | N81: 37203 | O81: =CONCATENATE("https://permalinkbnd.bnportugal.gov.pt/viewer/",N81,"/?offset=#page=",D81,"&viewer=picture&o=info&n=0&q=") -> https://permalinkbnd.bnportugal.gov.pt/viewer/37203/?offset=#page=1&viewer=picture&o=info&n=0&q= | P81: 637133 | Q81: https://purl.pt/4762 | R81: https://bndigital.bnportugal.gov.pt//i/?IIIF=/2b/63/53/2f/2b63532f-998a-4f7b-8b8c-b4e456bc6390/iiif/e-403-v_0000_000001.tif/full/!300,500/0/default.jpg | S81: Iconografia | T81: Português | V81: Epitome da vida de Luiz de Camoens | Y81: 1.ª ed. | Z81: Lisboa : s.n. | AA81: 1808 | AB81: 1808 | AC81: 1 gravura | AD81: Cardini, João, fl. 1804-1825? | AJ81: PURL 4762/0 | AL81: http://id.bnportugal.gov.pt/bib/catbnp/637133 | AM81: Livre | AR81: Epítome da vida de Luís de Camões
A82: 10160 | B82: 637139 | C82: 1 | D82: 1 | E82: https://purl.pt/4760 | F82: 1 site | G82: 1 | I82: =HYPERLINK(O82) -> https://permalinkbnd.bnportugal.gov.pt/viewer/37132/?offset=#page=1&viewer=picture&o=info&n=0&q= | M82: https://purl.pt/4760 | N82: 37132 | O82: =CONCATENATE("https://permalinkbnd.bnportugal.gov.pt/viewer/",N82,"/?offset=#page=",D82,"&viewer=picture&o=info&n=0&q=") -> https://permalinkbnd.bnportugal.gov.pt/viewer/37132/?offset=#page=1&viewer=picture&o=info&n=0&q= | P82: 637139 | Q82: https://purl.pt/4760 | R82: https://bndigital.bnportugal.gov.pt//i/?IIIF=/91/93/ef/9e/9193ef9e-3647-4d04-a920-6fce8a1629b8/iiif/e-404-v_0000_000001.tif/full/!300,500/0/default.jpg | S82: Iconografia | T82: Português | V82: Ao tricentenário de Luiz de Camões | W82: aos 10 de Junho de 1880, Rio de Janeiro | Y82: 1.ª ed. | Z82: Rio de Janeiro : s.n. | AA82: 1880 | AB82: 1880 | AC82: 1 gravura | AI82: Litografia António Lobo & Companhia | AJ82: PURL 4760/0 | AL82: http://id.bnportugal.gov.pt/bib/catbnp/637139 | AM82: Livre | AR82: Ao tricentenário de Luís de Camões
A83: 10162 | B83: 665442 | C83: 1 | D83: 1 | E83: https://purl.pt/5904 | F83: 1 | G83: 1 | I83: =HYPERLINK(O83) -> https://permalinkbnd.bnportugal.gov.pt/viewer/34623/?offset=#page=1&viewer=picture&o=info&n=0&q= | M83: https://purl.pt/5904 | N83: 34623 | O83: =CONCATENATE("https://permalinkbnd.bnportugal.gov.pt/viewer/",N83,"/?offset=#page=",D83,"&viewer=picture&o=info&n=0&q=") -> https://permalinkbnd.bnportugal.gov.pt/viewer/34623/?offset=#page=1&viewer=picture&o=info&n=0&q= | P83: 665442 | Q83: https://purl.pt/5904 | S83: Iconografia | V83: Tricentenário de Camões | Y83: 1.ª ed. | Z83: S.l. : s.n. | AA83: 1880 | AB83: 1880 | AC83: 1 gravura | AJ83: PURL 5904/0 | AL83: http://id.bnportugal.gov.pt/bib/catbnp/665442 | AM83: Livre
A84: 10163 | B84: 700486 | C84: 1 | D84: 1 | E84: https://purl.pt/6773 | F84: 1 | G84: 1 | I84: =HYPERLINK(O84) -> https://permalinkbnd.bnportugal.gov.pt/viewer/37092/?offset=#page=1&viewer=picture&o=info&n=0&q= | M84: https://purl.pt/6773 | N84: 37092 | O84: =CONCATENATE("https://permalinkbnd.bnportugal.gov.pt/viewer/",N84,"/?offset=#page=",D84,"&viewer=picture&o=info&n=0&q=") -> https://permalinkbnd.bnportugal.gov.pt/viewer/37092/?offset=#page=1&viewer=picture&o=info&n=0&q= | P84: 700486 | Q84: https://purl.pt/6773 | R84: https://bndigital.bnportugal.gov.pt//i/?IIIF=/68/60/bf/0c/6860bf0c-8b2d-42e5-8809-1edc675de42b/iiif/e-40-a_0000_000001.tif/full/!300,500/0/default.jpg | S84: Iconografia | T84: Português | V84: Camões lendo os Lusíadas a D. Sebastião | Y84: 1.ª ed. | Z84: Lisboa : s.n. | AA84: 1893 | AB84: 1893 | AC84: 1 gravura | AD84: Ramalho, António, 1858-1916 | AI84: Litografia de Portugal, Impressor | AJ84: PURL 6773/0 | AL84: http://id.bnportugal.gov.pt/bib/catbnp/700486 | AM84: Livre
A85: 10164 | B85: 700487 | C85: 1 | D85: 1 | E85: https://purl.pt/6771 | F85: 1 | G85: 1 | I85: =HYPERLINK(O85) -> https://permalinkbnd.bnportugal.gov.pt/viewer/37325/?offset=#page=1&viewer=picture&o=info&n=0&q= | M85: https://purl.pt/6771 | N85: 37325 | O85: =CONCATENATE("https://permalinkbnd.bnportugal.gov.pt/viewer/",N85,"/?offset=#page=",D85,"&viewer=picture&o=info&n=0&q=") -> https://permalinkbnd.bnportugal.gov.pt/viewer/37325/?offset=#page=1&viewer=picture&o=info&n=0&q= | P85: 700487 | Q85: https://purl.pt/6771 | R85: https://bndigital.bnportugal.gov.pt//i/?IIIF=/f1/a9/3d/d6/f1a93dd6-7849-41fe-998c-148d7cb7b2dd/iiif/e-41-a_0000_000001.tif/full/!300,500/0/default.jpg | S85: Iconografia | T85: Português | V85: Camões no leito de morte | Y85: 1.ª ed. | Z85: Lisboa : s.n. | AA85: 1861 | AB85: 1861 | AC85: 1 gravura | AD85: Cupertino, fl. 1860 | AJ85: PURL 6771/0 | AL85: http://id.bnportugal.gov.pt/bib/catbnp/700487 | AM85: Livre
A86: 10165 | B86: 704429 | C86: 1 | D86: 1 | E86: https://purl.pt/1227 | F86: 1 | G86: 1 | I86: =HYPERLINK(O86) -> https://permalinkbnd.bnportugal.gov.pt/viewer/33427/?offset=#page=1&viewer=picture&o=info&n=0&q= | M86: https://purl.pt/1227 | N86: 33427 | O86: =CONCATENATE("https://permalinkbnd.bnportugal.gov.pt/viewer/",N86,"/?offset=#page=",D86,"&viewer=picture&o=info&n=0&q=") -> https://permalinkbnd.bnportugal.gov.pt/viewer/33427/?offset=#page=1&viewer=picture&o=info&n=0&q= | P86: 704429 | Q86: https://purl.pt/1227 | R86: https://bndigital.bnportugal.gov.pt//i/?IIIF=/ed/6c/2b/55/ed6c2b55-9065-4ce7-97e4-d3437ec4bfa1/iiif/d-392-v_0000_000001.tif/full/!300,500/0/default.jpg | S86: Iconografia | T86: Português | V86: Os Lusíadas | W86: ilustração | Y86: 1.ª ed. | AA86: 1900 | AB86: 1900 | AC86: 1 desenho | AD86: Gameiro, Alfredo Roque, 1864-1935 | AJ86: PURL 1227/0 | AL86: http://id.bnportugal.gov.pt/bib/catbnp/704429 | AM86: Livre | AO86: Atribução de autor segundo nota ms. no verso
A87: 10166 | B87: 709106 | C87: 1 | D87: 1 | E87: https://purl.pt/6901 | F87: 1 | G87: 1 | I87: =HYPERLINK(O87) -> https://permalinkbnd.bnportugal.gov.pt/viewer/36374/?offset=#page=1&viewer=picture&o=info&n=0&q= | M87: https://purl.pt/6901 | N87: 36374 | O87: =CONCATENATE("https://permalinkbnd.bnportugal.gov.pt/viewer/",N87,"/?offset=#page=",D87,"&viewer=picture&o=info&n=0&q=") -> https://permalinkbnd.bnportugal.gov.pt/viewer/36374/?offset=#page=1&viewer=picture&o=info&n=0&q= | P87: 709106 | Q87: https://purl.pt/6901 | R87: https://bndigital.bnportugal.gov.pt//i/?IIIF=/c6/65/ed/04/c665ed04-906d-47be-afa9-f49402d8909b/iiif/e-271-a_0000_000001.tif/full/!300,500/0/default.jpg | S87: Iconografia | T87: Português | V87: Luiz de Camões | Y87: 1.ª ed. | Z87: S.l. : s.n. | AA87: 1878 | AB87: 1878 | AC87: 1 gravura | AD87: Grossi, ca 1880 | AJ87: PURL 6901/0 | AL87: http://id.bnportugal.gov.pt/bib/catbnp/709106 | AM87: Livre | AR87: Luís de Camões
A88: 10167 | B88: 709129 | C88: 1 | D88: 1 | E88: https://purl.pt/6844 | F88: 1 | G88: 1 | I88: =HYPERLINK(O88) -> https://permalinkbnd.bnportugal.gov.pt/viewer/36554/?offset=#page=1&viewer=picture&o=info&n=0&q= | M88: https://purl.pt/6844 | N88: 36554 | O88: =CONCATENATE("https://permalinkbnd.bnportugal.gov.pt/viewer/",N88,"/?offset=#page=",D88,"&viewer=picture&o=info&n=0&q=") -> https://permalinkbnd.bnportugal.gov.pt/viewer/36554/?offset=#page=1&viewer=picture&o=info&n=0&q= | P88: 709129 | Q88: https://purl.pt/6844 | R88: https://bndigital.bnportugal.gov.pt//i/?IIIF=/d5/4a/55/8b/d54a558b-4168-4ce9-95b6-7b9ac715137f/iiif/e-274-a_0000_000001.tif/full/!300,500/0/default.jpg | S88: Iconografia | T88: Português | V88: Vasco da Gama apresenta a D. Manuel as primicias da India | W88: Entraram pela foz do Tejo ameno... Lusiadas, canto X, est. 144 | Y88: 1.ª ed. | Z88: Lisboa ; : João Romano Torres | AA88: 1890 | AB88: 1890 | AC88: 1 imagem | AG88: Camões, Luís de, 1524-1580, Autor em citações ou excertos de textos ; Marinho, José Pires, 1857-1929?, Técnico gráfico ; Torres, João Romano, 1855-1935, Editor comercial | AJ88: PURL 6844/0 | AL88: http://id.bnportugal.gov.pt/bib/catbnp/709129 | AM88: Livre | AN88: Brinde aos assinantes do romance "A pecadora"
A89: 10169 | B89: 729122 | C89: 1 | D89: 1 | E89: https://purl.pt/12937 | F89: 1 | G89: 1 | I89: =HYPERLINK(O89) -> https://permalinkbnd.bnportugal.gov.pt/viewer/37663/?offset=#page=1&viewer=picture&o=info&n=0&q= | M89: https://purl.pt/12937 | N89: 37663 | O89: =CONCATENATE("https://permalinkbnd.bnportugal.gov.pt/viewer/",N89,"/?offset=#page=",D89,"&viewer=picture&o=info&n=0&q=") -> https://permalinkbnd.bnportugal.gov.pt/viewer/37663/?offset=#page=1&viewer=picture&o=info&n=0&q= | P89: 729122 | Q89: https://purl.pt/12937 | R89: https://bndigital.bnportugal.gov.pt//i/?IIIF=/15/56/29/ac/155629ac-1d4f-4db2-92f1-9e806d18975b/iiif/e-4482-p_0000_000001.tif/full/!300,500/0/default.jpg | S89: Iconografia | T89: Latim | V89: Ludovicus Camonius, Lusitanus epicorum poetar, in Hispania Princeps, vixit an. LV. obiit an M.DLXXIX | Y89: 1.ª ed. | Z89: Lisboa : na Officina Luisiana | AA89: 1779 | AB89: 1779 | AC89: 1 gravura | AD89: Rodrigues, António Fernandes, 1727-1807 | AI89: Oficina Luisiana, Impressor | AJ89: PURL 12937/0 | AL89: http://id.bnportugal.gov.pt/bib/catbnp/729122 | AM89: Livre
A90: 10170 | B90: 730341 | C90: 1 | D90: 1 | E90: https://purl.pt/12929 | F90: 1 site | G90: 1 | I90: =HYPERLINK(O90) -> https://permalinkbnd.bnportugal.gov.pt/viewer/37195/?offset=#page=1&viewer=picture&o=info&n=0&q= | M90: https://purl.pt/12929 | N90: 37195 | O90: =CONCATENATE("https://permalinkbnd.bnportugal.gov.pt/viewer/",N90,"/?offset=#page=",D90,"&viewer=picture&o=info&n=0&q=") -> https://permalinkbnd.bnportugal.gov.pt/viewer/37195/?offset=#page=1&viewer=picture&o=info&n=0&q= | P90: 730341 | Q90: https://purl.pt/12929 | S90: Iconografia | T90: Francês | V90: Camoens | Y90: 1.ª ed. | Z90: Paris : Furne | AA90: 1841 | AB90: 1841 | AC90: 1 gravura | AD90: Audibran, François Adolphe Bruneau, 1810-? | AJ90: PURL 12929/0 | AL90: http://id.bnportugal.gov.pt/bib/catbnp/730341 | AM90: Livre
A91: 10171 | B91: 733501 | C91: 1 | D91: 1 | E91: https://purl.pt/12938 | F91: 1 | G91: 1 | I91: =HYPERLINK(O91) -> https://permalinkbnd.bnportugal.gov.pt/viewer/37674/?offset=#page=1&viewer=picture&o=info&n=0&q= | M91: https://purl.pt/12938 | N91: 37674 | O91: =CONCATENATE("https://permalinkbnd.bnportugal.gov.pt/viewer/",N91,"/?offset=#page=",D91,"&viewer=picture&o=info&n=0&q=") -> https://permalinkbnd.bnportugal.gov.pt/viewer/37674/?offset=#page=1&viewer=picture&o=info&n=0&q= | P91: 733501 | Q91: https://purl.pt/12938 | S91: Iconografia | T91: Inglês | V91: Luis de Camoens | Y91: 1.ª ed. | Z91: London : Longman | AA91: 1820 | AB91: 1820 | AC91: 1 gravura | AD91: Skelton, William, 1763-1848 | AJ91: PURL 12938/0 | AK91: PCulture | AL91: http://id.bnportugal.gov.pt/bib/catbnp/733501 | AM91: Livre
A92: 10172 | B92: 742171 | C92: 1 | D92: 10 | E92: https://purl.pt/43810 | F92: 10, 18 [retratos de Camões e de Vasco da Gama] | G92: 10, 18 | I92: =HYPERLINK(O92) -> https://permalinkbnd.bnportugal.gov.pt/viewer/274166/?offset=#page=10&viewer=picture&o=info&n=0&q= | M92: https://purl.pt/43810 | N92: 274166 | O92: =CONCATENATE("https://permalinkbnd.bnportugal.gov.pt/viewer/",N92,"/?offset=#page=",D92,"&viewer=picture&o=info&n=0&q=") -> https://permalinkbnd.bnportugal.gov.pt/viewer/274166/?offset=#page=10&viewer=picture&o=info&n=0&q= | P92: 742171 | Q92: https://purl.pt/43810 | R92: https://bndigital.bnportugal.gov.pt//i/?IIIF=/20/0e/92/c5/200e92c5-aec5-4489-a61a-b6480cdafb72/iiif/cam-41-v_0005.tif/full/!300,500/0/default.jpg | S92: Livro impresso | T92: Francês | V92: Les Lusiades | Y92: 1.ª ed. | Z92: Lisboa : Tip da Comp. Nacional Editora | AA92: 1889 | AB92: 1889 | AC92: 338 p. | AD92: Camões, Luís de, 1524-1580 | AG92: Garin, Hyacinthe, Editor literário | AJ92: L. 5855 A. | AK92: CAM500 | AL92: http://id.bnportugal.gov.pt/bib/catbnp/742171 | AM92: Livre
A93: 10173 | B93: 742171 | C93: 1 | D93: 18 | E93: https://purl.pt/43810 | F93: 10, 18 [retratos de Camões e de Vasco da Gama] | G93: 10, 18 | I93: =HYPERLINK(O93) -> https://permalinkbnd.bnportugal.gov.pt/viewer/274166/?offset=#page=18&viewer=picture&o=info&n=0&q= | M93: https://purl.pt/43810 | N93: 274166 | O93: =CONCATENATE("https://permalinkbnd.bnportugal.gov.pt/viewer/",N93,"/?offset=#page=",D93,"&viewer=picture&o=info&n=0&q=") -> https://permalinkbnd.bnportugal.gov.pt/viewer/274166/?offset=#page=18&viewer=picture&o=info&n=0&q= | P93: 742171 | Q93: https://purl.pt/43810 | R93: https://bndigital.bnportugal.gov.pt//i/?IIIF=/20/0e/92/c5/200e92c5-aec5-4489-a61a-b6480cdafb72/iiif/cam-41-v_0005.tif/full/!300,500/0/default.jpg | S93: Livro impresso | T93: Francês | V93: Les Lusiades | Y93: 1.ª ed. | Z93: Lisboa : Tip da Comp. Nacional Editora | AA93: 1889 | AB93: 1889 | AC93: 338 p. | AD93: Camões, Luís de, 1524-1580 | AG93: Garin, Hyacinthe, Editor literário | AJ93: L. 5855 A. | AK93: CAM500 | AL93: http://id.bnportugal.gov.pt/bib/catbnp/742171 | AM93: Livre
A94: 10175 | B94: 764770 | C94: 1 | D94: 7 | E94: https://purl.pt/42608 | F94: 7 [portada e 46 apontamento final Canto I] | G94: 7 | I94: =HYPERLINK(O94) -> https://permalinkbnd.bnportugal.gov.pt/viewer/270042/?offset=#page=7&viewer=picture&o=info&n=0&q= | M94: https://purl.pt/42608 | N94: 270042 | O94: =CONCATENATE("https://permalinkbnd.bnportugal.gov.pt/viewer/",N94,"/?offset=#page=",D94,"&viewer=picture&o=info&n=0&q=") -> https://permalinkbnd.bnportugal.gov.pt/viewer/270042/?offset=#page=7&viewer=picture&o=info&n=0&q= | P94: 764770 | Q94: https://purl.pt/42608 | R94: https://bndigital.bnportugal.gov.pt//i/?IIIF=/9e/91/6e/ad/9e916ead-0a6f-45ca-96ba-ec9f9d845df0/iiif/cam-17-p_0000_000007.tif/full/!300,500/0/default.jpg | S94: Livro impresso | T94: Português | V94: Os Lusiadas | Y94: 1.ª ed. | Z94: Em Lisboa : por Pedro Crasbeeck : com privilegio, à custa de Domingos Fernandez livreyro | AA94: 1609 | AB94: 1609 | AC94: 2, 186 f. | AD94: Camões, Luís de, 1524-1580 | AG94: Cunha, Rodrigo da, 1577-1643, Personalidade a quem é dedicada a obra ; Sousa, Luís de, 1555-1632, Autor ; Mendonça, Pedro da Silva e, Autor ; Tasso, Torquato, 1544-1595, Autor ; Leitão, Diogo Taborda, 15--, Autor ; Tamayo de Vargas, Tomás, 1588-1641, Autor ; Bernardes, Diogo, ca 1530-1596, Autor ; Craesbeeck, Pedro, fl. 1597-1632, Impressor ; Norton, Tomás, 1804-1860, Antigo possuidor ; Fernandes, Domingos, 15---16--, Editor comercial ; Barreto, Domingos da Costa, Antigo possuidor ; Caminha, António Lourenço, ?-1831, Antigo possuidor | AJ94: F. 2553 | AK94: CAM500 | AL94: http://id.bnportugal.gov.pt/bib/catbnp/764770 | AM94: Livre
A95: 10179 | B95: 767226 | C95: 1 | D95: 4 | E95: https://purl.pt/43749 | F95: 4 | G95: 4 | I95: =HYPERLINK(O95) -> https://permalinkbnd.bnportugal.gov.pt/viewer/273943/?offset=#page=4&viewer=picture&o=info&n=0&q= | M95: https://purl.pt/43749 | N95: 273943 | O95: =CONCATENATE("https://permalinkbnd.bnportugal.gov.pt/viewer/",N95,"/?offset=#page=",D95,"&viewer=picture&o=info&n=0&q=") -> https://permalinkbnd.bnportugal.gov.pt/viewer/273943/?offset=#page=4&viewer=picture&o=info&n=0&q= | P95: 767226 | Q95: https://purl.pt/43749 | S95: Livro impresso | T95: Português | V95: Os Lusiadas | W95: poema épico... | Y95: Nova ed. cuidadosamente revista e conforme às de 1572, precedida da biografia do poeta e seguida de um dicionário dos nomes próprios | Z95: Lisboa : Livr. António Maria Pereira | AA95: 1875 | AB95: 1875 | AC95: XVIII, 457, 6 p. | AD95: Camões, Luís de, 1524-1580 | AJ95: CAM. 566 P. | AK95: CAM500 | AL95: http://id.bnportugal.gov.pt/bib/catbnp/767226 | AM95: Livre
A96: 10181 | B96: 767525 | C96: 1 | D96: 3 | E96: https://purl.pt/43772 | F96: 3 | G96: 3 | I96: =HYPERLINK(O96) -> https://permalinkbnd.bnportugal.gov.pt/viewer/273427/?offset=#page=3&viewer=picture&o=info&n=0&q= | M96: https://purl.pt/43772 | N96: 273427 | O96: =CONCATENATE("https://permalinkbnd.bnportugal.gov.pt/viewer/",N96,"/?offset=#page=",D96,"&viewer=picture&o=info&n=0&q=") -> https://permalinkbnd.bnportugal.gov.pt/viewer/273427/?offset=#page=3&viewer=picture&o=info&n=0&q= | P96: 767525 | Q96: https://purl.pt/43772 | R96: https://bndigital.bnportugal.gov.pt//i/?IIIF=/7c/53/55/55/7c535555-bf57-4fa5-b6f4-b9bad743d540/iiif/cam-106-2-v_0000_000001.tif/full/!300,500/0/default.jpg | S96: Livro impresso | T96: Português | V96: Á memoria de Luiz de Camões | W96: 301.º anniversario do fallecimento do grande épico | Y96: 1.ª ed. | Z96: Loanda : Tip. do Mercantil | AA96: 1881 | AB96: 1881 | AC96: 26, 2 p. | AE96: Sociedade Propagadora de Conhecimentos Geográfico-Africanos | AG96: Vilhena, Ernesto Jardim de, 1876-1967, Antigo possuidor | AJ96: H.G. 12224//6 V. | AK96: CAM500 | AL96: http://id.bnportugal.gov.pt/bib/catbnp/767525 | AM96: Livre
A97: 10187 | B97: 782745 | C97: 1 | D97: 6 | E97: https://purl.pt/43415 | F97: 6, 286, 322 | G97: 6 | I97: =HYPERLINK(O97) -> https://permalinkbnd.bnportugal.gov.pt/viewer/272372/?offset=#page=6&viewer=picture&o=info&n=0&q= | M97: https://purl.pt/43415 | N97: 272372 | O97: =CONCATENATE("https://permalinkbnd.bnportugal.gov.pt/viewer/",N97,"/?offset=#page=",D97,"&viewer=picture&o=info&n=0&q=") -> https://permalinkbnd.bnportugal.gov.pt/viewer/272372/?offset=#page=6&viewer=picture&o=info&n=0&q= | P97: 782745 | Q97: https://purl.pt/43415 | R97: https://bndigital.bnportugal.gov.pt//i/?IIIF=/a1/d0/ad/31/a1d0ad31-73b5-460a-ba20-5f53415efc39/iiif/cam-709-p_0007.tif/full/!300,500/0/default.jpg | S97: Livro impresso | T97: Português | V97: Os Lusiadas | W97: poema épico | Y97: Nova ed | Z97: Porto : Livr. Ed. Cruz Coutinho | AA97: 1889 | AB97: 1889 | AC97: XII, 480 p. | AD97: Camões, Luís de, 1524-1580 | AJ97: CAM. 709 P. | AK97: CAM500 | AL97: http://id.bnportugal.gov.pt/bib/catbnp/782745 | AM97: Livre
A98: 10191 | B98: 784907 | C98: 1 | D98: 21 | E98: https://purl.pt/43424 | F98: 21, 24, 25, 28, 29 [site], 32, 33, 36, 37, 40, 41 | G98: 21, 24, 25, 28, 29, 32, 33, 36, 37, 40, 41 | I98: =HYPERLINK(O98) -> https://permalinkbnd.bnportugal.gov.pt/viewer/272381/?offset=#page=21&viewer=picture&o=info&n=0&q= | M98: https://purl.pt/43424 | N98: 272381 | O98: =CONCATENATE("https://permalinkbnd.bnportugal.gov.pt/viewer/",N98,"/?offset=#page=",D98,"&viewer=picture&o=info&n=0&q=") -> https://permalinkbnd.bnportugal.gov.pt/viewer/272381/?offset=#page=21&viewer=picture&o=info&n=0&q= | P98: 784907 | Q98: https://purl.pt/43424 | R98: https://bndigital.bnportugal.gov.pt//i/?IIIF=/b1/0e/f2/ad/b10ef2ad-b90f-419d-ac6d-791303f80865/iiif/cam-738-p_0018.tif/full/!300,500/0/default.jpg | S98: Livro impresso | T98: Português | V98: Lusiadas de Luis de Camões a que se ajuntam a vida do Poeta, hum argumento historico dos Lusiadas... com 10 estampas | Y98: 1.ª ed. | Z98: Lisboa : Tip. de Eugénio Augusti | AA98: 1836 | AB98: 1836 | AD98: Camões, Luís de, 1524-1580 | AJ98: CAM. 738 P. | AK98: CAM500 | AL98: http://id.bnportugal.gov.pt/bib/catbnp/784907 | AM98: Livre
A99: 10192 | B99: 784907 | C99: 1 | D99: 24 | E99: https://purl.pt/43424 | F99: 21, 24, 25, 28, 29 [site], 32, 33, 36, 37, 40, 41 | G99: 21, 24, 25, 28, 29, 32, 33, 36, 37, 40, 41 | I99: =HYPERLINK(O99) -> https://permalinkbnd.bnportugal.gov.pt/viewer/272381/?offset=#page=24&viewer=picture&o=info&n=0&q= | M99: https://purl.pt/43424 | N99: 272381 | O99: =CONCATENATE("https://permalinkbnd.bnportugal.gov.pt/viewer/",N99,"/?offset=#page=",D99,"&viewer=picture&o=info&n=0&q=") -> https://permalinkbnd.bnportugal.gov.pt/viewer/272381/?offset=#page=24&viewer=picture&o=info&n=0&q= | P99: 784907 | Q99: https://purl.pt/43424 | R99: https://bndigital.bnportugal.gov.pt//i/?IIIF=/b1/0e/f2/ad/b10ef2ad-b90f-419d-ac6d-791303f80865/iiif/cam-738-p_0018.tif/full/!300,500/0/default.jpg | S99: Livro impresso | T99: Português | V99: Lusiadas de Luis de Camões a que se ajuntam a vida do Poeta, hum argumento historico dos Lusiadas... com 10 estampas | Y99: 1.ª ed. | Z99: Lisboa : Tip. de Eugénio Augusti | AA99: 1836 | AB99: 1836 | AD99: Camões, Luís de, 1524-1580 | AJ99: CAM. 738 P. | AK99: CAM500 | AL99: http://id.bnportugal.gov.pt/bib/catbnp/784907 | AM99: Livre
A100: 10193 | B100: 784907 | C100: 1 | D100: 25 | E100: https://purl.pt/43424 | F100: 21, 24, 25, 28, 29 [site], 32, 33, 36, 37, 40, 41 | G100: 21, 24, 25, 28, 29, 32, 33, 36, 37, 40, 41 | I100: =HYPERLINK(O100) -> https://permalinkbnd.bnportugal.gov.pt/viewer/272381/?offset=#page=25&viewer=picture&o=info&n=0&q= | M100: https://purl.pt/43424 | N100: 272381 | O100: =CONCATENATE("https://permalinkbnd.bnportugal.gov.pt/viewer/",N100,"/?offset=#page=",D100,"&viewer=picture&o=info&n=0&q=") -> https://permalinkbnd.bnportugal.gov.pt/viewer/272381/?offset=#page=25&viewer=picture&o=info&n=0&q= | P100: 784907 | Q100: https://purl.pt/43424 | R100: https://bndigital.bnportugal.gov.pt//i/?IIIF=/b1/0e/f2/ad/b10ef2ad-b90f-419d-ac6d-791303f80865/iiif/cam-738-p_0018.tif/full/!300,500/0/default.jpg | S100: Livro impresso | T100: Português | V100: Lusiadas de Luis de Camões a que se ajuntam a vida do Poeta, hum argumento historico dos Lusiadas... com 10 estampas | Y100: 1.ª ed. | Z100: Lisboa : Tip. de Eugénio Augusti | AA100: 1836 | AB100: 1836 | AD100: Camões, Luís de, 1524-1580 | AJ100: CAM. 738 P. | AK100: CAM500 | AL100: http://id.bnportugal.gov.pt/bib/catbnp/784907 | AM100: Livre
...

Sheet imagens-regina
A1: id | B1: pasta | C1: volume | D1: imagem | E1: purl | G1: imagens_texto | H1: imagens | I1: notas Regina | J1: url | K1: Categoria-1 | L1: Categoria-2 | M1: Categoria-3 | N1: url_purl | O1: number | P1: link_pagina | Q1: ncb | R1: purl | S1: capa | T1: tipo de material | U1: língua | V1: língua da obra original | W1: título | X1: subtítulo | Y1: título original | Z1: edição | AA1: publicação | AB1: data da publicação | AC1: data da publicação2 | AD1: dimensões | AE1: autor | AF1: autor - organização | AG1: co-autores | AH1: autores secundários | AI1: co-autores - organizações | AJ1: autores secundários - organizações | AK1: cota | AL1: coleção | AM1: id persistente | AN1: acesso | AO1: notas gerais | AP1: notas título | AQ1: notas conteúdo | AR1: sumário | AS1: título uniforme | AT1: título colectivo uniforme | AU1: Column1
A2: 9951 | B2: 367428 | C2: 1 | D2: 1 | E2: https://purl.pt/43428 | F2: =HYPERLINK(E2) -> https://purl.pt/43428 | G2: 1 | H2: 1 | J2: =HYPERLINK(P2) -> https://permalinkbnd.bnportugal.gov.pt/viewer/272369/?offset=#page=1&viewer=picture&o=info&n=0&q= | N2: https://purl.pt/43428 | O2: 272369 | P2: =CONCATENATE("https://permalinkbnd.bnportugal.gov.pt/viewer/",O2,"/?offset=#page=",D2,"&viewer=picture&o=info&n=0&q=") -> https://permalinkbnd.bnportugal.gov.pt/viewer/272369/?offset=#page=1&viewer=picture&o=info&n=0&q= | Q2: 367428 | R2: https://purl.pt/43428 | S2: https://bndigital.bnportugal.gov.pt//i/?IIIF=/a3/eb/b0/67/a3ebb067-89f3-40ff-a518-1fc158846d4b/iiif/cam-479-p_0003.tif/full/!300,500/0/default.jpg | T2: Livro impresso | U2: Italiano | W2: I Lusiadi | X2: poema | Z2: 1.ª ed. | AA2: Milano : Edoardo Sonzogno,editore | AB2: 1882 | AC2: 1882 | AD2: 196 p. | AE2: Camões, Luís de, 1524-1580 | AH2: Nervi, Antonio, 1760-1836, Tradutor | AK2: CAM. 479 P. | AL2: CAM500 | AM2: http://id.bnportugal.gov.pt/bib/catbnp/367428 | AN2: Livre
A3: 9968 | B3: 381074 | C3: 1 | D3: 499 | E3: https://purl.pt/43747 | F3: =HYPERLINK(E3) -> https://purl.pt/43747 | G3: 10 [site], 11, 103 [site pelicano direita], 107, 142, 107, 142, 145, 185, 235, 270 [site assassinato de Inês], 273, 306, 309 [site ninfas], 342, 345, 374, 377, 410, 413, 447, 499, 526 [site apontamento] [pintura de Camões por Columbano, portada, fac-símile do frontispício da 1.ª Ed. de Os Lusíadas, ilustrações da obra] | H3: 10, 11, 103, 145, 235, 270, 273, 306, 309, 342, 345, 374, 377, 410, 413, 447, 499 | J3: =HYPERLINK(P3) -> https://permalinkbnd.bnportugal.gov.pt/viewer/274089/?offset=#page=499&viewer=picture&o=info&n=0&q= | N3: https://purl.pt/43747 | O3: 274089 | P3: =CONCATENATE("https://permalinkbnd.bnportugal.gov.pt/viewer/",O3,"/?offset=#page=",D3,"&viewer=picture&o=info&n=0&q=") -> https://permalinkbnd.bnportugal.gov.pt/viewer/274089/?offset=#page=499&viewer=picture&o=info&n=0&q= | Q3: 381074 | R3: https://purl.pt/43747 | S3: https://bndigital.bnportugal.gov.pt//i/?IIIF=/7d/bb/9c/38/7dbb9c38-ff88-4f0e-8125-42d713ee62f7/iiif/cam-21-a_0007.tif/full/!300,500/0/default.jpg | T3: Livro impresso | U3: Português | W3: Os Lusíadas | X3: edição consagrada a comemorar o terceiro centenário do poeta... | Z3: 1.ª ed. | AA3: Lisboa : Of. de Castro Irmão | AB3: 1880 | AC3: 1880 | AD3: XCIII, 422 p., 1 il. | AE3: Camões, Luís de, 1524-1580 | AH3: Coelho, Adolfo, 1847-1919, Revisor ; Ortigão, Ramalho, 1836-1915, Autor da introdução, etc. ; Montoro, Reinaldo Carlos, 1831-?, Autor da introdução, etc. | AJ3: Gabinete Português de Leitura, Editor literário | AK3: L. 94571 V. | AL3: CAM500 | AM3: http://id.bnportugal.gov.pt/bib/catbnp/381074 | AN3: Livre
A4: 9993 | B4: 381465 | C4: 1 | D4: 644 | E4: https://purl.pt/43233 | F4: =HYPERLINK(E4) -> https://purl.pt/43233 | G4: 5 [site], 10 [site], 11 [site], 43, 46 [Vasco da Gama], 47, 100, 101, 160, 161, 163, 235, 237, 289, 291 [site Adamastor], 293, 343 [site apontamento livros e pena], 345, 347, 397, 443, 445, 495 [site Mercúrio, caduceu e navegador], 545 [site máquina do mundo], 547, 625, 627, 644 [monge com livro] [portadas, retrato de Camões, fotogravuras em cada Canto] | H4: 5, 10, 11, 43, 46 , 47, 101, 160, 161, 163, 235, 237, 291, 293, 343, 345, 347, 397, 443, 445, 495 , 545, 547, 627, 644 | J4: =HYPERLINK(P4) -> https://permalinkbnd.bnportugal.gov.pt/viewer/271573/?offset=#page=644&viewer=picture&o=info&n=0&q= | N4: https://purl.pt/43233 | O4: 271573 | P4: =CONCATENATE("https://permalinkbnd.bnportugal.gov.pt/viewer/",O4,"/?offset=#page=",D4,"&viewer=picture&o=info&n=0&q=") -> https://permalinkbnd.bnportugal.gov.pt/viewer/271573/?offset=#page=644&viewer=picture&o=info&n=0&q= | Q4: 381465 | R4: https://purl.pt/43233 | S4: https://bndigital.bnportugal.gov.pt//i/?IIIF=/1b/9b/a2/7b/1b9ba27b-8449-49d7-b8fa-ec3081a88a08/iiif/cam-30-a_0000_000005.tif/full/!300,500/0/default.jpg | T4: Livro impresso | U4: Português | W4: Os Lusíadas | X4: profusamente illustrada com desenhos allegoricos... | Z4: 1.ª ed. | AA4: Lisboa : Silvestre Castanheiro | AB4: 1898 | AC4: 1898 | AD4: XXXIII, 599 p. | AE4: Camões, Luís de, 1524-1580 | AH4: Belo, António Mendes, 1842-1929, Comentador (em meio audiovisual) ; Chagas, Pinheiro, 1842-1895, Comentador (em meio audiovisual) ; Costa, José Fernandes, 1848-1920, Comentador (em meio audiovisual) | AK4: L. 5864 A. | AL4: CAM500 | AM4: http://id.bnportugal.gov.pt/bib/catbnp/381465 | AN4: Livre
A5: 9994 | B5: 381468 | C5: 1 | D5: 8 | E5: https://purl.pt/43745 | F5: =HYPERLINK(E5) -> https://purl.pt/43745 | G5: 8 [site retrato de Camões] | H5: 8 | J5: =HYPERLINK(P5) -> https://permalinkbnd.bnportugal.gov.pt/viewer/274087/?offset=#page=8&viewer=picture&o=info&n=0&q= | N5: https://purl.pt/43745 | O5: 274087 | P5: =CONCATENATE("https://permalinkbnd.bnportugal.gov.pt/viewer/",O5,"/?offset=#page=",D5,"&viewer=picture&o=info&n=0&q=") -> https://permalinkbnd.bnportugal.gov.pt/viewer/274087/?offset=#page=8&viewer=picture&o=info&n=0&q= | Q5: 381468 | R5: https://purl.pt/43745 | S5: https://bndigital.bnportugal.gov.pt//i/?IIIF=/e0/20/89/c0/e02089c0-dfb3-4507-bf34-b897aa5b2b44/iiif/cam-33-a_0009.tif/full/!300,500/0/default.jpg | T5: Livro impresso | U5: Espanhol | V5: Português | W5: Os Lusiadas (Los Portugueses) | Z5: Edicion acompañada del legitimo texto portugues y de copiosas notas y noticias biograficas sobre el insigne poeta ibero | AA5: Badajoz : Establecimiento Tipográfico de José Santamaría | AB5: 1873 | AC5: 1873 | AD5: 263, 1 p. | AE5: Camões, Luís de, 1524-1580 | AH5: Soler y Arqués, Carlos, 1836-1896, Tradutor | AK5: CAM. 33 A. | AL5: CAM500 | AM5: http://id.bnportugal.gov.pt/bib/catbnp/381468 | AN5: Livre
A6: 9995 | B6: 381701 | C6: 1 | D6: 11 | E6: https://purl.pt/43724 | F6: =HYPERLINK(E6) -> https://purl.pt/43724 | G6: 11 | H6: 11 | J6: =HYPERLINK(P6) -> https://permalinkbnd.bnportugal.gov.pt/viewer/281141/?offset=#page=11&viewer=picture&o=info&n=0&q= | N6: https://purl.pt/43724 | O6: 281141 | P6: =CONCATENATE("https://permalinkbnd.bnportugal.gov.pt/viewer/",O6,"/?offset=#page=",D6,"&viewer=picture&o=info&n=0&q=") -> https://permalinkbnd.bnportugal.gov.pt/viewer/281141/?offset=#page=11&viewer=picture&o=info&n=0&q= | Q6: 381701 | R6: https://purl.pt/43724 | S6: https://bndigital.bnportugal.gov.pt//i/?IIIF=/58/a8/a6/57/58a8a657-7fb2-4700-9b55-408036c37806/iiif/cam-40-a_0001.tif/full/!300,500/0/default.jpg | T6: Livro impresso | U6: Poliglota | V6: Português | W6: Inês de Castro | X6: episódio extraído do canto terceiro do poema épico Os Lusíadas | Z6: 1.ª ed. | AA6: Lisboa : Imprensa Nacional | AB6: 1873 | AC6: 1873 | AD6: 76 p. | AE6: Camões, Luís de, 1524-1580 | AK6: CAM. 40 A. | AL6: CAM500 | AM6: http://id.bnportugal.gov.pt/bib/catbnp/381701 | AN6: Livre
A7: 9998 | B7: 381889 | C7: 1 | D7: 1 | E7: https://purl.pt/43659 | F7: =HYPERLINK(E7) -> https://purl.pt/43659 | G7: 1 [Inês de Castro, Vasco da Gama, Catarina de Ataíde e retrato de Camões] | H7: 1 | J7: =HYPERLINK(P7) -> https://permalinkbnd.bnportugal.gov.pt/viewer/273118/?offset=#page=1&viewer=picture&o=info&n=0&q= | N7: https://purl.pt/43659 | O7: 273118 | P7: =CONCATENATE("https://permalinkbnd.bnportugal.gov.pt/viewer/",O7,"/?offset=#page=",D7,"&viewer=picture&o=info&n=0&q=") -> https://permalinkbnd.bnportugal.gov.pt/viewer/273118/?offset=#page=1&viewer=picture&o=info&n=0&q= | Q7: 381889 | R7: https://purl.pt/43659 | S7: https://bndigital.bnportugal.gov.pt//i/?IIIF=/5b/91/40/8a/5b91408a-4af1-4a94-bccc-2d03ee894a1c/iiif/cam-44-2-a_0000_000001.tif/full/!300,500/0/default.jpg | T7: Periódico | U7: Português | W7: Pérolas de Camões | X7: publicação dedicada ao povo | Z7: 1.ª ed. | AA7: Lisboa : Lallement Fréres | AB7: 1880 | AC7: 1880 | AJ7: Lallement Frères, Editor comercial | AK7: CAM. 44//2 A. | AL7: CAM500 | AM7: http://id.bnportugal.gov.pt/bib/catbnp/381889 | AN7: Livre
A8: 9999 | B8: 381903 | C8: 1 | D8: 5 | E8: https://purl.pt/42920 | F8: =HYPERLINK(E8) -> https://purl.pt/42920 | G8: 5 [1.º] | H8: 5 | J8: =HYPERLINK(P8) -> https://permalinkbnd.bnportugal.gov.pt/viewer/270037/?offset=#page=5&viewer=picture&o=info&n=0&q= | N8: https://purl.pt/42920 | O8: 270037 | P8: =CONCATENATE("https://permalinkbnd.bnportugal.gov.pt/viewer/",O8,"/?offset=#page=",D8,"&viewer=picture&o=info&n=0&q=") -> https://permalinkbnd.bnportugal.gov.pt/viewer/270037/?offset=#page=5&viewer=picture&o=info&n=0&q= | Q8: 381903 | R8: https://purl.pt/42920 | S8: https://bndigital.bnportugal.gov.pt//i/?IIIF=/84/00/0c/50/84000c50-b90e-4a7c-aa5e-5cb3dfef4dab/iiif/cam-45-2-a_0000_000001.tif/full/!300,500/0/default.jpg | T8: Periódico | U8: Polaco | W8: Illustrowane Tygedniowe | Z8: 1.ª ed. | AB8: 1880 | AC8: 1880 | AK8: CAM. 45//2 A. | AL8: CAM500 | AM8: http://id.bnportugal.gov.pt/bib/catbnp/381903 | AN8: Livre
A9: 10000 | B9: 382749 | C9: 1 | D9: 7 | E9: https://purl.pt/42835 | F9: =HYPERLINK(E9) -> https://purl.pt/42835 | G9: 7 [site], 19, 23 [frisos site, esta obra contém mais apontamentos e frisos belíssimos] | J9: =HYPERLINK(P9) -> https://permalinkbnd.bnportugal.gov.pt/viewer/270109/?offset=#page=7&viewer=picture&o=info&n=0&q= | N9: https://purl.pt/42835 | O9: 270109 | P9: =CONCATENATE("https://permalinkbnd.bnportugal.gov.pt/viewer/",O9,"/?offset=#page=",D9,"&viewer=picture&o=info&n=0&q=") -> https://permalinkbnd.bnportugal.gov.pt/viewer/270109/?offset=#page=7&viewer=picture&o=info&n=0&q= | Q9: 382749 | R9: https://purl.pt/42835 | S9: https://bndigital.bnportugal.gov.pt//i/?IIIF=/60/58/22/4f/6058224f-9454-448f-8489-96a3a71253f5/iiif/cam-47-a_0000_000007.tif/full/!300,500/0/default.jpg | T9: Livro impresso | U9: Português | W9: Pretidão de amor | X9: endechas a Bárbara escrava seguidas da respectiva tradução em várias línguas... | Z9: 1.ª ed. | AA9: Lisboa : Imprensa Nacional | AB9: 1893 | AC9: 1893 | AD9: 2 v. | AE9: Camões, Luís de, 1524-1580 | AH9: Cunha, Xavier da, 1840-1920, Autor da introdução, etc. | AK9: CAM. 270 V. | AL9: CAM500 | AM9: http://id.bnportugal.gov.pt/bib/catbnp/382749 | AN9: Livre
A10: 10003 | B10: 382749 | C10: 1 | D10: 19 | E10: https://purl.pt/42835 | F10: =HYPERLINK(E10) -> https://purl.pt/42835 | J10: =HYPERLINK(P10) -> https://permalinkbnd.bnportugal.gov.pt/viewer/270109/?offset=#page=19&viewer=picture&o=info&n=0&q= | N10: https://purl.pt/42835 | O10: 270109 | P10: =CONCATENATE("https://permalinkbnd.bnportugal.gov.pt/viewer/",O10,"/?offset=#page=",D10,"&viewer=picture&o=info&n=0&q=") -> https://permalinkbnd.bnportugal.gov.pt/viewer/270109/?offset=#page=19&viewer=picture&o=info&n=0&q= | Q10: 382749 | R10: https://purl.pt/42835 | S10: https://bndigital.bnportugal.gov.pt//i/?IIIF=/60/58/22/4f/6058224f-9454-448f-8489-96a3a71253f5/iiif/cam-47-a_0000_000007.tif/full/!300,500/0/default.jpg | T10: Livro impresso | U10: Português | W10: Pretidão de amor | X10: endechas a Bárbara escrava seguidas da respectiva tradução em várias línguas... | Z10: 1.ª ed. | AA10: Lisboa : Imprensa Nacional | AB10: 1893 | AC10: 1893 | AD10: 2 v. | AE10: Camões, Luís de, 1524-1580 | AH10: Cunha, Xavier da, 1840-1920, Autor da introdução, etc. | AK10: CAM. 270 V. | AL10: CAM500 | AM10: http://id.bnportugal.gov.pt/bib/catbnp/382749 | AN10: Livre
B11: 382749 | C11: 1 | D11: 23 | E11: https://purl.pt/42835 | F11: =HYPERLINK(E11) -> https://purl.pt/42835 | J11: =HYPERLINK(P11) -> https://permalinkbnd.bnportugal.gov.pt/viewer/270109/?offset=#page=23&viewer=picture&o=info&n=0&q= | N11: https://purl.pt/42835 | O11: 270109 | P11: =CONCATENATE("https://permalinkbnd.bnportugal.gov.pt/viewer/",O11,"/?offset=#page=",D11,"&viewer=picture&o=info&n=0&q=") -> https://permalinkbnd.bnportugal.gov.pt/viewer/270109/?offset=#page=23&viewer=picture&o=info&n=0&q= | Q11: 382749 | R11: https://purl.pt/42835 | S11: https://bndigital.bnportugal.gov.pt//i/?IIIF=/60/58/22/4f/6058224f-9454-448f-8489-96a3a71253f5/iiif/cam-47-a_0000_000007.tif/full/!300,500/0/default.jpg | T11: Livro impresso | U11: Português | W11: Pretidão de amor | X11: endechas a Bárbara escrava seguidas da respectiva tradução em várias línguas... | Z11: 1.ª ed. | AA11: Lisboa : Imprensa Nacional | AB11: 1893 | AC11: 1893 | AD11: 2 v. | AE11: Camões, Luís de, 1524-1580 | AH11: Cunha, Xavier da, 1840-1920, Autor da introdução, etc. | AK11: CAM. 270 V. | AL11: CAM500 | AM11: http://id.bnportugal.gov.pt/bib/catbnp/382749 | AN11: Livre
B12: 382834 | C12: 1 | D12: 11 | E12: https://purl.pt/43815 | F12: =HYPERLINK(E12) -> https://purl.pt/43815 | G12: 11 [caravela com Vasco da Gama] | H12: 11 | J12: =HYPERLINK(P12) -> https://permalinkbnd.bnportugal.gov.pt/viewer/273316/?offset=#page=11&viewer=picture&o=info&n=0&q= | N12: https://purl.pt/43815 | O12: 273316 | P12: =CONCATENATE("https://permalinkbnd.bnportugal.gov.pt/viewer/",O12,"/?offset=#page=",D12,"&viewer=picture&o=info&n=0&q=") -> https://permalinkbnd.bnportugal.gov.pt/viewer/273316/?offset=#page=11&viewer=picture&o=info&n=0&q= | Q12: 382834 | R12: https://purl.pt/43815 | S12: https://bndigital.bnportugal.gov.pt//i/?IIIF=/b6/d0/71/c6/b6d071c6-e05d-4c17-96b2-07a62e35fb7f/iiif/cam-82-1-v_0000_000005.tif/full/!300,500/0/default.jpg | T12: Livro impresso | U12: Português | W12: Comemoração gloriosa da morte de Luiz de Camões 10 de Junho de 1889 | Z12: 1.ª ed. | AA12: Evora : Minerva Eborense de J. José Baptista, Rua d'Aviz | AB12: 1889 | AC12: 1889 | AD12: 12, 4 p. | AE12: Barata, António Francisco, 1836-1910 | AH12: Camões, Luís de, 1524-1580, Antecedente bibliográfico | AK12: CAM. 309//13 V. | AL12: CAM500 | AM12: http://id.bnportugal.gov.pt/bib/catbnp/382834 | AN12: Livre
A13: 10004 | B13: 382844 | C13: 1 | D13: 3 | E13: https://purl.pt/43227 | F13: =HYPERLINK(E13) -> https://purl.pt/43227 | G13: 3 | J13: =HYPERLINK(P13) -> https://permalinkbnd.bnportugal.gov.pt/viewer/271559/?offset=#page=3&viewer=picture&o=info&n=0&q= | N13: https://purl.pt/43227 | O13: 271559 | P13: =CONCATENATE("https://permalinkbnd.bnportugal.gov.pt/viewer/",O13,"/?offset=#page=",D13,"&viewer=picture&o=info&n=0&q=") -> https://permalinkbnd.bnportugal.gov.pt/viewer/271559/?offset=#page=3&viewer=picture&o=info&n=0&q= | Q13: 382844 | R13: https://purl.pt/43227 | S13: https://bndigital.bnportugal.gov.pt//i/?IIIF=/be/12/df/5e/be12df5e-248d-4e0b-823f-bb93ea5db616/iiif/cam-2058-v_0001.tif/full/!300,500/0/default.jpg | T13: Livro impresso | U13: Português | W13: A Luiz de Camões | X13: com notas curiosas e tres ineditos do poeta | Z13: 1.ª ed. | AA13: Evora : Tip. Minerva, de A.F. Barata | AB13: 1880 | AC13: 1880 | AD13: 24 p. | AE13: Barata, António Francisco, 1836-1910 | AH13: Camões, Luís de, 1524-1580, Antecedente bibliográfico | AK13: L. 599//32 A. | AL13: CAM500 | AM13: http://id.bnportugal.gov.pt/bib/catbnp/382844 | AN13: Livre
