Workbook

Sheet Folha1
A1: pasta | B1: volume | C1: imagem | D1: purl-hiperligação | E1: purl 2 | F1: n bnd | G1: l1 | H1: l2 | I1: l3 | J1: l4 | K1: imagens_texto | L1: Notas - Isabel Almeida | M1: link página | N1: l5 | O1: l6 | P1: link imagem | Q1: nada | R1: url_página | S1: nada 2 | T1: imagens | U1: notas Regina | V1: notas Regina 2 | W1: tem JPG
A2: 367428 | B2: 1 | C2: 1 | D2: https://purl.pt/43428 | E2: https://purl.pt/43428 | F2: 272369 | G2: https://permalinkbnd.bnportugal.gov.pt/viewer/ | H2: /?offset=#page= | I2: &viewer=picture&o=info&n=0&q= | J2: =CONCATENATE(G2,F2,H2,C2,I2) -> https://permalinkbnd.bnportugal.gov.pt/viewer/272369/?offset=#page=1&viewer=picture&o=info&n=0&q= | K2: 1 | L2: =VLOOKUP(A2,Folha2!$A$2:$B$2019,2,FALSE) -> I Lusiadi. Antonio Nervi, 1882. Trad. Paratextos vida. Trad. Paratextos notas (de rodapé em cada Canto). Trad. Paratextos argumentos. | M2: =HYPERLINK(J2) -> https://permalinkbnd.bnportugal.gov.pt/viewer/272369/?offset=#page=1&viewer=picture&o=info&n=0&q= | N2: C:\Users\mbaptista\OneDrive - Biblioteca Nacional de Portugal\Documentos\python\camoniana\imagens\capas\ | O2: =CONCATENATE(N2,A2,"\",B2,"\",C2,".jpg") -> C:\Users\mbaptista\OneDrive - Biblioteca Nacional de Portugal\Documentos\python\camoniana\imagens\capas\367428\1\1.jpg | P2: =HYPERLINK(O2) -> C:\Users\mbaptista\OneDrive - Biblioteca Nacional de Portugal\Documentos\python\camoniana\imagens\capas\367428\1\1.jpg | R2: https://permalinkbnd.bnportugal.gov.pt/viewer/272369/?offset=#page=1&viewer=picture&o=info&n=0&q= | T2: 1 | W2: Sim
A3: 381074 | B3: 1 | C3: 10 | D3: https://purl.pt/43747 | E3: https://purl.pt/43747 | F3: 274089 | G3: https://permalinkbnd.bnportugal.gov.pt/viewer/ | H3: /?offset=#page= | I3: &viewer=picture&o=info&n=0&q= | J3: =CONCATENATE(G3,F3,H3,C3,I3) -> https://permalinkbnd.bnportugal.gov.pt/viewer/274089/?offset=#page=10&viewer=picture&o=info&n=0&q= | K3: 10 [site], 11, 103 [site pelicano direita], 107, 142, 107, 142, 145, 185, 235, 270 [site assassinato de Inês], 273, 306, 309 [site ninfas], 342, 345, 374, 377, 410, 413, 447, 499, 526 [site apontamento] [pintura de Camões por Columbano, portada, fac-símile do frontispício da 1.ª Ed. de Os Lusíadas, ilustrações da obra] | L3: =VLOOKUP(A3,Folha2!$A$2:$B$2019,2,FALSE) -> Os Lusíadas, Rio de Janeiro, 1880, sem argumentos. | M3: =HYPERLINK(J3) -> https://permalinkbnd.bnportugal.gov.pt/viewer/274089/?offset=#page=10&viewer=picture&o=info&n=0&q= | N3: C:\Users\mbaptista\OneDrive - Biblioteca Nacional de Portugal\Documentos\python\camoniana\imagens\capas\ | O3: =CONCATENATE(N3,A3,"\",B3,"\",C3,".jpg") -> C:\Users\mbaptista\OneDrive - Biblioteca Nacional de Portugal\Documentos\python\camoniana\imagens\capas\381074\1\10.jpg | P3: =HYPERLINK(O3) -> C:\Users\mbaptista\OneDrive - Biblioteca Nacional de Portugal\Documentos\python\camoniana\imagens\capas\381074\1\10.jpg | T3: 10, 11, 103, 145, 235, 270, 273, 306, 309, 342, 345, 374, 377, 410, 413, 447, 499
A4: 381074 | B4: 1 | C4: 11 | D4: https://purl.pt/43747 | E4: https://purl.pt/43747 | F4: 274089 | G4: https://permalinkbnd.bnportugal.gov.pt/viewer/ | H4: /?offset=#page= | I4: &viewer=picture&o=info&n=0&q= | J4: =CONCATENATE(G4,F4,H4,C4,I4) -> https://permalinkbnd.bnportugal.gov.pt/viewer/274089/?offset=#page=11&viewer=picture&o=info&n=0&q= | K4: 10 [site], 11, 103 [site pelicano direita], 107, 142, 107, 142, 145, 185, 235, 270 [site assassinato de Inês], 273, 306, 309 [site ninfas], 342, 345, 374, 377, 410, 413, 447, 499, 526 [site apontamento] [pintura de Camões por Columbano, portada, fac-símile do frontispício da 1.ª Ed. de Os Lusíadas, ilustrações da obra] | L4: =VLOOKUP(A4,Folha2!$A$2:$B$2019,2,FALSE) -> Os Lusíadas, Rio de Janeiro, 1880, sem argumentos. | M4: =HYPERLINK(J4) -> https://permalinkbnd.bnportugal.gov.pt/viewer/274089/?offset=#page=11&viewer=picture&o=info&n=0&q= | N4: C:\Users\mbaptista\OneDrive - Biblioteca Nacional de Portugal\Documentos\python\camoniana\imagens\capas\ | O4: =CONCATENATE(N4,A4,"\",B4,"\",C4,".jpg") -> C:\Users\mbaptista\OneDrive - Biblioteca Nacional de Portugal\Documentos\python\camoniana\imagens\capas\381074\1\11.jpg | P4: =HYPERLINK(O4) -> C:\Users\mbaptista\OneDrive - Biblioteca Nacional de Portugal\Documentos\python\camoniana\imagens\capas\381074\1\11.jpg | T4: 10, 11, 103, 145, 235, 270, 273, 306, 309, 342, 345, 374, 377, 410, 413, 447, 499
A5: 381074 | B5: 1 | C5: 103 | D5: https://purl.pt/43747 | E5: https://purl.pt/43747 | F5: 274089 | G5: https://permalinkbnd.bnportugal.gov.pt/viewer/ | H5: /?offset=#page= | I5: &viewer=picture&o=info&n=0&q= | J5: =CONCATENATE(G5,F5,H5,C5,I5) -> https://permalinkbnd.bnportugal.gov.pt/viewer/274089/?offset=#page=103&viewer=picture&o=info&n=0&q= | K5: 10 [site], 11, 103 [site pelicano direita], 107, 142, 107, 142, 145, 185, 235, 270 [site assassinato de Inês], 273, 306, 309 [site ninfas], 342, 345, 374, 377, 410, 413, 447, 499, 526 [site apontamento] [pintura de Camões por Columbano, portada, fac-símile do frontispício da 1.ª Ed. de Os Lusíadas, ilustrações da obra] | L5: =VLOOKUP(A5,Folha2!$A$2:$B$2019,2,FALSE) -> Os Lusíadas, Rio de Janeiro, 1880, sem argumentos. | M5: =HYPERLINK(J5) -> https://permalinkbnd.bnportugal.gov.pt/viewer/274089/?offset=#page=103&viewer=picture&o=info&n=0&q= | N5: C:\Users\mbaptista\OneDrive - Biblioteca Nacional de Portugal\Documentos\python\camoniana\imagens\capas\ | O5: =CONCATENATE(N5,A5,"\",B5,"\",C5,".jpg") -> C:\Users\mbaptista\OneDrive - Biblioteca Nacional de Portugal\Documentos\python\camoniana\imagens\capas\381074\1\103.jpg | P5: =HYPERLINK(O5) -> C:\Users\mbaptista\OneDrive - Biblioteca Nacional de Portugal\Documentos\python\camoniana\imagens\capas\381074\1\103.jpg | T5: 10, 11, 103, 145, 235, 270, 273, 306, 309, 342, 345, 374, 377, 410, 413, 447, 499
A6: 381074 | B6: 1 | C6: 107 | D6: https://purl.pt/43747 | E6: https://purl.pt/43747 | F6: 274089 | G6: https://permalinkbnd.bnportugal.gov.pt/viewer/ | H6: /?offset=#page= | I6: &viewer=picture&o=info&n=0&q= | J6: =CONCATENATE(G6,F6,H6,C6,I6) -> https://permalinkbnd.bnportugal.gov.pt/viewer/274089/?offset=#page=107&viewer=picture&o=info&n=0&q= | K6: 10 [site], 11, 103 [site pelicano direita], 107, 142, 107, 142, 145, 185, 235, 270 [site assassinato de Inês], 273, 306, 309 [site ninfas], 342, 345, 374, 377, 410, 413, 447, 499, 526 [site apontamento] [pintura de Camões por Columbano, portada, fac-símile do frontispício da 1.ª Ed. de Os Lusíadas, ilustrações da obra] | L6: =VLOOKUP(A6,Folha2!$A$2:$B$2019,2,FALSE) -> Os Lusíadas, Rio de Janeiro, 1880, sem argumentos. | M6: =HYPERLINK(J6) -> https://permalinkbnd.bnportugal.gov.pt/viewer/274089/?offset=#page=107&viewer=picture&o=info&n=0&q= | N6: C:\Users\mbaptista\OneDrive - Biblioteca Nacional de Portugal\Documentos\python\camoniana\imagens\capas\ | O6: =CONCATENATE(N6,A6,"\",B6,"\",C6,".jpg") -> C:\Users\mbaptista\OneDrive - Biblioteca Nacional de Portugal\Documentos\python\camoniana\imagens\capas\381074\1\107.jpg | P6: =HYPERLINK(O6) -> C:\Users\mbaptista\OneDrive - Biblioteca Nacional de Portugal\Documentos\python\camoniana\imagens\capas\381074\1\107.jpg | T6: 10, 11, 103, 145, 235, 270, 273, 306, 309, 342, 345, 374, 377, 410, 413, 447, 499
A7: 381074 | B7: 1 | C7: 142 | D7: https://purl.pt/43747 | E7: https://purl.pt/43747 | F7: 274089 | G7: https://permalinkbnd.bnportugal.gov.pt/viewer/ | H7: /?offset=#page= | I7: &viewer=picture&o=info&n=0&q= | J7: =CONCATENATE(G7,F7,H7,C7,I7) -> https://permalinkbnd.bnportugal.gov.pt/viewer/274089/?offset=#page=142&viewer=picture&o=info&n=0&q= | K7: 10 [site], 11, 103 [site pelicano direita], 107, 142, 107, 142, 145, 185, 235, 270 [site assassinato de Inês], 273, 306, 309 [site ninfas], 342, 345, 374, 377, 410, 413, 447, 499, 526 [site apontamento] [pintura de Camões por Columbano, portada, fac-símile do frontispício da 1.ª Ed. de Os Lusíadas, ilustrações da obra] | L7: =VLOOKUP(A7,Folha2!$A$2:$B$2019,2,FALSE) -> Os Lusíadas, Rio de Janeiro, 1880, sem argumentos. | M7: =HYPERLINK(J7) -> https://permalinkbnd.bnportugal.gov.pt/viewer/274089/?offset=#page=142&viewer=picture&o=info&n=0&q= | N7: C:\Users\mbaptista\OneDrive - Biblioteca Nacional de Portugal\Documentos\python\camoniana\imagens\capas\ | O7: =CONCATENATE(N7,A7,"\",B7,"\",C7,".jpg") -> C:\Users\mbaptista\OneDrive - Biblioteca Nacional de Portugal\Documentos\python\camoniana\imagens\capas\381074\1\142.jpg | P7: =HYPERLINK(O7) -> C:\Users\mbaptista\OneDrive - Biblioteca Nacional de Portugal\Documentos\python\camoniana\imagens\capas\381074\1\142.jpg | T7: 10, 11, 103, 145, 235, 270, 273, 306, 309, 342, 345, 374, 377, 410, 413, 447, 499
A8: 381074 | B8: 1 | C8: 107 | D8: https://purl.pt/43747 | E8: https://purl.pt/43747 | F8: 274089 | G8: https://permalinkbnd.bnportugal.gov.pt/viewer/ | H8: /?offset=#page= | I8: &viewer=picture&o=info&n=0&q= | J8: =CONCATENATE(G8,F8,H8,C8,I8) -> https://permalinkbnd.bnportugal.gov.pt/viewer/274089/?offset=#page=107&viewer=picture&o=info&n=0&q= | K8: 10 [site], 11, 103 [site pelicano direita], 107, 142, 107, 142, 145, 185, 235, 270 [site assassinato de Inês], 273, 306, 309 [site ninfas], 342, 345, 374, 377, 410, 413, 447, 499, 526 [site apontamento] [pintura de Camões por Columbano, portada, fac-símile do frontispício da 1.ª Ed. de Os Lusíadas, ilustrações da obra] | L8: =VLOOKUP(A8,Folha2!$A$2:$B$2019,2,FALSE) -> Os Lusíadas, Rio de Janeiro, 1880, sem argumentos. | M8: =HYPERLINK(J8) -> https://permalinkbnd.bnportugal.gov.pt/viewer/274089/?offset=#page=107&viewer=picture&o=info&n=0&q= | N8: C:\Users\mbaptista\OneDrive - Biblioteca Nacional de Portugal\Documentos\python\camoniana\imagens\capas\ | O8: =CONCATENATE(N8,A8,"\",B8,"\",C8,".jpg") -> C:\Users\mbaptista\OneDrive - Biblioteca Nacional de Portugal\Documentos\python\camoniana\imagens\capas\381074\1\107.jpg | P8: =HYPERLINK(O8) -> C:\Users\mbaptista\OneDrive - Biblioteca Nacional de Portugal\Documentos\python\camoniana\imagens\capas\381074\1\107.jpg | T8: 10, 11, 103, 145, 235, 270, 273, 306, 309, 342, 345, 374, 377, 410, 413, 447, 499
A9: 381074 | B9: 1 | C9: 142 | D9: https://purl.pt/43747 | E9: https://purl.pt/43747 | F9: 274089 | G9: https://permalinkbnd.bnportugal.gov.pt/viewer/ | H9: /?offset=#page= | I9: &viewer=picture&o=info&n=0&q= | J9: =CONCATENATE(G9,F9,H9,C9,I9) -> https://permalinkbnd.bnportugal.gov.pt/viewer/274089/?offset=#page=142&viewer=picture&o=info&n=0&q= | K9: 10 [site], 11, 103 [site pelicano direita], 107, 142, 107, 142, 145, 185, 235, 270 [site assassinato de Inês], 273, 306, 309 [site ninfas], 342, 345, 374, 377, 410, 413, 447, 499, 526 [site apontamento] [pintura de Camões por Columbano, portada, fac-símile do frontispício da 1.ª Ed. de Os Lusíadas, ilustrações da obra] | L9: =VLOOKUP(A9,Folha2!$A$2:$B$2019,2,FALSE) -> Os Lusíadas, Rio de Janeiro, 1880, sem argumentos. | M9: =HYPERLINK(J9) -> https://permalinkbnd.bnportugal.gov.pt/viewer/274089/?offset=#page=142&viewer=picture&o=info&n=0&q= | N9: C:\Users\mbaptista\OneDrive - Biblioteca Nacional de Portugal\Documentos\python\camoniana\imagens\capas\ | O9: =CONCATENATE(N9,A9,"\",B9,"\",C9,".jpg") -> C:\Users\mbaptista\OneDrive - Biblioteca Nacional de Portugal\Documentos\python\camoniana\imagens\capas\381074\1\142.jpg | P9: =HYPERLINK(O9) -> C:\Users\mbaptista\OneDrive - Biblioteca Nacional de Portugal\Documentos\python\camoniana\imagens\capas\381074\1\142.jpg | T9: 10, 11, 103, 145, 235, 270, 273, 306, 309, 342, 345, 374, 377, 410, 413, 447, 499
A10: 381074 | B10: 1 | C10: 145 | D10: https://purl.pt/43747 | E10: https://purl.pt/43747 | F10: 274089 | G10: https://permalinkbnd.bnportugal.gov.pt/viewer/ | H10: /?offset=#page= | I10: &viewer=picture&o=info&n=0&q= | J10: =CONCATENATE(G10,F10,H10,C10,I10) -> https://permalinkbnd.bnportugal.gov.pt/viewer/274089/?offset=#page=145&viewer=picture&o=info&n=0&q= | K10: 10 [site], 11, 103 [site pelicano direita], 107, 142, 107, 142, 145, 185, 235, 270 [site assassinato de Inês], 273, 306, 309 [site ninfas], 342, 345, 374, 377, 410, 413, 447, 499, 526 [site apontamento] [pintura de Camões por Columbano, portada, fac-símile do frontispício da 1.ª Ed. de Os Lusíadas, ilustrações da obra] | L10: =VLOOKUP(A10,Folha2!$A$2:$B$2019,2,FALSE) -> Os Lusíadas, Rio de Janeiro, 1880, sem argumentos. | M10: =HYPERLINK(J10) -> https://permalinkbnd.bnportugal.gov.pt/viewer/274089/?offset=#page=145&viewer=picture&o=info&n=0&q= | N10: C:\Users\mbaptista\OneDrive - Biblioteca Nacional de Portugal\Documentos\python\camoniana\imagens\capas\ | O10: =CONCATENATE(N10,A10,"\",B10,"\",C10,".jpg") -> C:\Users\mbaptista\OneDrive - Biblioteca Nacional de Portugal\Documentos\python\camoniana\imagens\capas\381074\1\145.jpg | P10: =HYPERLINK(O10) -> C:\Users\mbaptista\OneDrive - Biblioteca Nacional de Portugal\Documentos\python\camoniana\imagens\capas\381074\1\145.jpg | T10: 10, 11, 103, 145, 235, 270, 273, 306, 309, 342, 345, 374, 377, 410, 413, 447, 499
A11: 381074 | B11: 1 | C11: 185 | D11: https://purl.pt/43747 | E11: https://purl.pt/43747 | F11: 274089 | G11: https://permalinkbnd.bnportugal.gov.pt/viewer/ | H11: /?offset=#page= | I11: &viewer=picture&o=info&n=0&q= | J11: =CONCATENATE(G11,F11,H11,C11,I11) -> https://permalinkbnd.bnportugal.gov.pt/viewer/274089/?offset=#page=185&viewer=picture&o=info&n=0&q= | K11: 10 [site], 11, 103 [site pelicano direita], 107, 142, 107, 142, 145, 185, 235, 270 [site assassinato de Inês], 273, 306, 309 [site ninfas], 342, 345, 374, 377, 410, 413, 447, 499, 526 [site apontamento] [pintura de Camões por Columbano, portada, fac-símile do frontispício da 1.ª Ed. de Os Lusíadas, ilustrações da obra] | L11: =VLOOKUP(A11,Folha2!$A$2:$B$2019,2,FALSE) -> Os Lusíadas, Rio de Janeiro, 1880, sem argumentos. | M11: =HYPERLINK(J11) -> https://permalinkbnd.bnportugal.gov.pt/viewer/274089/?offset=#page=185&viewer=picture&o=info&n=0&q= | N11: C:\Users\mbaptista\OneDrive - Biblioteca Nacional de Portugal\Documentos\python\camoniana\imagens\capas\ | O11: =CONCATENATE(N11,A11,"\",B11,"\",C11,".jpg") -> C:\Users\mbaptista\OneDrive - Biblioteca Nacional de Portugal\Documentos\python\camoniana\imagens\capas\381074\1\185.jpg | P11: =HYPERLINK(O11) -> C:\Users\mbaptista\OneDrive - Biblioteca Nacional de Portugal\Documentos\python\camoniana\imagens\capas\381074\1\185.jpg | T11: 10, 11, 103, 145, 235, 270, 273, 306, 309, 342, 345, 374, 377, 410, 413, 447, 499
A12: 381074 | B12: 1 | C12: 235 | D12: https://purl.pt/43747 | E12: https://purl.pt/43747 | F12: 274089 | G12: https://permalinkbnd.bnportugal.gov.pt/viewer/ | H12: /?offset=#page= | I12: &viewer=picture&o=info&n=0&q= | J12: =CONCATENATE(G12,F12,H12,C12,I12) -> https://permalinkbnd.bnportugal.gov.pt/viewer/274089/?offset=#page=235&viewer=picture&o=info&n=0&q= | K12: 10 [site], 11, 103 [site pelicano direita], 107, 142, 107, 142, 145, 185, 235, 270 [site assassinato de Inês], 273, 306, 309 [site ninfas], 342, 345, 374, 377, 410, 413, 447, 499, 526 [site apontamento] [pintura de Camões por Columbano, portada, fac-símile do frontispício da 1.ª Ed. de Os Lusíadas, ilustrações da obra] | L12: =VLOOKUP(A12,Folha2!$A$2:$B$2019,2,FALSE) -> Os Lusíadas, Rio de Janeiro, 1880, sem argumentos. | M12: =HYPERLINK(J12) -> https://permalinkbnd.bnportugal.gov.pt/viewer/274089/?offset=#page=235&viewer=picture&o=info&n=0&q= | N12: C:\Users\mbaptista\OneDrive - Biblioteca Nacional de Portugal\Documentos\python\camoniana\imagens\capas\ | O12: =CONCATENATE(N12,A12,"\",B12,"\",C12,".jpg") -> C:\Users\mbaptista\OneDrive - Biblioteca Nacional de Portugal\Documentos\python\camoniana\imagens\capas\381074\1\235.jpg | P12: =HYPERLINK(O12) -> C:\Users\mbaptista\OneDrive - Biblioteca Nacional de Portugal\Documentos\python\camoniana\imagens\capas\381074\1\235.jpg | T12: 10, 11, 103, 145, 235, 270, 273, 306, 309, 342, 345, 374, 377, 410, 413, 447, 499
A13: 381074 | B13: 1 | C13: 270 | D13: https://purl.pt/43747 | E13: https://purl.pt/43747 | F13: 274089 | G13: https://permalinkbnd.bnportugal.gov.pt/viewer/ | H13: /?offset=#page= | I13: &viewer=picture&o=info&n=0&q= | J13: =CONCATENATE(G13,F13,H13,C13,I13) -> https://permalinkbnd.bnportugal.gov.pt/viewer/274089/?offset=#page=270&viewer=picture&o=info&n=0&q= | K13: 10 [site], 11, 103 [site pelicano direita], 107, 142, 107, 142, 145, 185, 235, 270 [site assassinato de Inês], 273, 306, 309 [site ninfas], 342, 345, 374, 377, 410, 413, 447, 499, 526 [site apontamento] [pintura de Camões por Columbano, portada, fac-símile do frontispício da 1.ª Ed. de Os Lusíadas, ilustrações da obra] | L13: =VLOOKUP(A13,Folha2!$A$2:$B$2019,2,FALSE) -> Os Lusíadas, Rio de Janeiro, 1880, sem argumentos. | M13: =HYPERLINK(J13) -> https://permalinkbnd.bnportugal.gov.pt/viewer/274089/?offset=#page=270&viewer=picture&o=info&n=0&q= | N13: C:\Users\mbaptista\OneDrive - Biblioteca Nacional de Portugal\Documentos\python\camoniana\imagens\capas\ | O13: =CONCATENATE(N13,A13,"\",B13,"\",C13,".jpg") -> C:\Users\mbaptista\OneDrive - Biblioteca Nacional de Portugal\Documentos\python\camoniana\imagens\capas\381074\1\270.jpg | P13: =HYPERLINK(O13) -> C:\Users\mbaptista\OneDrive - Biblioteca Nacional de Portugal\Documentos\python\camoniana\imagens\capas\381074\1\270.jpg | T13: 10, 11, 103, 145, 235, 270, 273, 306, 309, 342, 345, 374, 377, 410, 413, 447, 499
A14: 381074 | B14: 1 | C14: 273 | D14: https://purl.pt/43747 | E14: https://purl.pt/43747 | F14: 274089 | G14: https://permalinkbnd.bnportugal.gov.pt/viewer/ | H14: /?offset=#page= | I14: &viewer=picture&o=info&n=0&q= | J14: =CONCATENATE(G14,F14,H14,C14,I14) -> https://permalinkbnd.bnportugal.gov.pt/viewer/274089/?offset=#page=273&viewer=picture&o=info&n=0&q= | K14: 10 [site], 11, 103 [site pelicano direita], 107, 142, 107, 142, 145, 185, 235, 270 [site assassinato de Inês], 273, 306, 309 [site ninfas], 342, 345, 374, 377, 410, 413, 447, 499, 526 [site apontamento] [pintura de Camões por Columbano, portada, fac-símile do frontispício da 1.ª Ed. de Os Lusíadas, ilustrações da obra] | L14: =VLOOKUP(A14,Folha2!$A$2:$B$2019,2,FALSE) -> Os Lusíadas, Rio de Janeiro, 1880, sem argumentos. | M14: =HYPERLINK(J14) -> https://permalinkbnd.bnportugal.gov.pt/viewer/274089/?offset=#page=273&viewer=picture&o=info&n=0&q= | N14: C:\Users\mbaptista\OneDrive - Biblioteca Nacional de Portugal\Documentos\python\camoniana\imagens\capas\ | O14: =CONCATENATE(N14,A14,"\",B14,"\",C14,".jpg") -> C:\Users\mbaptista\OneDrive - Biblioteca Nacional de Portugal\Documentos\python\camoniana\imagens\capas\381074\1\273.jpg | P14: =HYPERLINK(O14) -> C:\Users\mbaptista\OneDrive - Biblioteca Nacional de Portugal\Documentos\python\camoniana\imagens\capas\381074\1\273.jpg | T14: 10, 11, 103, 145, 235, 270, 273, 306, 309, 342, 345, 374, 377, 410, 413, 447, 499
... A23: 381074 | B23: 1 | C23: 447 | D23: https://purl.pt/43747 | E23: https://purl.pt/43747 | F23: 274089 | G23: https://permalinkbnd.bnportugal.gov.pt/viewer/ | H23: /?offset=#page= | I23: &viewer=picture&o=info&n=0&q= | J23: =CONCATENATE(G23,F23,H23,C23,I23) -> https://permalinkbnd.bnportugal.gov.pt/viewer/274089/?offset=#page=447&viewer=picture&o=info&n=0&q= | K23: 10 [site], 11, 103 [site pelicano direita], 107, 142, 107, 142, 145, 185, 235, 270 [site assassinato de Inês], 273, 306, 309 [site ninfas], 342, 345, 374, 377, 410, 413, 447, 499, 526 [site apontamento] [pintura de Camões por Columbano, portada, fac-símile do frontispício da 1.ª Ed. de Os Lusíadas, ilustrações da obra] | L23: =VLOOKUP(A23,Folha2!$A$2:$B$2019,2,FALSE) -> Os Lusíadas, Rio de Janeiro, 1880, sem argumentos. | M23: =HYPERLINK(J23) -> https://permalinkbnd.bnportugal.gov.pt/viewer/274089/?offset=#page=447&viewer=picture&o=info&n=0&q= | N23: C:\Users\mbaptista\OneDrive - Biblioteca Nacional de Portugal\Documentos\python\camoniana\imagens\capas\ | O23: =CONCATENATE(N23,A23,"\",B23,"\",C23,".jpg") -> C:\Users\mbaptista\OneDrive - Biblioteca Nacional de Portugal\Documentos\python\camoniana\imagens\capas\381074\1\447.jpg | P23: =HYPERLINK(O23) -> C:\Users\mbaptista\OneDrive - Biblioteca Nacional de Portugal\Documentos\python\camoniana\imagens\capas\381074\1\447.jpg | T23: 10, 11, 103, 145, 235, 270, 273, 306, 309, 342, 345, 374, 377, 410, 413, 447, 499
A24: 381074 | B24: 1 | C24: 499 | D24: https://purl.pt/43747 | E24: https://purl.pt/43747 | F24: 274089 | G24: https://permalinkbnd.bnportugal.gov.pt/viewer/ | H24: /?offset=#page= | I24: &viewer=picture&o=info&n=0&q= | J24: =CONCATENATE(G24,F24,H24,C24,I24) -> https://permalinkbnd.bnportugal.gov.pt/viewer/274089/?offset=#page=499&viewer=picture&o=info&n=0&q= | K24: 10 [site], 11, 103 [site pelicano direita], 107, 142, 107, 142, 145, 185, 235, 270 [site assassinato de Inês], 273, 306, 309 [site ninfas], 342, 345, 374, 377, 410, 413, 447, 499, 526 [site apontamento] [pintura de Camões por Columbano, portada, fac-símile do frontispício da 1.ª Ed. de Os Lusíadas, ilustrações da obra] | L24: =VLOOKUP(A24,Folha2!$A$2:$B$2019,2,FALSE) -> Os Lusíadas, Rio de Janeiro, 1880, sem argumentos. | M24: =HYPERLINK(J24) -> https://permalinkbnd.bnportugal.gov.pt/viewer/274089/?offset=#page=499&viewer=picture&o=info&n=0&q= | N24: C:\Users\mbaptista\OneDrive - Biblioteca Nacional de Portugal\Documentos\python\camoniana\imagens\capas\ | O24: =CONCATENATE(N24,A24,"\",B24,"\",C24,".jpg") -> C:\Users\mbaptista\OneDrive - Biblioteca Nacional de Portugal\Documentos\python\camoniana\imagens\capas\381074\1\499.jpg | P24: =HYPERLINK(O24) -> C:\Users\mbaptista\OneDrive - Biblioteca Nacional de Portugal\Documentos\python\camoniana\imagens\capas\381074\1\499.jpg | R24: https://permalinkbnd.bnportugal.gov.pt/viewer/274089/?offset=#page=499&viewer=picture&o=info&n=0&q= | T24: 10, 11, 103, 145, 235, 270, 273, 306, 309, 342, 345, 374, 377, 410, 413, 447, 499 | W24: Sim
A25: 381074 | B25: 1 | C25: 526 | D25: https://purl.pt/43747 | E25: https://purl.pt/43747 | F25: 274089 | G25: https://permalinkbnd.bnportugal.gov.pt/viewer/ | H25: /?offset=#page= | I25: &viewer=picture&o=info&n=0&q= | J25: =CONCATENATE(G25,F25,H25,C25,I25) -> https://permalinkbnd.bnportugal.gov.pt/viewer/274089/?offset=#page=526&viewer=picture&o=info&n=0&q= | K25: 10 [site], 11, 103 [site pelicano direita], 107, 142, 107, 142, 145, 185, 235, 270 [site assassinato de Inês], 273, 306, 309 [site ninfas], 342, 345, 374, 377, 410, 413, 447, 499, 526 [site apontamento] [pintura de Camões por Columbano, portada, fac-símile do frontispício da 1.ª Ed. de Os Lusíadas, ilustrações da obra] | L25: =VLOOKUP(A25,Folha2!$A$2:$B$2019,2,FALSE) -> Os Lusíadas, Rio de Janeiro, 1880, sem argumentos. | M25: =HYPERLINK(J25) -> https://permalinkbnd.bnportugal.gov.pt/viewer/274089/?offset=#page=526&viewer=picture&o=info&n=0&q= | N25: C:\Users\mbaptista\OneDrive - Biblioteca Nacional de Portugal\Documentos\python\camoniana\imagens\capas\ | O25: =CONCATENATE(N25,A25,"\",B25,"\",C25,".jpg") -> C:\Users\mbaptista\OneDrive - Biblioteca Nacional de Portugal\Documentos\python\camoniana\imagens\capas\381074\1\526.jpg | P25: =HYPERLINK(O25) -> C:\Users\mbaptista\OneDrive - Biblioteca Nacional de Portugal\Documentos\python\camoniana\imagens\capas\381074\1\526.jpg | T25: 10, 11, 103, 145, 235, 270, 273, 306, 309, 342, 345, 374, 377, 410, 413, 447, 499
A26: 381465 | C26: 5 | D26: https://purl.pt/43233 | E26: https://purl.pt/43233 | F26: 271573 | G26: https://permalinkbnd.bnportugal.gov.pt/viewer/ | H26: /?offset=#page= | I26: &viewer=picture&o=info&n=0&q= | J26: =CONCATENATE(G26,F26,H26,C26,I26) -> https://permalinkbnd.bnportugal.gov.pt/viewer/271573/?offset=#page=5&viewer=picture&o=info&n=0&q= | K26: 5 [site], 10 [site], 11 [site], 43, 46 [Vasco da Gama], 47, 100, 101, 160, 161, 163, 235, 237, 289, 291 [site Adamastor], 293, 343 [site apontamento livros e pena], 345, 347, 397, 443, 445, 495 [site Mercúrio, caduceu e navegador], 545 [site máquina do mundo], 547, 625, 627, 644 [monge com livro] [portadas, retrato de Camões, fotogravuras em cada Canto] | L26: =VLOOKUP(A26,Folha2!$A$2:$B$2019,2,FALSE) -> Os Lusíadas, 1898, obra dedicada à Comissão do Centenário e nos paratextos é referida a Celebração: Celebrações (1880); Paratextos argumentos e Iconografia figuras históricas. | M26: =HYPERLINK(J26) -> https://permalinkbnd.bnportugal.gov.pt/viewer/271573/?offset=#page=5&viewer=picture&o=info&n=0&q= | N26: C:\Users\mbaptista\OneDrive - Biblioteca Nacional de Portugal\Documentos\python\camoniana\imagens\capas\ | O26: =CONCATENATE(N26,A26,"\",B26,"\",C26,".jpg") -> C:\Users\mbaptista\OneDrive - Biblioteca Nacional de Portugal\Documentos\python\camoniana\imagens\capas\381465\\5.jpg | P26: =HYPERLINK(O26) -> C:\Users\mbaptista\OneDrive - Biblioteca Nacional de Portugal\Documentos\python\camoniana\imagens\capas\381465\\5.jpg | T26: 5, 10, 11, 43, 46 , 47, 101, 160, 161, 163, 235, 237, 291, 293, 343, 345, 347, 397, 443, 445, 495 , 545, 547, 627, 644
A27: 381465 | C27: 10 | D27: https://purl.pt/43233 | E27: https://purl.pt/43233 | F27: 271573 | G27: https://permalinkbnd.bnportugal.gov.pt/viewer/ | H27: /?offset=#page= | I27: &viewer=picture&o=info&n=0&q= | J27: =CONCATENATE(G27,F27,H27,C27,I27) -> https://permalinkbnd.bnportugal.gov.pt/viewer/271573/?offset=#page=10&viewer=picture&o=info&n=0&q= | K27: 5 [site], 10 [site], 11 [site], 43, 46 [Vasco da Gama], 47, 100, 101, 160, 161, 163, 235, 237, 289, 291 [site Adamastor], 293, 343 [site apontamento livros e pena], 345, 347, 397, 443, 445, 495 [site Mercúrio, caduceu e navegador], 545 [site máquina do mundo], 547, 625, 627, 644 [monge com livro] [portadas, retrato de Camões, fotogravuras em cada Canto] | L27: =VLOOKUP(A27,Folha2!$A$2:$B$2019,2,FALSE) -> Os Lusíadas, 1898, obra dedicada à Comissão do Centenário e nos paratextos é referida a Celebração: Celebrações (1880); Paratextos argumentos e Iconografia figuras históricas. | M27: =HYPERLINK(J27) -> https://permalinkbnd.bnportugal.gov.pt/viewer/271573/?offset=#page=10&viewer=picture&o=info&n=0&q= | N27: C:\Users\mbaptista\OneDrive - Biblioteca Nacional de Portugal\Documentos\python\camoniana\imagens\capas\ | O27: =CONCATENATE(N27,A27,"\",B27,"\",C27,".jpg") -> C:\Users\mbaptista\OneDrive - Biblioteca Nacional de Portugal\Documentos\python\camoniana\imagens\capas\381465\\10.jpg | P27: =HYPERLINK(O27) -> C:\Users\mbaptista\OneDrive - Biblioteca Nacional de Portugal\Documentos\python\camoniana\imagens\capas\381465\\10.jpg | T27: 5, 10, 11, 43, 46 , 47, 101, 160, 161, 163, 235, 237, 291, 293, 343, 345, 347, 397, 443, 445, 495 , 545, 547, 627, 644
A28: 381465 | C28: 43 | D28: https://purl.pt/43233 | E28: https://purl.pt/43233 | F28: 271573 | G28: https://permalinkbnd.bnportugal.gov.pt/viewer/ | H28: /?offset=#page= | I28: &viewer=picture&o=info&n=0&q= | J28: =CONCATENATE(G28,F28,H28,C28,I28) -> https://permalinkbnd.bnportugal.gov.pt/viewer/271573/?offset=#page=43&viewer=picture&o=info&n=0&q= | K28: 5 [site], 10 [site], 11 [site], 43, 46 [Vasco da Gama], 47, 100, 101, 160, 161, 163, 235, 237, 289, 291 [site Adamastor], 293, 343 [site apontamento livros e pena], 345, 347, 397, 443, 445, 495 [site Mercúrio, caduceu e navegador], 545 [site máquina do mundo], 547, 625, 627, 644 [monge com livro] [portadas, retrato de Camões, fotogravuras em cada Canto] | L28: =VLOOKUP(A28,Folha2!$A$2:$B$2019,2,FALSE) -> Os Lusíadas, 1898, obra dedicada à Comissão do Centenário e nos paratextos é referida a Celebração: Celebrações (1880); Paratextos argumentos e Iconografia figuras históricas. | M28: =HYPERLINK(J28) -> https://permalinkbnd.bnportugal.gov.pt/viewer/271573/?offset=#page=43&viewer=picture&o=info&n=0&q= | N28: C:\Users\mbaptista\OneDrive - Biblioteca Nacional de Portugal\Documentos\python\camoniana\imagens\capas\ | O28: =CONCATENATE(N28,A28,"\",B28,"\",C28,".jpg") -> C:\Users\mbaptista\OneDrive - Biblioteca Nacional de Portugal\Documentos\python\camoniana\imagens\capas\381465\\43.jpg | P28: =HYPERLINK(O28) -> C:\Users\mbaptista\OneDrive - Biblioteca Nacional de Portugal\Documentos\python\camoniana\imagens\capas\381465\\43.jpg | T28: 5, 10, 11, 43, 46 , 47, 101, 160, 161, 163, 235, 237, 291, 293, 343, 345, 347, 397, 443, 445, 495 , 545, 547, 627, 644
A29: 381465 | C29: 46 | D29: https://purl.pt/43233 | E29: https://purl.pt/43233 | F29: 271573 | G29: https://permalinkbnd.bnportugal.gov.pt/viewer/ | H29: /?offset=#page= | I29: &viewer=picture&o=info&n=0&q= | J29: =CONCATENATE(G29,F29,H29,C29,I29) -> https://permalinkbnd.bnportugal.gov.pt/viewer/271573/?offset=#page=46&viewer=picture&o=info&n=0&q= | K29: 5 [site], 10 [site], 11 [site], 43, 46 [Vasco da Gama], 47, 100, 101, 160, 161, 163, 235, 237, 289, 291 [site Adamastor], 293, 343 [site apontamento livros e pena], 345, 347, 397, 443, 445, 495 [site Mercúrio, caduceu e navegador], 545 [site máquina do mundo], 547, 625, 627, 644 [monge com livro] [portadas, retrato de Camões, fotogravuras em cada Canto] | L29: =VLOOKUP(A29,Folha2!$A$2:$B$2019,2,FALSE) -> Os Lusíadas, 1898, obra dedicada à Comissão do Centenário e nos paratextos é referida a Celebração: Celebrações (1880); Paratextos argumentos e Iconografia figuras históricas. | M29: =HYPERLINK(J29) -> https://permalinkbnd.bnportugal.gov.pt/viewer/271573/?offset=#page=46&viewer=picture&o=info&n=0&q= | N29: C:\Users\mbaptista\OneDrive - Biblioteca Nacional de Portugal\Documentos\python\camoniana\imagens\capas\ | O29: =CONCATENATE(N29,A29,"\",B29,"\",C29,".jpg") -> C:\Users\mbaptista\OneDrive - Biblioteca Nacional de Portugal\Documentos\python\camoniana\imagens\capas\381465\\46.jpg | P29: =HYPERLINK(O29) -> C:\Users\mbaptista\OneDrive - Biblioteca Nacional de Portugal\Documentos\python\camoniana\imagens\capas\381465\\46.jpg | T29: 5, 10, 11, 43, 46 , 47, 101, 160, 161, 163, 235, 237, 291, 293, 343, 345, 347, 397, 443, 445, 495 , 545, 547, 627, 644
A30: 381465 | C30: 47 | D30: https://purl.pt/43233 | E30: https://purl.pt/43233 | F30: 271573 | G30: https://permalinkbnd.bnportugal.gov.pt/viewer/ | H30: /?offset=#page= | I30: &viewer=picture&o=info&n=0&q= | J30: =CONCATENATE(G30,F30,H30,C30,I30) -> https://permalinkbnd.bnportugal.gov.pt/viewer/271573/?offset=#page=47&viewer=picture&o=info&n=0&q= | K30: 5 [site], 10 [site], 11 [site], 43, 46 [Vasco da Gama], 47, 100, 101, 160, 161, 163, 235, 237, 289, 291 [site Adamastor], 293, 343 [site apontamento livros e pena], 345, 347, 397, 443, 445, 495 [site Mercúrio, caduceu e navegador], 545 [site máquina do mundo], 547, 625, 627, 644 [monge com livro] [portadas, retrato de Camões, fotogravuras em cada Canto] | L30: =VLOOKUP(A30,Folha2!$A$2:$B$2019,2,FALSE) -> Os Lusíadas, 1898, obra dedicada à Comissão do Centenário e nos paratextos é referida a Celebração: Celebrações (1880); Paratextos argumentos e Iconografia figuras históricas. | M30: =HYPERLINK(J30) -> https://permalinkbnd.bnportugal.gov.pt/viewer/271573/?offset=#page=47&viewer=picture&o=info&n=0&q= | N30: C:\Users\mbaptista\OneDrive - Biblioteca Nacional de Portugal\Documentos\python\camoniana\imagens\capas\ | O30: =CONCATENATE(N30,A30,"\",B30,"\",C30,".jpg") -> C:\Users\mbaptista\OneDrive - Biblioteca Nacional de Portugal\Documentos\python\camoniana\imagens\capas\381465\\47.jpg | P30: =HYPERLINK(O30) -> C:\Users\mbaptista\OneDrive - Biblioteca Nacional de Portugal\Documentos\python\camoniana\imagens\capas\381465\\47.jpg | T30: 5, 10, 11, 43, 46 , 47, 101, 160, 161, 163, 235, 237, 291, 293, 343, 345, 347, 397, 443, 445, 495 , 545, 547, 627, 644
A31: 381465 | C31: 100 | D31: https://purl.pt/43233 | E31: https://purl.pt/43233 | F31: 271573 | G31: https://permalinkbnd.bnportugal.gov.pt/viewer/ | H31: /?offset=#page= | I31: &viewer=picture&o=info&n=0&q= | J31: =CONCATENATE(G31,F31,H31,C31,I31) -> https://permalinkbnd.bnportugal.gov.pt/viewer/271573/?offset=#page=100&viewer=picture&o=info&n=0&q= | K31: 5 [site], 10 [site], 11 [site], 43, 46 [Vasco da Gama], 47, 100, 101, 160, 161, 163, 235, 237, 289, 291 [site Adamastor], 293, 343 [site apontamento livros e pena], 345, 347, 397, 443, 445, 495 [site Mercúrio, caduceu e navegador], 545 [site máquina do mundo], 547, 625, 627, 644 [monge com livro] [portadas, retrato de Camões, fotogravuras em cada Canto] | L31: =VLOOKUP(A31,Folha2!$A$2:$B$2019,2,FALSE) -> Os Lusíadas, 1898, obra dedicada à Comissão do Centenário e nos paratextos é referida a Celebração: Celebrações (1880); Paratextos argumentos e Iconografia figuras históricas. | M31: =HYPERLINK(J31) -> https://permalinkbnd.bnportugal.gov.pt/viewer/271573/?offset=#page=100&viewer=picture&o=info&n=0&q= | N31: C:\Users\mbaptista\OneDrive - Biblioteca Nacional de Portugal\Documentos\python\camoniana\imagens\capas\ | O31: =CONCATENATE(N31,A31,"\",B31,"\",C31,".jpg") -> C:\Users\mbaptista\OneDrive - Biblioteca Nacional de Portugal\Documentos\python\camoniana\imagens\capas\381465\\100.jpg | P31: =HYPERLINK(O31) -> C:\Users\mbaptista\OneDrive - Biblioteca Nacional de Portugal\Documentos\python\camoniana\imagens\capas\381465\\100.jpg | T31: 5, 10, 11, 43, 46 , 47, 101, 160, 161, 163, 235, 237, 291, 293, 343, 345, 347, 397, 443, 445, 495 , 545, 547, 627, 644
A32: 381465 | C32: 101 | D32: https://purl.pt/43233 | E32: https://purl.pt/43233 | F32: 271573 | G32: https://permalinkbnd.bnportugal.gov.pt/viewer/ | H32: /?offset=#page= | I32: &viewer=picture&o=info&n=0&q= | J32: =CONCATENATE(G32,F32,H32,C32,I32) -> https://permalinkbnd.bnportugal.gov.pt/viewer/271573/?offset=#page=101&viewer=picture&o=info&n=0&q= | K32: 5 [site], 10 [site], 11 [site], 43, 46 [Vasco da Gama], 47, 100, 101, 160, 161, 163, 235, 237, 289, 291 [site Adamastor], 293, 343 [site apontamento livros e pena], 345, 347, 397, 443, 445, 495 [site Mercúrio, caduceu e navegador], 545 [site máquina do mundo], 547, 625, 627, 644 [monge com livro] [portadas, retrato de Camões, fotogravuras em cada Canto] | L32: =VLOOKUP(A32,Folha2!$A$2:$B$2019,2,FALSE) -> Os Lusíadas, 1898, obra dedicada à Comissão do Centenário e nos paratextos é referida a Celebração: Celebrações (1880); Paratextos argumentos e Iconografia figuras históricas. | M32: =HYPERLINK(J32) -> https://permalinkbnd.bnportugal.gov.pt/viewer/271573/?offset=#page=101&viewer=picture&o=info&n=0&q= | N32: C:\Users\mbaptista\OneDrive - Biblioteca Nacional de Portugal\Documentos\python\camoniana\imagens\capas\ | O32: =CONCATENATE(N32,A32,"\",B32,"\",C32,".jpg") -> C:\Users\mbaptista\OneDrive - Biblioteca Nacional de Portugal\Documentos\python\camoniana\imagens\capas\381465\\101.jpg | P32: =HYPERLINK(O32) -> C:\Users\mbaptista\OneDrive - Biblioteca Nacional de Portugal\Documentos\python\camoniana\imagens\capas\381465\\101.jpg | T32: 5, 10, 11, 43, 46 , 47, 101, 160, 161, 163, 235, 237, 291, 293, 343, 345, 347, 397, 443, 445, 495 , 545, 547, 627, 644
A33: 381465 | C33: 160 | D33: https://purl.pt/43233 | E33: https://purl.pt/43233 | F33: 271573 | G33: https://permalinkbnd.bnportugal.gov.pt/viewer/ | H33: /?offset=#page= | I33: &viewer=picture&o=info&n=0&q= | J33: =CONCATENATE(G33,F33,H33,C33,I33) -> https://permalinkbnd.bnportugal.gov.pt/viewer/271573/?offset=#page=160&viewer=picture&o=info&n=0&q= | K33: 5 [site], 10 [site], 11 [site], 43, 46 [Vasco da Gama], 47, 100, 101, 160, 161, 163, 235, 237, 289, 291 [site Adamastor], 293, 343 [site apontamento livros e pena], 345, 347, 397, 443, 445, 495 [site Mercúrio, caduceu e navegador], 545 [site máquina do mundo], 547, 625, 627, 644 [monge com livro] [portadas, retrato de Camões, fotogravuras em cada Canto] | L33: =VLOOKUP(A33,Folha2!$A$2:$B$2019,2,FALSE) -> Os Lusíadas, 1898, obra dedicada à Comissão do Centenário e nos paratextos é referida a Celebração: Celebrações (1880); Paratextos argumentos e Iconografia figuras históricas. | M33: =HYPERLINK(J33) -> https://permalinkbnd.bnportugal.gov.pt/viewer/271573/?offset=#page=160&viewer=picture&o=info&n=0&q= | N33: C:\Users\mbaptista\OneDrive - Biblioteca Nacional de Portugal\Documentos\python\camoniana\imagens\capas\ | O33: =CONCATENATE(N33,A33,"\",B33,"\",C33,".jpg") -> C:\Users\mbaptista\OneDrive - Biblioteca Nacional de Portugal\Documentos\python\camoniana\imagens\capas\381465\\160.jpg | P33: =HYPERLINK(O33) -> C:\Users\mbaptista\OneDrive - Biblioteca Nacional de Portugal\Documentos\python\camoniana\imagens\capas\381465\\160.jpg | T33: 5, 10, 11, 43, 46 , 47, 101, 160, 161, 163, 235, 237, 291, 293, 343, 345, 347, 397, 443, 445, 495 , 545, 547, 627, 644
A34: 381465 | C34: 161 | D34: https://purl.pt/43233 | E34: https://purl.pt/43233 | F34: 271573 | G34: https://permalinkbnd.bnportugal.gov.pt/viewer/ | H34: /?offset=#page= | I34: &viewer=picture&o=info&n=0&q= | J34: =CONCATENATE(G34,F34,H34,C34,I34) -> https://permalinkbnd.bnportugal.gov.pt/viewer/271573/?offset=#page=161&viewer=picture&o=info&n=0&q= | K34: 5 [site], 10 [site], 11 [site], 43, 46 [Vasco da Gama], 47, 100, 101, 160, 161, 163, 235, 237, 289, 291 [site Adamastor], 293, 343 [site apontamento livros e pena], 345, 347, 397, 443, 445, 495 [site Mercúrio, caduceu e navegador], 545 [site máquina do mundo], 547, 625, 627, 644 [monge com livro] [portadas, retrato de Camões, fotogravuras em cada Canto] | L34: =VLOOKUP(A34,Folha2!$A$2:$B$2019,2,FALSE) -> Os Lusíadas, 1898, obra dedicada à Comissão do Centenário e nos paratextos é referida a Celebração: Celebrações (1880); Paratextos argumentos e Iconografia figuras históricas. | M34: =HYPERLINK(J34) -> https://permalinkbnd.bnportugal.gov.pt/viewer/271573/?offset=#page=161&viewer=picture&o=info&n=0&q= | N34: C:\Users\mbaptista\OneDrive - Biblioteca Nacional de Portugal\Documentos\python\camoniana\imagens\capas\ | O34: =CONCATENATE(N34,A34,"\",B34,"\",C34,".jpg") -> C:\Users\mbaptista\OneDrive - Biblioteca Nacional de Portugal\Documentos\python\camoniana\imagens\capas\381465\\161.jpg | P34: =HYPERLINK(O34) -> C:\Users\mbaptista\OneDrive - Biblioteca Nacional de Portugal\Documentos\python\camoniana\imagens\capas\381465\\161.jpg | T34: 5, 10, 11, 43, 46 , 47, 101, 160, 161, 163, 235, 237, 291, 293, 343, 345, 347, 397, 443, 445, 495 , 545, 547, 627, 644
A35: 381465 | C35: 163 | D35: https://purl.pt/43233 | E35: https://purl.pt/43233 | F35: 271573 | G35: https://permalinkbnd.bnportugal.gov.pt/viewer/ | H35: /?offset=#page= | I35: &viewer=picture&o=info&n=0&q= | J35: =CONCATENATE(G35,F35,H35,C35,I35) -> https://permalinkbnd.bnportugal.gov.pt/viewer/271573/?offset=#page=163&viewer=picture&o=info&n=0&q= | K35: 5 [site], 10 [site], 11 [site], 43, 46 [Vasco da Gama], 47, 100, 101, 160, 161, 163, 235, 237, 289, 291 [site Adamastor], 293, 343 [site apontamento livros e pena], 345, 347, 397, 443, 445, 495 [site Mercúrio, caduceu e navegador], 545 [site máquina do mundo], 547, 625, 627, 644 [monge com livro] [portadas, retrato de Camões, fotogravuras em cada Canto] | L35: =VLOOKUP(A35,Folha2!$A$2:$B$2019,2,FALSE) -> Os Lusíadas, 1898, obra dedicada à Comissão do Centenário e nos paratextos é referida a Celebração: Celebrações (1880); Paratextos argumentos e Iconografia figuras históricas. | M35: =HYPERLINK(J35) -> https://permalinkbnd.bnportugal.gov.pt/viewer/271573/?offset=#page=163&viewer=picture&o=info&n=0&q= | N35: C:\Users\mbaptista\OneDrive - Biblioteca Nacional de Portugal\Documentos\python\camoniana\imagens\capas\ | O35: =CONCATENATE(N35,A35,"\",B35,"\",C35,".jpg") -> C:\Users\mbaptista\OneDrive - Biblioteca Nacional de Portugal\Documentos\python\camoniana\imagens\capas\381465\\163.jpg | P35: =HYPERLINK(O35) -> C:\Users\mbaptista\OneDrive - Biblioteca Nacional de Portugal\Documentos\python\camoniana\imagens\capas\381465\\163.jpg | T35: 5, 10, 11, 43, 46 , 47, 101, 160, 161, 163, 235, 237, 291, 293, 343, 345, 347, 397, 443, 445, 495 , 545, 547, 627, 644
A36: 381465 | C36: 235 | D36: https://purl.pt/43233 | E36: https://purl.pt/43233 | F36: 271573 | G36: https://permalinkbnd.bnportugal.gov.pt/viewer/ | H36: /?offset=#page= | I36: &viewer=picture&o=info&n=0&q= | J36: =CONCATENATE(G36,F36,H36,C36,I36) -> https://permalinkbnd.bnportugal.gov.pt/viewer/271573/?offset=#page=235&viewer=picture&o=info&n=0&q= | K36: 5 [site], 10 [site], 11 [site], 43, 46 [Vasco da Gama], 47, 100, 101, 160, 161, 163, 235, 237, 289, 291 [site Adamastor], 293, 343 [site apontamento livros e pena], 345, 347, 397, 443, 445, 495 [site Mercúrio, caduceu e navegador], 545 [site máquina do mundo], 547, 625, 627, 644 [monge com livro] [portadas, retrato de Camões, fotogravuras em cada Canto] | L36: =VLOOKUP(A36,Folha2!$A$2:$B$2019,2,FALSE) -> Os Lusíadas, 1898, obra dedicada à Comissão do Centenário e nos paratextos é referida a Celebração: Celebrações (1880); Paratextos argumentos e Iconografia figuras históricas. | M36: =HYPERLINK(J36) -> https://permalinkbnd.bnportugal.gov.pt/viewer/271573/?offset=#page=235&viewer=picture&o=info&n=0&q= | N36: C:\Users\mbaptista\OneDrive - Biblioteca Nacional de Portugal\Documentos\python\camoniana\imagens\capas\ | O36: =CONCATENATE(N36,A36,"\",B36,"\",C36,".jpg") -> C:\Users\mbaptista\OneDrive - Biblioteca Nacional de Portugal\Documentos\python\camoniana\imagens\capas\381465\\235.jpg | P36: =HYPERLINK(O36) -> C:\Users\mbaptista\OneDrive - Biblioteca Nacional de Portugal\Documentos\python\camoniana\imagens\capas\381465\\235.jpg | T36: 5, 10, 11, 43, 46 , 47, 101, 160, 161, 163, 235, 237, 291, 293, 343, 345, 347, 397, 443, 445, 495 , 545, 547, 627, 644
A37: 381465 | C37: 237 | D37: https://purl.pt/43233 | E37: https://purl.pt/43233 | F37: 271573 | G37: https://permalinkbnd.bnportugal.gov.pt/viewer/ | H37: /?offset=#page= | I37: &viewer=picture&o=info&n=0&q= | J37: =CONCATENATE(G37,F37,H37,C37,I37) -> https://permalinkbnd.bnportugal.gov.pt/viewer/271573/?offset=#page=237&viewer=picture&o=info&n=0&q= | K37: 5 [site], 10 [site], 11 [site], 43, 46 [Vasco da Gama], 47, 100, 101, 160, 161, 163, 235, 237, 289, 291 [site Adamastor], 293, 343 [site apontamento livros e pena], 345, 347, 397, 443, 445, 495 [site Mercúrio, caduceu e navegador], 545 [site máquina do mundo], 547, 625, 627, 644 [monge com livro] [portadas, retrato de Camões, fotogravuras em cada Canto] | L37: =VLOOKUP(A37,Folha2!$A$2:$B$2019,2,FALSE) -> Os Lusíadas, 1898, obra dedicada à Comissão do Centenário e nos paratextos é referida a Celebração: Celebrações (1880); Paratextos argumentos e Iconografia figuras históricas. | M37: =HYPERLINK(J37) -> https://permalinkbnd.bnportugal.gov.pt/viewer/271573/?offset=#page=237&viewer=picture&o=info&n=0&q= | N37: C:\Users\mbaptista\OneDrive - Biblioteca Nacional de Portugal\Documentos\python\camoniana\imagens\capas\ | O37: =CONCATENATE(N37,A37,"\",B37,"\",C37,".jpg") -> C:\Users\mbaptista\OneDrive - Biblioteca Nacional de Portugal\Documentos\python\camoniana\imagens\capas\381465\\237.jpg | P37: =HYPERLINK(O37) -> C:\Users\mbaptista\OneDrive - Biblioteca Nacional de Portugal\Documentos\python\camoniana\imagens\capas\381465\\237.jpg | T37: 5, 10, 11, 43, 46 , 47, 101, 160, 161, 163, 235, 237, 291, 293, 343, 345, 347, 397, 443, 445, 495 , 545, 547, 627, 644
... A51: 381465 | C51: 627 | D51: https://purl.pt/43233 | E51: https://purl.pt/43233 | F51: 271573 | G51: https://permalinkbnd.bnportugal.gov.pt/viewer/ | H51: /?offset=#page= | I51: &viewer=picture&o=info&n=0&q= | J51: =CONCATENATE(G51,F51,H51,C51,I51) -> https://permalinkbnd.bnportugal.gov.pt/viewer/271573/?offset=#page=627&viewer=picture&o=info&n=0&q= | K51: 5 [site], 10 [site], 11 [site], 43, 46 [Vasco da Gama], 47, 100, 101, 160, 161, 163, 235, 237, 289, 291 [site Adamastor], 293, 343 [site apontamento livros e pena], 345, 347, 397, 443, 445, 495 [site Mercúrio, caduceu e navegador], 545 [site máquina do mundo], 547, 625, 627, 644 [monge com livro] [portadas, retrato de Camões, fotogravuras em cada Canto] | L51: =VLOOKUP(A51,Folha2!$A$2:$B$2019,2,FALSE) -> Os Lusíadas, 1898, obra dedicada à Comissão do Centenário e nos paratextos é referida a Celebração: Celebrações (1880); Paratextos argumentos e Iconografia figuras históricas. | M51: =HYPERLINK(J51) -> https://permalinkbnd.bnportugal.gov.pt/viewer/271573/?offset=#page=627&viewer=picture&o=info&n=0&q= | N51: C:\Users\mbaptista\OneDrive - Biblioteca Nacional de Portugal\Documentos\python\camoniana\imagens\capas\ | O51: =CONCATENATE(N51,A51,"\",B51,"\",C51,".jpg") -> C:\Users\mbaptista\OneDrive - Biblioteca Nacional de Portugal\Documentos\python\camoniana\imagens\capas\381465\\627.jpg | P51: =HYPERLINK(O51) -> C:\Users\mbaptista\OneDrive - Biblioteca Nacional de Portugal\Documentos\python\camoniana\imagens\capas\381465\\627.jpg | T51: 5, 10, 11, 43, 46 , 47, 101, 160, 161, 163, 235, 237, 291, 293, 343, 345, 347, 397, 443, 445, 495 , 545, 547, 627, 644
A52: 381465 | B52: 1 | C52: 644 | D52: https://purl.pt/43233 | E52: https://purl.pt/43233 | F52: 271573 | G52: https://permalinkbnd.bnportugal.gov.pt/viewer/ | H52: /?offset=#page= | I52: &viewer=picture&o=info&n=0&q= | J52: =CONCATENATE(G52,F52,H52,C52,I52) -> https://permalinkbnd.bnportugal.gov.pt/viewer/271573/?offset=#page=644&viewer=picture&o=info&n=0&q= | K52: 5 [site], 10 [site], 11 [site], 43, 46 [Vasco da Gama], 47, 100, 101, 160, 161, 163, 235, 237, 289, 291 [site Adamastor], 293, 343 [site apontamento livros e pena], 345, 347, 397, 443, 445, 495 [site Mercúrio, caduceu e navegador], 545 [site máquina do mundo], 547, 625, 627, 644 [monge com livro] [portadas, retrato de Camões, fotogravuras em cada Canto] | L52: =VLOOKUP(A52,Folha2!$A$2:$B$2019,2,FALSE) -> Os Lusíadas, 1898, obra dedicada à Comissão do Centenário e nos paratextos é referida a Celebração: Celebrações (1880); Paratextos argumentos e Iconografia figuras históricas. | M52: =HYPERLINK(J52) -> https://permalinkbnd.bnportugal.gov.pt/viewer/271573/?offset=#page=644&viewer=picture&o=info&n=0&q= | N52: C:\Users\mbaptista\OneDrive - Biblioteca Nacional de Portugal\Documentos\python\camoniana\imagens\capas\ | O52: =CONCATENATE(N52,A52,"\",B52,"\",C52,".jpg") -> C:\Users\mbaptista\OneDrive - Biblioteca Nacional de Portugal\Documentos\python\camoniana\imagens\capas\381465\1\644.jpg | P52: =HYPERLINK(O52) -> C:\Users\mbaptista\OneDrive - Biblioteca Nacional de Portugal\Documentos\python\camoniana\imagens\capas\381465\1\644.jpg | R52: https://permalinkbnd.bnportugal.gov.pt/viewer/271573/?offset=#page=644&viewer=picture&o=info&n=0&q= | T52: 5, 10, 11, 43, 46 , 47, 101, 160, 161, 163, 235, 237, 291, 293, 343, 345, 347, 397, 443, 445, 495 , 545, 547, 627, 644 | W52: Sim
A53: 381468 | B53: 1 | C53: 8 | D53: https://purl.pt/43745 | E53: https://purl.pt/43745 | F53: 274087 | G53: https://permalinkbnd.bnportugal.gov.pt/viewer/ | H53: /?offset=#page= | I53: &viewer=picture&o=info&n=0&q= | J53: =CONCATENATE(G53,F53,H53,C53,I53) -> https://permalinkbnd.bnportugal.gov.pt/viewer/274087/?offset=#page=8&viewer=picture&o=info&n=0&q= | K53: 8 [site retrato de Camões] | L53: =VLOOKUP(A53,Folha2!$A$2:$B$2019,2,FALSE) -> Os Lusíadas/Los Portugueses, D. Carlos Soler y Arques, 1873. Bilingue, sem argumentos. Trad. Paratextos; Trad. Paratextos vida; Trad. Paratextos notas. | M53: =HYPERLINK(J53) -> https://permalinkbnd.bnportugal.gov.pt/viewer/274087/?offset=#page=8&viewer=picture&o=info&n=0&q= | N53: C:\Users\mbaptista\OneDrive - Biblioteca Nacional de Portugal\Documentos\python\camoniana\imagens\capas\ | O53: =CONCATENATE(N53,A53,"\",B53,"\",C53,".jpg") -> C:\Users\mbaptista\OneDrive - Biblioteca Nacional de Portugal\Documentos\python\camoniana\imagens\capas\381468\1\8.jpg | P53: =HYPERLINK(O53) -> C:\Users\mbaptista\OneDrive - Biblioteca Nacional de Portugal\Documentos\python\camoniana\imagens\capas\381468\1\8.jpg | R53: https://permalinkbnd.bnportugal.gov.pt/viewer/274087/?offset=#page=8&viewer=picture&o=info&n=0&q= | T53: 8 | W53: Sim
A54: 381701 | B54: 1 | C54: 11 | D54: https://purl.pt/43724 | E54: https://purl.pt/43724 | F54: 281141 | G54: https://permalinkbnd.bnportugal.gov.pt/viewer/ | H54: /?offset=#page= | I54: &viewer=picture&o=info&n=0&q= | J54: =CONCATENATE(G54,F54,H54,C54,I54) -> https://permalinkbnd.bnportugal.gov.pt/viewer/281141/?offset=#page=11&viewer=picture&o=info&n=0&q= | K54: 11 | L54: =VLOOKUP(A54,Folha2!$A$2:$B$2019,2,FALSE) -> Inês de Castro, 1873. [cópia digital não abre, consultado PDF via Miguel] Edição em catorze línguas, um ano depois das Celebrações (1872), mas sem referência. | M54: =HYPERLINK(J54) -> https://permalinkbnd.bnportugal.gov.pt/viewer/281141/?offset=#page=11&viewer=picture&o=info&n=0&q= | N54: C:\Users\mbaptista\OneDrive - Biblioteca Nacional de Portugal\Documentos\python\camoniana\imagens\capas\ | O54: =CONCATENATE(N54,A54,"\",B54,"\",C54,".jpg") -> C:\Users\mbaptista\OneDrive - Biblioteca Nacional de Portugal\Documentos\python\camoniana\imagens\capas\381701\1\11.jpg | P54: =HYPERLINK(O54) -> C:\Users\mbaptista\OneDrive - Biblioteca Nacional de Portugal\Documentos\python\camoniana\imagens\capas\381701\1\11.jpg | R54: https://permalinkbnd.bnportugal.gov.pt/viewer/281141/?offset=#page=11&viewer=picture&o=info&n=0&q= | T54: 11 | W54: Sim
A55: 381889 | B55: 1 | C55: 1 | D55: https://purl.pt/43659 | E55: https://purl.pt/43659 | F55: 273118 | G55: https://permalinkbnd.bnportugal.gov.pt/viewer/ | H55: /?offset=#page= | I55: &viewer=picture&o=info&n=0&q= | J55: =CONCATENATE(G55,F55,H55,C55,I55) -> https://permalinkbnd.bnportugal.gov.pt/viewer/273118/?offset=#page=1&viewer=picture&o=info&n=0&q= | K55: 1 [Inês de Castro, Vasco da Gama, Catarina de Ataíde e retrato de Camões] | L55: =VLOOKUP(A55,Folha2!$A$2:$B$2019,2,FALSE) -> Pérolas de Camões. 1880. Inês de Castro, Adamastor, Ilha dos Amores, sem argumentos, Soneto a Natércia [em Antologia não existe fragmento/soneto lírica?]. Iconografia, figuras históricas. | M55: =HYPERLINK(J55) -> https://permalinkbnd.bnportugal.gov.pt/viewer/273118/?offset=#page=1&viewer=picture&o=info&n=0&q= | N55: C:\Users\mbaptista\OneDrive - Biblioteca Nacional de Portugal\Documentos\python\camoniana\imagens\capas\ | O55: =CONCATENATE(N55,A55,"\",B55,"\",C55,".jpg") -> C:\Users\mbaptista\OneDrive - Biblioteca Nacional de Portugal\Documentos\python\camoniana\imagens\capas\381889\1\1.jpg | P55: =HYPERLINK(O55) -> C:\Users\mbaptista\OneDrive - Biblioteca Nacional de Portugal\Documentos\python\camoniana\imagens\capas\381889\1\1.jpg | R55: https://permalinkbnd.bnportugal.gov.pt/viewer/273118/?offset=#page=1&viewer=picture&o=info&n=0&q= | T55: 1 | W55: Sim
A56: 381903 | B56: 1 | C56: 5 | D56: https://purl.pt/42920 | E56: https://purl.pt/42920 | F56: 270037 | G56: https://permalinkbnd.bnportugal.gov.pt/viewer/ | H56: /?offset=#page= | I56: &viewer=picture&o=info&n=0&q= | J56: =CONCATENATE(G56,F56,H56,C56,I56) -> https://permalinkbnd.bnportugal.gov.pt/viewer/270037/?offset=#page=5&viewer=picture&o=info&n=0&q= | K56: 5 [1.º] | L56: =VLOOKUP(A56,Folha2!$A$2:$B$2019,2,FALSE) -> Artigo polaco? Séc. XIX: " Luiz de Camoens" da autoria de K. Kaszewskiego 1880, continuação do texto no CAM. 45//3 A. | M56: =HYPERLINK(J56) -> https://permalinkbnd.bnportugal.gov.pt/viewer/270037/?offset=#page=5&viewer=picture&o=info&n=0&q= | N56: C:\Users\mbaptista\OneDrive - Biblioteca Nacional de Portugal\Documentos\python\camoniana\imagens\capas\ | O56: =CONCATENATE(N56,A56,"\",B56,"\",C56,".jpg") -> C:\Users\mbaptista\OneDrive - Biblioteca Nacional de Portugal\Documentos\python\camoniana\imagens\capas\381903\1\5.jpg | P56: =HYPERLINK(O56) -> C:\Users\mbaptista\OneDrive - Biblioteca Nacional de Portugal\Documentos\python\camoniana\imagens\capas\381903\1\5.jpg | R56: https://permalinkbnd.bnportugal.gov.pt/viewer/270037/?offset=#page=5&viewer=picture&o=info&n=0&q= | T56: 5 | W56: Sim
A57: 382749 | B57: 1 | C57: 7 | D57: https://purl.pt/42835 | E57: https://purl.pt/42835 | F57: 270109 | G57: https://permalinkbnd.bnportugal.gov.pt/viewer/ | H57: /?offset=#page= | I57: &viewer=picture&o=info&n=0&q= | J57: =CONCATENATE(G57,F57,H57,C57,I57) -> https://permalinkbnd.bnportugal.gov.pt/viewer/270109/?offset=#page=7&viewer=picture&o=info&n=0&q= | K57: 7 [site], 19, 23 [frisos site, esta obra contém mais apontamentos e frisos belíssimos] | L57: =VLOOKUP(A57,Folha2!$A$2:$B$2019,2,FALSE) -> Pretidão de amor. Texto+tradução, 1893-1895. 2 Vols [dois exemplares da mesma obra: n.º 56 de Tomás de Carvalho e 137 da BNL]. Trad. Paratextos e Mulheres [Alice Moderno trad. para francês; Josephine Lévi trad. para italiano; Josephine de Zaleska trad. polaco; Josephine Constantini-Arntzen trad. norueguês; Mathilde Perry Conorado trad. para castelhano]. Celebrações (1880), traduções em celebração do 313.º aniversário do passamento de Camões (1893) | M57: =HYPERLINK(J57) -> https://permalinkbnd.bnportugal.gov.pt/viewer/270109/?offset=#page=7&viewer=picture&o=info&n=0&q= | N57: C:\Users\mbaptista\OneDrive - Biblioteca Nacional de Portugal\Documentos\python\camoniana\imagens\capas\ | O57: =CONCATENATE(N57,A57,"\",B57,"\",C57,".jpg") -> C:\Users\mbaptista\OneDrive - Biblioteca Nacional de Portugal\Documentos\python\camoniana\imagens\capas\382749\1\7.jpg | P57: =HYPERLINK(O57) -> C:\Users\mbaptista\OneDrive - Biblioteca Nacional de Portugal\Documentos\python\camoniana\imagens\capas\382749\1\7.jpg | R57: https://permalinkbnd.bnportugal.gov.pt/viewer/270109/?offset=#page=7&viewer=picture&o=info&n=0&q= | W57: Sim
A58: 382749 | B58: 1 | C58: 19 | D58: https://purl.pt/42835 | E58: https://purl.pt/42835 | F58: 270109 | G58: https://permalinkbnd.bnportugal.gov.pt/viewer/ | H58: /?offset=#page= | I58: &viewer=picture&o=info&n=0&q= | J58: =CONCATENATE(G58,F58,H58,C58,I58) -> https://permalinkbnd.bnportugal.gov.pt/viewer/270109/?offset=#page=19&viewer=picture&o=info&n=0&q= | L58: =VLOOKUP(A58,Folha2!$A$2:$B$2019,2,FALSE) -> Pretidão de amor. Texto+tradução, 1893-1895. 2 Vols [dois exemplares da mesma obra: n.º 56 de Tomás de Carvalho e 137 da BNL]. Trad. Paratextos e Mulheres [Alice Moderno trad. para francês; Josephine Lévi trad. para italiano; Josephine de Zaleska trad. polaco; Josephine Constantini-Arntzen trad. norueguês; Mathilde Perry Conorado trad. para castelhano]. Celebrações (1880), traduções em celebração do 313.º aniversário do passamento de Camões (1893) | M58: =HYPERLINK(J58) -> https://permalinkbnd.bnportugal.gov.pt/viewer/270109/?offset=#page=19&viewer=picture&o=info&n=0&q= | N58: C:\Users\mbaptista\OneDrive - Biblioteca Nacional de Portugal\Documentos\python\camoniana\imagens\capas\ | O58: =CONCATENATE(N58,A58,"\",B58,"\",C58,".jpg") -> C:\Users\mbaptista\OneDrive - Biblioteca Nacional de Portugal\Documentos\python\camoniana\imagens\capas\382749\1\19.jpg | P58: =HYPERLINK(O58) -> C:\Users\mbaptista\OneDrive - Biblioteca Nacional de Portugal\Documentos\python\camoniana\imagens\capas\382749\1\19.jpg | R58: https://permalinkbnd.bnportugal.gov.pt/viewer/270109/?offset=#page=19&viewer=picture&o=info&n=0&q= | W58: Sim
A59: 382749 | B59: 1 | C59: 23 | D59: https://purl.pt/42835 | E59: https://purl.pt/42835 | F59: 270109 | G59: https://permalinkbnd.bnportugal.gov.pt/viewer/ | H59: /?offset=#page= | I59: &viewer=picture&o=info&n=0&q= | J59: =CONCATENATE(G59,F59,H59,C59,I59) -> https://permalinkbnd.bnportugal.gov.pt/viewer/270109/?offset=#page=23&viewer=picture&o=info&n=0&q= | L59: =VLOOKUP(A59,Folha2!$A$2:$B$2019,2,FALSE) -> Pretidão de amor. Texto+tradução, 1893-1895. 2 Vols [dois exemplares da mesma obra: n.º 56 de Tomás de Carvalho e 137 da BNL]. Trad. Paratextos e Mulheres [Alice Moderno trad. para francês; Josephine Lévi trad. para italiano; Josephine de Zaleska trad. polaco; Josephine Constantini-Arntzen trad. norueguês; Mathilde Perry Conorado trad. para castelhano]. Celebrações (1880), traduções em celebração do 313.º aniversário do passamento de Camões (1893) | M59: =HYPERLINK(J59) -> https://permalinkbnd.bnportugal.gov.pt/viewer/270109/?offset=#page=23&viewer=picture&o=info&n=0&q= | N59: C:\Users\mbaptista\OneDrive - Biblioteca Nacional de Portugal\Documentos\python\camoniana\imagens\capas\ | O59: =CONCATENATE(N59,A59,"\",B59,"\",C59,".jpg") -> C:\Users\mbaptista\OneDrive - Biblioteca Nacional de Portugal\Documentos\python\camoniana\imagens\capas\382749\1\23.jpg | P59: =HYPERLINK(O59) -> C:\Users\mbaptista\OneDrive - Biblioteca Nacional de Portugal\Documentos\python\camoniana\imagens\capas\382749\1\23.jpg | R59: https://permalinkbnd.bnportugal.gov.pt/viewer/270109/?offset=#page=23&viewer=picture&o=info&n=0&q= | W59: Sim
A60: 382834 | B60: 1 | C60: 11 | D60: https://purl.pt/43815 | E60: https://purl.pt/43815 | F60: 273316 | G60: https://permalinkbnd.bnportugal.gov.pt/viewer/ | H60: /?offset=#page= | I60: &viewer=picture&o=info&n=0&q= | J60: =CONCATENATE(G60,F60,H60,C60,I60) -> https://permalinkbnd.bnportugal.gov.pt/viewer/273316/?offset=#page=11&viewer=picture&o=info&n=0&q= | K60: 11 [caravela com Vasco da Gama] | L60: =VLOOKUP(A60,Folha2!$A$2:$B$2019,2,FALSE) -> Benoliel, Sobre o episódio do Adamastor, 1898. Bibliografia crítica, estudo. | M60: =HYPERLINK(J60) -> https://permalinkbnd.bnportugal.gov.pt/viewer/273316/?offset=#page=11&viewer=picture&o=info&n=0&q= | N60: C:\Users\mbaptista\OneDrive - Biblioteca Nacional de Portugal\Documentos\python\camoniana\imagens\capas\ | O60: =CONCATENATE(N60,A60,"\",B60,"\",C60,".jpg") -> C:\Users\mbaptista\OneDrive - Biblioteca Nacional de Portugal\Documentos\python\camoniana\imagens\capas\382834\1\11.jpg | P60: =HYPERLINK(O60) -> C:\Users\mbaptista\OneDrive - Biblioteca Nacional de Portugal\Documentos\python\camoniana\imagens\capas\382834\1\11.jpg | R60: https://permalinkbnd.bnportugal.gov.pt/viewer/273316/?offset=#page=11&viewer=picture&o=info&n=0&q= | T60: 11 | W60: Sim
A61: 382844 | B61: 1 | C61: 3 | D61: https://purl.pt/43227 | E61: https://purl.pt/43227 | F61: 271559 | G61: https://permalinkbnd.bnportugal.gov.pt/viewer/ | H61: /?offset=#page= | I61: &viewer=picture&o=info&n=0&q= | J61: =CONCATENATE(G61,F61,H61,C61,I61) -> https://permalinkbnd.bnportugal.gov.pt/viewer/271559/?offset=#page=3&viewer=picture&o=info&n=0&q= | K61: 3 | L61: =VLOOKUP(A61,Folha2!$A$2:$B$2019,2,FALSE) -> Poema a Camões*Vida+Notas1880 [notas sobre a vida do Poeta, Im. 13]. Celebrações (1880), recepção criativa, tematização. Inclui soneto de Camões. | M61: =HYPERLINK(J61) -> https://permalinkbnd.bnportugal.gov.pt/viewer/271559/?offset=#page=3&viewer=picture&o=info&n=0&q= | N61: C:\Users\mbaptista\OneDrive - Biblioteca Nacional de Portugal\Documentos\python\camoniana\imagens\capas\ | O61: =CONCATENATE(N61,A61,"\",B61,"\",C61,".jpg") -> C:\Users\mbaptista\OneDrive - Biblioteca Nacional de Portugal\Documentos\python\camoniana\imagens\capas\382844\1\3.jpg | P61: =HYPERLINK(O61) -> C:\Users\mbaptista\OneDrive - Biblioteca Nacional de Portugal\Documentos\python\camoniana\imagens\capas\382844\1\3.jpg | R61: https://permalinkbnd.bnportugal.gov.pt/viewer/271559/?offset=#page=3&viewer=picture&o=info&n=0&q= | W61: Sim
A62: 382955 | B62: 1 | C62: 6 | D62: https://purl.pt/43816 | E62: https://purl.pt/43816 | F62: 274171 | G62: https://permalinkbnd.bnportugal.gov.pt/viewer/ | H62: /?offset=#page= | I62: &viewer=picture&o=info&n=0&q= | J62: =CONCATENATE(G62,F62,H62,C62,I62) -> https://permalinkbnd.bnportugal.gov.pt/viewer/274171/?offset=#page=6&viewer=picture&o=info&n=0&q= | K62: 6 [site, retrato do Poeta laureado] | L62: =VLOOKUP(A62,Folha2!$A$2:$B$2019,2,FALSE) -> Auto da cunhagem. Textos+poesias de homenagem a Camões+Retrato, 1880. A inserir Celebrações (1880), recepção criativa, tematização. | M62: =HYPERLINK(J62) -> https://permalinkbnd.bnportugal.gov.pt/viewer/274171/?offset=#page=6&viewer=picture&o=info&n=0&q= | N62: C:\Users\mbaptista\OneDrive - Biblioteca Nacional de Portugal\Documentos\python\camoniana\imagens\capas\ | O62: =CONCATENATE(N62,A62,"\",B62,"\",C62,".jpg") -> C:\Users\mbaptista\OneDrive - Biblioteca Nacional de Portugal\Documentos\python\camoniana\imagens\capas\382955\1\6.jpg | P62: =HYPERLINK(O62) -> C:\Users\mbaptista\OneDrive - Biblioteca Nacional de Portugal\Documentos\python\camoniana\imagens\capas\382955\1\6.jpg | R62: https://permalinkbnd.bnportugal.gov.pt/viewer/274171/?offset=#page=6&viewer=picture&o=info&n=0&q= | T62: 6 | W62: Sim
A63: 382972 | B63: 1 | C63: 14 | D63: https://purl.pt/43819 | E63: https://purl.pt/43819 | F63: 274229 | G63: https://permalinkbnd.bnportugal.gov.pt/viewer/ | H63: /?offset=#page= | I63: &viewer=picture&o=info&n=0&q= | J63: =CONCATENATE(G63,F63,H63,C63,I63) -> https://permalinkbnd.bnportugal.gov.pt/viewer/274229/?offset=#page=14&viewer=picture&o=info&n=0&q= | K63: 14 [site, imagem da medalha/gravura comemorativa do monumento erigido à memória do Poeta] | L63: =VLOOKUP(A63,Folha2!$A$2:$B$2019,2,FALSE) -> Tomás Ribeiro, Surrexit, 1880. Celebrações (1880), recepção criativa, tematização. | M63: =HYPERLINK(J63) -> https://permalinkbnd.bnportugal.gov.pt/viewer/274229/?offset=#page=14&viewer=picture&o=info&n=0&q= | N63: C:\Users\mbaptista\OneDrive - Biblioteca Nacional de Portugal\Documentos\python\camoniana\imagens\capas\ | O63: =CONCATENATE(N63,A63,"\",B63,"\",C63,".jpg") -> C:\Users\mbaptista\OneDrive - Biblioteca Nacional de Portugal\Documentos\python\camoniana\imagens\capas\382972\1\14.jpg | P63: =HYPERLINK(O63) -> C:\Users\mbaptista\OneDrive - Biblioteca Nacional de Portugal\Documentos\python\camoniana\imagens\capas\382972\1\14.jpg | R63: https://permalinkbnd.bnportugal.gov.pt/viewer/274229/?offset=#page=14&viewer=picture&o=info&n=0&q= | T63: 14 | W63: Sim
A64: 382978 | B64: 1 | C64: 7 | D64: https://purl.pt/43823 | E64: https://purl.pt/43823 | F64: 274235 | G64: https://permalinkbnd.bnportugal.gov.pt/viewer/ | H64: /?offset=#page= | I64: &viewer=picture&o=info&n=0&q= | J64: =CONCATENATE(G64,F64,H64,C64,I64) -> https://permalinkbnd.bnportugal.gov.pt/viewer/274235/?offset=#page=7&viewer=picture&o=info&n=0&q= | K64: 7 [site], 13 [site, itinerário do cortejo triunfal], 15 [site préstito cívico e triunfal] | L64: =VLOOKUP(A64,Folha2!$A$2:$B$2019,2,FALSE) -> Programa, 1880. Iconografia, Lugares de memória. | M64: =HYPERLINK(J64) -> https://permalinkbnd.bnportugal.gov.pt/viewer/274235/?offset=#page=7&viewer=picture&o=info&n=0&q= | N64: C:\Users\mbaptista\OneDrive - Biblioteca Nacional de Portugal\Documentos\python\camoniana\imagens\capas\ | O64: =CONCATENATE(N64,A64,"\",B64,"\",C64,".jpg") -> C:\Users\mbaptista\OneDrive - Biblioteca Nacional de Portugal\Documentos\python\camoniana\imagens\capas\382978\1\7.jpg | P64: =HYPERLINK(O64) -> C:\Users\mbaptista\OneDrive - Biblioteca Nacional de Portugal\Documentos\python\camoniana\imagens\capas\382978\1\7.jpg | R64: https://permalinkbnd.bnportugal.gov.pt/viewer/274235/?offset=#page=7&viewer=picture&o=info&n=0&q= | T64: 7, 13, 15 | W64: Sim
A65: 382978 | B65: 1 | C65: 13 | D65: https://purl.pt/43823 | E65: https://purl.pt/43823 | F65: 274235 | G65: https://permalinkbnd.bnportugal.gov.pt/viewer/ | H65: /?offset=#page= | I65: &viewer=picture&o=info&n=0&q= | J65: =CONCATENATE(G65,F65,H65,C65,I65) -> https://permalinkbnd.bnportugal.gov.pt/viewer/274235/?offset=#page=13&viewer=picture&o=info&n=0&q= | K65: 7 [site], 13 [site, itinerário do cortejo triunfal], 15 [site préstito cívico e triunfal] | L65: =VLOOKUP(A65,Folha2!$A$2:$B$2019,2,FALSE) -> Programa, 1880. Iconografia, Lugares de memória. | M65: =HYPERLINK(J65) -> https://permalinkbnd.bnportugal.gov.pt/viewer/274235/?offset=#page=13&viewer=picture&o=info&n=0&q= | N65: C:\Users\mbaptista\OneDrive - Biblioteca Nacional de Portugal\Documentos\python\camoniana\imagens\capas\ | O65: =CONCATENATE(N65,A65,"\",B65,"\",C65,".jpg") -> C:\Users\mbaptista\OneDrive - Biblioteca Nacional de Portugal\Documentos\python\camoniana\imagens\capas\382978\1\13.jpg | P65: =HYPERLINK(O65) -> C:\Users\mbaptista\OneDrive - Biblioteca Nacional de Portugal\Documentos\python\camoniana\imagens\capas\382978\1\13.jpg | R65: https://permalinkbnd.bnportugal.gov.pt/viewer/274235/?offset=#page=13&viewer=picture&o=info&n=0&q= | T65: 7, 13, 15 | W65: Sim
A66: 382978 | B66: 1 | C66: 15 | D66: https://purl.pt/43823 | E66: https://purl.pt/43823 | F66: 274235 | G66: https://permalinkbnd.bnportugal.gov.pt/viewer/ | H66: /?offset=#page= | I66: &viewer=picture&o=info&n=0&q= | J66: =CONCATENATE(G66,F66,H66,C66,I66) -> https://permalinkbnd.bnportugal.gov.pt/viewer/274235/?offset=#page=15&viewer=picture&o=info&n=0&q= | K66: 7 [site], 13 [site, itinerário do cortejo triunfal], 15 [site préstito cívico e triunfal] | L66: =VLOOKUP(A66,Folha2!$A$2:$B$2019,2,FALSE) -> Programa, 1880. Iconografia, Lugares de memória. | M66: =HYPERLINK(J66) -> https://permalinkbnd.bnportugal.gov.pt/viewer/274235/?offset=#page=15&viewer=picture&o=info&n=0&q= | N66: C:\Users\mbaptista\OneDrive - Biblioteca Nacional de Portugal\Documentos\python\camoniana\imagens\capas\ | O66: =CONCATENATE(N66,A66,"\",B66,"\",C66,".jpg") -> C:\Users\mbaptista\OneDrive - Biblioteca Nacional de Portugal\Documentos\python\camoniana\imagens\capas\382978\1\15.jpg | P66: =HYPERLINK(O66) -> C:\Users\mbaptista\OneDrive - Biblioteca Nacional de Portugal\Documentos\python\camoniana\imagens\capas\382978\1\15.jpg | R66: https://permalinkbnd.bnportugal.gov.pt/viewer/274235/?offset=#page=15&viewer=picture&o=info&n=0&q= | T66: 7, 13, 15 | W66: Sim
A67: 382981 | B67: 1 | C67: 9 | D67: https://purl.pt/43818 | E67: https://purl.pt/43818 | F67: 1880 | G67: https://permalinkbnd.bnportugal.gov.pt/viewer/ | H67: /?offset=#page= | I67: &viewer=picture&o=info&n=0&q= | J67: =CONCATENATE(G67,F67,H67,C67,I67) -> https://permalinkbnd.bnportugal.gov.pt/viewer/1880/?offset=#page=9&viewer=picture&o=info&n=0&q= | K67: 9 | L67: =VLOOKUP(A67,Folha2!$A$2:$B$2019,2,FALSE) -> Relatório. Rio de Janeiro, 1880, com anexos. Figuras Femininas [Im. 24: Adelina Lopes VIeira, poetisa e recitadora, existe indicação em revista de 1880 de homenagem a Camões em que a autora participa, cf. https://ccbibliotecas.azores.gov.pt/cgi-bin/koha/opac-detail.pl?biblionumber=5486; Lucinda Furtado Coelho, arte dramática; Im. 57: oferta a Maria Belizaria de Andrade Varela, viúva do poeta Fagundes Varela]. | M67: =HYPERLINK(J67) -> https://permalinkbnd.bnportugal.gov.pt/viewer/1880/?offset=#page=9&viewer=picture&o=info&n=0&q= | N67: C:\Users\mbaptista\OneDrive - Biblioteca Nacional de Portugal\Documentos\python\camoniana\imagens\capas\ | O67: =CONCATENATE(N67,A67,"\",B67,"\",C67,".jpg") -> C:\Users\mbaptista\OneDrive - Biblioteca Nacional de Portugal\Documentos\python\camoniana\imagens\capas\382981\1\9.jpg | P67: =HYPERLINK(O67) -> C:\Users\mbaptista\OneDrive - Biblioteca Nacional de Portugal\Documentos\python\camoniana\imagens\capas\382981\1\9.jpg | R67: https://permalinkbnd.bnportugal.gov.pt/viewer/1880/?offset=#page=9&viewer=picture&o=info&n=0&q= | W67: Sim
A68: 385945 | B68: 1 | C68: 10 | D68: https://purl.pt/43873 | E68: https://purl.pt/43873 | F68: 273149 | G68: https://permalinkbnd.bnportugal.gov.pt/viewer/ | H68: /?offset=#page= | I68: &viewer=picture&o=info&n=0&q= | J68: =CONCATENATE(G68,F68,H68,C68,I68) -> https://permalinkbnd.bnportugal.gov.pt/viewer/273149/?offset=#page=10&viewer=picture&o=info&n=0&q= | K68: 10 [fotografia do autor], 11 [portada], 15 | L68: =VLOOKUP(A68,Folha2!$A$2:$B$2019,2,FALSE) -> Francisco Xavier Esteves (ed.), Album Literário, 1880. Figuras Femininas [Guiomar Torresão; D. Agua de Valldaura]. Celebrações (1880), recepção criativa, tematização e centão. Tradução/versão livre soneto de Camões, cf. Im. 37; Soneto de Camões: "Quando o sol encoberto vai mostrando", cf. Im. 38, redondilhas em espanhol, Camões, cf. 39. | M68: =HYPERLINK(J68) -> https://permalinkbnd.bnportugal.gov.pt/viewer/273149/?offset=#page=10&viewer=picture&o=info&n=0&q= | N68: C:\Users\mbaptista\OneDrive - Biblioteca Nacional de Portugal\Documentos\python\camoniana\imagens\capas\ | O68: =CONCATENATE(N68,A68,"\",B68,"\",C68,".jpg") -> C:\Users\mbaptista\OneDrive - Biblioteca Nacional de Portugal\Documentos\python\camoniana\imagens\capas\385945\1\10.jpg | P68: =HYPERLINK(O68) -> C:\Users\mbaptista\OneDrive - Biblioteca Nacional de Portugal\Documentos\python\camoniana\imagens\capas\385945\1\10.jpg
A69: 385945 | B69: 1 | C69: 11 | D69: https://purl.pt/43873 | E69: https://purl.pt/43873 | F69: 273149 | G69: https://permalinkbnd.bnportugal.gov.pt/viewer/ | H69: /?offset=#page= | I69: &viewer=picture&o=info&n=0&q= | J69: =CONCATENATE(G69,F69,H69,C69,I69) -> https://permalinkbnd.bnportugal.gov.pt/viewer/273149/?offset=#page=11&viewer=picture&o=info&n=0&q= | K69: 10 [fotografia do autor], 11 [portada], 15 | L69: =VLOOKUP(A69,Folha2!$A$2:$B$2019,2,FALSE) -> Francisco Xavier Esteves (ed.), Album Literário, 1880. Figuras Femininas [Guiomar Torresão; D. Agua de Valldaura]. Celebrações (1880), recepção criativa, tematização e centão. Tradução/versão livre soneto de Camões, cf. Im. 37; Soneto de Camões: "Quando o sol encoberto vai mostrando", cf. Im. 38, redondilhas em espanhol, Camões, cf. 39. | M69: =HYPERLINK(J69) -> https://permalinkbnd.bnportugal.gov.pt/viewer/273149/?offset=#page=11&viewer=picture&o=info&n=0&q= | N69: C:\Users\mbaptista\OneDrive - Biblioteca Nacional de Portugal\Documentos\python\camoniana\imagens\capas\ | O69: =CONCATENATE(N69,A69,"\",B69,"\",C69,".jpg") -> C:\Users\mbaptista\OneDrive - Biblioteca Nacional de Portugal\Documentos\python\camoniana\imagens\capas\385945\1\11.jpg | P69: =HYPERLINK(O69) -> C:\Users\mbaptista\OneDrive - Biblioteca Nacional de Portugal\Documentos\python\camoniana\imagens\capas\385945\1\11.jpg
A70: 385945 | B70: 1 | C70: 15 | D70: https://purl.pt/43873 | E70: https://purl.pt/43873 | F70: 273149 | G70: https://permalinkbnd.bnportugal.gov.pt/viewer/ | H70: /?offset=#page= | I70: &viewer=picture&o=info&n=0&q= | J70: =CONCATENATE(G70,F70,H70,C70,I70) -> https://permalinkbnd.bnportugal.gov.pt/viewer/273149/?offset=#page=15&viewer=picture&o=info&n=0&q= | K70: 10 [fotografia do autor], 11 [portada], 15 | L70: =VLOOKUP(A70,Folha2!$A$2:$B$2019,2,FALSE) -> Francisco Xavier Esteves (ed.), Album Literário, 1880. Figuras Femininas [Guiomar Torresão; D. Agua de Valldaura]. Celebrações (1880), recepção criativa, tematização e centão. Tradução/versão livre soneto de Camões, cf. Im. 37; Soneto de Camões: "Quando o sol encoberto vai mostrando", cf. Im. 38, redondilhas em espanhol, Camões, cf. 39. | M70: =HYPERLINK(J70) -> https://permalinkbnd.bnportugal.gov.pt/viewer/273149/?offset=#page=15&viewer=picture&o=info&n=0&q= | N70: C:\Users\mbaptista\OneDrive - Biblioteca Nacional de Portugal\Documentos\python\camoniana\imagens\capas\ | O70: =CONCATENATE(N70,A70,"\",B70,"\",C70,".jpg") -> C:\Users\mbaptista\OneDrive - Biblioteca Nacional de Portugal\Documentos\python\camoniana\imagens\capas\385945\1\15.jpg | P70: =HYPERLINK(O70) -> C:\Users\mbaptista\OneDrive - Biblioteca Nacional de Portugal\Documentos\python\camoniana\imagens\capas\385945\1\15.jpg | R70: https://permalinkbnd.bnportugal.gov.pt/viewer/273149/?offset=#page=15&viewer=picture&o=info&n=0&q= | T70: 15 | W70: Sim
A71: 385949 | B71: 1 | C71: 1 | D71: https://purl.pt/43866 | E71: https://purl.pt/43866 | F71: 274256 | G71: https://permalinkbnd.bnportugal.gov.pt/viewer/ | H71: /?offset=#page= | I71: &viewer=picture&o=info&n=0&q= | J71: =CONCATENATE(G71,F71,H71,C71,I71) -> https://permalinkbnd.bnportugal.gov.pt/viewer/274256/?offset=#page=1&viewer=picture&o=info&n=0&q= | K71: 1 | L71: =VLOOKUP(A71,Folha2!$A$2:$B$2019,2,FALSE) -> Centro Republicano. Açores, 1880. Fragmentos épica e canção: Recolha epigráfica? | M71: =HYPERLINK(J71) -> https://permalinkbnd.bnportugal.gov.pt/viewer/274256/?offset=#page=1&viewer=picture&o=info&n=0&q= | N71: C:\Users\mbaptista\OneDrive - Biblioteca Nacional de Portugal\Documentos\python\camoniana\imagens\capas\ | O71: =CONCATENATE(N71,A71,"\",B71,"\",C71,".jpg") -> C:\Users\mbaptista\OneDrive - Biblioteca Nacional de Portugal\Documentos\python\camoniana\imagens\capas\385949\1\1.jpg | P71: =HYPERLINK(O71) -> C:\Users\mbaptista\OneDrive - Biblioteca Nacional de Portugal\Documentos\python\camoniana\imagens\capas\385949\1\1.jpg | R71: https://permalinkbnd.bnportugal.gov.pt/viewer/274256/?offset=#page=1&viewer=picture&o=info&n=0&q= | T71: 1 | W71: Sim
A72: 386935 | B72: 1 | C72: 1 | D72: https://purl.pt/43871 | E72: https://purl.pt/43871 | F72: 273122 | G72: https://permalinkbnd.bnportugal.gov.pt/viewer/ | H72: /?offset=#page= | I72: &viewer=picture&o=info&n=0&q= | J72: =CONCATENATE(G72,F72,H72,C72,I72) -> https://permalinkbnd.bnportugal.gov.pt/viewer/273122/?offset=#page=1&viewer=picture&o=info&n=0&q= | K72: 1 | L72: =VLOOKUP(A72,Folha2!$A$2:$B$2019,2,FALSE) -> Viana a Camões, 1880. Publicação Comemorativa: não parece periódico do Tricentenário do Imortal Cantor dos Lusíadas. Figuras Femininas [Zulmira E. A. de Sá, poema em homenagem ao Poeta]. Celebrações (1880), recepção criativa, tematização | M72: =HYPERLINK(J72) -> https://permalinkbnd.bnportugal.gov.pt/viewer/273122/?offset=#page=1&viewer=picture&o=info&n=0&q= | N72: C:\Users\mbaptista\OneDrive - Biblioteca Nacional de Portugal\Documentos\python\camoniana\imagens\capas\ | O72: =CONCATENATE(N72,A72,"\",B72,"\",C72,".jpg") -> C:\Users\mbaptista\OneDrive - Biblioteca Nacional de Portugal\Documentos\python\camoniana\imagens\capas\386935\1\1.jpg | P72: =HYPERLINK(O72) -> C:\Users\mbaptista\OneDrive - Biblioteca Nacional de Portugal\Documentos\python\camoniana\imagens\capas\386935\1\1.jpg | R72: https://permalinkbnd.bnportugal.gov.pt/viewer/273122/?offset=#page=1&viewer=picture&o=info&n=0&q= | W72: Sim
A73: 386992 | B73: 1 | C73: 1 | D73: https://purl.pt/43661 | E73: https://purl.pt/43661 | F73: 273124 | G73: https://permalinkbnd.bnportugal.gov.pt/viewer/ | H73: /?offset=#page= | I73: &viewer=picture&o=info&n=0&q= | J73: =CONCATENATE(G73,F73,H73,C73,I73) -> https://permalinkbnd.bnportugal.gov.pt/viewer/273124/?offset=#page=1&viewer=picture&o=info&n=0&q= | K73: 1 | L73: =VLOOKUP(A73,Folha2!$A$2:$B$2019,2,FALSE) -> Homenagem. S. Miguel, Açores, 1880, com duas digitalizações em cores distintas da mesma peça. Será um periódico? Não. | M73: =HYPERLINK(J73) -> https://permalinkbnd.bnportugal.gov.pt/viewer/273124/?offset=#page=1&viewer=picture&o=info&n=0&q= | N73: C:\Users\mbaptista\OneDrive - Biblioteca Nacional de Portugal\Documentos\python\camoniana\imagens\capas\ | O73: =CONCATENATE(N73,A73,"\",B73,"\",C73,".jpg") -> C:\Users\mbaptista\OneDrive - Biblioteca Nacional de Portugal\Documentos\python\camoniana\imagens\capas\386992\1\1.jpg | P73: =HYPERLINK(O73) -> C:\Users\mbaptista\OneDrive - Biblioteca Nacional de Portugal\Documentos\python\camoniana\imagens\capas\386992\1\1.jpg | R73: https://permalinkbnd.bnportugal.gov.pt/viewer/273124/?offset=#page=1&viewer=picture&o=info&n=0&q= | T73: 1 | W73: Sim
A74: 396405 | B74: 1 | C74: 1 | D74: https://purl.pt/6115 | E74: https://purl.pt/6115 | F74: 36059 | G74: https://permalinkbnd.bnportugal.gov.pt/viewer/ | H74: /?offset=#page= | I74: &viewer=picture&o=info&n=0&q= | J74: =CONCATENATE(G74,F74,H74,C74,I74) -> https://permalinkbnd.bnportugal.gov.pt/viewer/36059/?offset=#page=1&viewer=picture&o=info&n=0&q= | K74: 1 | L74: =VLOOKUP(A74,Folha2!$A$2:$B$2019,2,FALSE) -> Fernando Jorge Fialho, 1992, com epígrafe: "Daquele cuja lira sonorosa/ será mais afamada que ditosa". Consultada cópia interna. | M74: =HYPERLINK(J74) -> https://permalinkbnd.bnportugal.gov.pt/viewer/36059/?offset=#page=1&viewer=picture&o=info&n=0&q= | N74: C:\Users\mbaptista\OneDrive - Biblioteca Nacional de Portugal\Documentos\python\camoniana\imagens\capas\ | O74: =CONCATENATE(N74,A74,"\",B74,"\",C74,".jpg") -> C:\Users\mbaptista\OneDrive - Biblioteca Nacional de Portugal\Documentos\python\camoniana\imagens\capas\396405\1\1.jpg | P74: =HYPERLINK(O74) -> C:\Users\mbaptista\OneDrive - Biblioteca Nacional de Portugal\Documentos\python\camoniana\imagens\capas\396405\1\1.jpg | R74: https://permalinkbnd.bnportugal.gov.pt/viewer/36059/?offset=#page=1&viewer=picture&o=info&n=0&q= | T74: 1 | W74: Sim
A75: 397670 | B75: 1 | C75: 11 | D75: https://purl.pt/43874 | E75: https://purl.pt/43874 | F75: 273150 | G75: https://permalinkbnd.bnportugal.gov.pt/viewer/ | H75: /?offset=#page= | I75: &viewer=picture&o=info&n=0&q= | J75: =CONCATENATE(G75,F75,H75,C75,I75) -> https://permalinkbnd.bnportugal.gov.pt/viewer/273150/?offset=#page=11&viewer=picture&o=info&n=0&q= | K75: 11, 13 [apontamento sobre o Centenário de Camões, site?] | L75: =VLOOKUP(A75,Folha2!$A$2:$B$2019,2,FALSE) -> Episódio da Ilha de Vénus. Trd. De Cournand, 1880, sem argumento. Bilingue. Trad. Paratextos gerais e Celebrações (1880), traduções. | M75: =HYPERLINK(J75) -> https://permalinkbnd.bnportugal.gov.pt/viewer/273150/?offset=#page=11&viewer=picture&o=info&n=0&q= | N75: C:\Users\mbaptista\OneDrive - Biblioteca Nacional de Portugal\Documentos\python\camoniana\imagens\capas\ | O75: =CONCATENATE(N75,A75,"\",B75,"\",C75,".jpg") -> C:\Users\mbaptista\OneDrive - Biblioteca Nacional de Portugal\Documentos\python\camoniana\imagens\capas\397670\1\11.jpg | P75: =HYPERLINK(O75) -> C:\Users\mbaptista\OneDrive - Biblioteca Nacional de Portugal\Documentos\python\camoniana\imagens\capas\397670\1\11.jpg | R75: https://permalinkbnd.bnportugal.gov.pt/viewer/273150/?offset=#page=11&viewer=picture&o=info&n=0&q= | U75: pag. assumida 11 | W75: Sim
A76: 397670 | C76: 13 | D76: https://purl.pt/43874 | E76: https://purl.pt/43874 | F76: 273150 | G76: https://permalinkbnd.bnportugal.gov.pt/viewer/ | H76: /?offset=#page= | I76: &viewer=picture&o=info&n=0&q= | J76: =CONCATENATE(G76,F76,H76,C76,I76) -> https://permalinkbnd.bnportugal.gov.pt/viewer/273150/?offset=#page=13&viewer=picture&o=info&n=0&q= | K76: 11, 13 [apontamento sobre o Centenário de Camões, site?] | L76: =VLOOKUP(A76,Folha2!$A$2:$B$2019,2,FALSE) -> Episódio da Ilha de Vénus. Trd. De Cournand, 1880, sem argumento. Bilingue. Trad. Paratextos gerais e Celebrações (1880), traduções. | M76: =HYPERLINK(J76) -> https://permalinkbnd.bnportugal.gov.pt/viewer/273150/?offset=#page=13&viewer=picture&o=info&n=0&q= | N76: C:\Users\mbaptista\OneDrive - Biblioteca Nacional de Portugal\Documentos\python\camoniana\imagens\capas\ | O76: =CONCATENATE(N76,A76,"\",B76,"\",C76,".jpg") -> C:\Users\mbaptista\OneDrive - Biblioteca Nacional de Portugal\Documentos\python\camoniana\imagens\capas\397670\\13.jpg | P76: =HYPERLINK(O76) -> C:\Users\mbaptista\OneDrive - Biblioteca Nacional de Portugal\Documentos\python\camoniana\imagens\capas\397670\\13.jpg
A77: 397818 | B77: 1 | C77: 6 | D77: https://purl.pt/43426 | E77: https://purl.pt/43426 | F77: 272368 | G77: https://permalinkbnd.bnportugal.gov.pt/viewer/ | H77: /?offset=#page= | I77: &viewer=picture&o=info&n=0&q= | J77: =CONCATENATE(G77,F77,H77,C77,I77) -> https://permalinkbnd.bnportugal.gov.pt/viewer/272368/?offset=#page=6&viewer=picture&o=info&n=0&q= | K77: 6, 106 [retrato de Camões, padrão levantado por Vasco da Gama] | L77: =VLOOKUP(A77,Folha2!$A$2:$B$2019,2,FALSE) -> Os Lusíadas. Inocêncio Francisco da Silva, 1891. Paratextos vida e Paratextos argumentos. Iconografia outros [padrão]. | M77: =HYPERLINK(J77) -> https://permalinkbnd.bnportugal.gov.pt/viewer/272368/?offset=#page=6&viewer=picture&o=info&n=0&q= | N77: C:\Users\mbaptista\OneDrive - Biblioteca Nacional de Portugal\Documentos\python\camoniana\imagens\capas\ | O77: =CONCATENATE(N77,A77,"\",B77,"\",C77,".jpg") -> C:\Users\mbaptista\OneDrive - Biblioteca Nacional de Portugal\Documentos\python\camoniana\imagens\capas\397818\1\6.jpg | P77: =HYPERLINK(O77) -> C:\Users\mbaptista\OneDrive - Biblioteca Nacional de Portugal\Documentos\python\camoniana\imagens\capas\397818\1\6.jpg | R77: https://permalinkbnd.bnportugal.gov.pt/viewer/272368/?offset=#page=6&viewer=picture&o=info&n=0&q= | T77: 6 | W77: Sim
A78: 397818 | B78: 1 | C78: 106 | D78: https://purl.pt/43426 | E78: https://purl.pt/43426 | F78: 272368 | G78: https://permalinkbnd.bnportugal.gov.pt/viewer/ | H78: /?offset=#page= | I78: &viewer=picture&o=info&n=0&q= | J78: =CONCATENATE(G78,F78,H78,C78,I78) -> https://permalinkbnd.bnportugal.gov.pt/viewer/272368/?offset=#page=106&viewer=picture&o=info&n=0&q= | K78: 6, 106 [retrato de Camões, padrão levantado por Vasco da Gama] | L78: =VLOOKUP(A78,Folha2!$A$2:$B$2019,2,FALSE) -> Os Lusíadas. Inocêncio Francisco da Silva, 1891. Paratextos vida e Paratextos argumentos. Iconografia outros [padrão]. | M78: =HYPERLINK(J78) -> https://permalinkbnd.bnportugal.gov.pt/viewer/272368/?offset=#page=106&viewer=picture&o=info&n=0&q= | N78: C:\Users\mbaptista\OneDrive - Biblioteca Nacional de Portugal\Documentos\python\camoniana\imagens\capas\ | O78: =CONCATENATE(N78,A78,"\",B78,"\",C78,".jpg") -> C:\Users\mbaptista\OneDrive - Biblioteca Nacional de Portugal\Documentos\python\camoniana\imagens\capas\397818\1\106.jpg | P78: =HYPERLINK(O78) -> C:\Users\mbaptista\OneDrive - Biblioteca Nacional de Portugal\Documentos\python\camoniana\imagens\capas\397818\1\106.jpg
A79: 397822 | B79: 1 | C79: 7 | D79: https://purl.pt/43741 | E79: https://purl.pt/43741 | F79: 274090 | G79: https://permalinkbnd.bnportugal.gov.pt/viewer/ | H79: /?offset=#page= | I79: &viewer=picture&o=info&n=0&q= | J79: =CONCATENATE(G79,F79,H79,C79,I79) -> https://permalinkbnd.bnportugal.gov.pt/viewer/274090/?offset=#page=7&viewer=picture&o=info&n=0&q= | K79: 7, 388 [apontamento site] | L79: =VLOOKUP(A79,Folha2!$A$2:$B$2019,2,FALSE) -> Os Lusíadas, 1898, sem argumentos. Paratextos notas [espécie de didascália]. | M79: =HYPERLINK(J79) -> https://permalinkbnd.bnportugal.gov.pt/viewer/274090/?offset=#page=7&viewer=picture&o=info&n=0&q= | N79: C:\Users\mbaptista\OneDrive - Biblioteca Nacional de Portugal\Documentos\python\camoniana\imagens\capas\ | O79: =CONCATENATE(N79,A79,"\",B79,"\",C79,".jpg") -> C:\Users\mbaptista\OneDrive - Biblioteca Nacional de Portugal\Documentos\python\camoniana\imagens\capas\397822\1\7.jpg | P79: =HYPERLINK(O79) -> C:\Users\mbaptista\OneDrive - Biblioteca Nacional de Portugal\Documentos\python\camoniana\imagens\capas\397822\1\7.jpg | R79: https://permalinkbnd.bnportugal.gov.pt/viewer/274090/?offset=#page=7&viewer=picture&o=info&n=0&q= | U79: pag. assumida 7 | W79: Sim
A80: 397822 | B80: 1 | C80: 388 | D80: https://purl.pt/43741 | E80: https://purl.pt/43741 | F80: 274090 | G80: https://permalinkbnd.bnportugal.gov.pt/viewer/ | H80: /?offset=#page= | I80: &viewer=picture&o=info&n=0&q= | J80: =CONCATENATE(G80,F80,H80,C80,I80) -> https://permalinkbnd.bnportugal.gov.pt/viewer/274090/?offset=#page=388&viewer=picture&o=info&n=0&q= | K80: 7, 388 [apontamento site] | L80: =VLOOKUP(A80,Folha2!$A$2:$B$2019,2,FALSE) -> Os Lusíadas, 1898, sem argumentos. Paratextos notas [espécie de didascália]. | M80: =HYPERLINK(J80) -> https://permalinkbnd.bnportugal.gov.pt/viewer/274090/?offset=#page=388&viewer=picture&o=info&n=0&q= | N80: C:\Users\mbaptista\OneDrive - Biblioteca Nacional de Portugal\Documentos\python\camoniana\imagens\capas\ | O80: =CONCATENATE(N80,A80,"\",B80,"\",C80,".jpg") -> C:\Users\mbaptista\OneDrive - Biblioteca Nacional de Portugal\Documentos\python\camoniana\imagens\capas\397822\1\388.jpg | P80: =HYPERLINK(O80) -> C:\Users\mbaptista\OneDrive - Biblioteca Nacional de Portugal\Documentos\python\camoniana\imagens\capas\397822\1\388.jpg
A81: 397852 | B81: 1 | C81: 14 | D81: https://purl.pt/43811 | E81: https://purl.pt/43811 | F81: 274172 | G81: https://permalinkbnd.bnportugal.gov.pt/viewer/ | H81: /?offset=#page= | I81: &viewer=picture&o=info&n=0&q= | J81: =CONCATENATE(G81,F81,H81,C81,I81) -> https://permalinkbnd.bnportugal.gov.pt/viewer/274172/?offset=#page=14&viewer=picture&o=info&n=0&q= | K81: 14 [vinheta site] | L81: =VLOOKUP(A81,Folha2!$A$2:$B$2019,2,FALSE) -> Les Lusiades (I), Henri Courtois, 1887, sem argumentos. Bilingue. 1.º fascículo, que inclui apenas o C. I. no sétimo aniversário do Tricentenário. Trad. Paratextos gerais e Celebrações (1880), traduções. | M81: =HYPERLINK(J81) -> https://permalinkbnd.bnportugal.gov.pt/viewer/274172/?offset=#page=14&viewer=picture&o=info&n=0&q= | N81: C:\Users\mbaptista\OneDrive - Biblioteca Nacional de Portugal\Documentos\python\camoniana\imagens\capas\ | O81: =CONCATENATE(N81,A81,"\",B81,"\",C81,".jpg") -> C:\Users\mbaptista\OneDrive - Biblioteca Nacional de Portugal\Documentos\python\camoniana\imagens\capas\397852\1\14.jpg | P81: =HYPERLINK(O81) -> C:\Users\mbaptista\OneDrive - Biblioteca Nacional de Portugal\Documentos\python\camoniana\imagens\capas\397852\1\14.jpg | R81: https://permalinkbnd.bnportugal.gov.pt/viewer/274172/?offset=#page=14&viewer=picture&o=info&n=0&q= | U81: pag. assumida 14 | W81: Sim
A82: 397863 | B82: 1 | C82: 11 | D82: https://purl.pt/43931 | E82: https://purl.pt/43931 | F82: 273148 | G82: https://permalinkbnd.bnportugal.gov.pt/viewer/ | H82: /?offset=#page= | I82: &viewer=picture&o=info&n=0&q= | J82: =CONCATENATE(G82,F82,H82,C82,I82) -> https://permalinkbnd.bnportugal.gov.pt/viewer/273148/?offset=#page=11&viewer=picture&o=info&n=0&q= | K82: 11 [portada] | L82: =VLOOKUP(A82,Folha2!$A$2:$B$2019,2,FALSE) -> A ode ao Conde de Redondo, 1884. No quarto aniversário do Tricentenário. | M82: =HYPERLINK(J82) -> https://permalinkbnd.bnportugal.gov.pt/viewer/273148/?offset=#page=11&viewer=picture&o=info&n=0&q= | N82: C:\Users\mbaptista\OneDrive - Biblioteca Nacional de Portugal\Documentos\python\camoniana\imagens\capas\ | O82: =CONCATENATE(N82,A82,"\",B82,"\",C82,".jpg") -> C:\Users\mbaptista\OneDrive - Biblioteca Nacional de Portugal\Documentos\python\camoniana\imagens\capas\397863\1\11.jpg | P82: =HYPERLINK(O82) -> C:\Users\mbaptista\OneDrive - Biblioteca Nacional de Portugal\Documentos\python\camoniana\imagens\capas\397863\1\11.jpg | R82: https://permalinkbnd.bnportugal.gov.pt/viewer/273148/?offset=#page=11&viewer=picture&o=info&n=0&q= | U82: pag. assumida 11 | W82: Sim
A83: 397876 | B83: 1 | C83: 9 | D83: https://purl.pt/43825 | E83: https://purl.pt/43825 | F83: 274230 | G83: https://permalinkbnd.bnportugal.gov.pt/viewer/ | H83: /?offset=#page= | I83: &viewer=picture&o=info&n=0&q= | J83: =CONCATENATE(G83,F83,H83,C83,I83) -> https://permalinkbnd.bnportugal.gov.pt/viewer/274230/?offset=#page=9&viewer=picture&o=info&n=0&q= | K83: 9 | L83: =VLOOKUP(A83,Folha2!$A$2:$B$2019,2,FALSE) -> Sonnets choisis, 1879 . Trad. Paratextos gerais e trad. paratextos notas [em rodapé]. | M83: =HYPERLINK(J83) -> https://permalinkbnd.bnportugal.gov.pt/viewer/274230/?offset=#page=9&viewer=picture&o=info&n=0&q= | N83: C:\Users\mbaptista\OneDrive - Biblioteca Nacional de Portugal\Documentos\python\camoniana\imagens\capas\ | O83: =CONCATENATE(N83,A83,"\",B83,"\",C83,".jpg") -> C:\Users\mbaptista\OneDrive - Biblioteca Nacional de Portugal\Documentos\python\camoniana\imagens\capas\397876\1\9.jpg | P83: =HYPERLINK(O83) -> C:\Users\mbaptista\OneDrive - Biblioteca Nacional de Portugal\Documentos\python\camoniana\imagens\capas\397876\1\9.jpg | R83: https://permalinkbnd.bnportugal.gov.pt/viewer/274230/?offset=#page=9&viewer=picture&o=info&n=0&q= | U83: pag. assumida 9 | W83: Sim
A84: 397877 | B84: 1 | C84: 9 | D84: https://purl.pt/43875 | E84: https://purl.pt/43875 | F84: 1576 | G84: https://permalinkbnd.bnportugal.gov.pt/viewer/ | H84: /?offset=#page= | I84: &viewer=picture&o=info&n=0&q= | J84: =CONCATENATE(G84,F84,H84,C84,I84) -> https://permalinkbnd.bnportugal.gov.pt/viewer/1576/?offset=#page=9&viewer=picture&o=info&n=0&q= | K84: 9 [retrato de Camões] | L84: =VLOOKUP(A84,Folha2!$A$2:$B$2019,2,FALSE) -> Tercetos e um soneto. Magalhães Gandavo, 1894. Tercetos entram em elegias. | M84: =HYPERLINK(J84) -> https://permalinkbnd.bnportugal.gov.pt/viewer/1576/?offset=#page=9&viewer=picture&o=info&n=0&q= | N84: C:\Users\mbaptista\OneDrive - Biblioteca Nacional de Portugal\Documentos\python\camoniana\imagens\capas\ | O84: =CONCATENATE(N84,A84,"\",B84,"\",C84,".jpg") -> C:\Users\mbaptista\OneDrive - Biblioteca Nacional de Portugal\Documentos\python\camoniana\imagens\capas\397877\1\9.jpg | P84: =HYPERLINK(O84) -> C:\Users\mbaptista\OneDrive - Biblioteca Nacional de Portugal\Documentos\python\camoniana\imagens\capas\397877\1\9.jpg | R84: https://permalinkbnd.bnportugal.gov.pt/viewer/1576/?offset=#page=9&viewer=picture&o=info&n=0&q= | T84: 9 | W84: Sim
A85: 401648 | B85: 1 | C85: 1 | D85: https://purl.pt/43662 | E85: https://purl.pt/43662 | F85: 273125 | G85: https://permalinkbnd.bnportugal.gov.pt/viewer/ | H85: /?offset=#page= | I85: &viewer=picture&o=info&n=0&q= | J85: =CONCATENATE(G85,F85,H85,C85,I85) -> https://permalinkbnd.bnportugal.gov.pt/viewer/273125/?offset=#page=1&viewer=picture&o=info&n=0&q= | K85: 1, 3 [site] [portada, retrato Camões] | L85: =VLOOKUP(A85,Folha2!$A$2:$B$2019,2,FALSE) -> Plutarcho Portuguez+Retrato 1881. Inserir em Celebrações (1880), vida. | M85: =HYPERLINK(J85) -> https://permalinkbnd.bnportugal.gov.pt/viewer/273125/?offset=#page=1&viewer=picture&o=info&n=0&q= | N85: C:\Users\mbaptista\OneDrive - Biblioteca Nacional de Portugal\Documentos\python\camoniana\imagens\capas\ | O85: =CONCATENATE(N85,A85,"\",B85,"\",C85,".jpg") -> C:\Users\mbaptista\OneDrive - Biblioteca Nacional de Portugal\Documentos\python\camoniana\imagens\capas\401648\1\1.jpg | P85: =HYPERLINK(O85) -> C:\Users\mbaptista\OneDrive - Biblioteca Nacional de Portugal\Documentos\python\camoniana\imagens\capas\401648\1\1.jpg
A86: 401648 | B86: 1 | C86: 3 | D86: https://purl.pt/43662 | E86: https://purl.pt/43662 | F86: 273125 | G86: https://permalinkbnd.bnportugal.gov.pt/viewer/ | H86: /?offset=#page= | I86: &viewer=picture&o=info&n=0&q= | J86: =CONCATENATE(G86,F86,H86,C86,I86) -> https://permalinkbnd.bnportugal.gov.pt/viewer/273125/?offset=#page=3&viewer=picture&o=info&n=0&q= | K86: 1, 3 [site] [portada, retrato Camões] | L86: =VLOOKUP(A86,Folha2!$A$2:$B$2019,2,FALSE) -> Plutarcho Portuguez+Retrato 1881. Inserir em Celebrações (1880), vida. | M86: =HYPERLINK(J86) -> https://permalinkbnd.bnportugal.gov.pt/viewer/273125/?offset=#page=3&viewer=picture&o=info&n=0&q= | N86: C:\Users\mbaptista\OneDrive - Biblioteca Nacional de Portugal\Documentos\python\camoniana\imagens\capas\ | O86: =CONCATENATE(N86,A86,"\",B86,"\",C86,".jpg") -> C:\Users\mbaptista\OneDrive - Biblioteca Nacional de Portugal\Documentos\python\camoniana\imagens\capas\401648\1\3.jpg | P86: =HYPERLINK(O86) -> C:\Users\mbaptista\OneDrive - Biblioteca Nacional de Portugal\Documentos\python\camoniana\imagens\capas\401648\1\3.jpg | R86: https://permalinkbnd.bnportugal.gov.pt/viewer/273125/?offset=#page=3&viewer=picture&o=info&n=0&q= | T86: 3 | W86: Sim
A87: 401658 | B87: 1 | C87: 1 | D87: https://purl.pt/43862 | E87: https://purl.pt/43862 | F87: 3 | G87: https://permalinkbnd.bnportugal.gov.pt/viewer/ | H87: /?offset=#page= | I87: &viewer=picture&o=info&n=0&q= | J87: =CONCATENATE(G87,F87,H87,C87,I87) -> https://permalinkbnd.bnportugal.gov.pt/viewer/3/?offset=#page=1&viewer=picture&o=info&n=0&q= | K87: 1 | L87: =VLOOKUP(A87,Folha2!$A$2:$B$2019,2,FALSE) -> Victor Hugo celebra Camões, 1880. Celebrações (1880), nótulas | M87: =HYPERLINK(J87) -> https://permalinkbnd.bnportugal.gov.pt/viewer/3/?offset=#page=1&viewer=picture&o=info&n=0&q= | N87: C:\Users\mbaptista\OneDrive - Biblioteca Nacional de Portugal\Documentos\python\camoniana\imagens\capas\ | O87: =CONCATENATE(N87,A87,"\",B87,"\",C87,".jpg") -> C:\Users\mbaptista\OneDrive - Biblioteca Nacional de Portugal\Documentos\python\camoniana\imagens\capas\401658\1\1.jpg | P87: =HYPERLINK(O87) -> C:\Users\mbaptista\OneDrive - Biblioteca Nacional de Portugal\Documentos\python\camoniana\imagens\capas\401658\1\1.jpg | R87: https://permalinkbnd.bnportugal.gov.pt/viewer/3/?offset=#page=1&viewer=picture&o=info&n=0&q= | T87: 1 | W87: Sim
A88: 401739 | B88: 1 | C88: 1 | D88: https://purl.pt/43865 | E88: https://purl.pt/43865 | F88: 274260 | G88: https://permalinkbnd.bnportugal.gov.pt/viewer/ | H88: /?offset=#page= | I88: &viewer=picture&o=info&n=0&q= | J88: =CONCATENATE(G88,F88,H88,C88,I88) -> https://permalinkbnd.bnportugal.gov.pt/viewer/274260/?offset=#page=1&viewer=picture&o=info&n=0&q= | K88: 1 | L88: =VLOOKUP(A88,Folha2!$A$2:$B$2019,2,FALSE) -> Homenagem a Camões, 1880 | M88: =HYPERLINK(J88) -> https://permalinkbnd.bnportugal.gov.pt/viewer/274260/?offset=#page=1&viewer=picture&o=info&n=0&q= | N88: C:\Users\mbaptista\OneDrive - Biblioteca Nacional de Portugal\Documentos\python\camoniana\imagens\capas\ | O88: =CONCATENATE(N88,A88,"\",B88,"\",C88,".jpg") -> C:\Users\mbaptista\OneDrive - Biblioteca Nacional de Portugal\Documentos\python\camoniana\imagens\capas\401739\1\1.jpg | P88: =HYPERLINK(O88) -> C:\Users\mbaptista\OneDrive - Biblioteca Nacional de Portugal\Documentos\python\camoniana\imagens\capas\401739\1\1.jpg | R88: https://permalinkbnd.bnportugal.gov.pt/viewer/274260/?offset=#page=1&viewer=picture&o=info&n=0&q= | T88: 1 | W88: Sim
A89: 402086 | B89: 1 | C89: 16 | D89: https://purl.pt/43891 | E89: https://purl.pt/43891 | F89: 274280 | G89: https://permalinkbnd.bnportugal.gov.pt/viewer/ | H89: /?offset=#page= | I89: &viewer=picture&o=info&n=0&q= | J89: =CONCATENATE(G89,F89,H89,C89,I89) -> https://permalinkbnd.bnportugal.gov.pt/viewer/274280/?offset=#page=16&viewer=picture&o=info&n=0&q= | K89: 16 [site], 22 | L89: =VLOOKUP(A89,Folha2!$A$2:$B$2019,2,FALSE) -> José do Canto, Colecção Camoniana, 1895 | M89: =HYPERLINK(J89) -> https://permalinkbnd.bnportugal.gov.pt/viewer/274280/?offset=#page=16&viewer=picture&o=info&n=0&q= | N89: C:\Users\mbaptista\OneDrive - Biblioteca Nacional de Portugal\Documentos\python\camoniana\imagens\capas\ | O89: =CONCATENATE(N89,A89,"\",B89,"\",C89,".jpg") -> C:\Users\mbaptista\OneDrive - Biblioteca Nacional de Portugal\Documentos\python\camoniana\imagens\capas\402086\1\16.jpg | P89: =HYPERLINK(O89) -> C:\Users\mbaptista\OneDrive - Biblioteca Nacional de Portugal\Documentos\python\camoniana\imagens\capas\402086\1\16.jpg | R89: https://permalinkbnd.bnportugal.gov.pt/viewer/274280/?offset=#page=16&viewer=picture&o=info&n=0&q= | T89: 16, 22 | W89: Sim
A90: 402086 | B90: 1 | C90: 22 | D90: https://purl.pt/43891 | E90: https://purl.pt/43891 | F90: 274280 | G90: https://permalinkbnd.bnportugal.gov.pt/viewer/ | H90: /?offset=#page= | I90: &viewer=picture&o=info&n=0&q= | J90: =CONCATENATE(G90,F90,H90,C90,I90) -> https://permalinkbnd.bnportugal.gov.pt/viewer/274280/?offset=#page=22&viewer=picture&o=info&n=0&q= | K90: 16 [site], 22 | L90: =VLOOKUP(A90,Folha2!$A$2:$B$2019,2,FALSE) -> José do Canto, Colecção Camoniana, 1895 | M90: =HYPERLINK(J90) -> https://permalinkbnd.bnportugal.gov.pt/viewer/274280/?offset=#page=22&viewer=picture&o=info&n=0&q= | N90: C:\Users\mbaptista\OneDrive - Biblioteca Nacional de Portugal\Documentos\python\camoniana\imagens\capas\ | O90: =CONCATENATE(N90,A90,"\",B90,"\",C90,".jpg") -> C:\Users\mbaptista\OneDrive - Biblioteca Nacional de Portugal\Documentos\python\camoniana\imagens\capas\402086\1\22.jpg | P90: =HYPERLINK(O90) -> C:\Users\mbaptista\OneDrive - Biblioteca Nacional de Portugal\Documentos\python\camoniana\imagens\capas\402086\1\22.jpg | R90: https://permalinkbnd.bnportugal.gov.pt/viewer/274280/?offset=#page=22&viewer=picture&o=info&n=0&q= | T90: 16, 22 | W90: Sim
A91: 402917 | B91: 1 | C91: 9 | D91: https://purl.pt/43923 | E91: https://purl.pt/43923 | F91: 273560 | G91: https://permalinkbnd.bnportugal.gov.pt/viewer/ | H91: /?offset=#page= | I91: &viewer=picture&o=info&n=0&q= | J91: =CONCATENATE(G91,F91,H91,C91,I91) -> https://permalinkbnd.bnportugal.gov.pt/viewer/273560/?offset=#page=9&viewer=picture&o=info&n=0&q= | K91: 9 | L91: =VLOOKUP(A91,Folha2!$A$2:$B$2019,2,FALSE) -> Adolf Von Schack, Camões em Sinta, 1891. No 311.º aniversário da morte do Poeta: Celebrações Recepção criativa. Tematização. | M91: =HYPERLINK(J91) -> https://permalinkbnd.bnportugal.gov.pt/viewer/273560/?offset=#page=9&viewer=picture&o=info&n=0&q= | N91: C:\Users\mbaptista\OneDrive - Biblioteca Nacional de Portugal\Documentos\python\camoniana\imagens\capas\ | O91: =CONCATENATE(N91,A91,"\",B91,"\",C91,".jpg") -> C:\Users\mbaptista\OneDrive - Biblioteca Nacional de Portugal\Documentos\python\camoniana\imagens\capas\402917\1\9.jpg | P91: =HYPERLINK(O91) -> C:\Users\mbaptista\OneDrive - Biblioteca Nacional de Portugal\Documentos\python\camoniana\imagens\capas\402917\1\9.jpg | R91: https://permalinkbnd.bnportugal.gov.pt/viewer/273560/?offset=#page=9&viewer=picture&o=info&n=0&q= | U91: pag. assumida 9 | W91: Sim
A92: 404543 | B92: 1 | C92: 7 | D92: https://purl.pt/43827 | E92: https://purl.pt/43827 | F92: 273347 | G92: https://permalinkbnd.bnportugal.gov.pt/viewer/ | H92: /?offset=#page= | I92: &viewer=picture&o=info&n=0&q= | J92: =CONCATENATE(G92,F92,H92,C92,I92) -> https://permalinkbnd.bnportugal.gov.pt/viewer/273347/?offset=#page=7&viewer=picture&o=info&n=0&q= | K92: 7 | L92: =VLOOKUP(A92,Folha2!$A$2:$B$2019,2,FALSE) -> Excertos d'Os Lusíadas, canto II, 1889. Vénus e os Portugueses, Canto III, Inês de Castro e Batalha de Salado; C. IV: Batalha de Aljubarrota; C. V: Adamastor; C. VI: Os Doze; C. IX: Ilha dos Amores, sem argumentos. | M92: =HYPERLINK(J92) -> https://permalinkbnd.bnportugal.gov.pt/viewer/273347/?offset=#page=7&viewer=picture&o=info&n=0&q= | N92: C:\Users\mbaptista\OneDrive - Biblioteca Nacional de Portugal\Documentos\python\camoniana\imagens\capas\ | O92: =CONCATENATE(N92,A92,"\",B92,"\",C92,".jpg") -> C:\Users\mbaptista\OneDrive - Biblioteca Nacional de Portugal\Documentos\python\camoniana\imagens\capas\404543\1\7.jpg | P92: =HYPERLINK(O92) -> C:\Users\mbaptista\OneDrive - Biblioteca Nacional de Portugal\Documentos\python\camoniana\imagens\capas\404543\1\7.jpg | R92: https://permalinkbnd.bnportugal.gov.pt/viewer/273347/?offset=#page=7&viewer=picture&o=info&n=0&q= | U92: pag. assumida 7 | W92: Sim
A93: 404800 | B93: 1 | C93: 3 | D93: https://purl.pt/43914 | E93: https://purl.pt/43914 | F93: 274348 | G93: https://permalinkbnd.bnportugal.gov.pt/viewer/ | H93: /?offset=#page= | I93: &viewer=picture&o=info&n=0&q= | J93: =CONCATENATE(G93,F93,H93,C93,I93) -> https://permalinkbnd.bnportugal.gov.pt/viewer/274348/?offset=#page=3&viewer=picture&o=info&n=0&q= | K93: 3, 21, 69 | L93: =VLOOKUP(A93,Folha2!$A$2:$B$2019,2,FALSE) -> Os festejos do centenário da Índia, 1898. 4.º centenário da Índia. A inserir celebrações (1898), iconografia. | M93: =HYPERLINK(J93) -> https://permalinkbnd.bnportugal.gov.pt/viewer/274348/?offset=#page=3&viewer=picture&o=info&n=0&q= | N93: C:\Users\mbaptista\OneDrive - Biblioteca Nacional de Portugal\Documentos\python\camoniana\imagens\capas\ | O93: =CONCATENATE(N93,A93,"\",B93,"\",C93,".jpg") -> C:\Users\mbaptista\OneDrive - Biblioteca Nacional de Portugal\Documentos\python\camoniana\imagens\capas\404800\1\3.jpg | P93: =HYPERLINK(O93) -> C:\Users\mbaptista\OneDrive - Biblioteca Nacional de Portugal\Documentos\python\camoniana\imagens\capas\404800\1\3.jpg
A94: 404800 | B94: 1 | C94: 21 | D94: https://purl.pt/43914 | E94: https://purl.pt/43914 | F94: 274348 | G94: https://permalinkbnd.bnportugal.gov.pt/viewer/ | H94: /?offset=#page= | I94: &viewer=picture&o=info&n=0&q= | J94: =CONCATENATE(G94,F94,H94,C94,I94) -> https://permalinkbnd.bnportugal.gov.pt/viewer/274348/?offset=#page=21&viewer=picture&o=info&n=0&q= | K94: 3, 21, 69 | L94: =VLOOKUP(A94,Folha2!$A$2:$B$2019,2,FALSE) -> Os festejos do centenário da Índia, 1898. 4.º centenário da Índia. A inserir celebrações (1898), iconografia. | M94: =HYPERLINK(J94) -> https://permalinkbnd.bnportugal.gov.pt/viewer/274348/?offset=#page=21&viewer=picture&o=info&n=0&q= | N94: C:\Users\mbaptista\OneDrive - Biblioteca Nacional de Portugal\Documentos\python\camoniana\imagens\capas\ | O94: =CONCATENATE(N94,A94,"\",B94,"\",C94,".jpg") -> C:\Users\mbaptista\OneDrive - Biblioteca Nacional de Portugal\Documentos\python\camoniana\imagens\capas\404800\1\21.jpg | P94: =HYPERLINK(O94) -> C:\Users\mbaptista\OneDrive - Biblioteca Nacional de Portugal\Documentos\python\camoniana\imagens\capas\404800\1\21.jpg | R94: https://permalinkbnd.bnportugal.gov.pt/viewer/274348/?offset=#page=21&viewer=picture&o=info&n=0&q= | T94: 21, 69 | W94: Sim
A95: 404800 | B95: 1 | C95: 69 | D95: https://purl.pt/43914 | E95: https://purl.pt/43914 | F95: 274348 | G95: https://permalinkbnd.bnportugal.gov.pt/viewer/ | H95: /?offset=#page= | I95: &viewer=picture&o=info&n=0&q= | J95: =CONCATENATE(G95,F95,H95,C95,I95) -> https://permalinkbnd.bnportugal.gov.pt/viewer/274348/?offset=#page=69&viewer=picture&o=info&n=0&q= | K95: 3, 21, 69 | L95: =VLOOKUP(A95,Folha2!$A$2:$B$2019,2,FALSE) -> Os festejos do centenário da Índia, 1898. 4.º centenário da Índia. A inserir celebrações (1898), iconografia. | M95: =HYPERLINK(J95) -> https://permalinkbnd.bnportugal.gov.pt/viewer/274348/?offset=#page=69&viewer=picture&o=info&n=0&q= | N95: C:\Users\mbaptista\OneDrive - Biblioteca Nacional de Portugal\Documentos\python\camoniana\imagens\capas\ | O95: =CONCATENATE(N95,A95,"\",B95,"\",C95,".jpg") -> C:\Users\mbaptista\OneDrive - Biblioteca Nacional de Portugal\Documentos\python\camoniana\imagens\capas\404800\1\69.jpg | P95: =HYPERLINK(O95) -> C:\Users\mbaptista\OneDrive - Biblioteca Nacional de Portugal\Documentos\python\camoniana\imagens\capas\404800\1\69.jpg | R95: https://permalinkbnd.bnportugal.gov.pt/viewer/274348/?offset=#page=69&viewer=picture&o=info&n=0&q= | T95: 21, 69 | W95: Sim
A96: 410449 | B96: 1 | C96: 6 | D96: https://purl.pt/43911 | E96: https://purl.pt/43911 | F96: 274346 | G96: https://permalinkbnd.bnportugal.gov.pt/viewer/ | H96: /?offset=#page= | I96: &viewer=picture&o=info&n=0&q= | J96: =CONCATENATE(G96,F96,H96,C96,I96) -> https://permalinkbnd.bnportugal.gov.pt/viewer/274346/?offset=#page=6&viewer=picture&o=info&n=0&q= | K96: 6 [site] | L96: =VLOOKUP(A96,Folha2!$A$2:$B$2019,2,FALSE) -> Los Lusiadas, D. Carlos Soler y Arques, 1873. Bilingue, sem argumentos. Trad. Paratextos; Trad. Paratextos notas; Trad. Paratextos vida. Celebrações 1872, ainda que sem referência explícita. | M96: =HYPERLINK(J96) -> https://permalinkbnd.bnportugal.gov.pt/viewer/274346/?offset=#page=6&viewer=picture&o=info&n=0&q= | N96: C:\Users\mbaptista\OneDrive - Biblioteca Nacional de Portugal\Documentos\python\camoniana\imagens\capas\ | O96: =CONCATENATE(N96,A96,"\",B96,"\",C96,".jpg") -> C:\Users\mbaptista\OneDrive - Biblioteca Nacional de Portugal\Documentos\python\camoniana\imagens\capas\410449\1\6.jpg | P96: =HYPERLINK(O96) -> C:\Users\mbaptista\OneDrive - Biblioteca Nacional de Portugal\Documentos\python\camoniana\imagens\capas\410449\1\6.jpg | R96: https://permalinkbnd.bnportugal.gov.pt/viewer/274346/?offset=#page=6&viewer=picture&o=info&n=0&q= | T96: 6 | W96: Sim
A97: 411542 | B97: 1 | C97: 1 | D97: https://purl.pt/43786 | E97: https://purl.pt/43786 | F97: 273798 | G97: https://permalinkbnd.bnportugal.gov.pt/viewer/ | H97: /?offset=#page= | I97: &viewer=picture&o=info&n=0&q= | J97: =CONCATENATE(G97,F97,H97,C97,I97) -> https://permalinkbnd.bnportugal.gov.pt/viewer/273798/?offset=#page=1&viewer=picture&o=info&n=0&q= | K97: 1 | L97: =VLOOKUP(A97,Folha2!$A$2:$B$2019,2,FALSE) -> Magalhães Lima, O centenário no estrangeiro, 1897 conferência. | M97: =HYPERLINK(J97) -> https://permalinkbnd.bnportugal.gov.pt/viewer/273798/?offset=#page=1&viewer=picture&o=info&n=0&q= | N97: C:\Users\mbaptista\OneDrive - Biblioteca Nacional de Portugal\Documentos\python\camoniana\imagens\capas\ | O97: =CONCATENATE(N97,A97,"\",B97,"\",C97,".jpg") -> C:\Users\mbaptista\OneDrive - Biblioteca Nacional de Portugal\Documentos\python\camoniana\imagens\capas\411542\1\1.jpg | P97: =HYPERLINK(O97) -> C:\Users\mbaptista\OneDrive - Biblioteca Nacional de Portugal\Documentos\python\camoniana\imagens\capas\411542\1\1.jpg | R97: https://permalinkbnd.bnportugal.gov.pt/viewer/273798/?offset=#page=1&viewer=picture&o=info&n=0&q= | U97: pag. assumida 1 | W97: Sim
A98: 426512 | B98: 1 | C98: 1 | D98: https://purl.pt/43588 | E98: https://purl.pt/43588 | F98: 272882 | G98: https://permalinkbnd.bnportugal.gov.pt/viewer/ | H98: /?offset=#page= | I98: &viewer=picture&o=info&n=0&q= | J98: =CONCATENATE(G98,F98,H98,C98,I98) -> https://permalinkbnd.bnportugal.gov.pt/viewer/272882/?offset=#page=1&viewer=picture&o=info&n=0&q= | K98: 1 | L98: =VLOOKUP(A98,Folha2!$A$2:$B$2019,2,FALSE) -> D. Maria Cornélia Pacheco, Homenagem a Camões. Lamentações de Jau, 187? | M98: =HYPERLINK(J98) -> https://permalinkbnd.bnportugal.gov.pt/viewer/272882/?offset=#page=1&viewer=picture&o=info&n=0&q= | N98: C:\Users\mbaptista\OneDrive - Biblioteca Nacional de Portugal\Documentos\python\camoniana\imagens\capas\ | O98: =CONCATENATE(N98,A98,"\",B98,"\",C98,".jpg") -> C:\Users\mbaptista\OneDrive - Biblioteca Nacional de Portugal\Documentos\python\camoniana\imagens\capas\426512\1\1.jpg | P98: =HYPERLINK(O98) -> C:\Users\mbaptista\OneDrive - Biblioteca Nacional de Portugal\Documentos\python\camoniana\imagens\capas\426512\1\1.jpg | R98: https://permalinkbnd.bnportugal.gov.pt/viewer/272882/?offset=#page=1&viewer=picture&o=info&n=0&q= | T98: 1 | W98: Sim
A99: 446302 | B99: 1 | C99: 11 | D99: https://purl.pt/43429 | E99: https://purl.pt/43429 | F99: 1880 | G99: https://permalinkbnd.bnportugal.gov.pt/viewer/ | H99: /?offset=#page= | I99: &viewer=picture&o=info&n=0&q= | J99: =CONCATENATE(G99,F99,H99,C99,I99) -> https://permalinkbnd.bnportugal.gov.pt/viewer/1880/?offset=#page=11&viewer=picture&o=info&n=0&q= | K99: 11 | L99: =VLOOKUP(A99,Folha2!$A$2:$B$2019,2,FALSE) -> Primeiros documentos para a história da comemoração camoniana de 1880, 1887. | M99: =HYPERLINK(J99) -> https://permalinkbnd.bnportugal.gov.pt/viewer/1880/?offset=#page=11&viewer=picture&o=info&n=0&q= | N99: C:\Users\mbaptista\OneDrive - Biblioteca Nacional de Portugal\Documentos\python\camoniana\imagens\capas\ | O99: =CONCATENATE(N99,A99,"\",B99,"\",C99,".jpg") -> C:\Users\mbaptista\OneDrive - Biblioteca Nacional de Portugal\Documentos\python\camoniana\imagens\capas\446302\1\11.jpg | P99: =HYPERLINK(O99) -> C:\Users\mbaptista\OneDrive - Biblioteca Nacional de Portugal\Documentos\python\camoniana\imagens\capas\446302\1\11.jpg | R99: https://permalinkbnd.bnportugal.gov.pt/viewer/1880/?offset=#page=11&viewer=picture&o=info&n=0&q= | W99: Sim
A100: 452363 | B100: 1 | C100: 1 | D100: https://purl.pt/11841 | E100: https://purl.pt/11841 | F100: 35644 | G100: https://permalinkbnd.bnportugal.gov.pt/viewer/ | H100: /?offset=#page= | I100: &viewer=picture&o=info&n=0&q= | J100: =CONCATENATE(G100,F100,H100,C100,I100) -> https://permalinkbnd.bnportugal.gov.pt/viewer/35644/?offset=#page=1&viewer=picture&o=info&n=0&q= | K100: 1 site | L100: =VLOOKUP(A100,Folha2!$A$2:$B$2019,2,FALSE) -> Lubin David, Camões, 1887? | M100: =HYPERLINK(J100) -> https://permalinkbnd.bnportugal.gov.pt/viewer/35644/?offset=#page=1&viewer=picture&o=info&n=0&q= | N100: C:\Users\mbaptista\OneDrive - Biblioteca Nacional de Portugal\Documentos\python\camoniana\imagens\capas\ | O100: =CONCATENATE(N100,A100,"\",B100,"\",C100,".jpg") -> C:\Users\mbaptista\OneDrive - Biblioteca Nacional de Portugal\Documentos\python\camoniana\imagens\capas\452363\1\1.jpg | P100: =HYPERLINK(O100) -> C:\Users\mbaptista\OneDrive - Biblioteca Nacional de Portugal\Documentos\python\camoniana\imagens\capas\452363\1\1.jpg | R100: https://permalinkbnd.bnportugal.gov.pt/viewer/35644/?offset=#page=1&viewer=picture&o=info&n=0&q= | T100: 1 | W100: Sim
A101: 453897 | B101: 1 | C101: 9 | D101: https://purl.pt/43792 | E101: https://purl.pt/43792 | F101: 1880 | G101: https://permalinkbnd.bnportugal.gov.pt/viewer/ | H101: /?offset=#page= | I101: &viewer=picture&o=info&n=0&q= | J101: =CONCATENATE(G101,F101,H101,C101,I101) -> https://permalinkbnd.bnportugal.gov.pt/viewer/1880/?offset=#page=9&viewer=picture&o=info&n=0&q= | K101: 9 | L101: =VLOOKUP(A101,Folha2!$A$2:$B$2019,2,FALSE) -> À memória de Luís de Camões, 1880. Excerto do episódio Os doze. In A sentinela, semanário bracarense. | M101: =HYPERLINK(J101) -> https://permalinkbnd.bnportugal.gov.pt/viewer/1880/?offset=#page=9&viewer=picture&o=info&n=0&q= | N101: C:\Users\mbaptista\OneDrive - Biblioteca Nacional de Portugal\Documentos\python\camoniana\imagens\capas\ | O101: =CONCATENATE(N101,A101,"\",B101,"\",C101,".jpg") -> C:\Users\mbaptista\OneDrive - Biblioteca Nacional de Portugal\Documentos\python\camoniana\imagens\capas\453897\1\9.jpg | P101: =HYPERLINK(O101) -> C:\Users\mbaptista\OneDrive - Biblioteca Nacional de Portugal\Documentos\python\camoniana\imagens\capas\453897\1\9.jpg | R101: https://permalinkbnd.bnportugal.gov.pt/viewer/1880/?offset=#page=9&viewer=picture&o=info&n=0&q= | T101: 9 | W101: Sim
A102: 454218 | B102: 1 | C102: 3 | D102: https://purl.pt/43793 | E102: https://purl.pt/43793 | F102: 273923 | G102: https://permalinkbnd.bnportugal.gov.pt/viewer/ | H102: /?offset=#page= | I102: &viewer=picture&o=info&n=0&q= | J102: =CONCATENATE(G102,F102,H102,C102,I102) -> https://permalinkbnd.bnportugal.gov.pt/viewer/273923/?offset=#page=3&viewer=picture&o=info&n=0&q= | K102: 3 | L102: =VLOOKUP(A102,Folha2!$A$2:$B$2019,2,FALSE) -> Vida de Luís de Camões e seu retrato (retoma o texto de 1772), 1881 | M102: =HYPERLINK(J102) -> https://permalinkbnd.bnportugal.gov.pt/viewer/273923/?offset=#page=3&viewer=picture&o=info&n=0&q= | N102: C:\Users\mbaptista\OneDrive - Biblioteca Nacional de Portugal\Documentos\python\camoniana\imagens\capas\ | O102: =CONCATENATE(N102,A102,"\",B102,"\",C102,".jpg") -> C:\Users\mbaptista\OneDrive - Biblioteca Nacional de Portugal\Documentos\python\camoniana\imagens\capas\454218\1\3.jpg | P102: =HYPERLINK(O102) -> C:\Users\mbaptista\OneDrive - Biblioteca Nacional de Portugal\Documentos\python\camoniana\imagens\capas\454218\1\3.jpg | R102: https://permalinkbnd.bnportugal.gov.pt/viewer/273923/?offset=#page=3&viewer=picture&o=info&n=0&q= | T102: 3 | W102: Sim
A103: 455268 | B103: 1 | C103: 8 | D103: https://purl.pt/42934 | E103: https://purl.pt/42934 | F103: 270331 | G103: https://permalinkbnd.bnportugal.gov.pt/viewer/ | H103: /?offset=#page= | I103: &viewer=picture&o=info&n=0&q= | J103: =CONCATENATE(G103,F103,H103,C103,I103) -> https://permalinkbnd.bnportugal.gov.pt/viewer/270331/?offset=#page=8&viewer=picture&o=info&n=0&q= | K103: 8, 62 [1.º: retrato de Camões e visita do Rei de Melinde a V. da Gama] 8 [2.º: Vasco da Gama em Calecute] | L103: =VLOOKUP(A103,Folha2!$A$2:$B$2019,2,FALSE) -> I Lusiadi, Antonio Nervi, 1821, 2.ª ed. 2 Vols [1.º: até ao C. V, com notas; 2.º até ao C. X, com notas]. Trad. Paratextos; Trad. Paratextos vida; Trad. Paratextos notas; Trad. Paratextos argumentos; Mulheres [M. de Staël]. | M103: =HYPERLINK(J103) -> https://permalinkbnd.bnportugal.gov.pt/viewer/270331/?offset=#page=8&viewer=picture&o=info&n=0&q= | N103: C:\Users\mbaptista\OneDrive - Biblioteca Nacional de Portugal\Documentos\python\camoniana\imagens\capas\ | O103: =CONCATENATE(N103,A103,"\",B103,"\",C103,".jpg") -> C:\Users\mbaptista\OneDrive - Biblioteca Nacional de Portugal\Documentos\python\camoniana\imagens\capas\455268\1\8.jpg | P103: =HYPERLINK(O103) -> C:\Users\mbaptista\OneDrive - Biblioteca Nacional de Portugal\Documentos\python\camoniana\imagens\capas\455268\1\8.jpg | R103: https://permalinkbnd.bnportugal.gov.pt/viewer/270331/?offset=#page=8&viewer=picture&o=info&n=0&q= | T103: 8, 62, 8 | W103: Sim
A104: 455268 | B104: 1 | C104: 62 | D104: https://purl.pt/42934 | E104: https://purl.pt/42934 | F104: 270331 | G104: https://permalinkbnd.bnportugal.gov.pt/viewer/ | H104: /?offset=#page= | I104: &viewer=picture&o=info&n=0&q= | J104: =CONCATENATE(G104,F104,H104,C104,I104) -> https://permalinkbnd.bnportugal.gov.pt/viewer/270331/?offset=#page=62&viewer=picture&o=info&n=0&q= | K104: 8, 62 [1.º: retrato de Camões e visita do Rei de Melinde a V. da Gama] 8 [2.º: Vasco da Gama em Calecute] | L104: =VLOOKUP(A104,Folha2!$A$2:$B$2019,2,FALSE) -> I Lusiadi, Antonio Nervi, 1821, 2.ª ed. 2 Vols [1.º: até ao C. V, com notas; 2.º até ao C. X, com notas]. Trad. Paratextos; Trad. Paratextos vida; Trad. Paratextos notas; Trad. Paratextos argumentos; Mulheres [M. de Staël]. | M104: =HYPERLINK(J104) -> https://permalinkbnd.bnportugal.gov.pt/viewer/270331/?offset=#page=62&viewer=picture&o=info&n=0&q= | N104: C:\Users\mbaptista\OneDrive - Biblioteca Nacional de Portugal\Documentos\python\camoniana\imagens\capas\ | O104: =CONCATENATE(N104,A104,"\",B104,"\",C104,".jpg") -> C:\Users\mbaptista\OneDrive - Biblioteca Nacional de Portugal\Documentos\python\camoniana\imagens\capas\455268\1\62.jpg | P104: =HYPERLINK(O104) -> C:\Users\mbaptista\OneDrive - Biblioteca Nacional de Portugal\Documentos\python\camoniana\imagens\capas\455268\1\62.jpg | R104: https://permalinkbnd.bnportugal.gov.pt/viewer/270331/?offset=#page=62&viewer=picture&o=info&n=0&q= | T104: 8, 62, 8 | W104: Sim
A105: 455268 | B105: 2 | C105: 8 | D105: https://purl.pt/42934 | E105: https://purl.pt/42934 | F105: 270331 | G105: https://permalinkbnd.bnportugal.gov.pt/viewer/ | H105: /?offset=#page= | I105: &viewer=picture&o=info&n=0&q= | J105: =CONCATENATE(G105,F105,H105,C105,I105) -> https://permalinkbnd.bnportugal.gov.pt/viewer/270331/?offset=#page=8&viewer=picture&o=info&n=0&q= | K105: 8, 62 [1.º: retrato de Camões e visita do Rei de Melinde a V. da Gama] 8 [2.º: Vasco da Gama em Calecute] | L105: =VLOOKUP(A105,Folha2!$A$2:$B$2019,2,FALSE) -> I Lusiadi, Antonio Nervi, 1821, 2.ª ed. 2 Vols [1.º: até ao C. V, com notas; 2.º até ao C. X, com notas]. Trad. Paratextos; Trad. Paratextos vida; Trad. Paratextos notas; Trad. Paratextos argumentos; Mulheres [M. de Staël]. | M105: https://permalinkbnd.bnportugal.gov.pt/viewer/270331/?medianame=cam-409-v_0000_&o=volume#page=8&viewer=picture&o=volume&n=0&q= | N105: C:\Users\mbaptista\OneDrive - Biblioteca Nacional de Portugal\Documentos\python\camoniana\imagens\capas\ | O105: =CONCATENATE(N105,A105,"\",B105,"\",C105,".jpg") -> C:\Users\mbaptista\OneDrive - Biblioteca Nacional de Portugal\Documentos\python\camoniana\imagens\capas\455268\2\8.jpg | P105: =HYPERLINK(O105) -> C:\Users\mbaptista\OneDrive - Biblioteca Nacional de Portugal\Documentos\python\camoniana\imagens\capas\455268\2\8.jpg | R105: https://permalinkbnd.bnportugal.gov.pt/viewer/270331/?offset=#page=8&viewer=picture&o=info&n=0&q= | T105: 8, 62, 8 | W105: Sim
A106: 455275 | B106: 1 | C106: 10 | D106: https://purl.pt/42943 | E106: https://purl.pt/42943 | F106: 270345 | G106: https://permalinkbnd.bnportugal.gov.pt/viewer/ | H106: /?offset=#page= | I106: &viewer=picture&o=info&n=0&q= | J106: =CONCATENATE(G106,F106,H106,C106,I106) -> https://permalinkbnd.bnportugal.gov.pt/viewer/270345/?offset=#page=10&viewer=picture&o=info&n=0&q= | K106: 10, 13 [1.º: retrato de Camões, portada, 426 apontamento caravela; 3.º: 154, apontamento site] | L106: =VLOOKUP(A106,Folha2!$A$2:$B$2019,2,FALSE) -> Obras Completas, 1843. 3 Vols. [1.º Épica, com notas sobre os Cantos, sem argumentos; 2.º Lírica: sonetos, éclogas, canções, odes, com notas; 3.º Cont. Lírica: redondilhas, sôbolos rios, cartas poema, convites, mote, disparates, cantiga, endechas, sextinas, elegias, trovas, esparsas, vilancete, epístolas, oitavas; Teatro: Seleuco, Anfitriões, Filodemo; Cartas; notas até às cartas] Paratextos vida; Paratextos notas [épica, lírica e cartas]. | M106: =HYPERLINK(J106) -> https://permalinkbnd.bnportugal.gov.pt/viewer/270345/?offset=#page=10&viewer=picture&o=info&n=0&q= | N106: C:\Users\mbaptista\OneDrive - Biblioteca Nacional de Portugal\Documentos\python\camoniana\imagens\capas\ | O106: =CONCATENATE(N106,A106,"\",B106,"\",C106,".jpg") -> C:\Users\mbaptista\OneDrive - Biblioteca Nacional de Portugal\Documentos\python\camoniana\imagens\capas\455275\1\10.jpg | P106: =HYPERLINK(O106) -> C:\Users\mbaptista\OneDrive - Biblioteca Nacional de Portugal\Documentos\python\camoniana\imagens\capas\455275\1\10.jpg | R106: https://permalinkbnd.bnportugal.gov.pt/viewer/270345/?offset=#page=10&viewer=picture&o=info&n=0&q= | T106: 10 | W106: Sim
A107: 455275 | B107: 1 | C107: 13 | D107: https://purl.pt/42943 | E107: https://purl.pt/42943 | F107: 270345 | G107: https://permalinkbnd.bnportugal.gov.pt/viewer/ | H107: /?offset=#page= | I107: &viewer=picture&o=info&n=0&q= | J107: =CONCATENATE(G107,F107,H107,C107,I107) -> https://permalinkbnd.bnportugal.gov.pt/viewer/270345/?offset=#page=13&viewer=picture&o=info&n=0&q= | K107: 10, 13 [1.º: retrato de Camões, portada, 426 apontamento caravela; 3.º: 154, apontamento site] | L107: =VLOOKUP(A107,Folha2!$A$2:$B$2019,2,FALSE) -> Obras Completas, 1843. 3 Vols. [1.º Épica, com notas sobre os Cantos, sem argumentos; 2.º Lírica: sonetos, éclogas, canções, odes, com notas; 3.º Cont. Lírica: redondilhas, sôbolos rios, cartas poema, convites, mote, disparates, cantiga, endechas, sextinas, elegias, trovas, esparsas, vilancete, epístolas, oitavas; Teatro: Seleuco, Anfitriões, Filodemo; Cartas; notas até às cartas] Paratextos vida; Paratextos notas [épica, lírica e cartas]. | M107: =HYPERLINK(J107) -> https://permalinkbnd.bnportugal.gov.pt/viewer/270345/?offset=#page=13&viewer=picture&o=info&n=0&q= | N107: C:\Users\mbaptista\OneDrive - Biblioteca Nacional de Portugal\Documentos\python\camoniana\imagens\capas\ | O107: =CONCATENATE(N107,A107,"\",B107,"\",C107,".jpg") -> C:\Users\mbaptista\OneDrive - Biblioteca Nacional de Portugal\Documentos\python\camoniana\imagens\capas\455275\1\13.jpg | P107: =HYPERLINK(O107) -> C:\Users\mbaptista\OneDrive - Biblioteca Nacional de Portugal\Documentos\python\camoniana\imagens\capas\455275\1\13.jpg
A108: 455275 | B108: 1 | C108: 426 | D108: https://purl.pt/42943 | E108: https://purl.pt/42943 | F108: 270345 | G108: https://permalinkbnd.bnportugal.gov.pt/viewer/ | H108: /?offset=#page= | I108: &viewer=picture&o=info&n=0&q= | J108: =CONCATENATE(G108,F108,H108,C108,I108) -> https://permalinkbnd.bnportugal.gov.pt/viewer/270345/?offset=#page=426&viewer=picture&o=info&n=0&q= | K108: 10, 13 [1.º: retrato de Camões, portada, 426 apontamento caravela; 3.º: 154, apontamento site] | L108: =VLOOKUP(A108,Folha2!$A$2:$B$2019,2,FALSE) -> Obras Completas, 1843. 3 Vols. [1.º Épica, com notas sobre os Cantos, sem argumentos; 2.º Lírica: sonetos, éclogas, canções, odes, com notas; 3.º Cont. Lírica: redondilhas, sôbolos rios, cartas poema, convites, mote, disparates, cantiga, endechas, sextinas, elegias, trovas, esparsas, vilancete, epístolas, oitavas; Teatro: Seleuco, Anfitriões, Filodemo; Cartas; notas até às cartas] Paratextos vida; Paratextos notas [épica, lírica e cartas]. | M108: =HYPERLINK(J108) -> https://permalinkbnd.bnportugal.gov.pt/viewer/270345/?offset=#page=426&viewer=picture&o=info&n=0&q= | N108: C:\Users\mbaptista\OneDrive - Biblioteca Nacional de Portugal\Documentos\python\camoniana\imagens\capas\ | O108: =CONCATENATE(N108,A108,"\",B108,"\",C108,".jpg") -> C:\Users\mbaptista\OneDrive - Biblioteca Nacional de Portugal\Documentos\python\camoniana\imagens\capas\455275\1\426.jpg | P108: =HYPERLINK(O108) -> C:\Users\mbaptista\OneDrive - Biblioteca Nacional de Portugal\Documentos\python\camoniana\imagens\capas\455275\1\426.jpg
A109: 455275 | B109: 3 | C109: 154 | D109: https://purl.pt/42943 | E109: https://purl.pt/42943 | F109: 270345 | G109: https://permalinkbnd.bnportugal.gov.pt/viewer/ | H109: /?offset=#page= | I109: &viewer=picture&o=info&n=0&q= | J109: =CONCATENATE(G109,F109,H109,C109,I109) -> https://permalinkbnd.bnportugal.gov.pt/viewer/270345/?offset=#page=154&viewer=picture&o=info&n=0&q= | K109: 10, 13 [1.º: retrato de Camões, portada, 426 apontamento caravela; 3.º: 154, apontamento site] | L109: =VLOOKUP(A109,Folha2!$A$2:$B$2019,2,FALSE) -> Obras Completas, 1843. 3 Vols. [1.º Épica, com notas sobre os Cantos, sem argumentos; 2.º Lírica: sonetos, éclogas, canções, odes, com notas; 3.º Cont. Lírica: redondilhas, sôbolos rios, cartas poema, convites, mote, disparates, cantiga, endechas, sextinas, elegias, trovas, esparsas, vilancete, epístolas, oitavas; Teatro: Seleuco, Anfitriões, Filodemo; Cartas; notas até às cartas] Paratextos vida; Paratextos notas [épica, lírica e cartas]. | M109: https://permalinkbnd.bnportugal.gov.pt/viewer/270345/?medianame=cam-412-v_0000_&o=volume#page=154&viewer=picture&o=volume&n=0&q= | N109: C:\Users\mbaptista\OneDrive - Biblioteca Nacional de Portugal\Documentos\python\camoniana\imagens\capas\ | O109: =CONCATENATE(N109,A109,"\",B109,"\",C109,".jpg") -> C:\Users\mbaptista\OneDrive - Biblioteca Nacional de Portugal\Documentos\python\camoniana\imagens\capas\455275\3\154.jpg | P109: =HYPERLINK(O109) -> C:\Users\mbaptista\OneDrive - Biblioteca Nacional de Portugal\Documentos\python\camoniana\imagens\capas\455275\3\154.jpg
A110: 458290 | B110: 1 | C110: 10 | D110: https://purl.pt/43921 | E110: https://purl.pt/43921 | F110: 273525 | G110: https://permalinkbnd.bnportugal.gov.pt/viewer/ | H110: /?offset=#page= | I110: &viewer=picture&o=info&n=0&q= | J110: =CONCATENATE(G110,F110,H110,C110,I110) -> https://permalinkbnd.bnportugal.gov.pt/viewer/273525/?offset=#page=10&viewer=picture&o=info&n=0&q= | K110: 10, 11 [7, 15 e 37 apontamentos site] | L110: =VLOOKUP(A110,Folha2!$A$2:$B$2019,2,FALSE) -> O episódio da Ilha de Vénus+ 2 versões livres em francês, 1890. Recepção criativa em francês. Tematização. Refere em paratexto as celebrações de 1880: Celebrações (1880), recepção criativa, tematização. Imagem 10 de Vénus parece estar esfumada. | M110: =HYPERLINK(J110) -> https://permalinkbnd.bnportugal.gov.pt/viewer/273525/?offset=#page=10&viewer=picture&o=info&n=0&q= | N110: C:\Users\mbaptista\OneDrive - Biblioteca Nacional de Portugal\Documentos\python\camoniana\imagens\capas\ | O110: =CONCATENATE(N110,A110,"\",B110,"\",C110,".jpg") -> C:\Users\mbaptista\OneDrive - Biblioteca Nacional de Portugal\Documentos\python\camoniana\imagens\capas\458290\1\10.jpg | P110: =HYPERLINK(O110) -> C:\Users\mbaptista\OneDrive - Biblioteca Nacional de Portugal\Documentos\python\camoniana\imagens\capas\458290\1\10.jpg | R110: https://permalinkbnd.bnportugal.gov.pt/viewer/273525/?offset=#page=10&viewer=picture&o=info&n=0&q= | T110: 10 | U110: imagem pouco vísivel | W110: Sim
A111: 458290 | B111: 1 | C111: 11 | D111: https://purl.pt/43921 | E111: https://purl.pt/43921 | F111: 273525 | G111: https://permalinkbnd.bnportugal.gov.pt/viewer/ | H111: /?offset=#page= | I111: &viewer=picture&o=info&n=0&q= | J111: =CONCATENATE(G111,F111,H111,C111,I111) -> https://permalinkbnd.bnportugal.gov.pt/viewer/273525/?offset=#page=11&viewer=picture&o=info&n=0&q= | K111: 10, 11 [7, 15 e 37 apontamentos site] | L111: =VLOOKUP(A111,Folha2!$A$2:$B$2019,2,FALSE) -> O episódio da Ilha de Vénus+ 2 versões livres em francês, 1890. Recepção criativa em francês. Tematização. Refere em paratexto as celebrações de 1880: Celebrações (1880), recepção criativa, tematização. Imagem 10 de Vénus parece estar esfumada. | M111: =HYPERLINK(J111) -> https://permalinkbnd.bnportugal.gov.pt/viewer/273525/?offset=#page=11&viewer=picture&o=info&n=0&q= | N111: C:\Users\mbaptista\OneDrive - Biblioteca Nacional de Portugal\Documentos\python\camoniana\imagens\capas\ | O111: =CONCATENATE(N111,A111,"\",B111,"\",C111,".jpg") -> C:\Users\mbaptista\OneDrive - Biblioteca Nacional de Portugal\Documentos\python\camoniana\imagens\capas\458290\1\11.jpg | P111: =HYPERLINK(O111) -> C:\Users\mbaptista\OneDrive - Biblioteca Nacional de Portugal\Documentos\python\camoniana\imagens\capas\458290\1\11.jpg
A112: 458290 | B112: 1 | C112: 7 | D112: https://purl.pt/43921 | E112: https://purl.pt/43921 | F112: 273525 | G112: https://permalinkbnd.bnportugal.gov.pt/viewer/ | H112: /?offset=#page= | I112: &viewer=picture&o=info&n=0&q= | J112: =CONCATENATE(G112,F112,H112,C112,I112) -> https://permalinkbnd.bnportugal.gov.pt/viewer/273525/?offset=#page=7&viewer=picture&o=info&n=0&q= | K112: 10, 11 [7, 15 e 37 apontamentos site] | L112: =VLOOKUP(A112,Folha2!$A$2:$B$2019,2,FALSE) -> O episódio da Ilha de Vénus+ 2 versões livres em francês, 1890. Recepção criativa em francês. Tematização. Refere em paratexto as celebrações de 1880: Celebrações (1880), recepção criativa, tematização. Imagem 10 de Vénus parece estar esfumada. | M112: =HYPERLINK(J112) -> https://permalinkbnd.bnportugal.gov.pt/viewer/273525/?offset=#page=7&viewer=picture&o=info&n=0&q= | N112: C:\Users\mbaptista\OneDrive - Biblioteca Nacional de Portugal\Documentos\python\camoniana\imagens\capas\ | O112: =CONCATENATE(N112,A112,"\",B112,"\",C112,".jpg") -> C:\Users\mbaptista\OneDrive - Biblioteca Nacional de Portugal\Documentos\python\camoniana\imagens\capas\458290\1\7.jpg | P112: =HYPERLINK(O112) -> C:\Users\mbaptista\OneDrive - Biblioteca Nacional de Portugal\Documentos\python\camoniana\imagens\capas\458290\1\7.jpg
A113: 458290 | B113: 1 | C113: 15 | D113: https://purl.pt/43921 | E113: https://purl.pt/43921 | F113: 273525 | G113: https://permalinkbnd.bnportugal.gov.pt/viewer/ | H113: /?offset=#page= | I113: &viewer=picture&o=info&n=0&q= | J113: =CONCATENATE(G113,F113,H113,C113,I113) -> https://permalinkbnd.bnportugal.gov.pt/viewer/273525/?offset=#page=15&viewer=picture&o=info&n=0&q= | K113: 10, 11 [7, 15 e 37 apontamentos site] | L113: =VLOOKUP(A113,Folha2!$A$2:$B$2019,2,FALSE) -> O episódio da Ilha de Vénus+ 2 versões livres em francês, 1890. Recepção criativa em francês. Tematização. Refere em paratexto as celebrações de 1880: Celebrações (1880), recepção criativa, tematização. Imagem 10 de Vénus parece estar esfumada. | M113: =HYPERLINK(J113) -> https://permalinkbnd.bnportugal.gov.pt/viewer/273525/?offset=#page=15&viewer=picture&o=info&n=0&q= | N113: C:\Users\mbaptista\OneDrive - Biblioteca Nacional de Portugal\Documentos\python\camoniana\imagens\capas\ | O113: =CONCATENATE(N113,A113,"\",B113,"\",C113,".jpg") -> C:\Users\mbaptista\OneDrive - Biblioteca Nacional de Portugal\Documentos\python\camoniana\imagens\capas\458290\1\15.jpg | P113: =HYPERLINK(O113) -> C:\Users\mbaptista\OneDrive - Biblioteca Nacional de Portugal\Documentos\python\camoniana\imagens\capas\458290\1\15.jpg
A114: 458290 | B114: 1 | C114: 37 | D114: https://purl.pt/43921 | E114: https://purl.pt/43921 | F114: 273525 | G114: https://permalinkbnd.bnportugal.gov.pt/viewer/ | H114: /?offset=#page= | I114: &viewer=picture&o=info&n=0&q= | J114: =CONCATENATE(G114,F114,H114,C114,I114) -> https://permalinkbnd.bnportugal.gov.pt/viewer/273525/?offset=#page=37&viewer=picture&o=info&n=0&q= | K114: 10, 11 [7, 15 e 37 apontamentos site] | L114: =VLOOKUP(A114,Folha2!$A$2:$B$2019,2,FALSE) -> O episódio da Ilha de Vénus+ 2 versões livres em francês, 1890. Recepção criativa em francês. Tematização. Refere em paratexto as celebrações de 1880: Celebrações (1880), recepção criativa, tematização. Imagem 10 de Vénus parece estar esfumada. | M114: =HYPERLINK(J114) -> https://permalinkbnd.bnportugal.gov.pt/viewer/273525/?offset=#page=37&viewer=picture&o=info&n=0&q= | N114: C:\Users\mbaptista\OneDrive - Biblioteca Nacional de Portugal\Documentos\python\camoniana\imagens\capas\ | O114: =CONCATENATE(N114,A114,"\",B114,"\",C114,".jpg") -> C:\Users\mbaptista\OneDrive - Biblioteca Nacional de Portugal\Documentos\python\camoniana\imagens\capas\458290\1\37.jpg | P114: =HYPERLINK(O114) -> C:\Users\mbaptista\OneDrive - Biblioteca Nacional de Portugal\Documentos\python\camoniana\imagens\capas\458290\1\37.jpg
A115: 458655 | B115: 1 | C115: 5 | D115: https://purl.pt/42928 | E115: https://purl.pt/42928 | F115: 270116 | G115: https://permalinkbnd.bnportugal.gov.pt/viewer/ | H115: /?offset=#page= | I115: &viewer=picture&o=info&n=0&q= | J115: =CONCATENATE(G115,F115,H115,C115,I115) -> https://permalinkbnd.bnportugal.gov.pt/viewer/270116/?offset=#page=5&viewer=picture&o=info&n=0&q= | K115: 5, 11 [1.º: imagem, portada], 5 [2.º retrato de Camões], 12 [3.º: partida de V. da Gama para a Índia], 12 [4.º: O espírito do Cabo surge à frota de V. da Gama], 11 [7.º: portada], 12 [8.º: Ilha dos Amores] | L115: =VLOOKUP(A115,Folha2!$A$2:$B$2019,2,FALSE) -> Florilégio Camoniano, 1887-1890. 8 Vols. [1.º: C. I, até est. 8; C. III, estâncias 120-135: Episódio Inês de Castro; sonetos (bilingue: pt+inglês); 2.º: textos sobre a comemoração do Tricentenário por membros da Sociedade Nacional Camoniana, poemas tematização; 3.º: Trad. Frag. Canto V e Frag. Canto I, até est. 10 por Victor Perrodil (bilingue pt+francês), com notas, tematização; 4.º: Trad. Frag. Canto V, episódio do Adamastor por J. R. Jauffret, Felicia Hemans, tradutora, Marc-Monnier, V. Perrodil, A. Quetelet; 5.º: Miscelânea: Camões exilado em Goa por Alfred Guyon, texto e poema traduzidos por Alberto de Armada; soneto por J. V. de Vasconcelos; A Camões, poema por A. Moreira Cabral no aniversário...; texto sobre Catherine d'Athayde por A. de C.; poema "The last song of Camões" by Rev. W. Lisle Bowles; 6.º: discursos e poesias pronunciados por Conde de Samodães, Francisco José Patrício, António Moreira Cabral e A. F. Araújo e Silva, no Porto, Palácio de Cristal, por ocasião do 308.º aniversário do passamento do Poeta; 7.º: sessão comemorativa 309.º aniversário, Porto Palácio de Cristal, textos de Conde de Samodães, Domingos Alexandre F. da Silva, Joaquim de Araújo, poema de António Moreira Cabral, J. F. Patrício; poema de Tomás Ribeiro; 8.º: Episódio Ilha de Vénus trad./versões por Baour-Lormian e Parseval Grandmaison] Trad. Paratextos; Trad. Paratextos vida; Trad. Paratextos notas; Mulheres [1.º: Parat. vida por Amália; 4.º: tradutora] 307.º aniversário da morte de Camões. Celebrações (1880), recepção criativa, tematização. | M115: =HYPERLINK(J115) -> https://permalinkbnd.bnportugal.gov.pt/viewer/270116/?offset=#page=5&viewer=picture&o=info&n=0&q= | N115: C:\Users\mbaptista\OneDrive - Biblioteca Nacional de Portugal\Documentos\python\camoniana\imagens\capas\ | O115: =CONCATENATE(N115,A115,"\",B115,"\",C115,".jpg") -> C:\Users\mbaptista\OneDrive - Biblioteca Nacional de Portugal\Documentos\python\camoniana\imagens\capas\458655\1\5.jpg | P115: =HYPERLINK(O115) -> C:\Users\mbaptista\OneDrive - Biblioteca Nacional de Portugal\Documentos\python\camoniana\imagens\capas\458655\1\5.jpg | T115: 11, 5, 12, 12, 11, 12
A116: 458655 | B116: 1 | C116: 11 | D116: https://purl.pt/42928 | E116: https://purl.pt/42928 | F116: 270116 | G116: https://permalinkbnd.bnportugal.gov.pt/viewer/ | H116: /?offset=#page= | I116: &viewer=picture&o=info&n=0&q= | J116: =CONCATENATE(G116,F116,H116,C116,I116) -> https://permalinkbnd.bnportugal.gov.pt/viewer/270116/?offset=#page=11&viewer=picture&o=info&n=0&q= | K116: 5, 11 [1.º: imagem, portada], 5 [2.º retrato de Camões], 12 [3.º: partida de V. da Gama para a Índia], 12 [4.º: O espírito do Cabo surge à frota de V. da Gama], 11 [7.º: portada], 12 [8.º: Ilha dos Amores] | L116: =VLOOKUP(A116,Folha2!$A$2:$B$2019,2,FALSE) -> Florilégio Camoniano, 1887-1890. 8 Vols. [1.º: C. I, até est. 8; C. III, estâncias 120-135: Episódio Inês de Castro; sonetos (bilingue: pt+inglês); 2.º: textos sobre a comemoração do Tricentenário por membros da Sociedade Nacional Camoniana, poemas tematização; 3.º: Trad. Frag. Canto V e Frag. Canto I, até est. 10 por Victor Perrodil (bilingue pt+francês), com notas, tematização; 4.º: Trad. Frag. Canto V, episódio do Adamastor por J. R. Jauffret, Felicia Hemans, tradutora, Marc-Monnier, V. Perrodil, A. Quetelet; 5.º: Miscelânea: Camões exilado em Goa por Alfred Guyon, texto e poema traduzidos por Alberto de Armada; soneto por J. V. de Vasconcelos; A Camões, poema por A. Moreira Cabral no aniversário...; texto sobre Catherine d'Athayde por A. de C.; poema "The last song of Camões" by Rev. W. Lisle Bowles; 6.º: discursos e poesias pronunciados por Conde de Samodães, Francisco José Patrício, António Moreira Cabral e A. F. Araújo e Silva, no Porto, Palácio de Cristal, por ocasião do 308.º aniversário do passamento do Poeta; 7.º: sessão comemorativa 309.º aniversário, Porto Palácio de Cristal, textos de Conde de Samodães, Domingos Alexandre F. da Silva, Joaquim de Araújo, poema de António Moreira Cabral, J. F. Patrício; poema de Tomás Ribeiro; 8.º: Episódio Ilha de Vénus trad./versões por Baour-Lormian e Parseval Grandmaison] Trad. Paratextos; Trad. Paratextos vida; Trad. Paratextos notas; Mulheres [1.º: Parat. vida por Amália; 4.º: tradutora] 307.º aniversário da morte de Camões. Celebrações (1880), recepção criativa, tematização. | M116: =HYPERLINK(J116) -> https://permalinkbnd.bnportugal.gov.pt/viewer/270116/?offset=#page=11&viewer=picture&o=info&n=0&q= | N116: C:\Users\mbaptista\OneDrive - Biblioteca Nacional de Portugal\Documentos\python\camoniana\imagens\capas\ | O116: =CONCATENATE(N116,A116,"\",B116,"\",C116,".jpg") -> C:\Users\mbaptista\OneDrive - Biblioteca Nacional de Portugal\Documentos\python\camoniana\imagens\capas\458655\1\11.jpg | P116: =HYPERLINK(O116) -> C:\Users\mbaptista\OneDrive - Biblioteca Nacional de Portugal\Documentos\python\camoniana\imagens\capas\458655\1\11.jpg | R116: https://permalinkbnd.bnportugal.gov.pt/viewer/270116/?offset=#page=11&viewer=picture&o=info&n=0&q= | T116: 11, 5, 12, 12, 11, 12 | W116: Sim
A117: 458655 | B117: 2 | C117: 5 | D117: https://purl.pt/42928 | E117: https://purl.pt/42928 | F117: 270116 | G117: https://permalinkbnd.bnportugal.gov.pt/viewer/ | H117: /?offset=#page= | I117: &viewer=picture&o=info&n=0&q= | J117: =CONCATENATE(G117,F117,H117,C117,I117) -> https://permalinkbnd.bnportugal.gov.pt/viewer/270116/?offset=#page=5&viewer=picture&o=info&n=0&q= | K117: 5, 11 [1.º: imagem, portada], 5 [2.º retrato de Camões], 12 [3.º: partida de V. da Gama para a Índia], 12 [4.º: O espírito do Cabo surge à frota de V. da Gama], 11 [7.º: portada], 12 [8.º: Ilha dos Amores] | L117: =VLOOKUP(A117,Folha2!$A$2:$B$2019,2,FALSE) -> Florilégio Camoniano, 1887-1890. 8 Vols. [1.º: C. I, até est. 8; C. III, estâncias 120-135: Episódio Inês de Castro; sonetos (bilingue: pt+inglês); 2.º: textos sobre a comemoração do Tricentenário por membros da Sociedade Nacional Camoniana, poemas tematização; 3.º: Trad. Frag. Canto V e Frag. Canto I, até est. 10 por Victor Perrodil (bilingue pt+francês), com notas, tematização; 4.º: Trad. Frag. Canto V, episódio do Adamastor por J. R. Jauffret, Felicia Hemans, tradutora, Marc-Monnier, V. Perrodil, A. Quetelet; 5.º: Miscelânea: Camões exilado em Goa por Alfred Guyon, texto e poema traduzidos por Alberto de Armada; soneto por J. V. de Vasconcelos; A Camões, poema por A. Moreira Cabral no aniversário...; texto sobre Catherine d'Athayde por A. de C.; poema "The last song of Camões" by Rev. W. Lisle Bowles; 6.º: discursos e poesias pronunciados por Conde de Samodães, Francisco José Patrício, António Moreira Cabral e A. F. Araújo e Silva, no Porto, Palácio de Cristal, por ocasião do 308.º aniversário do passamento do Poeta; 7.º: sessão comemorativa 309.º aniversário, Porto Palácio de Cristal, textos de Conde de Samodães, Domingos Alexandre F. da Silva, Joaquim de Araújo, poema de António Moreira Cabral, J. F. Patrício; poema de Tomás Ribeiro; 8.º: Episódio Ilha de Vénus trad./versões por Baour-Lormian e Parseval Grandmaison] Trad. Paratextos; Trad. Paratextos vida; Trad. Paratextos notas; Mulheres [1.º: Parat. vida por Amália; 4.º: tradutora] 307.º aniversário da morte de Camões. Celebrações (1880), recepção criativa, tematização. | M117: https://permalinkbnd.bnportugal.gov.pt/viewer/270116/?medianame=cam-153-a_0000_&o=volume#page=5&viewer=picture&o=volume&n=0&q= | N117: C:\Users\mbaptista\OneDrive - Biblioteca Nacional de Portugal\Documentos\python\camoniana\imagens\capas\ | O117: =CONCATENATE(N117,A117,"\",B117,"\",C117,".jpg") -> C:\Users\mbaptista\OneDrive - Biblioteca Nacional de Portugal\Documentos\python\camoniana\imagens\capas\458655\2\5.jpg | P117: =HYPERLINK(O117) -> C:\Users\mbaptista\OneDrive - Biblioteca Nacional de Portugal\Documentos\python\camoniana\imagens\capas\458655\2\5.jpg | R117: https://permalinkbnd.bnportugal.gov.pt/viewer/270116/?offset=#page=5&viewer=picture&o=info&n=0&q= | T117: 11, 5, 12, 12, 11, 12 | W117: Sim
A118: 458655 | B118: 3 | C118: 12 | D118: https://purl.pt/42928 | E118: https://purl.pt/42928 | F118: 270116 | G118: https://permalinkbnd.bnportugal.gov.pt/viewer/ | H118: /?offset=#page= | I118: &viewer=picture&o=info&n=0&q= | J118: =CONCATENATE(G118,F118,H118,C118,I118) -> https://permalinkbnd.bnportugal.gov.pt/viewer/270116/?offset=#page=12&viewer=picture&o=info&n=0&q= | K118: 5, 11 [1.º: imagem, portada], 5 [2.º retrato de Camões], 12 [3.º: partida de V. da Gama para a Índia], 12 [4.º: O espírito do Cabo surge à frota de V. da Gama], 11 [7.º: portada], 12 [8.º: Ilha dos Amores] | L118: =VLOOKUP(A118,Folha2!$A$2:$B$2019,2,FALSE) -> Florilégio Camoniano, 1887-1890. 8 Vols. [1.º: C. I, até est. 8; C. III, estâncias 120-135: Episódio Inês de Castro; sonetos (bilingue: pt+inglês); 2.º: textos sobre a comemoração do Tricentenário por membros da Sociedade Nacional Camoniana, poemas tematização; 3.º: Trad. Frag. Canto V e Frag. Canto I, até est. 10 por Victor Perrodil (bilingue pt+francês), com notas, tematização; 4.º: Trad. Frag. Canto V, episódio do Adamastor por J. R. Jauffret, Felicia Hemans, tradutora, Marc-Monnier, V. Perrodil, A. Quetelet; 5.º: Miscelânea: Camões exilado em Goa por Alfred Guyon, texto e poema traduzidos por Alberto de Armada; soneto por J. V. de Vasconcelos; A Camões, poema por A. Moreira Cabral no aniversário...; texto sobre Catherine d'Athayde por A. de C.; poema "The last song of Camões" by Rev. W. Lisle Bowles; 6.º: discursos e poesias pronunciados por Conde de Samodães, Francisco José Patrício, António Moreira Cabral e A. F. Araújo e Silva, no Porto, Palácio de Cristal, por ocasião do 308.º aniversário do passamento do Poeta; 7.º: sessão comemorativa 309.º aniversário, Porto Palácio de Cristal, textos de Conde de Samodães, Domingos Alexandre F. da Silva, Joaquim de Araújo, poema de António Moreira Cabral, J. F. Patrício; poema de Tomás Ribeiro; 8.º: Episódio Ilha de Vénus trad./versões por Baour-Lormian e Parseval Grandmaison] Trad. Paratextos; Trad. Paratextos vida; Trad. Paratextos notas; Mulheres [1.º: Parat. vida por Amália; 4.º: tradutora] 307.º aniversário da morte de Camões. Celebrações (1880), recepção criativa, tematização. | M118: https://permalinkbnd.bnportugal.gov.pt/viewer/270116/?medianame=cam-153-a_0000_&o=volume?&medianame=cam-154-a_0000_&viewer=picture&o=volume#page=12&viewer=picture&o=volume&n=0&q= | N118: C:\Users\mbaptista\OneDrive - Biblioteca Nacional de Portugal\Documentos\python\camoniana\imagens\capas\ | O118: =CONCATENATE(N118,A118,"\",B118,"\",C118,".jpg") -> C:\Users\mbaptista\OneDrive - Biblioteca Nacional de Portugal\Documentos\python\camoniana\imagens\capas\458655\3\12.jpg | P118: =HYPERLINK(O118) -> C:\Users\mbaptista\OneDrive - Biblioteca Nacional de Portugal\Documentos\python\camoniana\imagens\capas\458655\3\12.jpg | R118: https://permalinkbnd.bnportugal.gov.pt/viewer/270116/?offset=#page=12&viewer=picture&o=info&n=0&q= | T118: 11, 5, 12, 12, 11, 12 | U118: sem imagem | W118: Sim
A119: 458655 | B119: 4 | C119: 12 | D119: https://purl.pt/42928 | E119: https://purl.pt/42928 | F119: 270116 | G119: https://permalinkbnd.bnportugal.gov.pt/viewer/ | H119: /?offset=#page= | I119: &viewer=picture&o=info&n=0&q= | J119: =CONCATENATE(G119,F119,H119,C119,I119) -> https://permalinkbnd.bnportugal.gov.pt/viewer/270116/?offset=#page=12&viewer=picture&o=info&n=0&q= | K119: 5, 11 [1.º: imagem, portada], 5 [2.º retrato de Camões], 12 [3.º: partida de V. da Gama para a Índia], 12 [4.º: O espírito do Cabo surge à frota de V. da Gama], 11 [7.º: portada], 12 [8.º: Ilha dos Amores] | L119: =VLOOKUP(A119,Folha2!$A$2:$B$2019,2,FALSE) -> Florilégio Camoniano, 1887-1890. 8 Vols. [1.º: C. I, até est. 8; C. III, estâncias 120-135: Episódio Inês de Castro; sonetos (bilingue: pt+inglês); 2.º: textos sobre a comemoração do Tricentenário por membros da Sociedade Nacional Camoniana, poemas tematização; 3.º: Trad. Frag. Canto V e Frag. Canto I, até est. 10 por Victor Perrodil (bilingue pt+francês), com notas, tematização; 4.º: Trad. Frag. Canto V, episódio do Adamastor por J. R. Jauffret, Felicia Hemans, tradutora, Marc-Monnier, V. Perrodil, A. Quetelet; 5.º: Miscelânea: Camões exilado em Goa por Alfred Guyon, texto e poema traduzidos por Alberto de Armada; soneto por J. V. de Vasconcelos; A Camões, poema por A. Moreira Cabral no aniversário...; texto sobre Catherine d'Athayde por A. de C.; poema "The last song of Camões" by Rev. W. Lisle Bowles; 6.º: discursos e poesias pronunciados por Conde de Samodães, Francisco José Patrício, António Moreira Cabral e A. F. Araújo e Silva, no Porto, Palácio de Cristal, por ocasião do 308.º aniversário do passamento do Poeta; 7.º: sessão comemorativa 309.º aniversário, Porto Palácio de Cristal, textos de Conde de Samodães, Domingos Alexandre F. da Silva, Joaquim de Araújo, poema de António Moreira Cabral, J. F. Patrício; poema de Tomás Ribeiro; 8.º: Episódio Ilha de Vénus trad./versões por Baour-Lormian e Parseval Grandmaison] Trad. Paratextos; Trad. Paratextos vida; Trad. Paratextos notas; Mulheres [1.º: Parat. vida por Amália; 4.º: tradutora] 307.º aniversário da morte de Camões. Celebrações (1880), recepção criativa, tematização. | M119: https://permalinkbnd.bnportugal.gov.pt/viewer/270116/?medianame=cam-153-a_0000_&o=volume?&viewer=picture&o=volume?&medianame=cam-155-a_0000_&viewer=picture&o=volume#page=12&viewer=picture&o=volume&n=0&q= | N119: C:\Users\mbaptista\OneDrive - Biblioteca Nacional de Portugal\Documentos\python\camoniana\imagens\capas\ | O119: =CONCATENATE(N119,A119,"\",B119,"\",C119,".jpg") -> C:\Users\mbaptista\OneDrive - Biblioteca Nacional de Portugal\Documentos\python\camoniana\imagens\capas\458655\4\12.jpg | P119: =HYPERLINK(O119) -> C:\Users\mbaptista\OneDrive - Biblioteca Nacional de Portugal\Documentos\python\camoniana\imagens\capas\458655\4\12.jpg | R119: https://permalinkbnd.bnportugal.gov.pt/viewer/270116/?offset=#page=12&viewer=picture&o=info&n=0&q= | T119: 11, 5, 12, 12, 11, 12 | U119: sem imagem | W119: Sim
A120: 458655 | C120: 11 | D120: https://purl.pt/42928 | E120: https://purl.pt/42928 | F120: 270116 | G120: https://permalinkbnd.bnportugal.gov.pt/viewer/ | H120: /?offset=#page= | I120: &viewer=picture&o=info&n=0&q= | J120: =CONCATENATE(G120,F120,H120,C120,I120) -> https://permalinkbnd.bnportugal.gov.pt/viewer/270116/?offset=#page=11&viewer=picture&o=info&n=0&q= | K120: 5, 11 [1.º: imagem, portada], 5 [2.º retrato de Camões], 12 [3.º: partida de V. da Gama para a Índia], 12 [4.º: O espírito do Cabo surge à frota de V. da Gama], 11 [7.º: portada], 12 [8.º: Ilha dos Amores] | L120: =VLOOKUP(A120,Folha2!$A$2:$B$2019,2,FALSE) -> Florilégio Camoniano, 1887-1890. 8 Vols. [1.º: C. I, até est. 8; C. III, estâncias 120-135: Episódio Inês de Castro; sonetos (bilingue: pt+inglês); 2.º: textos sobre a comemoração do Tricentenário por membros da Sociedade Nacional Camoniana, poemas tematização; 3.º: Trad. Frag. Canto V e Frag. Canto I, até est. 10 por Victor Perrodil (bilingue pt+francês), com notas, tematização; 4.º: Trad. Frag. Canto V, episódio do Adamastor por J. R. Jauffret, Felicia Hemans, tradutora, Marc-Monnier, V. Perrodil, A. Quetelet; 5.º: Miscelânea: Camões exilado em Goa por Alfred Guyon, texto e poema traduzidos por Alberto de Armada; soneto por J. V. de Vasconcelos; A Camões, poema por A. Moreira Cabral no aniversário...; texto sobre Catherine d'Athayde por A. de C.; poema "The last song of Camões" by Rev. W. Lisle Bowles; 6.º: discursos e poesias pronunciados por Conde de Samodães, Francisco José Patrício, António Moreira Cabral e A. F. Araújo e Silva, no Porto, Palácio de Cristal, por ocasião do 308.º aniversário do passamento do Poeta; 7.º: sessão comemorativa 309.º aniversário, Porto Palácio de Cristal, textos de Conde de Samodães, Domingos Alexandre F. da Silva, Joaquim de Araújo, poema de António Moreira Cabral, J. F. Patrício; poema de Tomás Ribeiro; 8.º: Episódio Ilha de Vénus trad./versões por Baour-Lormian e Parseval Grandmaison] Trad. Paratextos; Trad. Paratextos vida; Trad. Paratextos notas; Mulheres [1.º: Parat. vida por Amália; 4.º: tradutora] 307.º aniversário da morte de Camões. Celebrações (1880), recepção criativa, tematização. | N120: C:\Users\mbaptista\OneDrive - Biblioteca Nacional de Portugal\Documentos\python\camoniana\imagens\capas\ | O120: =CONCATENATE(N120,A120,"\",B120,"\",C120,".jpg") -> C:\Users\mbaptista\OneDrive - Biblioteca Nacional de Portugal\Documentos\python\camoniana\imagens\capas\458655\\11.jpg | P120: =HYPERLINK(O120) -> C:\Users\mbaptista\OneDrive - Biblioteca Nacional de Portugal\Documentos\python\camoniana\imagens\capas\458655\\11.jpg | R120: https://permalinkbnd.bnportugal.gov.pt/viewer/270116/?offset=#page=11&viewer=picture&o=info&n=0&q= | T120: 11, 5, 12, 12, 11, 12 | U120: sem imagem | W120: Sim | X120: Falta link
A121: 458655 | B121: 8 | C121: 12 | D121: https://purl.pt/42928 | E121: https://purl.pt/42928 | F121: 270116 | G121: https://permalinkbnd.bnportugal.gov.pt/viewer/ | H121: /?offset=#page= | I121: &viewer=picture&o=info&n=0&q= | J121: =CONCATENATE(G121,F121,H121,C121,I121) -> https://permalinkbnd.bnportugal.gov.pt/viewer/270116/?offset=#page=12&viewer=picture&o=info&n=0&q= | K121: 5, 11 [1.º: imagem, portada], 5 [2.º retrato de Camões], 12 [3.º: partida de V. da Gama para a Índia], 12 [4.º: O espírito do Cabo surge à frota de V. da Gama], 11 [7.º: portada], 12 [8.º: Ilha dos Amores] | L121: =VLOOKUP(A121,Folha2!$A$2:$B$2019,2,FALSE) -> Florilégio Camoniano, 1887-1890. 8 Vols. [1.º: C. I, até est. 8; C. III, estâncias 120-135: Episódio Inês de Castro; sonetos (bilingue: pt+inglês); 2.º: textos sobre a comemoração do Tricentenário por membros da Sociedade Nacional Camoniana, poemas tematização; 3.º: Trad. Frag. Canto V e Frag. Canto I, até est. 10 por Victor Perrodil (bilingue pt+francês), com notas, tematização; 4.º: Trad. Frag. Canto V, episódio do Adamastor por J. R. Jauffret, Felicia Hemans, tradutora, Marc-Monnier, V. Perrodil, A. Quetelet; 5.º: Miscelânea: Camões exilado em Goa por Alfred Guyon, texto e poema traduzidos por Alberto de Armada; soneto por J. V. de Vasconcelos; A Camões, poema por A. Moreira Cabral no aniversário...; texto sobre Catherine d'Athayde por A. de C.; poema "The last song of Camões" by Rev. W. Lisle Bowles; 6.º: discursos e poesias pronunciados por Conde de Samodães, Francisco José Patrício, António Moreira Cabral e A. F. Araújo e Silva, no Porto, Palácio de Cristal, por ocasião do 308.º aniversário do passamento do Poeta; 7.º: sessão comemorativa 309.º aniversário, Porto Palácio de Cristal, textos de Conde de Samodães, Domingos Alexandre F. da Silva, Joaquim de Araújo, poema de António Moreira Cabral, J. F. Patrício; poema de Tomás Ribeiro; 8.º: Episódio Ilha de Vénus trad./versões por Baour-Lormian e Parseval Grandmaison] Trad. Paratextos; Trad. Paratextos vida; Trad. Paratextos notas; Mulheres [1.º: Parat. vida por Amália; 4.º: tradutora] 307.º aniversário da morte de Camões. Celebrações (1880), recepção criativa, tematização. | M121: https://permalinkbnd.bnportugal.gov.pt/viewer/270116/?medianame=cam-153-a_0000_&o=volume?&viewer=picture&o=volume?&viewer=picture&o=volume?&viewer=picture&o=volume?&viewer=picture&o=volume?&viewer=picture&o=volume?&viewer=picture&o=volume?&viewer=picture&o=volume?&viewer=picture&o=volume?&viewer=picture&o=volume?&medianame=cam-159-a_0000_&viewer=picture&o=volume#page=12&viewer=picture&o=volume&n=0&q= | N121: C:\Users\mbaptista\OneDrive - Biblioteca Nacional de Portugal\Documentos\python\camoniana\imagens\capas\ | O121: =CONCATENATE(N121,A121,"\",B121,"\",C121,".jpg") -> C:\Users\mbaptista\OneDrive - Biblioteca Nacional de Portugal\Documentos\python\camoniana\imagens\capas\458655\8\12.jpg | P121: =HYPERLINK(O121) -> C:\Users\mbaptista\OneDrive - Biblioteca Nacional de Portugal\Documentos\python\camoniana\imagens\capas\458655\8\12.jpg | R121: https://permalinkbnd.bnportugal.gov.pt/viewer/270116/?offset=#page=12&viewer=picture&o=info&n=0&q= | T121: 11, 5, 12, 12, 11, 12 | U121: sem imagem | W121: Sim
...

Sheet Folha4
A1: pasta | B1: volume | C1: imagem | D1: purl-hiperligação | E1: purl 2 | F1: n bnd | G1: l1 | H1: l2 | I1: l3 | J1: l4 | K1: imagens_texto | L1: Notas | M1: link página | N1: l5 | O1: l6 | P1: link imagem | Q1: nada | R1: url_página | S1: nada 2 | T1: imagens | U1: notas Regina | V1: notas Regina 2 | W1: tem JPG
A2: 367428 | B2: 1 | C2: 1 | D2: https://purl.pt/43428 | E2: https://purl.pt/43428 | F2: 272369 | G2: https://permalinkbnd.bnportugal.gov.pt/viewer/ | H2: /?offset=#page= | I2: &viewer=picture&o=info&n=0&q= | J2: =CONCATENATE(G2,F2,H2,C2,I2) -> https://permalinkbnd.bnportugal.gov.pt/viewer/272369/?offset=#page=1&viewer=picture&o=info&n=0&q= | K2: 1 | L2: =VLOOKUP(A2,Folha2!$A$2:$B$2019,2,FALSE) -> I Lusiadi. Antonio Nervi, 1882. Trad. Paratextos vida. Trad. Paratextos notas (de rodapé em cada Canto). Trad. Paratextos argumentos. | M2: =HYPERLINK(J2) -> https://permalinkbnd.bnportugal.gov.pt/viewer/272369/?offset=#page=1&viewer=picture&o=info&n=0&q= | N2: C:\Users\mbaptista\OneDrive - Biblioteca Nacional de Portugal\Documentos\python\camoniana\imagens\capas\ | O2: =CONCATENATE(N2,A2,"\",B2,"\",C2,".jpg") -> C:\Users\mbaptista\OneDrive - Biblioteca Nacional de Portugal\Documentos\python\camoniana\imagens\capas\367428\1\1.jpg | P2: =HYPERLINK(O2) -> C:\Users\mbaptista\OneDrive - Biblioteca Nacional de Portugal\Documentos\python\camoniana\imagens\capas\367428\1\1.jpg | R2: https://permalinkbnd.bnportugal.gov.pt/viewer/272369/?offset=#page=1&viewer=picture&o=info&n=0&q= | T2: 1 | W2: Sim
A3: 381074 | B3: 1 | C3: 10 | D3: https://purl.pt/43747 | E3: https://purl.pt/43747 | F3: 274089 | G3: https://permalinkbnd.bnportugal.gov.pt/viewer/ | H3: /?offset=#page= | I3: &viewer=picture&o=info&n=0&q= | J3: =CONCATENATE(G3,F3,H3,C3,I3) -> https://permalinkbnd.bnportugal.gov.pt/viewer/274089/?offset=#page=10&viewer=picture&o=info&n=0&q= | K3: 10 [site], 11, 103 [site pelicano direita], 107, 142, 107, 142, 145, 185, 235, 270 [site assassinato de Inês], 273, 306, 309 [site ninfas], 342, 345, 374, 377, 410, 413, 447, 499, 526 [site apontamento] [pintura de Camões por Columbano, portada, fac-símile do frontispício da 1.ª Ed. de Os Lusíadas, ilustrações da obra] | L3: =VLOOKUP(A3,Folha2!$A$2:$B$2019,2,FALSE) -> Os Lusíadas, Rio de Janeiro, 1880, sem argumentos. | M3: =HYPERLINK(J3) -> https://permalinkbnd.bnportugal.gov.pt/viewer/274089/?offset=#page=10&viewer=picture&o=info&n=0&q= | N3: C:\Users\mbaptista\OneDrive - Biblioteca Nacional de Portugal\Documentos\python\camoniana\imagens\capas\ | O3: =CONCATENATE(N3,A3,"\",B3,"\",C3,".jpg") -> C:\Users\mbaptista\OneDrive - Biblioteca Nacional de Portugal\Documentos\python\camoniana\imagens\capas\381074\1\10.jpg | P3: =HYPERLINK(O3) -> C:\Users\mbaptista\OneDrive - Biblioteca Nacional de Portugal\Documentos\python\camoniana\imagens\capas\381074\1\10.jpg | T3: 10, 11, 103, 145, 235, 270, 273, 306, 309, 342, 345, 374, 377, 410, 413, 447, 499
A4: 381074 | B4: 1 | C4: 11 | D4: https://purl.pt/43747 | E4: https://purl.pt/43747 | F4: 274089 | G4: https://permalinkbnd.bnportugal.gov.pt/viewer/ | H4: /?offset=#page= | I4: &viewer=picture&o=info&n=0&q= | J4: =CONCATENATE(G4,F4,H4,C4,I4) -> https://permalinkbnd.bnportugal.gov.pt/viewer/274089/?offset=#page=11&viewer=picture&o=info&n=0&q= | K4: 10 [site], 11, 103 [site pelicano direita], 107, 142, 107, 142, 145, 185, 235, 270 [site assassinato de Inês], 273, 306, 309 [site ninfas], 342, 345, 374, 377, 410, 413, 447, 499, 526 [site apontamento] [pintura de Camões por Columbano, portada, fac-símile do frontispício da 1.ª Ed. de Os Lusíadas, ilustrações da obra] | L4: =VLOOKUP(A4,Folha2!$A$2:$B$2019,2,FALSE) -> Os Lusíadas, Rio de Janeiro, 1880, sem argumentos. | M4: =HYPERLINK(J4) -> https://permalinkbnd.bnportugal.gov.pt/viewer/274089/?offset=#page=11&viewer=picture&o=info&n=0&q= | N4: C:\Users\mbaptista\OneDrive - Biblioteca Nacional de Portugal\Documentos\python\camoniana\imagens\capas\ | O4: =CONCATENATE(N4,A4,"\",B4,"\",C4,".jpg") -> C:\Users\mbaptista\OneDrive - Biblioteca Nacional de Portugal\Documentos\python\camoniana\imagens\capas\381074\1\11.jpg | P4: =HYPERLINK(O4) -> C:\Users\mbaptista\OneDrive - Biblioteca Nacional de Portugal\Documentos\python\camoniana\imagens\capas\381074\1\11.jpg | T4: 10, 11, 103, 145, 235, 270, 273, 306, 309, 342, 345, 374, 377, 410, 413, 447, 499
A5: 381074 | B5: 1 | C5: 103 | D5: https://purl.pt/43747 | E5: https://purl.pt/43747 | F5: 274089 | G5: https://permalinkbnd.bnportugal.gov.pt/viewer/ | H5: /?offset=#page= | I5: &viewer=picture&o=info&n=0&q= | J5: =CONCATENATE(G5,F5,H5,C5,I5) -> https://permalinkbnd.bnportugal.gov.pt/viewer/274089/?offset=#page=103&viewer=picture&o=info&n=0&q= | K5: 10 [site], 11, 103 [site pelicano direita], 107, 142, 107, 142, 145, 185, 235, 270 [site assassinato de Inês], 273, 306, 309 [site ninfas], 342, 345, 374, 377, 410, 413, 447, 499, 526 [site apontamento] [pintura de Camões por Columbano, portada, fac-símile do frontispício da 1.ª Ed. de Os Lusíadas, ilustrações da obra] | L5: =VLOOKUP(A5,Folha2!$A$2:$B$2019,2,FALSE) -> Os Lusíadas, Rio de Janeiro, 1880, sem argumentos. | M5: =HYPERLINK(J5) -> https://permalinkbnd.bnportugal.gov.pt/viewer/274089/?offset=#page=103&viewer=picture&o=info&n=0&q= | N5: C:\Users\mbaptista\OneDrive - Biblioteca Nacional de Portugal\Documentos\python\camoniana\imagens\capas\ | O5: =CONCATENATE(N5,A5,"\",B5,"\",C5,".jpg") -> C:\Users\mbaptista\OneDrive - Biblioteca Nacional de Portugal\Documentos\python\camoniana\imagens\capas\381074\1\103.jpg | P5: =HYPERLINK(O5) -> C:\Users\mbaptista\OneDrive - Biblioteca Nacional de Portugal\Documentos\python\camoniana\imagens\capas\381074\1\103.jpg | T5: 10, 11, 103, 145, 235, 270, 273, 306, 309, 342, 345, 374, 377, 410, 413, 447, 499
A6: 381074 | B6: 1 | C6: 107 | D6: https://purl.pt/43747 | E6: https://purl.pt/43747 | F6: 274089 | G6: https://permalinkbnd.bnportugal.gov.pt/viewer/ | H6: /?offset=#page= | I6: &viewer=picture&o=info&n=0&q= | J6: =CONCATENATE(G6,F6,H6,C6,I6) -> https://permalinkbnd.bnportugal.gov.pt/viewer/274089/?offset=#page=107&viewer=picture&o=info&n=0&q= | K6: 10 [site], 11, 103 [site pelicano direita], 107, 142, 107, 142, 145, 185, 235, 270 [site assassinato de Inês], 273, 306, 309 [site ninfas], 342, 345, 374, 377, 410, 413, 447, 499, 526 [site apontamento] [pintura de Camões por Columbano, portada, fac-símile do frontispício da 1.ª Ed. de Os Lusíadas, ilustrações da obra] | L6: =VLOOKUP(A6,Folha2!$A$2:$B$2019,2,FALSE) -> Os Lusíadas, Rio de Janeiro, 1880, sem argumentos. | M6: =HYPERLINK(J6) -> https://permalinkbnd.bnportugal.gov.pt/viewer/274089/?offset=#page=107&viewer=picture&o=info&n=0&q= | N6: C:\Users\mbaptista\OneDrive - Biblioteca Nacional de Portugal\Documentos\python\camoniana\imagens\capas\ | O6: =CONCATENATE(N6,A6,"\",B6,"\",C6,".jpg") -> C:\Users\mbaptista\OneDrive - Biblioteca Nacional de Portugal\Documentos\python\camoniana\imagens\capas\381074\1\107.jpg | P6: =HYPERLINK(O6) -> C:\Users\mbaptista\OneDrive - Biblioteca Nacional de Portugal\Documentos\python\camoniana\imagens\capas\381074\1\107.jpg | T6: 10, 11, 103, 145, 235, 270, 273, 306, 309, 342, 345, 374, 377, 410, 413, 447, 499
A7: 381074 | B7: 1 | C7: 142 | D7: https://purl.pt/43747 | E7: https://purl.pt/43747 | F7: 274089 | G7: https://permalinkbnd.bnportugal.gov.pt/viewer/ | H7: /?offset=#page= | I7: &viewer=picture&o=info&n=0&q= | J7: =CONCATENATE(G7,F7,H7,C7,I7) -> https://permalinkbnd.bnportugal.gov.pt/viewer/274089/?offset=#page=142&viewer=picture&o=info&n=0&q= | K7: 10 [site], 11, 103 [site pelicano direita], 107, 142, 107, 142, 145, 185, 235, 270 [site assassinato de Inês], 273, 306, 309 [site ninfas], 342, 345, 374, 377, 410, 413, 447, 499, 526 [site apontamento] [pintura de Camões por Columbano, portada, fac-símile do frontispício da 1.ª Ed. de Os Lusíadas, ilustrações da obra] | L7: =VLOOKUP(A7,Folha2!$A$2:$B$2019,2,FALSE) -> Os Lusíadas, Rio de Janeiro, 1880, sem argumentos. | M7: =HYPERLINK(J7) -> https://permalinkbnd.bnportugal.gov.pt/viewer/274089/?offset=#page=142&viewer=picture&o=info&n=0&q= | N7: C:\Users\mbaptista\OneDrive - Biblioteca Nacional de Portugal\Documentos\python\camoniana\imagens\capas\ | O7: =CONCATENATE(N7,A7,"\",B7,"\",C7,".jpg") -> C:\Users\mbaptista\OneDrive - Biblioteca Nacional de Portugal\Documentos\python\camoniana\imagens\capas\381074\1\142.jpg | P7: =HYPERLINK(O7) -> C:\Users\mbaptista\OneDrive - Biblioteca Nacional de Portugal\Documentos\python\camoniana\imagens\capas\381074\1\142.jpg | T7: 10, 11, 103, 145, 235, 270, 273, 306, 309, 342, 345, 374, 377, 410, 413, 447, 499
A8: 381074 | B8: 1 | C8: 107 | D8: https://purl.pt/43747 | E8: https://purl.pt/43747 | F8: 274089 | G8: https://permalinkbnd.bnportugal.gov.pt/viewer/ | H8: /?offset=#page= | I8: &viewer=picture&o=info&n=0&q= | J8: =CONCATENATE(G8,F8,H8,C8,I8) -> https://permalinkbnd.bnportugal.gov.pt/viewer/274089/?offset=#page=107&viewer=picture&o=info&n=0&q= | K8: 10 [site], 11, 103 [site pelicano direita], 107, 142, 107, 142, 145, 185, 235, 270 [site assassinato de Inês], 273, 306, 309 [site ninfas], 342, 345, 374, 377, 410, 413, 447, 499, 526 [site apontamento] [pintura de Camões por Columbano, portada, fac-símile do frontispício da 1.ª Ed. de Os Lusíadas, ilustrações da obra] | L8: =VLOOKUP(A8,Folha2!$A$2:$B$2019,2,FALSE) -> Os Lusíadas, Rio de Janeiro, 1880, sem argumentos. | M8: =HYPERLINK(J8) -> https://permalinkbnd.bnportugal.gov.pt/viewer/274089/?offset=#page=107&viewer=picture&o=info&n=0&q= | N8: C:\Users\mbaptista\OneDrive - Biblioteca Nacional de Portugal\Documentos\python\camoniana\imagens\capas\ | O8: =CONCATENATE(N8,A8,"\",B8,"\",C8,".jpg") -> C:\Users\mbaptista\OneDrive - Biblioteca Nacional de Portugal\Documentos\python\camoniana\imagens\capas\381074\1\107.jpg | P8: =HYPERLINK(O8) -> C:\Users\mbaptista\OneDrive - Biblioteca Nacional de Portugal\Documentos\python\camoniana\imagens\capas\381074\1\107.jpg | T8: 10, 11, 103, 145, 235, 270, 273, 306, 309, 342, 345, 374, 377, 410, 413, 447, 499
A9: 381074 | B9: 1 | C9: 142 | D9: https://purl.pt/43747 | E9: https://purl.pt/43747 | F9: 274089 | G9: https://permalinkbnd.bnportugal.gov.pt/viewer/ | H9: /?offset=#page= | I9: &viewer=picture&o=info&n=0&q= | J9: =CONCATENATE(G9,F9,H9,C9,I9) -> https://permalinkbnd.bnportugal.gov.pt/viewer/274089/?offset=#page=142&viewer=picture&o=info&n=0&q= | K9: 10 [site], 11, 103 [site pelicano direita], 107, 142, 107, 142, 145, 185, 235, 270 [site assassinato de Inês], 273, 306, 309 [site ninfas], 342, 345, 374, 377, 410, 413, 447, 499, 526 [site apontamento] [pintura de Camões por Columbano, portada, fac-símile do frontispício da 1.ª Ed. de Os Lusíadas, ilustrações da obra] | L9: =VLOOKUP(A9,Folha2!$A$2:$B$2019,2,FALSE) -> Os Lusíadas, Rio de Janeiro, 1880, sem argumentos. | M9: =HYPERLINK(J9) -> https://permalinkbnd.bnportugal.gov.pt/viewer/274089/?offset=#page=142&viewer=picture&o=info&n=0&q= | N9: C:\Users\mbaptista\OneDrive - Biblioteca Nacional de Portugal\Documentos\python\camoniana\imagens\capas\ | O9: =CONCATENATE(N9,A9,"\",B9,"\",C9,".jpg") -> C:\Users\mbaptista\OneDrive - Biblioteca Nacional de Portugal\Documentos\python\camoniana\imagens\capas\381074\1\142.jpg | P9: =HYPERLINK(O9) -> C:\Users\mbaptista\OneDrive - Biblioteca Nacional de Portugal\Documentos\python\camoniana\imagens\capas\381074\1\142.jpg | T9: 10, 11, 103, 145, 235, 270, 273, 306, 309, 342, 345, 374, 377, 410, 413, 447, 499
A10: 381074 | B10: 1 | C10: 145 | D10: https://purl.pt/43747 | E10: https://purl.pt/43747 | F10: 274089 | G10: https://permalinkbnd.bnportugal.gov.pt/viewer/ | H10: /?offset=#page= | I10: &viewer=picture&o=info&n=0&q= | J10: =CONCATENATE(G10,F10,H10,C10,I10) -> https://permalinkbnd.bnportugal.gov.pt/viewer/274089/?offset=#page=145&viewer=picture&o=info&n=0&q= | K10: 10 [site], 11, 103 [site pelicano direita], 107, 142, 107, 142, 145, 185, 235, 270 [site assassinato de Inês], 273, 306, 309 [site ninfas], 342, 345, 374, 377, 410, 413, 447, 499, 526 [site apontamento] [pintura de Camões por Columbano, portada, fac-símile do frontispício da 1.ª Ed. de Os Lusíadas, ilustrações da obra] | L10: =VLOOKUP(A10,Folha2!$A$2:$B$2019,2,FALSE) -> Os Lusíadas, Rio de Janeiro, 1880, sem argumentos. | M10: =HYPERLINK(J10) -> https://permalinkbnd.bnportugal.gov.pt/viewer/274089/?offset=#page=145&viewer=picture&o=info&n=0&q= | N10: C:\Users\mbaptista\OneDrive - Biblioteca Nacional de Portugal\Documentos\python\camoniana\imagens\capas\ | O10: =CONCATENATE(N10,A10,"\",B10,"\",C10,".jpg") -> C:\Users\mbaptista\OneDrive - Biblioteca Nacional de Portugal\Documentos\python\camoniana\imagens\capas\381074\1\145.jpg | P10: =HYPERLINK(O10) -> C:\Users\mbaptista\OneDrive - Biblioteca Nacional de Portugal\Documentos\python\camoniana\imagens\capas\381074\1\145.jpg | T10: 10, 11, 103, 145, 235, 270, 273, 306, 309, 342, 345, 374, 377, 410, 413, 447, 499
A11: 381074 | B11: 1 | C11: 185 | D11: https://purl.pt/43747 | E11: https://purl.pt/43747 | F11: 274089 | G11: https://permalinkbnd.bnportugal.gov.pt/viewer/ | H11: /?offset=#page= | I11: &viewer=picture&o=info&n=0&q= | J11: =CONCATENATE(G11,F11,H11,C11,I11) -> https://permalinkbnd.bnportugal.gov.pt/viewer/274089/?offset=#page=185&viewer=picture&o=info&n=0&q= | K11: 10 [site], 11, 103 [site pelicano direita], 107, 142, 107, 142, 145, 185, 235, 270 [site assassinato de Inês], 273, 306, 309 [site ninfas], 342, 345, 374, 377, 410, 413, 447, 499, 526 [site apontamento] [pintura de Camões por Columbano, portada, fac-símile do frontispício da 1.ª Ed. de Os Lusíadas, ilustrações da obra] | L11: =VLOOKUP(A11,Folha2!$A$2:$B$2019,2,FALSE) -> Os Lusíadas, Rio de Janeiro, 1880, sem argumentos. | M11: =HYPERLINK(J11) -> https://permalinkbnd.bnportugal.gov.pt/viewer/274089/?offset=#page=185&viewer=picture&o=info&n=0&q= | N11: C:\Users\mbaptista\OneDrive - Biblioteca Nacional de Portugal\Documentos\python\camoniana\imagens\capas\ | O11: =CONCATENATE(N11,A11,"\",B11,"\",C11,".jpg") -> C:\Users\mbaptista\OneDrive - Biblioteca Nacional de Portugal\Documentos\python\camoniana\imagens\capas\381074\1\185.jpg | P11: =HYPERLINK(O11) -> C:\Users\mbaptista\OneDrive - Biblioteca Nacional de Portugal\Documentos\python\camoniana\imagens\capas\381074\1\185.jpg | T11: 10, 11, 103, 145, 235, 270, 273, 306, 309, 342, 345, 374, 377, 410, 413, 447, 499
A12: 381074 | B12: 1 | C12: 235 | D12: https://purl.pt/43747 | E12: https://purl.pt/43747 | F12: 274089 | G12: https://permalinkbnd.bnportugal.gov.pt/viewer/ | H12: /?offset=#page= | I12: &viewer=picture&o=info&n=0&q= | J12: =CONCATENATE(G12,F12,H12,C12,I12) -> https://permalinkbnd.bnportugal.gov.pt/viewer/274089/?offset=#page=235&viewer=picture&o=info&n=0&q= | K12: 10 [site], 11, 103 [site pelicano direita], 107, 142, 107, 142, 145, 185, 235, 270 [site assassinato de Inês], 273, 306, 309 [site ninfas], 342, 345, 374, 377, 410, 413, 447, 499, 526 [site apontamento] [pintura de Camões por Columbano, portada, fac-símile do frontispício da 1.ª Ed. de Os Lusíadas, ilustrações da obra] | L12: =VLOOKUP(A12,Folha2!$A$2:$B$2019,2,FALSE) -> Os Lusíadas, Rio de Janeiro, 1880, sem argumentos. | M12: =HYPERLINK(J12) -> https://permalinkbnd.bnportugal.gov.pt/viewer/274089/?offset=#page=235&viewer=picture&o=info&n=0&q= | N12: C:\Users\mbaptista\OneDrive - Biblioteca Nacional de Portugal\Documentos\python\camoniana\imagens\capas\ | O12: =CONCATENATE(N12,A12,"\",B12,"\",C12,".jpg") -> C:\Users\mbaptista\OneDrive - Biblioteca Nacional de Portugal\Documentos\python\camoniana\imagens\capas\381074\1\235.jpg | P12: =HYPERLINK(O12) -> C:\Users\mbaptista\OneDrive - Biblioteca Nacional de Portugal\Documentos\python\camoniana\imagens\capas\381074\1\235.jpg | T12: 10, 11, 103, 145, 235, 270, 273, 306, 309, 342, 345, 374, 377, 410, 413, 447, 499
A13: 381074 | B13: 1 | C13: 270 | D13: https://purl.pt/43747 | E13: https://purl.pt/43747 | F13: 274089 | G13: https://permalinkbnd.bnportugal.gov.pt/viewer/ | H13: /?offset=#page= | I13: &viewer=picture&o=info&n=0&q= | J13: =CONCATENATE(G13,F13,H13,C13,I13) -> https://permalinkbnd.bnportugal.gov.pt/viewer/274089/?offset=#page=270&viewer=picture&o=info&n=0&q= | K13: 10 [site], 11, 103 [site pelicano direita], 107, 142, 107, 142, 145, 185, 235, 270 [site assassinato de Inês], 273, 306, 309 [site ninfas], 342, 345, 374, 377, 410, 413, 447, 499, 526 [site apontamento] [pintura de Camões por Columbano, portada, fac-símile do frontispício da 1.ª Ed. de Os Lusíadas, ilustrações da obra] | L13: =VLOOKUP(A13,Folha2!$A$2:$B$2019,2,FALSE) -> Os Lusíadas, Rio de Janeiro, 1880, sem argumentos. | M13: =HYPERLINK(J13) -> https://permalinkbnd.bnportugal.gov.pt/viewer/274089/?offset=#page=270&viewer=picture&o=info&n=0&q= | N13: C:\Users\mbaptista\OneDrive - Biblioteca Nacional de Portugal\Documentos\python\camoniana\imagens\capas\ | O13: =CONCATENATE(N13,A13,"\",B13,"\",C13,".jpg") -> C:\Users\mbaptista\OneDrive - Biblioteca Nacional de Portugal\Documentos\python\camoniana\imagens\capas\381074\1\270.jpg | P13: =HYPERLINK(O13) -> C:\Users\mbaptista\OneDrive - Biblioteca Nacional de Portugal\Documentos\python\camoniana\imagens\capas\381074\1\270.jpg | T13: 10, 11, 103, 145, 235, 270, 273, 306, 309, 342, 345, 374, 377, 410, 413, 447, 499
A14: 381074 | B14: 1 | C14: 273 | D14: https://purl.pt/43747 | E14: https://purl.pt/43747 | F14: 274089 | G14: https://permalinkbnd.bnportugal.gov.pt/viewer/ | H14: /?offset=#page= | I14: &viewer=picture&o=info&n=0&q= | J14: =CONCATENATE(G14,F14,H14,C14,I14) -> https://permalinkbnd.bnportugal.gov.pt/viewer/274089/?offset=#page=273&viewer=picture&o=info&n=0&q= | K14: 10 [site], 11, 103 [site pelicano direita], 107, 142, 107, 142, 145, 185, 235, 270 [site assassinato de Inês], 273, 306, 309 [site ninfas], 342, 345, 374, 377, 410, 413, 447, 499, 526 [site apontamento] [pintura de Camões por Columbano, portada, fac-símile do frontispício da 1.ª Ed. de Os Lusíadas, ilustrações da obra] | L14: =VLOOKUP(A14,Folha2!$A$2:$B$2019,2,FALSE) -> Os Lusíadas, Rio de Janeiro, 1880, sem argumentos. | M14: =HYPERLINK(J14) -> https://permalinkbnd.bnportugal.gov.pt/viewer/274089/?offset=#page=273&viewer=picture&o=info&n=0&q= | N14: C:\Users\mbaptista\OneDrive - Biblioteca Nacional de Portugal\Documentos\python\camoniana\imagens\capas\ | O14: =CONCATENATE(N14,A14,"\",B14,"\",C14,".jpg") -> C:\Users\mbaptista\OneDrive - Biblioteca Nacional de Portugal\Documentos\python\camoniana\imagens\capas\381074\1\273.jpg | P14: =HYPERLINK(O14) -> C:\Users\mbaptista\OneDrive - Biblioteca Nacional de Portugal\Documentos\python\camoniana\imagens\capas\381074\1\273.jpg | T14: 10, 11, 103, 145, 235, 270, 273, 306, 309, 342, 345, 374, 377, 410, 413, 447, 499
... A23: 381074 | B23: 1 | C23: 447 | D23: https://purl.pt/43747 | E23: https://purl.pt/43747 | F23: 274089 | G23: https://permalinkbnd.bnportugal.gov.pt/viewer/ | H23: /?offset=#page= | I23: &viewer=picture&o=info&n=0&q= | J23: =CONCATENATE(G23,F23,H23,C23,I23) -> https://permalinkbnd.bnportugal.gov.pt/viewer/274089/?offset=#page=447&viewer=picture&o=info&n=0&q= | K23: 10 [site], 11, 103 [site pelicano direita], 107, 142, 107, 142, 145, 185, 235, 270 [site assassinato de Inês], 273, 306, 309 [site ninfas], 342, 345, 374, 377, 410, 413, 447, 499, 526 [site apontamento] [pintura de Camões por Columbano, portada, fac-símile do frontispício da 1.ª Ed. de Os Lusíadas, ilustrações da obra] | L23: =VLOOKUP(A23,Folha2!$A$2:$B$2019,2,FALSE) -> Os Lusíadas, Rio de Janeiro, 1880, sem argumentos. | M23: =HYPERLINK(J23) -> https://permalinkbnd.bnportugal.gov.pt/viewer/274089/?offset=#page=447&viewer=picture&o=info&n=0&q= | N23: C:\Users\mbaptista\OneDrive - Biblioteca Nacional de Portugal\Documentos\python\camoniana\imagens\capas\ | O23: =CONCATENATE(N23,A23,"\",B23,"\",C23,".jpg") -> C:\Users\mbaptista\OneDrive - Biblioteca Nacional de Portugal\Documentos\python\camoniana\imagens\capas\381074\1\447.jpg | P23: =HYPERLINK(O23) -> C:\Users\mbaptista\OneDrive - Biblioteca Nacional de Portugal\Documentos\python\camoniana\imagens\capas\381074\1\447.jpg | T23: 10, 11, 103, 145, 235, 270, 273, 306, 309, 342, 345, 374, 377, 410, 413, 447, 499
A24: 381074 | B24: 1 | C24: 499 | D24: https://purl.pt/43747 | E24: https://purl.pt/43747 | F24: 274089 | G24: https://permalinkbnd.bnportugal.gov.pt/viewer/ | H24: /?offset=#page= | I24: &viewer=picture&o=info&n=0&q= | J24: =CONCATENATE(G24,F24,H24,C24,I24) -> https://permalinkbnd.bnportugal.gov.pt/viewer/274089/?offset=#page=499&viewer=picture&o=info&n=0&q= | K24: 10 [site], 11, 103 [site pelicano direita], 107, 142, 107, 142, 145, 185, 235, 270 [site assassinato de Inês], 273, 306, 309 [site ninfas], 342, 345, 374, 377, 410, 413, 447, 499, 526 [site apontamento] [pintura de Camões por Columbano, portada, fac-símile do frontispício da 1.ª Ed. de Os Lusíadas, ilustrações da obra] | L24: =VLOOKUP(A24,Folha2!$A$2:$B$2019,2,FALSE) -> Os Lusíadas, Rio de Janeiro, 1880, sem argumentos. | M24: =HYPERLINK(J24) -> https://permalinkbnd.bnportugal.gov.pt/viewer/274089/?offset=#page=499&viewer=picture&o=info&n=0&q= | N24: C:\Users\mbaptista\OneDrive - Biblioteca Nacional de Portugal\Documentos\python\camoniana\imagens\capas\ | O24: =CONCATENATE(N24,A24,"\",B24,"\",C24,".jpg") -> C:\Users\mbaptista\OneDrive - Biblioteca Nacional de Portugal\Documentos\python\camoniana\imagens\capas\381074\1\499.jpg | P24: =HYPERLINK(O24) -> C:\Users\mbaptista\OneDrive - Biblioteca Nacional de Portugal\Documentos\python\camoniana\imagens\capas\381074\1\499.jpg | R24: https://permalinkbnd.bnportugal.gov.pt/viewer/274089/?offset=#page=499&viewer=picture&o=info&n=0&q= | T24: 10, 11, 103, 145, 235, 270, 273, 306, 309, 342, 345, 374, 377, 410, 413, 447, 499 | W24: Sim
A25: 381074 | B25: 1 | C25: 526 | D25: https://purl.pt/43747 | E25: https://purl.pt/43747 | F25: 274089 | G25: https://permalinkbnd.bnportugal.gov.pt/viewer/ | H25: /?offset=#page= | I25: &viewer=picture&o=info&n=0&q= | J25: =CONCATENATE(G25,F25,H25,C25,I25) -> https://permalinkbnd.bnportugal.gov.pt/viewer/274089/?offset=#page=526&viewer=picture&o=info&n=0&q= | K25: 10 [site], 11, 103 [site pelicano direita], 107, 142, 107, 142, 145, 185, 235, 270 [site assassinato de Inês], 273, 306, 309 [site ninfas], 342, 345, 374, 377, 410, 413, 447, 499, 526 [site apontamento] [pintura de Camões por Columbano, portada, fac-símile do frontispício da 1.ª Ed. de Os Lusíadas, ilustrações da obra] | L25: =VLOOKUP(A25,Folha2!$A$2:$B$2019,2,FALSE) -> Os Lusíadas, Rio de Janeiro, 1880, sem argumentos. | M25: =HYPERLINK(J25) -> https://permalinkbnd.bnportugal.gov.pt/viewer/274089/?offset=#page=526&viewer=picture&o=info&n=0&q= | N25: C:\Users\mbaptista\OneDrive - Biblioteca Nacional de Portugal\Documentos\python\camoniana\imagens\capas\ | O25: =CONCATENATE(N25,A25,"\",B25,"\",C25,".jpg") -> C:\Users\mbaptista\OneDrive - Biblioteca Nacional de Portugal\Documentos\python\camoniana\imagens\capas\381074\1\526.jpg | P25: =HYPERLINK(O25) -> C:\Users\mbaptista\OneDrive - Biblioteca Nacional de Portugal\Documentos\python\camoniana\imagens\capas\381074\1\526.jpg | T25: 10, 11, 103, 145, 235, 270, 273, 306, 309, 342, 345, 374, 377, 410, 413, 447, 499
A26: 381465 | C26: 5 | D26: https://purl.pt/43233 | E26: https://purl.pt/43233 | F26: 271573 | G26: https://permalinkbnd.bnportugal.gov.pt/viewer/ | H26: /?offset=#page= | I26: &viewer=picture&o=info&n=0&q= | J26: =CONCATENATE(G26,F26,H26,C26,I26) -> https://permalinkbnd.bnportugal.gov.pt/viewer/271573/?offset=#page=5&viewer=picture&o=info&n=0&q= | K26: 5 [site], 10 [site], 11 [site], 43, 46 [Vasco da Gama], 47, 100, 101, 160, 161, 163, 235, 237, 289, 291 [site Adamastor], 293, 343 [site apontamento livros e pena], 345, 347, 397, 443, 445, 495 [site Mercúrio, caduceu e navegador], 545 [site máquina do mundo], 547, 625, 627, 644 [monge com livro] [portadas, retrato de Camões, fotogravuras em cada Canto] | L26: =VLOOKUP(A26,Folha2!$A$2:$B$2019,2,FALSE) -> Os Lusíadas, 1898, obra dedicada à Comissão do Centenário e nos paratextos é referida a Celebração: Celebrações (1880); Paratextos argumentos e Iconografia figuras históricas. | M26: =HYPERLINK(J26) -> https://permalinkbnd.bnportugal.gov.pt/viewer/271573/?offset=#page=5&viewer=picture&o=info&n=0&q= | N26: C:\Users\mbaptista\OneDrive - Biblioteca Nacional de Portugal\Documentos\python\camoniana\imagens\capas\ | O26: =CONCATENATE(N26,A26,"\",B26,"\",C26,".jpg") -> C:\Users\mbaptista\OneDrive - Biblioteca Nacional de Portugal\Documentos\python\camoniana\imagens\capas\381465\\5.jpg | P26: =HYPERLINK(O26) -> C:\Users\mbaptista\OneDrive - Biblioteca Nacional de Portugal\Documentos\python\camoniana\imagens\capas\381465\\5.jpg | T26: 5, 10, 11, 43, 46 , 47, 101, 160, 161, 163, 235, 237, 291, 293, 343, 345, 347, 397, 443, 445, 495 , 545, 547, 627, 644
A27: 381465 | C27: 10 | D27: https://purl.pt/43233 | E27: https://purl.pt/43233 | F27: 271573 | G27: https://permalinkbnd.bnportugal.gov.pt/viewer/ | H27: /?offset=#page= | I27: &viewer=picture&o=info&n=0&q= | J27: =CONCATENATE(G27,F27,H27,C27,I27) -> https://permalinkbnd.bnportugal.gov.pt/viewer/271573/?offset=#page=10&viewer=picture&o=info&n=0&q= | K27: 5 [site], 10 [site], 11 [site], 43, 46 [Vasco da Gama], 47, 100, 101, 160, 161, 163, 235, 237, 289, 291 [site Adamastor], 293, 343 [site apontamento livros e pena], 345, 347, 397, 443, 445, 495 [site Mercúrio, caduceu e navegador], 545 [site máquina do mundo], 547, 625, 627, 644 [monge com livro] [portadas, retrato de Camões, fotogravuras em cada Canto] | L27: =VLOOKUP(A27,Folha2!$A$2:$B$2019,2,FALSE) -> Os Lusíadas, 1898, obra dedicada à Comissão do Centenário e nos paratextos é referida a Celebração: Celebrações (1880); Paratextos argumentos e Iconografia figuras históricas. | M27: =HYPERLINK(J27) -> https://permalinkbnd.bnportugal.gov.pt/viewer/271573/?offset=#page=10&viewer=picture&o=info&n=0&q= | N27: C:\Users\mbaptista\OneDrive - Biblioteca Nacional de Portugal\Documentos\python\camoniana\imagens\capas\ | O27: =CONCATENATE(N27,A27,"\",B27,"\",C27,".jpg") -> C:\Users\mbaptista\OneDrive - Biblioteca Nacional de Portugal\Documentos\python\camoniana\imagens\capas\381465\\10.jpg | P27: =HYPERLINK(O27) -> C:\Users\mbaptista\OneDrive - Biblioteca Nacional de Portugal\Documentos\python\camoniana\imagens\capas\381465\\10.jpg | T27: 5, 10, 11, 43, 46 , 47, 101, 160, 161, 163, 235, 237, 291, 293, 343, 345, 347, 397, 443, 445, 495 , 545, 547, 627, 644
A28: 381465 | C28: 43 | D28: https://purl.pt/43233 | E28: https://purl.pt/43233 | F28: 271573 | G28: https://permalinkbnd.bnportugal.gov.pt/viewer/ | H28: /?offset=#page= | I28: &viewer=picture&o=info&n=0&q= | J28: =CONCATENATE(G28,F28,H28,C28,I28) -> https://permalinkbnd.bnportugal.gov.pt/viewer/271573/?offset=#page=43&viewer=picture&o=info&n=0&q= | K28: 5 [site], 10 [site], 11 [site], 43, 46 [Vasco da Gama], 47, 100, 101, 160, 161, 163, 235, 237, 289, 291 [site Adamastor], 293, 343 [site apontamento livros e pena], 345, 347, 397, 443, 445, 495 [site Mercúrio, caduceu e navegador], 545 [site máquina do mundo], 547, 625, 627, 644 [monge com livro] [portadas, retrato de Camões, fotogravuras em cada Canto] | L28: =VLOOKUP(A28,Folha2!$A$2:$B$2019,2,FALSE) -> Os Lusíadas, 1898, obra dedicada à Comissão do Centenário e nos paratextos é referida a Celebração: Celebrações (1880); Paratextos argumentos e Iconografia figuras históricas. | M28: =HYPERLINK(J28) -> https://permalinkbnd.bnportugal.gov.pt/viewer/271573/?offset=#page=43&viewer=picture&o=info&n=0&q= | N28: C:\Users\mbaptista\OneDrive - Biblioteca Nacional de Portugal\Documentos\python\camoniana\imagens\capas\ | O28: =CONCATENATE(N28,A28,"\",B28,"\",C28,".jpg") -> C:\Users\mbaptista\OneDrive - Biblioteca Nacional de Portugal\Documentos\python\camoniana\imagens\capas\381465\\43.jpg | P28: =HYPERLINK(O28) -> C:\Users\mbaptista\OneDrive - Biblioteca Nacional de Portugal\Documentos\python\camoniana\imagens\capas\381465\\43.jpg | T28: 5, 10, 11, 43, 46 , 47, 101, 160, 161, 163, 235, 237, 291, 293, 343, 345, 347, 397, 443, 445, 495 , 545, 547, 627, 644
A29: 381465 | C29: 46 | D29: https://purl.pt/43233 | E29: https://purl.pt/43233 | F29: 271573 | G29: https://permalinkbnd.bnportugal.gov.pt/viewer/ | H29: /?offset=#page= | I29: &viewer=picture&o=info&n=0&q= | J29: =CONCATENATE(G29,F29,H29,C29,I29) -> https://permalinkbnd.bnportugal.gov.pt/viewer/271573/?offset=#page=46&viewer=picture&o=info&n=0&q= | K29: 5 [site], 10 [site], 11 [site], 43, 46 [Vasco da Gama], 47, 100, 101, 160, 161, 163, 235, 237, 289, 291 [site Adamastor], 293, 343 [site apontamento livros e pena], 345, 347, 397, 443, 445, 495 [site Mercúrio, caduceu e navegador], 545 [site máquina do mundo], 547, 625, 627, 644 [monge com livro] [portadas, retrato de Camões, fotogravuras em cada Canto] | L29: =VLOOKUP(A29,Folha2!$A$2:$B$2019,2,FALSE) -> Os Lusíadas, 1898, obra dedicada à Comissão do Centenário e nos paratextos é referida a Celebração: Celebrações (1880); Paratextos argumentos e Iconografia figuras históricas. | M29: =HYPERLINK(J29) -> https://permalinkbnd.bnportugal.gov.pt/viewer/271573/?offset=#page=46&viewer=picture&o=info&n=0&q= | N29: C:\Users\mbaptista\OneDrive - Biblioteca Nacional de Portugal\Documentos\python\camoniana\imagens\capas\ | O29: =CONCATENATE(N29,A29,"\",B29,"\",C29,".jpg") -> C:\Users\mbaptista\OneDrive - Biblioteca Nacional de Portugal\Documentos\python\camoniana\imagens\capas\381465\\46.jpg | P29: =HYPERLINK(O29) -> C:\Users\mbaptista\OneDrive - Biblioteca Nacional de Portugal\Documentos\python\camoniana\imagens\capas\381465\\46.jpg | T29: 5, 10, 11, 43, 46 , 47, 101, 160, 161, 163, 235, 237, 291, 293, 343, 345, 347, 397, 443, 445, 495 , 545, 547, 627, 644
A30: 381465 | C30: 47 | D30: https://purl.pt/43233 | E30: https://purl.pt/43233 | F30: 271573 | G30: https://permalinkbnd.bnportugal.gov.pt/viewer/ | H30: /?offset=#page= | I30: &viewer=picture&o=info&n=0&q= | J30: =CONCATENATE(G30,F30,H30,C30,I30) -> https://permalinkbnd.bnportugal.gov.pt/viewer/271573/?offset=#page=47&viewer=picture&o=info&n=0&q= | K30: 5 [site], 10 [site], 11 [site], 43, 46 [Vasco da Gama], 47, 100, 101, 160, 161, 163, 235, 237, 289, 291 [site Adamastor], 293, 343 [site apontamento livros e pena], 345, 347, 397, 443, 445, 495 [site Mercúrio, caduceu e navegador], 545 [site máquina do mundo], 547, 625, 627, 644 [monge com livro] [portadas, retrato de Camões, fotogravuras em cada Canto] | L30: =VLOOKUP(A30,Folha2!$A$2:$B$2019,2,FALSE) -> Os Lusíadas, 1898, obra dedicada à Comissão do Centenário e nos paratextos é referida a Celebração: Celebrações (1880); Paratextos argumentos e Iconografia figuras históricas. | M30: =HYPERLINK(J30) -> https://permalinkbnd.bnportugal.gov.pt/viewer/271573/?offset=#page=47&viewer=picture&o=info&n=0&q= | N30: C:\Users\mbaptista\OneDrive - Biblioteca Nacional de Portugal\Documentos\python\camoniana\imagens\capas\ | O30: =CONCATENATE(N30,A30,"\",B30,"\",C30,".jpg") -> C:\Users\mbaptista\OneDrive - Biblioteca Nacional de Portugal\Documentos\python\camoniana\imagens\capas\381465\\47.jpg | P30: =HYPERLINK(O30) -> C:\Users\mbaptista\OneDrive - Biblioteca Nacional de Portugal\Documentos\python\camoniana\imagens\capas\381465\\47.jpg | T30: 5, 10, 11, 43, 46 , 47, 101, 160, 161, 163, 235, 237, 291, 293, 343, 345, 347, 397, 443, 445, 495 , 545, 547, 627, 644
A31: 381465 | C31: 100 | D31: https://purl.pt/43233 | E31: https://purl.pt/43233 | F31: 271573 | G31: https://permalinkbnd.bnportugal.gov.pt/viewer/ | H31: /?offset=#page= | I31: &viewer=picture&o=info&n=0&q= | J31: =CONCATENATE(G31,F31,H31,C31,I31) -> https://permalinkbnd.bnportugal.gov.pt/viewer/271573/?offset=#page=100&viewer=picture&o=info&n=0&q= | K31: 5 [site], 10 [site], 11 [site], 43, 46 [Vasco da Gama], 47, 100, 101, 160, 161, 163, 235, 237, 289, 291 [site Adamastor], 293, 343 [site apontamento livros e pena], 345, 347, 397, 443, 445, 495 [site Mercúrio, caduceu e navegador], 545 [site máquina do mundo], 547, 625, 627, 644 [monge com livro] [portadas, retrato de Camões, fotogravuras em cada Canto] | L31: =VLOOKUP(A31,Folha2!$A$2:$B$2019,2,FALSE) -> Os Lusíadas, 1898, obra dedicada à Comissão do Centenário e nos paratextos é referida a Celebração: Celebrações (1880); Paratextos argumentos e Iconografia figuras históricas. | M31: =HYPERLINK(J31) -> https://permalinkbnd.bnportugal.gov.pt/viewer/271573/?offset=#page=100&viewer=picture&o=info&n=0&q= | N31: C:\Users\mbaptista\OneDrive - Biblioteca Nacional de Portugal\Documentos\python\camoniana\imagens\capas\ | O31: =CONCATENATE(N31,A31,"\",B31,"\",C31,".jpg") -> C:\Users\mbaptista\OneDrive - Biblioteca Nacional de Portugal\Documentos\python\camoniana\imagens\capas\381465\\100.jpg | P31: =HYPERLINK(O31) -> C:\Users\mbaptista\OneDrive - Biblioteca Nacional de Portugal\Documentos\python\camoniana\imagens\capas\381465\\100.jpg | T31: 5, 10, 11, 43, 46 , 47, 101, 160, 161, 163, 235, 237, 291, 293, 343, 345, 347, 397, 443, 445, 495 , 545, 547, 627, 644
A32: 381465 | C32: 101 | D32: https://purl.pt/43233 | E32: https://purl.pt/43233 | F32: 271573 | G32: https://permalinkbnd.bnportugal.gov.pt/viewer/ | H32: /?offset=#page= | I32: &viewer=picture&o=info&n=0&q= | J32: =CONCATENATE(G32,F32,H32,C32,I32) -> https://permalinkbnd.bnportugal.gov.pt/viewer/271573/?offset=#page=101&viewer=picture&o=info&n=0&q= | K32: 5 [site], 10 [site], 11 [site], 43, 46 [Vasco da Gama], 47, 100, 101, 160, 161, 163, 235, 237, 289, 291 [site Adamastor], 293, 343 [site apontamento livros e pena], 345, 347, 397, 443, 445, 495 [site Mercúrio, caduceu e navegador], 545 [site máquina do mundo], 547, 625, 627, 644 [monge com livro] [portadas, retrato de Camões, fotogravuras em cada Canto] | L32: =VLOOKUP(A32,Folha2!$A$2:$B$2019,2,FALSE) -> Os Lusíadas, 1898, obra dedicada à Comissão do Centenário e nos paratextos é referida a Celebração: Celebrações (1880); Paratextos argumentos e Iconografia figuras históricas. | M32: =HYPERLINK(J32) -> https://permalinkbnd.bnportugal.gov.pt/viewer/271573/?offset=#page=101&viewer=picture&o=info&n=0&q= | N32: C:\Users\mbaptista\OneDrive - Biblioteca Nacional de Portugal\Documentos\python\camoniana\imagens\capas\ | O32: =CONCATENATE(N32,A32,"\",B32,"\",C32,".jpg") -> C:\Users\mbaptista\OneDrive - Biblioteca Nacional de Portugal\Documentos\python\camoniana\imagens\capas\381465\\101.jpg | P32: =HYPERLINK(O32) -> C:\Users\mbaptista\OneDrive - Biblioteca Nacional de Portugal\Documentos\python\camoniana\imagens\capas\381465\\101.jpg | T32: 5, 10, 11, 43, 46 , 47, 101, 160, 161, 163, 235, 237, 291, 293, 343, 345, 347, 397, 443, 445, 495 , 545, 547, 627, 644
A33: 381465 | C33: 160 | D33: https://purl.pt/43233 | E33: https://purl.pt/43233 | F33: 271573 | G33: https://permalinkbnd.bnportugal.gov.pt/viewer/ | H33: /?offset=#page= | I33: &viewer=picture&o=info&n=0&q= | J33: =CONCATENATE(G33,F33,H33,C33,I33) -> https://permalinkbnd.bnportugal.gov.pt/viewer/271573/?offset=#page=160&viewer=picture&o=info&n=0&q= | K33: 5 [site], 10 [site], 11 [site], 43, 46 [Vasco da Gama], 47, 100, 101, 160, 161, 163, 235, 237, 289, 291 [site Adamastor], 293, 343 [site apontamento livros e pena], 345, 347, 397, 443, 445, 495 [site Mercúrio, caduceu e navegador], 545 [site máquina do mundo], 547, 625, 627, 644 [monge com livro] [portadas, retrato de Camões, fotogravuras em cada Canto] | L33: =VLOOKUP(A33,Folha2!$A$2:$B$2019,2,FALSE) -> Os Lusíadas, 1898, obra dedicada à Comissão do Centenário e nos paratextos é referida a Celebração: Celebrações (1880); Paratextos argumentos e Iconografia figuras históricas. | M33: =HYPERLINK(J33) -> https://permalinkbnd.bnportugal.gov.pt/viewer/271573/?offset=#page=160&viewer=picture&o=info&n=0&q= | N33: C:\Users\mbaptista\OneDrive - Biblioteca Nacional de Portugal\Documentos\python\camoniana\imagens\capas\ | O33: =CONCATENATE(N33,A33,"\",B33,"\",C33,".jpg") -> C:\Users\mbaptista\OneDrive - Biblioteca Nacional de Portugal\Documentos\python\camoniana\imagens\capas\381465\\160.jpg | P33: =HYPERLINK(O33) -> C:\Users\mbaptista\OneDrive - Biblioteca Nacional de Portugal\Documentos\python\camoniana\imagens\capas\381465\\160.jpg | T33: 5, 10, 11, 43, 46 , 47, 101, 160, 161, 163, 235, 237, 291, 293, 343, 345, 347, 397, 443, 445, 495 , 545, 547, 627, 644
A34: 381465 | C34: 161 | D34: https://purl.pt/43233 | E34: https://purl.pt/43233 | F34: 271573 | G34: https://permalinkbnd.bnportugal.gov.pt/viewer/ | H34: /?offset=#page= | I34: &viewer=picture&o=info&n=0&q= | J34: =CONCATENATE(G34,F34,H34,C34,I34) -> https://permalinkbnd.bnportugal.gov.pt/viewer/271573/?offset=#page=161&viewer=picture&o=info&n=0&q= | K34: 5 [site], 10 [site], 11 [site], 43, 46 [Vasco da Gama], 47, 100, 101, 160, 161, 163, 235, 237, 289, 291 [site Adamastor], 293, 343 [site apontamento livros e pena], 345, 347, 397, 443, 445, 495 [site Mercúrio, caduceu e navegador], 545 [site máquina do mundo], 547, 625, 627, 644 [monge com livro] [portadas, retrato de Camões, fotogravuras em cada Canto] | L34: =VLOOKUP(A34,Folha2!$A$2:$B$2019,2,FALSE) -> Os Lusíadas, 1898, obra dedicada à Comissão do Centenário e nos paratextos é referida a Celebração: Celebrações (1880); Paratextos argumentos e Iconografia figuras históricas. | M34: =HYPERLINK(J34) -> https://permalinkbnd.bnportugal.gov.pt/viewer/271573/?offset=#page=161&viewer=picture&o=info&n=0&q= | N34: C:\Users\mbaptista\OneDrive - Biblioteca Nacional de Portugal\Documentos\python\camoniana\imagens\capas\ | O34: =CONCATENATE(N34,A34,"\",B34,"\",C34,".jpg") -> C:\Users\mbaptista\OneDrive - Biblioteca Nacional de Portugal\Documentos\python\camoniana\imagens\capas\381465\\161.jpg | P34: =HYPERLINK(O34) -> C:\Users\mbaptista\OneDrive - Biblioteca Nacional de Portugal\Documentos\python\camoniana\imagens\capas\381465\\161.jpg | T34: 5, 10, 11, 43, 46 , 47, 101, 160, 161, 163, 235, 237, 291, 293, 343, 345, 347, 397, 443, 445, 495 , 545, 547, 627, 644
A35: 381465 | C35: 163 | D35: https://purl.pt/43233 | E35: https://purl.pt/43233 | F35: 271573 | G35: https://permalinkbnd.bnportugal.gov.pt/viewer/ | H35: /?offset=#page= | I35: &viewer=picture&o=info&n=0&q= | J35: =CONCATENATE(G35,F35,H35,C35,I35) -> https://permalinkbnd.bnportugal.gov.pt/viewer/271573/?offset=#page=163&viewer=picture&o=info&n=0&q= | K35: 5 [site], 10 [site], 11 [site], 43, 46 [Vasco da Gama], 47, 100, 101, 160, 161, 163, 235, 237, 289, 291 [site Adamastor], 293, 343 [site apontamento livros e pena], 345, 347, 397, 443, 445, 495 [site Mercúrio, caduceu e navegador], 545 [site máquina do mundo], 547, 625, 627, 644 [monge com livro] [portadas, retrato de Camões, fotogravuras em cada Canto] | L35: =VLOOKUP(A35,Folha2!$A$2:$B$2019,2,FALSE) -> Os Lusíadas, 1898, obra dedicada à Comissão do Centenário e nos paratextos é referida a Celebração: Celebrações (1880); Paratextos argumentos e Iconografia figuras históricas. | M35: =HYPERLINK(J35) -> https://permalinkbnd.bnportugal.gov.pt/viewer/271573/?offset=#page=163&viewer=picture&o=info&n=0&q= | N35: C:\Users\mbaptista\OneDrive - Biblioteca Nacional de Portugal\Documentos\python\camoniana\imagens\capas\ | O35: =CONCATENATE(N35,A35,"\",B35,"\",C35,".jpg") -> C:\Users\mbaptista\OneDrive - Biblioteca Nacional de Portugal\Documentos\python\camoniana\imagens\capas\381465\\163.jpg | P35: =HYPERLINK(O35) -> C:\Users\mbaptista\OneDrive - Biblioteca Nacional de Portugal\Documentos\python\camoniana\imagens\capas\381465\\163.jpg | T35: 5, 10, 11, 43, 46 , 47, 101, 160, 161, 163, 235, 237, 291, 293, 343, 345, 347, 397, 443, 445, 495 , 545, 547, 627, 644
A36: 381465 | C36: 235 | D36: https://purl.pt/43233 | E36: https://purl.pt/43233 | F36: 271573 | G36: https://permalinkbnd.bnportugal.gov.pt/viewer/ | H36: /?offset=#page= | I36: &viewer=picture&o=info&n=0&q= | J36: =CONCATENATE(G36,F36,H36,C36,I36) -> https://permalinkbnd.bnportugal.gov.pt/viewer/271573/?offset=#page=235&viewer=picture&o=info&n=0&q= | K36: 5 [site], 10 [site], 11 [site], 43, 46 [Vasco da Gama], 47, 100, 101, 160, 161, 163, 235, 237, 289, 291 [site Adamastor], 293, 343 [site apontamento livros e pena], 345, 347, 397, 443, 445, 495 [site Mercúrio, caduceu e navegador], 545 [site máquina do mundo], 547, 625, 627, 644 [monge com livro] [portadas, retrato de Camões, fotogravuras em cada Canto] | L36: =VLOOKUP(A36,Folha2!$A$2:$B$2019,2,FALSE) -> Os Lusíadas, 1898, obra dedicada à Comissão do Centenário e nos paratextos é referida a Celebração: Celebrações (1880); Paratextos argumentos e Iconografia figuras históricas. | M36: =HYPERLINK(J36) -> https://permalinkbnd.bnportugal.gov.pt/viewer/271573/?offset=#page=235&viewer=picture&o=info&n=0&q= | N36: C:\Users\mbaptista\OneDrive - Biblioteca Nacional de Portugal\Documentos\python\camoniana\imagens\capas\ | O36: =CONCATENATE(N36,A36,"\",B36,"\",C36,".jpg") -> C:\Users\mbaptista\OneDrive - Biblioteca Nacional de Portugal\Documentos\python\camoniana\imagens\capas\381465\\235.jpg | P36: =HYPERLINK(O36) -> C:\Users\mbaptista\OneDrive - Biblioteca Nacional de Portugal\Documentos\python\camoniana\imagens\capas\381465\\235.jpg | T36: 5, 10, 11, 43, 46 , 47, 101, 160, 161, 163, 235, 237, 291, 293, 343, 345, 347, 397, 443, 445, 495 , 545, 547, 627, 644
A37: 381465 | C37: 237 | D37: https://purl.pt/43233 | E37: https://purl.pt/43233 | F37: 271573 | G37: https://permalinkbnd.bnportugal.gov.pt/viewer/ | H37: /?offset=#page= | I37: &viewer=picture&o=info&n=0&q= | J37: =CONCATENATE(G37,F37,H37,C37,I37) -> https://permalinkbnd.bnportugal.gov.pt/viewer/271573/?offset=#page=237&viewer=picture&o=info&n=0&q= | K37: 5 [site], 10 [site], 11 [site], 43, 46 [Vasco da Gama], 47, 100, 101, 160, 161, 163, 235, 237, 289, 291 [site Adamastor], 293, 343 [site apontamento livros e pena], 345, 347, 397, 443, 445, 495 [site Mercúrio, caduceu e navegador], 545 [site máquina do mundo], 547, 625, 627, 644 [monge com livro] [portadas, retrato de Camões, fotogravuras em cada Canto] | L37: =VLOOKUP(A37,Folha2!$A$2:$B$2019,2,FALSE) -> Os Lusíadas, 1898, obra dedicada à Comissão do Centenário e nos paratextos é referida a Celebração: Celebrações (1880); Paratextos argumentos e Iconografia figuras históricas. | M37: =HYPERLINK(J37) -> https://permalinkbnd.bnportugal.gov.pt/viewer/271573/?offset=#page=237&viewer=picture&o=info&n=0&q= | N37: C:\Users\mbaptista\OneDrive - Biblioteca Nacional de Portugal\Documentos\python\camoniana\imagens\capas\ | O37: =CONCATENATE(N37,A37,"\",B37,"\",C37,".jpg") -> C:\Users\mbaptista\OneDrive - Biblioteca Nacional de Portugal\Documentos\python\camoniana\imagens\capas\381465\\237.jpg | P37: =HYPERLINK(O37) -> C:\Users\mbaptista\OneDrive - Biblioteca Nacional de Portugal\Documentos\python\camoniana\imagens\capas\381465\\237.jpg | T37: 5, 10, 11, 43, 46 , 47, 101, 160, 161, 163, 235, 237, 291, 293, 343, 345, 347, 397, 443, 445, 495 , 545, 547, 627, 644
... A51: 381465 | C51: 627 | D51: https://purl.pt/43233 | E51: https://purl.pt/43233 | F51: 271573 | G51: https://permalinkbnd.bnportugal.gov.pt/viewer/ | H51: /?offset=#page= | I51: &viewer=picture&o=info&n=0&q= | J51: =CONCATENATE(G51,F51,H51,C51,I51) -> https://permalinkbnd.bnportugal.gov.pt/viewer/271573/?offset=#page=627&viewer=picture&o=info&n=0&q= | K51: 5 [site], 10 [site], 11 [site], 43, 46 [Vasco da Gama], 47, 100, 101, 160, 161, 163, 235, 237, 289, 291 [site Adamastor], 293, 343 [site apontamento livros e pena], 345, 347, 397, 443, 445, 495 [site Mercúrio, caduceu e navegador], 545 [site máquina do mundo], 547, 625, 627, 644 [monge com livro] [portadas, retrato de Camões, fotogravuras em cada Canto] | L51: =VLOOKUP(A51,Folha2!$A$2:$B$2019,2,FALSE) -> Os Lusíadas, 1898, obra dedicada à Comissão do Centenário e nos paratextos é referida a Celebração: Celebrações (1880); Paratextos argumentos e Iconografia figuras históricas. | M51: =HYPERLINK(J51) -> https://permalinkbnd.bnportugal.gov.pt/viewer/271573/?offset=#page=627&viewer=picture&o=info&n=0&q= | N51: C:\Users\mbaptista\OneDrive - Biblioteca Nacional de Portugal\Documentos\python\camoniana\imagens\capas\ | O51: =CONCATENATE(N51,A51,"\",B51,"\",C51,".jpg") -> C:\Users\mbaptista\OneDrive - Biblioteca Nacional de Portugal\Documentos\python\camoniana\imagens\capas\381465\\627.jpg | P51: =HYPERLINK(O51) -> C:\Users\mbaptista\OneDrive - Biblioteca Nacional de Portugal\Documentos\python\camoniana\imagens\capas\381465\\627.jpg | T51: 5, 10, 11, 43, 46 , 47, 101, 160, 161, 163, 235, 237, 291, 293, 343, 345, 347, 397, 443, 445, 495 , 545, 547, 627, 644
A52: 381465 | B52: 1 | C52: 644 | D52: https://purl.pt/43233 | E52: https://purl.pt/43233 | F52: 271573 | G52: https://permalinkbnd.bnportugal.gov.pt/viewer/ | H52: /?offset=#page= | I52: &viewer=picture&o=info&n=0&q= | J52: =CONCATENATE(G52,F52,H52,C52,I52) -> https://permalinkbnd.bnportugal.gov.pt/viewer/271573/?offset=#page=644&viewer=picture&o=info&n=0&q= | K52: 5 [site], 10 [site], 11 [site], 43, 46 [Vasco da Gama], 47, 100, 101, 160, 161, 163, 235, 237, 289, 291 [site Adamastor], 293, 343 [site apontamento livros e pena], 345, 347, 397, 443, 445, 495 [site Mercúrio, caduceu e navegador], 545 [site máquina do mundo], 547, 625, 627, 644 [monge com livro] [portadas, retrato de Camões, fotogravuras em cada Canto] | L52: =VLOOKUP(A52,Folha2!$A$2:$B$2019,2,FALSE) -> Os Lusíadas, 1898, obra dedicada à Comissão do Centenário e nos paratextos é referida a Celebração: Celebrações (1880); Paratextos argumentos e Iconografia figuras históricas. | M52: =HYPERLINK(J52) -> https://permalinkbnd.bnportugal.gov.pt/viewer/271573/?offset=#page=644&viewer=picture&o=info&n=0&q= | N52: C:\Users\mbaptista\OneDrive - Biblioteca Nacional de Portugal\Documentos\python\camoniana\imagens\capas\ | O52: =CONCATENATE(N52,A52,"\",B52,"\",C52,".jpg") -> C:\Users\mbaptista\OneDrive - Biblioteca Nacional de Portugal\Documentos\python\camoniana\imagens\capas\381465\1\644.jpg | P52: =HYPERLINK(O52) -> C:\Users\mbaptista\OneDrive - Biblioteca Nacional de Portugal\Documentos\python\camoniana\imagens\capas\381465\1\644.jpg | R52: https://permalinkbnd.bnportugal.gov.pt/viewer/271573/?offset=#page=644&viewer=picture&o=info&n=0&q= | T52: 5, 10, 11, 43, 46 , 47, 101, 160, 161, 163, 235, 237, 291, 293, 343, 345, 347, 397, 443, 445, 495 , 545, 547, 627, 644 | W52: Sim
A53: 381468 | B53: 1 | C53: 8 | D53: https://purl.pt/43745 | E53: https://purl.pt/43745 | F53: 274087 | G53: https://permalinkbnd.bnportugal.gov.pt/viewer/ | H53: /?offset=#page= | I53: &viewer=picture&o=info&n=0&q= | J53: =CONCATENATE(G53,F53,H53,C53,I53) -> https://permalinkbnd.bnportugal.gov.pt/viewer/274087/?offset=#page=8&viewer=picture&o=info&n=0&q= | K53: 8 [site retrato de Camões] | L53: =VLOOKUP(A53,Folha2!$A$2:$B$2019,2,FALSE) -> Os Lusíadas/Los Portugueses, D. Carlos Soler y Arques, 1873. Bilingue, sem argumentos. Trad. Paratextos; Trad. Paratextos vida; Trad. Paratextos notas. | M53: =HYPERLINK(J53) -> https://permalinkbnd.bnportugal.gov.pt/viewer/274087/?offset=#page=8&viewer=picture&o=info&n=0&q= | N53: C:\Users\mbaptista\OneDrive - Biblioteca Nacional de Portugal\Documentos\python\camoniana\imagens\capas\ | O53: =CONCATENATE(N53,A53,"\",B53,"\",C53,".jpg") -> C:\Users\mbaptista\OneDrive - Biblioteca Nacional de Portugal\Documentos\python\camoniana\imagens\capas\381468\1\8.jpg | P53: =HYPERLINK(O53) -> C:\Users\mbaptista\OneDrive - Biblioteca Nacional de Portugal\Documentos\python\camoniana\imagens\capas\381468\1\8.jpg | R53: https://permalinkbnd.bnportugal.gov.pt/viewer/274087/?offset=#page=8&viewer=picture&o=info&n=0&q= | T53: 8 | W53: Sim
A54: 381701 | B54: 1 | C54: 11 | D54: https://purl.pt/43724 | E54: https://purl.pt/43724 | F54: 281141 | G54: https://permalinkbnd.bnportugal.gov.pt/viewer/ | H54: /?offset=#page= | I54: &viewer=picture&o=info&n=0&q= | J54: =CONCATENATE(G54,F54,H54,C54,I54) -> https://permalinkbnd.bnportugal.gov.pt/viewer/281141/?offset=#page=11&viewer=picture&o=info&n=0&q= | K54: 11 | L54: =VLOOKUP(A54,Folha2!$A$2:$B$2019,2,FALSE) -> Inês de Castro, 1873. [cópia digital não abre, consultado PDF via Miguel] Edição em catorze línguas, um ano depois das Celebrações (1872), mas sem referência. | M54: =HYPERLINK(J54) -> https://permalinkbnd.bnportugal.gov.pt/viewer/281141/?offset=#page=11&viewer=picture&o=info&n=0&q= | N54: C:\Users\mbaptista\OneDrive - Biblioteca Nacional de Portugal\Documentos\python\camoniana\imagens\capas\ | O54: =CONCATENATE(N54,A54,"\",B54,"\",C54,".jpg") -> C:\Users\mbaptista\OneDrive - Biblioteca Nacional de Portugal\Documentos\python\camoniana\imagens\capas\381701\1\11.jpg | P54: =HYPERLINK(O54) -> C:\Users\mbaptista\OneDrive - Biblioteca Nacional de Portugal\Documentos\python\camoniana\imagens\capas\381701\1\11.jpg | R54: https://permalinkbnd.bnportugal.gov.pt/viewer/281141/?offset=#page=11&viewer=picture&o=info&n=0&q= | T54: 11 | W54: Sim
A55: 381889 | B55: 1 | C55: 1 | D55: https://purl.pt/43659 | E55: https://purl.pt/43659 | F55: 273118 | G55: https://permalinkbnd.bnportugal.gov.pt/viewer/ | H55: /?offset=#page= | I55: &viewer=picture&o=info&n=0&q= | J55: =CONCATENATE(G55,F55,H55,C55,I55) -> https://permalinkbnd.bnportugal.gov.pt/viewer/273118/?offset=#page=1&viewer=picture&o=info&n=0&q= | K55: 1 [Inês de Castro, Vasco da Gama, Catarina de Ataíde e retrato de Camões] | L55: =VLOOKUP(A55,Folha2!$A$2:$B$2019,2,FALSE) -> Pérolas de Camões. 1880. Inês de Castro, Adamastor, Ilha dos Amores, sem argumentos, Soneto a Natércia [em Antologia não existe fragmento/soneto lírica?]. Iconografia, figuras históricas. | M55: =HYPERLINK(J55) -> https://permalinkbnd.bnportugal.gov.pt/viewer/273118/?offset=#page=1&viewer=picture&o=info&n=0&q= | N55: C:\Users\mbaptista\OneDrive - Biblioteca Nacional de Portugal\Documentos\python\camoniana\imagens\capas\ | O55: =CONCATENATE(N55,A55,"\",B55,"\",C55,".jpg") -> C:\Users\mbaptista\OneDrive - Biblioteca Nacional de Portugal\Documentos\python\camoniana\imagens\capas\381889\1\1.jpg | P55: =HYPERLINK(O55) -> C:\Users\mbaptista\OneDrive - Biblioteca Nacional de Portugal\Documentos\python\camoniana\imagens\capas\381889\1\1.jpg | R55: https://permalinkbnd.bnportugal.gov.pt/viewer/273118/?offset=#page=1&viewer=picture&o=info&n=0&q= | T55: 1 | W55: Sim
A56: 381903 | B56: 1 | C56: 5 | D56: https://purl.pt/42920 | E56: https://purl.pt/42920 | F56: 270037 | G56: https://permalinkbnd.bnportugal.gov.pt/viewer/ | H56: /?offset=#page= | I56: &viewer=picture&o=info&n=0&q= | J56: =CONCATENATE(G56,F56,H56,C56,I56) -> https://permalinkbnd.bnportugal.gov.pt/viewer/270037/?offset=#page=5&viewer=picture&o=info&n=0&q= | K56: 5 [1.º] | L56: =VLOOKUP(A56,Folha2!$A$2:$B$2019,2,FALSE) -> Artigo polaco? Séc. XIX: " Luiz de Camoens" da autoria de K. Kaszewskiego 1880, continuação do texto no CAM. 45//3 A. | M56: =HYPERLINK(J56) -> https://permalinkbnd.bnportugal.gov.pt/viewer/270037/?offset=#page=5&viewer=picture&o=info&n=0&q= | N56: C:\Users\mbaptista\OneDrive - Biblioteca Nacional de Portugal\Documentos\python\camoniana\imagens\capas\ | O56: =CONCATENATE(N56,A56,"\",B56,"\",C56,".jpg") -> C:\Users\mbaptista\OneDrive - Biblioteca Nacional de Portugal\Documentos\python\camoniana\imagens\capas\381903\1\5.jpg | P56: =HYPERLINK(O56) -> C:\Users\mbaptista\OneDrive - Biblioteca Nacional de Portugal\Documentos\python\camoniana\imagens\capas\381903\1\5.jpg | R56: https://permalinkbnd.bnportugal.gov.pt/viewer/270037/?offset=#page=5&viewer=picture&o=info&n=0&q= | T56: 5 | W56: Sim
A57: 382749 | B57: 1 | C57: 7 | D57: https://purl.pt/42835 | E57: https://purl.pt/42835 | F57: 270109 | G57: https://permalinkbnd.bnportugal.gov.pt/viewer/ | H57: /?offset=#page= | I57: &viewer=picture&o=info&n=0&q= | J57: =CONCATENATE(G57,F57,H57,C57,I57) -> https://permalinkbnd.bnportugal.gov.pt/viewer/270109/?offset=#page=7&viewer=picture&o=info&n=0&q= | K57: 7 [site], 19, 23 [frisos site, esta obra contém mais apontamentos e frisos belíssimos] | L57: =VLOOKUP(A57,Folha2!$A$2:$B$2019,2,FALSE) -> Pretidão de amor. Texto+tradução, 1893-1895. 2 Vols [dois exemplares da mesma obra: n.º 56 de Tomás de Carvalho e 137 da BNL]. Trad. Paratextos e Mulheres [Alice Moderno trad. para francês; Josephine Lévi trad. para italiano; Josephine de Zaleska trad. polaco; Josephine Constantini-Arntzen trad. norueguês; Mathilde Perry Conorado trad. para castelhano]. Celebrações (1880), traduções em celebração do 313.º aniversário do passamento de Camões (1893) | M57: =HYPERLINK(J57) -> https://permalinkbnd.bnportugal.gov.pt/viewer/270109/?offset=#page=7&viewer=picture&o=info&n=0&q= | N57: C:\Users\mbaptista\OneDrive - Biblioteca Nacional de Portugal\Documentos\python\camoniana\imagens\capas\ | O57: =CONCATENATE(N57,A57,"\",B57,"\",C57,".jpg") -> C:\Users\mbaptista\OneDrive - Biblioteca Nacional de Portugal\Documentos\python\camoniana\imagens\capas\382749\1\7.jpg | P57: =HYPERLINK(O57) -> C:\Users\mbaptista\OneDrive - Biblioteca Nacional de Portugal\Documentos\python\camoniana\imagens\capas\382749\1\7.jpg | R57: https://permalinkbnd.bnportugal.gov.pt/viewer/270109/?offset=#page=7&viewer=picture&o=info&n=0&q= | W57: Sim
